Workbook

Sheet Master Roles
A1: APPSCODE | B1: ROLE_ID | C1: STATUS | D1: DESC | E1: SQL
A2: CK | B2: ADMIN | C2: A | D2: ACCOUNT ADMIN | E2: =CONCATENATE("INSERT INTO T_CORE_ROLE(ROLE_APPSCODE, ROLE_ID, ROLE_STATUS, ROLE_DESC, ROLE_DT_CREATE, ROLE_UID_CREATE, ROLE_DT_LUPD, ROLE_UID_LUPD) VALUES ('",A2,"','",B2,"','",C2,"','",D2,"',NOW(),'SYS',NOW(),'SYS');") -> INSERT INTO T_CORE_ROLE(ROLE_APPSCODE, ROLE_ID, ROLE_STATUS, ROLE_DESC, ROLE_DT_CREATE, ROLE_UID_CREATE, ROLE_DT_LUPD, ROLE_UID_LUPD) VALUES ('CK','ADMIN','A','ACCOUNT ADMIN',NOW(),'SYS',NOW(),'SYS');
A3: CK | B3: OFFICER | C3: A | D3: OFFICER | E3: =CONCATENATE("INSERT INTO T_CORE_ROLE(ROLE_APPSCODE, ROLE_ID, ROLE_STATUS, ROLE_DESC, ROLE_DT_CREATE, ROLE_UID_CREATE, ROLE_DT_LUPD, ROLE_UID_LUPD) VALUES ('",A3,"','",B3,"','",C3,"','",D3,"',NOW(),'SYS',NOW(),'SYS');") -> INSERT INTO T_CORE_ROLE(ROLE_APPSCODE, ROLE_ID, ROLE_STATUS, ROLE_DESC, ROLE_DT_CREATE, ROLE_UID_CREATE, ROLE_DT_LUPD, ROLE_UID_LUPD) VALUES ('CK','OFFICER','A','OFFICER',NOW(),'SYS',NOW(),'SYS');
A4: CK | B4: OPERATIONS | C4: A | D4: OPERATIONS | E4: =CONCATENATE("INSERT INTO T_CORE_ROLE(ROLE_APPSCODE, ROLE_ID, ROLE_STATUS, ROLE_DESC, ROLE_DT_CREATE, ROLE_UID_CREATE, ROLE_DT_LUPD, ROLE_UID_LUPD) VALUES ('",A4,"','",B4,"','",C4,"','",D4,"',NOW(),'SYS',NOW(),'SYS');") -> INSERT INTO T_CORE_ROLE(ROLE_APPSCODE, ROLE_ID, ROLE_STATUS, ROLE_DESC, ROLE_DT_CREATE, ROLE_UID_CREATE, ROLE_DT_LUPD, ROLE_UID_LUPD) VALUES ('CK','OPERATIONS','A','OPERATIONS',NOW(),'SYS',NOW(),'SYS');
A5: CK | B5: FINANCE | C5: A | D5: FINANCE | E5: =CONCATENATE("INSERT INTO T_CORE_ROLE(ROLE_APPSCODE, ROLE_ID, ROLE_STATUS, ROLE_DESC, ROLE_DT_CREATE, ROLE_UID_CREATE, ROLE_DT_LUPD, ROLE_UID_LUPD) VALUES ('",A5,"','",B5,"','",C5,"','",D5,"',NOW(),'SYS',NOW(),'SYS');") -> INSERT INTO T_CORE_ROLE(ROLE_APPSCODE, ROLE_ID, ROLE_STATUS, ROLE_DESC, ROLE_DT_CREATE, ROLE_UID_CREATE, ROLE_DT_LUPD, ROLE_UID_LUPD) VALUES ('CK','FINANCE','A','FINANCE',NOW(),'SYS',NOW(),'SYS');
A6: CK | B6: SYS_SUPER_ADMIN | C6: A | D6: SYSTEM SUPER ADMIN | E6: =CONCATENATE("INSERT INTO T_CORE_ROLE(ROLE_APPSCODE, ROLE_ID, ROLE_STATUS, ROLE_DESC, ROLE_DT_CREATE, ROLE_UID_CREATE, ROLE_DT_LUPD, ROLE_UID_LUPD) VALUES ('",A6,"','",B6,"','",C6,"','",D6,"',NOW(),'SYS',NOW(),'SYS');") -> INSERT INTO T_CORE_ROLE(ROLE_APPSCODE, ROLE_ID, ROLE_STATUS, ROLE_DESC, ROLE_DT_CREATE, ROLE_UID_CREATE, ROLE_DT_LUPD, ROLE_UID_LUPD) VALUES ('CK','SYS_SUPER_ADMIN','A','SYSTEM SUPER ADMIN',NOW(),'SYS',NOW(),'SYS');
A8: CKT | B8: ADMIN | C8: A | D8: ACCOUNT ADMIN | E8: =CONCATENATE("INSERT INTO T_CORE_ROLE(ROLE_APPSCODE, ROLE_ID, ROLE_STATUS, ROLE_DESC, ROLE_DT_CREATE, ROLE_UID_CREATE, ROLE_DT_LUPD, ROLE_UID_LUPD) VALUES ('",A8,"','",B8,"','",C8,"','",D8,"',NOW(),'SYS',NOW(),'SYS');") -> INSERT INTO T_CORE_ROLE(ROLE_APPSCODE, ROLE_ID, ROLE_STATUS, ROLE_DESC, ROLE_DT_CREATE, ROLE_UID_CREATE, ROLE_DT_LUPD, ROLE_UID_LUPD) VALUES ('CKT','ADMIN','A','ACCOUNT ADMIN',NOW(),'SYS',NOW(),'SYS');
A9: CKT | B9: OFFICER | C9: A | D9: OFFICER | E9: =CONCATENATE("INSERT INTO T_CORE_ROLE(ROLE_APPSCODE, ROLE_ID, ROLE_STATUS, ROLE_DESC, ROLE_DT_CREATE, ROLE_UID_CREATE, ROLE_DT_LUPD, ROLE_UID_LUPD) VALUES ('",A9,"','",B9,"','",C9,"','",D9,"',NOW(),'SYS',NOW(),'SYS');") -> INSERT INTO T_CORE_ROLE(ROLE_APPSCODE, ROLE_ID, ROLE_STATUS, ROLE_DESC, ROLE_DT_CREATE, ROLE_UID_CREATE, ROLE_DT_LUPD, ROLE_UID_LUPD) VALUES ('CKT','OFFICER','A','OFFICER',NOW(),'SYS',NOW(),'SYS');
A10: CKT | B10: FF_FINANCE | C10: A | D10: FINANCE | E10: =CONCATENATE("INSERT INTO T_CORE_ROLE(ROLE_APPSCODE, ROLE_ID, ROLE_STATUS, ROLE_DESC, ROLE_DT_CREATE, ROLE_UID_CREATE, ROLE_DT_LUPD, ROLE_UID_LUPD) VALUES ('",A10,"','",B10,"','",C10,"','",D10,"',NOW(),'SYS',NOW(),'SYS');") -> INSERT INTO T_CORE_ROLE(ROLE_APPSCODE, ROLE_ID, ROLE_STATUS, ROLE_DESC, ROLE_DT_CREATE, ROLE_UID_CREATE, ROLE_DT_LUPD, ROLE_UID_LUPD) VALUES ('CKT','FF_FINANCE','A','FINANCE',NOW(),'SYS',NOW(),'SYS');
A11: CKT | B11: OP_ADMIN | C11: A | D11: OPERATIONS ADMIN | E11: =CONCATENATE("INSERT INTO T_CORE_ROLE(ROLE_APPSCODE, ROLE_ID, ROLE_STATUS, ROLE_DESC, ROLE_DT_CREATE, ROLE_UID_CREATE, ROLE_DT_LUPD, ROLE_UID_LUPD) VALUES ('",A11,"','",B11,"','",C11,"','",D11,"',NOW(),'SYS',NOW(),'SYS');") -> INSERT INTO T_CORE_ROLE(ROLE_APPSCODE, ROLE_ID, ROLE_STATUS, ROLE_DESC, ROLE_DT_CREATE, ROLE_UID_CREATE, ROLE_DT_LUPD, ROLE_UID_LUPD) VALUES ('CKT','OP_ADMIN','A','OPERATIONS ADMIN',NOW(),'SYS',NOW(),'SYS');
A12: CKT | B12: SP_OP_ADMIN | C12: A | D12: OPERATIONS ADMIN | E12: =CONCATENATE("INSERT INTO T_CORE_ROLE(ROLE_APPSCODE, ROLE_ID, ROLE_STATUS, ROLE_DESC, ROLE_DT_CREATE, ROLE_UID_CREATE, ROLE_DT_LUPD, ROLE_UID_LUPD) VALUES ('",A12,"','",B12,"','",C12,"','",D12,"',NOW(),'SYS',NOW(),'SYS');") -> INSERT INTO T_CORE_ROLE(ROLE_APPSCODE, ROLE_ID, ROLE_STATUS, ROLE_DESC, ROLE_DT_CREATE, ROLE_UID_CREATE, ROLE_DT_LUPD, ROLE_UID_LUPD) VALUES ('CKT','SP_OP_ADMIN','A','OPERATIONS ADMIN',NOW(),'SYS',NOW(),'SYS');
A13: CKT | B13: SP_L1 | C13: A | D13: LEVEL 1 SUPPORT | E13: =CONCATENATE("INSERT INTO T_CORE_ROLE(ROLE_APPSCODE, ROLE_ID, ROLE_STATUS, ROLE_DESC, ROLE_DT_CREATE, ROLE_UID_CREATE, ROLE_DT_LUPD, ROLE_UID_LUPD) VALUES ('",A13,"','",B13,"','",C13,"','",D13,"',NOW(),'SYS',NOW(),'SYS');") -> INSERT INTO T_CORE_ROLE(ROLE_APPSCODE, ROLE_ID, ROLE_STATUS, ROLE_DESC, ROLE_DT_CREATE, ROLE_UID_CREATE, ROLE_DT_LUPD, ROLE_UID_LUPD) VALUES ('CKT','SP_L1','A','LEVEL 1 SUPPORT',NOW(),'SYS',NOW(),'SYS');
A14: CKT | B14: SP_COM | C14: A | D14: COMMERCIAL | E14: =CONCATENATE("INSERT INTO T_CORE_ROLE(ROLE_APPSCODE, ROLE_ID, ROLE_STATUS, ROLE_DESC, ROLE_DT_CREATE, ROLE_UID_CREATE, ROLE_DT_LUPD, ROLE_UID_LUPD) VALUES ('",A14,"','",B14,"','",C14,"','",D14,"',NOW(),'SYS',NOW(),'SYS');") -> INSERT INTO T_CORE_ROLE(ROLE_APPSCODE, ROLE_ID, ROLE_STATUS, ROLE_DESC, ROLE_DT_CREATE, ROLE_UID_CREATE, ROLE_DT_LUPD, ROLE_UID_LUPD) VALUES ('CKT','SP_COM','A','COMMERCIAL',NOW(),'SYS',NOW(),'SYS');
... A29: CKDO | B29: SP_FIN_ADMIN | C29: A | D29: FINANCE ADMIN | E29: =CONCATENATE("INSERT INTO T_CORE_ROLE(ROLE_APPSCODE, ROLE_ID, ROLE_STATUS, ROLE_DESC, ROLE_DT_CREATE, ROLE_UID_CREATE, ROLE_DT_LUPD, ROLE_UID_LUPD) VALUES ('",A29,"','",B29,"','",C29,"','",D29,"',NOW(),'SYS',NOW(),'SYS');") -> INSERT INTO T_CORE_ROLE(ROLE_APPSCODE, ROLE_ID, ROLE_STATUS, ROLE_DESC, ROLE_DT_CREATE, ROLE_UID_CREATE, ROLE_DT_LUPD, ROLE_UID_LUPD) VALUES ('CKDO','SP_FIN_ADMIN','A','FINANCE ADMIN',NOW(),'SYS',NOW(),'SYS');
A32: NOTE:
B33: SP_FIN_ADMIN WILL REPLACE FINANCE_VERIFIER AND FINANCE_ADMIN
B34: SP_FIN_HD WILL REPLACE FINANCE_APPROVER

Sheet User Roles
A1: User ID | B1: USR_ACCNID | C1: ACCOUNT TYPE | D1: APPSCODE | E1: ROLE ID | F1: IS ADMIN | G1: TEMP ROLE | H1: STATUS
A2: ALKNAR_U001 | B2: ALKNAR | C2: ACC_TYPE_CO | D2: CK | E2: OFFICER | F2: N | G2: N | H2: A | I2: =CONCATENATE("INSERT INTO T_CORE_USR_ROLE(UROL_UID, UROL_APPSCODE, UROL_ROLEID, UROL_ADMIN_OPT, UROL_STATUS, UROL_DT_CREATE, UROL_UID_CREATE, UROL_DT_LUPD, UROL_UID_LUPD, UROL_TEMP_ROLE) VALUES('",A2,"','",D2,"','",E2,"','",F2,"','",H2,"',NOW(),'SYS', NOW(),'SYS','",G2,"');") -> INSERT INTO T_CORE_USR_ROLE(UROL_UID, UROL_APPSCODE, UROL_ROLEID, UROL_ADMIN_OPT, UROL_STATUS, UROL_DT_CREATE, UROL_UID_CREATE, UROL_DT_LUPD, UROL_UID_LUPD, UROL_TEMP_ROLE) VALUES('ALKNAR_U001','CK','OFFICER','N','A',NOW(),'SYS', NOW(),'SYS','N');
A3: ALKNAR_U002 | B3: ALKNAR | C3: ACC_TYPE_CO | D3: CK | E3: OFFICER | F3: N | G3: N | H3: A | I3: =CONCATENATE("INSERT INTO T_CORE_USR_ROLE(UROL_UID, UROL_APPSCODE, UROL_ROLEID, UROL_ADMIN_OPT, UROL_STATUS, UROL_DT_CREATE, UROL_UID_CREATE, UROL_DT_LUPD, UROL_UID_LUPD, UROL_TEMP_ROLE) VALUES('",A3,"','",D3,"','",E3,"','",F3,"','",H3,"',NOW(),'SYS', NOW(),'SYS','",G3,"');") -> INSERT INTO T_CORE_USR_ROLE(UROL_UID, UROL_APPSCODE, UROL_ROLEID, UROL_ADMIN_OPT, UROL_STATUS, UROL_DT_CREATE, UROL_UID_CREATE, UROL_DT_LUPD, UROL_UID_LUPD, UROL_TEMP_ROLE) VALUES('ALKNAR_U002','CK','OFFICER','N','A',NOW(),'SYS', NOW(),'SYS','N');
A4: ALKNAR_U003 | B4: ALKNAR | C4: ACC_TYPE_CO | D4: CK | E4: OFFICER | F4: N | G4: N | H4: A | I4: =CONCATENATE("INSERT INTO T_CORE_USR_ROLE(UROL_UID, UROL_APPSCODE, UROL_ROLEID, UROL_ADMIN_OPT, UROL_STATUS, UROL_DT_CREATE, UROL_UID_CREATE, UROL_DT_LUPD, UROL_UID_LUPD, UROL_TEMP_ROLE) VALUES('",A4,"','",D4,"','",E4,"','",F4,"','",H4,"',NOW(),'SYS', NOW(),'SYS','",G4,"');") -> INSERT INTO T_CORE_USR_ROLE(UROL_UID, UROL_APPSCODE, UROL_ROLEID, UROL_ADMIN_OPT, UROL_STATUS, UROL_DT_CREATE, UROL_UID_CREATE, UROL_DT_LUPD, UROL_UID_LUPD, UROL_TEMP_ROLE) VALUES('ALKNAR_U003','CK','OFFICER','N','A',NOW(),'SYS', NOW(),'SYS','N');
A5: ALMGA_U001 | B5: ALMGA | C5: ACC_TYPE_CO | D5: CK | E5: OFFICER | F5: N | G5: N | H5: A | I5: =CONCATENATE("INSERT INTO T_CORE_USR_ROLE(UROL_UID, UROL_APPSCODE, UROL_ROLEID, UROL_ADMIN_OPT, UROL_STATUS, UROL_DT_CREATE, UROL_UID_CREATE, UROL_DT_LUPD, UROL_UID_LUPD, UROL_TEMP_ROLE) VALUES('",A5,"','",D5,"','",E5,"','",F5,"','",H5,"',NOW(),'SYS', NOW(),'SYS','",G5,"');") -> INSERT INTO T_CORE_USR_ROLE(UROL_UID, UROL_APPSCODE, UROL_ROLEID, UROL_ADMIN_OPT, UROL_STATUS, UROL_DT_CREATE, UROL_UID_CREATE, UROL_DT_LUPD, UROL_UID_LUPD, UROL_TEMP_ROLE) VALUES('ALMGA_U001','CK','OFFICER','N','A',NOW(),'SYS', NOW(),'SYS','N');
A6: ALMGA_U002 | B6: ALMGA | C6: ACC_TYPE_CO | D6: CK | E6: OFFICER | F6: N | G6: N | H6: A | I6: =CONCATENATE("INSERT INTO T_CORE_USR_ROLE(UROL_UID, UROL_APPSCODE, UROL_ROLEID, UROL_ADMIN_OPT, UROL_STATUS, UROL_DT_CREATE, UROL_UID_CREATE, UROL_DT_LUPD, UROL_UID_LUPD, UROL_TEMP_ROLE) VALUES('",A6,"','",D6,"','",E6,"','",F6,"','",H6,"',NOW(),'SYS', NOW(),'SYS','",G6,"');") -> INSERT INTO T_CORE_USR_ROLE(UROL_UID, UROL_APPSCODE, UROL_ROLEID, UROL_ADMIN_OPT, UROL_STATUS, UROL_DT_CREATE, UROL_UID_CREATE, UROL_DT_LUPD, UROL_UID_LUPD, UROL_TEMP_ROLE) VALUES('ALMGA_U002','CK','OFFICER','N','A',NOW(),'SYS', NOW(),'SYS','N');
A7: ALMGA_U003 | B7: ALMGA | C7: ACC_TYPE_CO | D7: CK | E7: OFFICER | F7: N | G7: N | H7: A | I7: =CONCATENATE("INSERT INTO T_CORE_USR_ROLE(UROL_UID, UROL_APPSCODE, UROL_ROLEID, UROL_ADMIN_OPT, UROL_STATUS, UROL_DT_CREATE, UROL_UID_CREATE, UROL_DT_LUPD, UROL_UID_LUPD, UROL_TEMP_ROLE) VALUES('",A7,"','",D7,"','",E7,"','",F7,"','",H7,"',NOW(),'SYS', NOW(),'SYS','",G7,"');") -> INSERT INTO T_CORE_USR_ROLE(UROL_UID, UROL_APPSCODE, UROL_ROLEID, UROL_ADMIN_OPT, UROL_STATUS, UROL_DT_CREATE, UROL_UID_CREATE, UROL_DT_LUPD, UROL_UID_LUPD, UROL_TEMP_ROLE) VALUES('ALMGA_U003','CK','OFFICER','N','A',NOW(),'SYS', NOW(),'SYS','N');
A8: ASPIND_U001 | B8: ASPIND | C8: ACC_TYPE_CO | D8: CK | E8: OFFICER | F8: N | G8: N | H8: A | I8: =CONCATENATE("INSERT INTO T_CORE_USR_ROLE(UROL_UID, UROL_APPSCODE, UROL_ROLEID, UROL_ADMIN_OPT, UROL_STATUS, UROL_DT_CREATE, UROL_UID_CREATE, UROL_DT_LUPD, UROL_UID_LUPD, UROL_TEMP_ROLE) VALUES('",A8,"','",D8,"','",E8,"','",F8,"','",H8,"',NOW(),'SYS', NOW(),'SYS','",G8,"');") -> INSERT INTO T_CORE_USR_ROLE(UROL_UID, UROL_APPSCODE, UROL_ROLEID, UROL_ADMIN_OPT, UROL_STATUS, UROL_DT_CREATE, UROL_UID_CREATE, UROL_DT_LUPD, UROL_UID_LUPD, UROL_TEMP_ROLE) VALUES('ASPIND_U001','CK','OFFICER','N','A',NOW(),'SYS', NOW(),'SYS','N');
A9: ASPIND_U002 | B9: ASPIND | C9: ACC_TYPE_CO | D9: CK | E9: OFFICER | F9: N | G9: N | H9: A | I9: =CONCATENATE("INSERT INTO T_CORE_USR_ROLE(UROL_UID, UROL_APPSCODE, UROL_ROLEID, UROL_ADMIN_OPT, UROL_STATUS, UROL_DT_CREATE, UROL_UID_CREATE, UROL_DT_LUPD, UROL_UID_LUPD, UROL_TEMP_ROLE) VALUES('",A9,"','",D9,"','",E9,"','",F9,"','",H9,"',NOW(),'SYS', NOW(),'SYS','",G9,"');") -> INSERT INTO T_CORE_USR_ROLE(UROL_UID, UROL_APPSCODE, UROL_ROLEID, UROL_ADMIN_OPT, UROL_STATUS, UROL_DT_CREATE, UROL_UID_CREATE, UROL_DT_LUPD, UROL_UID_LUPD, UROL_TEMP_ROLE) VALUES('ASPIND_U002','CK','OFFICER','N','A',NOW(),'SYS', NOW(),'SYS','N');
A10: ASPIND_U003 | B10: ASPIND | C10: ACC_TYPE_CO | D10: CK | E10: OFFICER | F10: N | G10: N | H10: A | I10: =CONCATENATE("INSERT INTO T_CORE_USR_ROLE(UROL_UID, UROL_APPSCODE, UROL_ROLEID, UROL_ADMIN_OPT, UROL_STATUS, UROL_DT_CREATE, UROL_UID_CREATE, UROL_DT_LUPD, UROL_UID_LUPD, UROL_TEMP_ROLE) VALUES('",A10,"','",D10,"','",E10,"','",F10,"','",H10,"',NOW(),'SYS', NOW(),'SYS','",G10,"');") -> INSERT INTO T_CORE_USR_ROLE(UROL_UID, UROL_APPSCODE, UROL_ROLEID, UROL_ADMIN_OPT, UROL_STATUS, UROL_DT_CREATE, UROL_UID_CREATE, UROL_DT_LUPD, UROL_UID_LUPD, UROL_TEMP_ROLE) VALUES('ASPIND_U003','CK','OFFICER','N','A',NOW(),'SYS', NOW(),'SYS','N');
A11: COMLG_U001 | B11: COMLG | C11: ACC_TYPE_FF | D11: CK | E11: OFFICER | F11: N | G11: N | H11: A | I11: =CONCATENATE("INSERT INTO T_CORE_USR_ROLE(UROL_UID, UROL_APPSCODE, UROL_ROLEID, UROL_ADMIN_OPT, UROL_STATUS, UROL_DT_CREATE, UROL_UID_CREATE, UROL_DT_LUPD, UROL_UID_LUPD, UROL_TEMP_ROLE) VALUES('",A11,"','",D11,"','",E11,"','",F11,"','",H11,"',NOW(),'SYS', NOW(),'SYS','",G11,"');") -> INSERT INTO T_CORE_USR_ROLE(UROL_UID, UROL_APPSCODE, UROL_ROLEID, UROL_ADMIN_OPT, UROL_STATUS, UROL_DT_CREATE, UROL_UID_CREATE, UROL_DT_LUPD, UROL_UID_LUPD, UROL_TEMP_ROLE) VALUES('COMLG_U001','CK','OFFICER','N','A',NOW(),'SYS', NOW(),'SYS','N');
A12: COMLG_U002 | B12: COMLG | C12: ACC_TYPE_FF | D12: CK | E12: OFFICER | F12: N | G12: N | H12: A | I12: =CONCATENATE("INSERT INTO T_CORE_USR_ROLE(UROL_UID, UROL_APPSCODE, UROL_ROLEID, UROL_ADMIN_OPT, UROL_STATUS, UROL_DT_CREATE, UROL_UID_CREATE, UROL_DT_LUPD, UROL_UID_LUPD, UROL_TEMP_ROLE) VALUES('",A12,"','",D12,"','",E12,"','",F12,"','",H12,"',NOW(),'SYS', NOW(),'SYS','",G12,"');") -> INSERT INTO T_CORE_USR_ROLE(UROL_UID, UROL_APPSCODE, UROL_ROLEID, UROL_ADMIN_OPT, UROL_STATUS, UROL_DT_CREATE, UROL_UID_CREATE, UROL_DT_LUPD, UROL_UID_LUPD, UROL_TEMP_ROLE) VALUES('COMLG_U002','CK','OFFICER','N','A',NOW(),'SYS', NOW(),'SYS','N');
A13: COMLG_U003 | B13: COMLG | C13: ACC_TYPE_FF | D13: CK | E13: OFFICER | F13: N | G13: N | H13: A | I13: =CONCATENATE("INSERT INTO T_CORE_USR_ROLE(UROL_UID, UROL_APPSCODE, UROL_ROLEID, UROL_ADMIN_OPT, UROL_STATUS, UROL_DT_CREATE, UROL_UID_CREATE, UROL_DT_LUPD, UROL_UID_LUPD, UROL_TEMP_ROLE) VALUES('",A13,"','",D13,"','",E13,"','",F13,"','",H13,"',NOW(),'SYS', NOW(),'SYS','",G13,"');") -> INSERT INTO T_CORE_USR_ROLE(UROL_UID, UROL_APPSCODE, UROL_ROLEID, UROL_ADMIN_OPT, UROL_STATUS, UROL_DT_CREATE, UROL_UID_CREATE, UROL_DT_LUPD, UROL_UID_LUPD, UROL_TEMP_ROLE) VALUES('COMLG_U003','CK','OFFICER','N','A',NOW(),'SYS', NOW(),'SYS','N');
... A38: GLI_U001 | B38: GLI | C38: ACC_TYPE_SP | D38: CKT | E38: SP_OP_ADMIN | F38: N | G38: N | H38: A | I38: =CONCATENATE("INSERT INTO T_CORE_USR_ROLE(UROL_UID, UROL_APPSCODE, UROL_ROLEID, UROL_ADMIN_OPT, UROL_STATUS, UROL_DT_CREATE, UROL_UID_CREATE, UROL_DT_LUPD, UROL_UID_LUPD, UROL_TEMP_ROLE) VALUES('",A38,"','",D38,"','",E38,"','",F38,"','",H38,"',NOW(),'SYS', NOW(),'SYS','",G38,"');") -> INSERT INTO T_CORE_USR_ROLE(UROL_UID, UROL_APPSCODE, UROL_ROLEID, UROL_ADMIN_OPT, UROL_STATUS, UROL_DT_CREATE, UROL_UID_CREATE, UROL_DT_LUPD, UROL_UID_LUPD, UROL_TEMP_ROLE) VALUES('GLI_U001','CKT','SP_OP_ADMIN','N','A',NOW(),'SYS', NOW(),'SYS','N');
A39: GLI_L1 | B39: GLI | C39: ACC_TYPE_SP | D39: CKT | E39: SP_L1 | F39: N | G39: N | H39: A
A40: GLI_SYS_ADMIN | B40: GLI | C40: ACC_TYPE_SP | D40: CKT | E40: SYS_SUPER_ADMIN | F40: N | G40: N | H40: A | I40: =CONCATENATE("INSERT INTO T_CORE_USR_ROLE(UROL_UID, UROL_APPSCODE, UROL_ROLEID, UROL_ADMIN_OPT, UROL_STATUS, UROL_DT_CREATE, UROL_UID_CREATE, UROL_DT_LUPD, UROL_UID_LUPD, UROL_TEMP_ROLE) VALUES('",A40,"','",D40,"','",E40,"','",F40,"','",H40,"',NOW(),'SYS', NOW(),'SYS','",G40,"');") -> INSERT INTO T_CORE_USR_ROLE(UROL_UID, UROL_APPSCODE, UROL_ROLEID, UROL_ADMIN_OPT, UROL_STATUS, UROL_DT_CREATE, UROL_UID_CREATE, UROL_DT_LUPD, UROL_UID_LUPD, UROL_TEMP_ROLE) VALUES('GLI_SYS_ADMIN','CKT','SYS_SUPER_ADMIN','N','A',NOW(),'SYS', NOW(),'SYS','N');
A41: GLI_U001 | B41: GLI | C41: ACC_TYPE_SP | D41: CKDO | E41: FINANCE_ADMIN | F41: N | G41: N | H41: A | I41: =CONCATENATE("INSERT INTO T_CORE_USR_ROLE(UROL_UID, UROL_APPSCODE, UROL_ROLEID, UROL_ADMIN_OPT, UROL_STATUS, UROL_DT_CREATE, UROL_UID_CREATE, UROL_DT_LUPD, UROL_UID_LUPD, UROL_TEMP_ROLE) VALUES('",A41,"','",D41,"','",E41,"','",F41,"','",H41,"',NOW(),'SYS', NOW(),'SYS','",G41,"');") -> INSERT INTO T_CORE_USR_ROLE(UROL_UID, UROL_APPSCODE, UROL_ROLEID, UROL_ADMIN_OPT, UROL_STATUS, UROL_DT_CREATE, UROL_UID_CREATE, UROL_DT_LUPD, UROL_UID_LUPD, UROL_TEMP_ROLE) VALUES('GLI_U001','CKDO','FINANCE_ADMIN','N','A',NOW(),'SYS', NOW(),'SYS','N');
A42: GLI_U001 | B42: GLI | C42: ACC_TYPE_SP | D42: CKDO | E42: SP_OP_ADMIN | F42: N | G42: N | H42: A | I42: =CONCATENATE("INSERT INTO T_CORE_USR_ROLE(UROL_UID, UROL_APPSCODE, UROL_ROLEID, UROL_ADMIN_OPT, UROL_STATUS, UROL_DT_CREATE, UROL_UID_CREATE, UROL_DT_LUPD, UROL_UID_LUPD, UROL_TEMP_ROLE) VALUES('",A42,"','",D42,"','",E42,"','",F42,"','",H42,"',NOW(),'SYS', NOW(),'SYS','",G42,"');") -> INSERT INTO T_CORE_USR_ROLE(UROL_UID, UROL_APPSCODE, UROL_ROLEID, UROL_ADMIN_OPT, UROL_STATUS, UROL_DT_CREATE, UROL_UID_CREATE, UROL_DT_LUPD, UROL_UID_LUPD, UROL_TEMP_ROLE) VALUES('GLI_U001','CKDO','SP_OP_ADMIN','N','A',NOW(),'SYS', NOW(),'SYS','N');
A43: GLI_L1 | B43: GLI | C43: ACC_TYPE_SP | D43: CKDO | E43: SP_L1 | F43: N | G43: N | H43: A | I43: =CONCATENATE("INSERT INTO T_CORE_USR_ROLE(UROL_UID, UROL_APPSCODE, UROL_ROLEID, UROL_ADMIN_OPT, UROL_STATUS, UROL_DT_CREATE, UROL_UID_CREATE, UROL_DT_LUPD, UROL_UID_LUPD, UROL_TEMP_ROLE) VALUES('",A43,"','",D43,"','",E43,"','",F43,"','",H43,"',NOW(),'SYS', NOW(),'SYS','",G43,"');") -> INSERT INTO T_CORE_USR_ROLE(UROL_UID, UROL_APPSCODE, UROL_ROLEID, UROL_ADMIN_OPT, UROL_STATUS, UROL_DT_CREATE, UROL_UID_CREATE, UROL_DT_LUPD, UROL_UID_LUPD, UROL_TEMP_ROLE) VALUES('GLI_L1','CKDO','SP_L1','N','A',NOW(),'SYS', NOW(),'SYS','N');
A44: GLI_U001 | B44: GLI | C44: ACC_TYPE_SP | D44: CKDO | E44: SP_L1 | F44: N | G44: N | H44: A | I44: =CONCATENATE("INSERT INTO T_CORE_USR_ROLE(UROL_UID, UROL_APPSCODE, UROL_ROLEID, UROL_ADMIN_OPT, UROL_STATUS, UROL_DT_CREATE, UROL_UID_CREATE, UROL_DT_LUPD, UROL_UID_LUPD, UROL_TEMP_ROLE) VALUES('",A44,"','",D44,"','",E44,"','",F44,"','",H44,"',NOW(),'SYS', NOW(),'SYS','",G44,"');") -> INSERT INTO T_CORE_USR_ROLE(UROL_UID, UROL_APPSCODE, UROL_ROLEID, UROL_ADMIN_OPT, UROL_STATUS, UROL_DT_CREATE, UROL_UID_CREATE, UROL_DT_LUPD, UROL_UID_LUPD, UROL_TEMP_ROLE) VALUES('GLI_U001','CKDO','SP_L1','N','A',NOW(),'SYS', NOW(),'SYS','N');

Sheet CK Master Tables
A1: CREDIT UPDATE STATE
A2: ID | B2: NAME | C2: DESC | D2: DESC OTH | E2: STATUS | F2: SQL
A3: NEW | B3: NEW | C3: NEW | D3: NEW | E3: A | F3: =CONCATENATE(G3,H3) -> INSERT INTO `T_CK_MST_CREDIT_UPDATE_STATE` (`ST_ID`,`ST_NAME`,`ST_DESC`,`ST_DESC_OTH`,`ST_STATUS`,`ST_DT_CREATE`,`ST_UID_CREATE`,`ST_DT_LUPD`,`ST_UID_LUPD`) VALUES('NEW','NEW','NEW','NEW','A',NOW(),'SYS',NOW(),'SYS'); | G3: =CONCATENATE("INSERT INTO `T_CK_MST_CREDIT_UPDATE_STATE` (`ST_ID`,`ST_NAME`,`ST_DESC`,`ST_DESC_OTH`,`ST_STATUS`,`ST_DT_CREATE`,`ST_UID_CREATE`,`ST_DT_LUPD`,`ST_UID_LUPD`) ") -> INSERT INTO `T_CK_MST_CREDIT_UPDATE_STATE` (`ST_ID`,`ST_NAME`,`ST_DESC`,`ST_DESC_OTH`,`ST_STATUS`,`ST_DT_CREATE`,`ST_UID_CREATE`,`ST_DT_LUPD`,`ST_UID_LUPD`) | H3: =CONCATENATE(" VALUES('",A3,"','",B3,"','",C3,"','",D3,"','",E3,"',NOW(),'SYS',NOW(),'SYS');") -> VALUES('NEW','NEW','NEW','NEW','A',NOW(),'SYS',NOW(),'SYS');
A4: SUB | B4: SUBMITTED | C4: SUBMITTED | D4: SUBMITTED | E4: A | F4: =CONCATENATE(G4,H4) -> INSERT INTO `T_CK_MST_CREDIT_UPDATE_STATE` (`ST_ID`,`ST_NAME`,`ST_DESC`,`ST_DESC_OTH`,`ST_STATUS`,`ST_DT_CREATE`,`ST_UID_CREATE`,`ST_DT_LUPD`,`ST_UID_LUPD`) VALUES('SUB','SUBMITTED','SUBMITTED','SUBMITTED','A',NOW(),'SYS',NOW(),'SYS'); | G4: =CONCATENATE("INSERT INTO `T_CK_MST_CREDIT_UPDATE_STATE` (`ST_ID`,`ST_NAME`,`ST_DESC`,`ST_DESC_OTH`,`ST_STATUS`,`ST_DT_CREATE`,`ST_UID_CREATE`,`ST_DT_LUPD`,`ST_UID_LUPD`) ") -> INSERT INTO `T_CK_MST_CREDIT_UPDATE_STATE` (`ST_ID`,`ST_NAME`,`ST_DESC`,`ST_DESC_OTH`,`ST_STATUS`,`ST_DT_CREATE`,`ST_UID_CREATE`,`ST_DT_LUPD`,`ST_UID_LUPD`) | H4: =CONCATENATE(" VALUES('",A4,"','",B4,"','",C4,"','",D4,"','",E4,"',NOW(),'SYS',NOW(),'SYS');") -> VALUES('SUB','SUBMITTED','SUBMITTED','SUBMITTED','A',NOW(),'SYS',NOW(),'SYS');
A5: DEL | B5: DELETED | C5: DELETED | D5: DELETED | E5: A | F5: =CONCATENATE(G5,H5) -> INSERT INTO `T_CK_MST_CREDIT_UPDATE_STATE` (`ST_ID`,`ST_NAME`,`ST_DESC`,`ST_DESC_OTH`,`ST_STATUS`,`ST_DT_CREATE`,`ST_UID_CREATE`,`ST_DT_LUPD`,`ST_UID_LUPD`) VALUES('DEL','DELETED','DELETED','DELETED','A',NOW(),'SYS',NOW(),'SYS'); | G5: =CONCATENATE("INSERT INTO `T_CK_MST_CREDIT_UPDATE_STATE` (`ST_ID`,`ST_NAME`,`ST_DESC`,`ST_DESC_OTH`,`ST_STATUS`,`ST_DT_CREATE`,`ST_UID_CREATE`,`ST_DT_LUPD`,`ST_UID_LUPD`) ") -> INSERT INTO `T_CK_MST_CREDIT_UPDATE_STATE` (`ST_ID`,`ST_NAME`,`ST_DESC`,`ST_DESC_OTH`,`ST_STATUS`,`ST_DT_CREATE`,`ST_UID_CREATE`,`ST_DT_LUPD`,`ST_UID_LUPD`) | H5: =CONCATENATE(" VALUES('",A5,"','",B5,"','",C5,"','",D5,"','",E5,"',NOW(),'SYS',NOW(),'SYS');") -> VALUES('DEL','DELETED','DELETED','DELETED','A',NOW(),'SYS',NOW(),'SYS');
A6: APP | B6: APPROVED | C6: APPROVED | D6: APPROVED | E6: A | F6: =CONCATENATE(G6,H6) -> INSERT INTO `T_CK_MST_CREDIT_UPDATE_STATE` (`ST_ID`,`ST_NAME`,`ST_DESC`,`ST_DESC_OTH`,`ST_STATUS`,`ST_DT_CREATE`,`ST_UID_CREATE`,`ST_DT_LUPD`,`ST_UID_LUPD`) VALUES('APP','APPROVED','APPROVED','APPROVED','A',NOW(),'SYS',NOW(),'SYS'); | G6: =CONCATENATE("INSERT INTO `T_CK_MST_CREDIT_UPDATE_STATE` (`ST_ID`,`ST_NAME`,`ST_DESC`,`ST_DESC_OTH`,`ST_STATUS`,`ST_DT_CREATE`,`ST_UID_CREATE`,`ST_DT_LUPD`,`ST_UID_LUPD`) ") -> INSERT INTO `T_CK_MST_CREDIT_UPDATE_STATE` (`ST_ID`,`ST_NAME`,`ST_DESC`,`ST_DESC_OTH`,`ST_STATUS`,`ST_DT_CREATE`,`ST_UID_CREATE`,`ST_DT_LUPD`,`ST_UID_LUPD`) | H6: =CONCATENATE(" VALUES('",A6,"','",B6,"','",C6,"','",D6,"','",E6,"',NOW(),'SYS',NOW(),'SYS');") -> VALUES('APP','APPROVED','APPROVED','APPROVED','A',NOW(),'SYS',NOW(),'SYS');
A7: REJ | B7: REJECTED | C7: REJECTED | D7: REJECTED | E7: A | F7: =CONCATENATE(G7,H7) -> INSERT INTO `T_CK_MST_CREDIT_UPDATE_STATE` (`ST_ID`,`ST_NAME`,`ST_DESC`,`ST_DESC_OTH`,`ST_STATUS`,`ST_DT_CREATE`,`ST_UID_CREATE`,`ST_DT_LUPD`,`ST_UID_LUPD`) VALUES('REJ','REJECTED','REJECTED','REJECTED','A',NOW(),'SYS',NOW(),'SYS'); | G7: =CONCATENATE("INSERT INTO `T_CK_MST_CREDIT_UPDATE_STATE` (`ST_ID`,`ST_NAME`,`ST_DESC`,`ST_DESC_OTH`,`ST_STATUS`,`ST_DT_CREATE`,`ST_UID_CREATE`,`ST_DT_LUPD`,`ST_UID_LUPD`) ") -> INSERT INTO `T_CK_MST_CREDIT_UPDATE_STATE` (`ST_ID`,`ST_NAME`,`ST_DESC`,`ST_DESC_OTH`,`ST_STATUS`,`ST_DT_CREATE`,`ST_UID_CREATE`,`ST_DT_LUPD`,`ST_UID_LUPD`) | H7: =CONCATENATE(" VALUES('",A7,"','",B7,"','",C7,"','",D7,"','",E7,"',NOW(),'SYS',NOW(),'SYS');") -> VALUES('REJ','REJECTED','REJECTED','REJECTED','A',NOW(),'SYS',NOW(),'SYS');

Sheet Menu_EX_CK2
A1: MENU_ID | B1: MENU_APPS_CODE | C1: REMARKS | D1: MENU_GROUP_LABEL | E1: MENU_GROUP_LABEL_OTH | F1: MENU_NAME | G1: MENU_NAME_OTH | H1: MENU_SEQ | I1: MENU_PATH | J1: MENU_ICON | K1: MENU_PARENT | L1: MENU_STATUS | M1: SQL
A2: CK_MH_080000 | B2: CK | D2: Help | E2: Help | F2: Help | G2: Help | H2: 80000 | I2: /help | J2: help | K2: NULL | L2: A | M2: =CONCATENATE("INSERT INTO T_CORE_MENU_EX (MENU_ID, MENU_APPS_CODE, MENU_GROUP_LABEL, MENU_GROUP_LABEL_OTH, MENU_NAME, MENU_NAME_OTH, MENU_SEQ, MENU_PATH, MENU_ICON, MENU_PARENT, MENU_STATUS, MENU_DT_CREATE, MENU_UID_CREATE, MENU_DT_LUPD, MENU_UID_LUPD) ") -> INSERT INTO T_CORE_MENU_EX (MENU_ID, MENU_APPS_CODE, MENU_GROUP_LABEL, MENU_GROUP_LABEL_OTH, MENU_NAME, MENU_NAME_OTH, MENU_SEQ, MENU_PATH, MENU_ICON, MENU_PARENT, MENU_STATUS, MENU_DT_CREATE, MENU_UID_CREATE, MENU_DT_LUPD, MENU_UID_LUPD) | N2: =CONCATENATE(" VALUES('",A2,"','",B2,"','",D2,"','",E2,"','",F2,"','",G2,"',",IF(H2="NULL","NULL",CONCATENATE("'",H2,"'")),",",IF(I2="NULL","NULL",CONCATENATE("'",I2,"'")),",",IF(J2="NULL","NULL",CONCATENATE("'",J2,"'")),",",IF(K2="NULL","NULL",CONCATENATE("'",K2,"'")),",'A',NOW(),'SYS',NOW(),'SYS');") -> VALUES('CK_MH_080000','CK','Help','Help','Help','Help','80000','/help','help',NULL,'A',NOW(),'SYS',NOW(),'SYS'); | O2: =CONCATENATE(M2,N2) -> INSERT INTO T_CORE_MENU_EX (MENU_ID, MENU_APPS_CODE, MENU_GROUP_LABEL, MENU_GROUP_LABEL_OTH, MENU_NAME, MENU_NAME_OTH, MENU_SEQ, MENU_PATH, MENU_ICON, MENU_PARENT, MENU_STATUS, MENU_DT_CREATE, MENU_UID_CREATE, MENU_DT_LUPD, MENU_UID_LUPD) VALUES('CK_MH_080000','CK','Help','Help','Help','Help','80000','/help','help',NULL,'A',NOW(),'SYS',NOW(),'SYS');
A3: CKT_MS_010000 | B3: CKT | D3: Services | E3: Services | F3: Services | G3: Services | H3: 10000 | I3: / | J3: grid_view | K3: NULL | L3: A | M3: =CONCATENATE("INSERT INTO T_CORE_MENU_EX (MENU_ID, MENU_APPS_CODE, MENU_GROUP_LABEL, MENU_GROUP_LABEL_OTH, MENU_NAME, MENU_NAME_OTH, MENU_SEQ, MENU_PATH, MENU_ICON, MENU_PARENT, MENU_STATUS, MENU_DT_CREATE, MENU_UID_CREATE, MENU_DT_LUPD, MENU_UID_LUPD) ") -> INSERT INTO T_CORE_MENU_EX (MENU_ID, MENU_APPS_CODE, MENU_GROUP_LABEL, MENU_GROUP_LABEL_OTH, MENU_NAME, MENU_NAME_OTH, MENU_SEQ, MENU_PATH, MENU_ICON, MENU_PARENT, MENU_STATUS, MENU_DT_CREATE, MENU_UID_CREATE, MENU_DT_LUPD, MENU_UID_LUPD) | N3: =CONCATENATE(" VALUES('",A3,"','",B3,"','",D3,"','",E3,"','",F3,"','",G3,"',",IF(H3="NULL","NULL",CONCATENATE("'",H3,"'")),",",IF(I3="NULL","NULL",CONCATENATE("'",I3,"'")),",",IF(J3="NULL","NULL",CONCATENATE("'",J3,"'")),",",IF(K3="NULL","NULL",CONCATENATE("'",K3,"'")),",'A',NOW(),'SYS',NOW(),'SYS');") -> VALUES('CKT_MS_010000','CKT','Services','Services','Services','Services','10000','/','grid_view',NULL,'A',NOW(),'SYS',NOW(),'SYS'); | O3: =CONCATENATE(M3,N3) -> INSERT INTO T_CORE_MENU_EX (MENU_ID, MENU_APPS_CODE, MENU_GROUP_LABEL, MENU_GROUP_LABEL_OTH, MENU_NAME, MENU_NAME_OTH, MENU_SEQ, MENU_PATH, MENU_ICON, MENU_PARENT, MENU_STATUS, MENU_DT_CREATE, MENU_UID_CREATE, MENU_DT_LUPD, MENU_UID_LUPD) VALUES('CKT_MS_010000','CKT','Services','Services','Services','Services','10000','/','grid_view',NULL,'A',NOW(),'SYS',NOW(),'SYS');
A4: CKT_MA_030000 | B4: CKT | D4: Administrations | E4: Administrations | F4: Administrations | G4: Administrations | H4: 30000 | I4: NULL | J4: admin_panel_settings | K4: NULL | L4: A | M4: =CONCATENATE("INSERT INTO T_CORE_MENU_EX (MENU_ID, MENU_APPS_CODE, MENU_GROUP_LABEL, MENU_GROUP_LABEL_OTH, MENU_NAME, MENU_NAME_OTH, MENU_SEQ, MENU_PATH, MENU_ICON, MENU_PARENT, MENU_STATUS, MENU_DT_CREATE, MENU_UID_CREATE, MENU_DT_LUPD, MENU_UID_LUPD) ") -> INSERT INTO T_CORE_MENU_EX (MENU_ID, MENU_APPS_CODE, MENU_GROUP_LABEL, MENU_GROUP_LABEL_OTH, MENU_NAME, MENU_NAME_OTH, MENU_SEQ, MENU_PATH, MENU_ICON, MENU_PARENT, MENU_STATUS, MENU_DT_CREATE, MENU_UID_CREATE, MENU_DT_LUPD, MENU_UID_LUPD) | N4: =CONCATENATE(" VALUES('",A4,"','",B4,"','",D4,"','",E4,"','",F4,"','",G4,"',",IF(H4="NULL","NULL",CONCATENATE("'",H4,"'")),",",IF(I4="NULL","NULL",CONCATENATE("'",I4,"'")),",",IF(J4="NULL","NULL",CONCATENATE("'",J4,"'")),",",IF(K4="NULL","NULL",CONCATENATE("'",K4,"'")),",'A',NOW(),'SYS',NOW(),'SYS');") -> VALUES('CKT_MA_030000','CKT','Administrations','Administrations','Administrations','Administrations','30000',NULL,'admin_panel_settings',NULL,'A',NOW(),'SYS',NOW(),'SYS'); | O4: =CONCATENATE(M4,N4) -> INSERT INTO T_CORE_MENU_EX (MENU_ID, MENU_APPS_CODE, MENU_GROUP_LABEL, MENU_GROUP_LABEL_OTH, MENU_NAME, MENU_NAME_OTH, MENU_SEQ, MENU_PATH, MENU_ICON, MENU_PARENT, MENU_STATUS, MENU_DT_CREATE, MENU_UID_CREATE, MENU_DT_LUPD, MENU_UID_LUPD) VALUES('CKT_MA_030000','CKT','Administrations','Administrations','Administrations','Administrations','30000',NULL,'admin_panel_settings',NULL,'A',NOW(),'SYS',NOW(),'SYS');
A5: CKT_MA_030100 | B5: CKT | F5: Manage Trucks | G5: Manage Trucks | H5: 30100 | I5: /administrations/truck-management/list | J5: NULL | K5: CKT_MA_030000 | L5: A | M5: =CONCATENATE("INSERT INTO T_CORE_MENU_EX (MENU_ID, MENU_APPS_CODE, MENU_GROUP_LABEL, MENU_GROUP_LABEL_OTH, MENU_NAME, MENU_NAME_OTH, MENU_SEQ, MENU_PATH, MENU_ICON, MENU_PARENT, MENU_STATUS, MENU_DT_CREATE, MENU_UID_CREATE, MENU_DT_LUPD, MENU_UID_LUPD) ") -> INSERT INTO T_CORE_MENU_EX (MENU_ID, MENU_APPS_CODE, MENU_GROUP_LABEL, MENU_GROUP_LABEL_OTH, MENU_NAME, MENU_NAME_OTH, MENU_SEQ, MENU_PATH, MENU_ICON, MENU_PARENT, MENU_STATUS, MENU_DT_CREATE, MENU_UID_CREATE, MENU_DT_LUPD, MENU_UID_LUPD) | N5: =CONCATENATE(" VALUES('",A5,"','",B5,"','",D5,"','",E5,"','",F5,"','",G5,"',",IF(H5="NULL","NULL",CONCATENATE("'",H5,"'")),",",IF(I5="NULL","NULL",CONCATENATE("'",I5,"'")),",",IF(J5="NULL","NULL",CONCATENATE("'",J5,"'")),",",IF(K5="NULL","NULL",CONCATENATE("'",K5,"'")),",'A',NOW(),'SYS',NOW(),'SYS');") -> VALUES('CKT_MA_030100','CKT','','','Manage Trucks','Manage Trucks','30100','/administrations/truck-management/list',NULL,'CKT_MA_030000','A',NOW(),'SYS',NOW(),'SYS'); | O5: =CONCATENATE(M5,N5) -> INSERT INTO T_CORE_MENU_EX (MENU_ID, MENU_APPS_CODE, MENU_GROUP_LABEL, MENU_GROUP_LABEL_OTH, MENU_NAME, MENU_NAME_OTH, MENU_SEQ, MENU_PATH, MENU_ICON, MENU_PARENT, MENU_STATUS, MENU_DT_CREATE, MENU_UID_CREATE, MENU_DT_LUPD, MENU_UID_LUPD) VALUES('CKT_MA_030100','CKT','','','Manage Trucks','Manage Trucks','30100','/administrations/truck-management/list',NULL,'CKT_MA_030000','A',NOW(),'SYS',NOW(),'SYS');
A6: CKT_MA_030200 | B6: CKT | F6: Manage Drivers | G6: Manage Drivers | H6: 30200 | I6: /administrations/driver-management/list | J6: NULL | K6: CKT_MA_030000 | L6: A | M6: =CONCATENATE("INSERT INTO T_CORE_MENU_EX (MENU_ID, MENU_APPS_CODE, MENU_GROUP_LABEL, MENU_GROUP_LABEL_OTH, MENU_NAME, MENU_NAME_OTH, MENU_SEQ, MENU_PATH, MENU_ICON, MENU_PARENT, MENU_STATUS, MENU_DT_CREATE, MENU_UID_CREATE, MENU_DT_LUPD, MENU_UID_LUPD) ") -> INSERT INTO T_CORE_MENU_EX (MENU_ID, MENU_APPS_CODE, MENU_GROUP_LABEL, MENU_GROUP_LABEL_OTH, MENU_NAME, MENU_NAME_OTH, MENU_SEQ, MENU_PATH, MENU_ICON, MENU_PARENT, MENU_STATUS, MENU_DT_CREATE, MENU_UID_CREATE, MENU_DT_LUPD, MENU_UID_LUPD) | N6: =CONCATENATE(" VALUES('",A6,"','",B6,"','",D6,"','",E6,"','",F6,"','",G6,"',",IF(H6="NULL","NULL",CONCATENATE("'",H6,"'")),",",IF(I6="NULL","NULL",CONCATENATE("'",I6,"'")),",",IF(J6="NULL","NULL",CONCATENATE("'",J6,"'")),",",IF(K6="NULL","NULL",CONCATENATE("'",K6,"'")),",'A',NOW(),'SYS',NOW(),'SYS');") -> VALUES('CKT_MA_030200','CKT','','','Manage Drivers','Manage Drivers','30200','/administrations/driver-management/list',NULL,'CKT_MA_030000','A',NOW(),'SYS',NOW(),'SYS'); | O6: =CONCATENATE(M6,N6) -> INSERT INTO T_CORE_MENU_EX (MENU_ID, MENU_APPS_CODE, MENU_GROUP_LABEL, MENU_GROUP_LABEL_OTH, MENU_NAME, MENU_NAME_OTH, MENU_SEQ, MENU_PATH, MENU_ICON, MENU_PARENT, MENU_STATUS, MENU_DT_CREATE, MENU_UID_CREATE, MENU_DT_LUPD, MENU_UID_LUPD) VALUES('CKT_MA_030200','CKT','','','Manage Drivers','Manage Drivers','30200','/administrations/driver-management/list',NULL,'CKT_MA_030000','A',NOW(),'SYS',NOW(),'SYS');
A7: CKT_MA_030300 | B7: CKT | F7: Manage Locations | G7: Manage Locations | H7: 30300 | I7: /administrations/location-management/list | J7: NULL | K7: CKT_MA_030000 | L7: A | M7: =CONCATENATE("INSERT INTO T_CORE_MENU_EX (MENU_ID, MENU_APPS_CODE, MENU_GROUP_LABEL, MENU_GROUP_LABEL_OTH, MENU_NAME, MENU_NAME_OTH, MENU_SEQ, MENU_PATH, MENU_ICON, MENU_PARENT, MENU_STATUS, MENU_DT_CREATE, MENU_UID_CREATE, MENU_DT_LUPD, MENU_UID_LUPD) ") -> INSERT INTO T_CORE_MENU_EX (MENU_ID, MENU_APPS_CODE, MENU_GROUP_LABEL, MENU_GROUP_LABEL_OTH, MENU_NAME, MENU_NAME_OTH, MENU_SEQ, MENU_PATH, MENU_ICON, MENU_PARENT, MENU_STATUS, MENU_DT_CREATE, MENU_UID_CREATE, MENU_DT_LUPD, MENU_UID_LUPD) | N7: =CONCATENATE(" VALUES('",A7,"','",B7,"','",D7,"','",E7,"','",F7,"','",G7,"',",IF(H7="NULL","NULL",CONCATENATE("'",H7,"'")),",",IF(I7="NULL","NULL",CONCATENATE("'",I7,"'")),",",IF(J7="NULL","NULL",CONCATENATE("'",J7,"'")),",",IF(K7="NULL","NULL",CONCATENATE("'",K7,"'")),",'A',NOW(),'SYS',NOW(),'SYS');") -> VALUES('CKT_MA_030300','CKT','','','Manage Locations','Manage Locations','30300','/administrations/location-management/list',NULL,'CKT_MA_030000','A',NOW(),'SYS',NOW(),'SYS'); | O7: =CONCATENATE(M7,N7) -> INSERT INTO T_CORE_MENU_EX (MENU_ID, MENU_APPS_CODE, MENU_GROUP_LABEL, MENU_GROUP_LABEL_OTH, MENU_NAME, MENU_NAME_OTH, MENU_SEQ, MENU_PATH, MENU_ICON, MENU_PARENT, MENU_STATUS, MENU_DT_CREATE, MENU_UID_CREATE, MENU_DT_LUPD, MENU_UID_LUPD) VALUES('CKT_MA_030300','CKT','','','Manage Locations','Manage Locations','30300','/administrations/location-management/list',NULL,'CKT_MA_030000','A',NOW(),'SYS',NOW(),'SYS');
A8: CKT_MA_030400 | B8: CKT | F8: Manage Rentals | G8: Manage Rentals | H8: 30400 | I8: /administrations/rental-management/list | J8: NULL | K8: CKT_MA_030000 | L8: A | M8: =CONCATENATE("INSERT INTO T_CORE_MENU_EX (MENU_ID, MENU_APPS_CODE, MENU_GROUP_LABEL, MENU_GROUP_LABEL_OTH, MENU_NAME, MENU_NAME_OTH, MENU_SEQ, MENU_PATH, MENU_ICON, MENU_PARENT, MENU_STATUS, MENU_DT_CREATE, MENU_UID_CREATE, MENU_DT_LUPD, MENU_UID_LUPD) ") -> INSERT INTO T_CORE_MENU_EX (MENU_ID, MENU_APPS_CODE, MENU_GROUP_LABEL, MENU_GROUP_LABEL_OTH, MENU_NAME, MENU_NAME_OTH, MENU_SEQ, MENU_PATH, MENU_ICON, MENU_PARENT, MENU_STATUS, MENU_DT_CREATE, MENU_UID_CREATE, MENU_DT_LUPD, MENU_UID_LUPD) | N8: =CONCATENATE(" VALUES('",A8,"','",B8,"','",D8,"','",E8,"','",F8,"','",G8,"',",IF(H8="NULL","NULL",CONCATENATE("'",H8,"'")),",",IF(I8="NULL","NULL",CONCATENATE("'",I8,"'")),",",IF(J8="NULL","NULL",CONCATENATE("'",J8,"'")),",",IF(K8="NULL","NULL",CONCATENATE("'",K8,"'")),",'A',NOW(),'SYS',NOW(),'SYS');") -> VALUES('CKT_MA_030400','CKT','','','Manage Rentals','Manage Rentals','30400','/administrations/rental-management/list',NULL,'CKT_MA_030000','A',NOW(),'SYS',NOW(),'SYS'); | O8: =CONCATENATE(M8,N8) -> INSERT INTO T_CORE_MENU_EX (MENU_ID, MENU_APPS_CODE, MENU_GROUP_LABEL, MENU_GROUP_LABEL_OTH, MENU_NAME, MENU_NAME_OTH, MENU_SEQ, MENU_PATH, MENU_ICON, MENU_PARENT, MENU_STATUS, MENU_DT_CREATE, MENU_UID_CREATE, MENU_DT_LUPD, MENU_UID_LUPD) VALUES('CKT_MA_030400','CKT','','','Manage Rentals','Manage Rentals','30400','/administrations/rental-management/list',NULL,'CKT_MA_030000','A',NOW(),'SYS',NOW(),'SYS');
A9: CKT_MA_030500 | B9: CKT | F9: Manage Rate Table | G9: Manage Rate Table | H9: 30500 | I9: /administrations/rateTable-management/list | J9: NULL | K9: CKT_MA_030000 | L9: A | M9: =CONCATENATE("INSERT INTO T_CORE_MENU_EX (MENU_ID, MENU_APPS_CODE, MENU_GROUP_LABEL, MENU_GROUP_LABEL_OTH, MENU_NAME, MENU_NAME_OTH, MENU_SEQ, MENU_PATH, MENU_ICON, MENU_PARENT, MENU_STATUS, MENU_DT_CREATE, MENU_UID_CREATE, MENU_DT_LUPD, MENU_UID_LUPD) ") -> INSERT INTO T_CORE_MENU_EX (MENU_ID, MENU_APPS_CODE, MENU_GROUP_LABEL, MENU_GROUP_LABEL_OTH, MENU_NAME, MENU_NAME_OTH, MENU_SEQ, MENU_PATH, MENU_ICON, MENU_PARENT, MENU_STATUS, MENU_DT_CREATE, MENU_UID_CREATE, MENU_DT_LUPD, MENU_UID_LUPD) | N9: =CONCATENATE(" VALUES('",A9,"','",B9,"','",D9,"','",E9,"','",F9,"','",G9,"',",IF(H9="NULL","NULL",CONCATENATE("'",H9,"'")),",",IF(I9="NULL","NULL",CONCATENATE("'",I9,"'")),",",IF(J9="NULL","NULL",CONCATENATE("'",J9,"'")),",",IF(K9="NULL","NULL",CONCATENATE("'",K9,"'")),",'A',NOW(),'SYS',NOW(),'SYS');") -> VALUES('CKT_MA_030500','CKT','','','Manage Rate Table','Manage Rate Table','30500','/administrations/rateTable-management/list',NULL,'CKT_MA_030000','A',NOW(),'SYS',NOW(),'SYS'); | O9: =CONCATENATE(M9,N9) -> INSERT INTO T_CORE_MENU_EX (MENU_ID, MENU_APPS_CODE, MENU_GROUP_LABEL, MENU_GROUP_LABEL_OTH, MENU_NAME, MENU_NAME_OTH, MENU_SEQ, MENU_PATH, MENU_ICON, MENU_PARENT, MENU_STATUS, MENU_DT_CREATE, MENU_UID_CREATE, MENU_DT_LUPD, MENU_UID_LUPD) VALUES('CKT_MA_030500','CKT','','','Manage Rate Table','Manage Rate Table','30500','/administrations/rateTable-management/list',NULL,'CKT_MA_030000','A',NOW(),'SYS',NOW(),'SYS');
A10: CKT_MA_030600 | B10: CKT | F10: Live Monitoring | G10: Live Monitoring | H10: 30600 | I10: /administrations/live-monitoring | J10: NULL | K10: CKT_MA_030000 | L10: A | M10: =CONCATENATE("INSERT INTO T_CORE_MENU_EX (MENU_ID, MENU_APPS_CODE, MENU_GROUP_LABEL, MENU_GROUP_LABEL_OTH, MENU_NAME, MENU_NAME_OTH, MENU_SEQ, MENU_PATH, MENU_ICON, MENU_PARENT, MENU_STATUS, MENU_DT_CREATE, MENU_UID_CREATE, MENU_DT_LUPD, MENU_UID_LUPD) ") -> INSERT INTO T_CORE_MENU_EX (MENU_ID, MENU_APPS_CODE, MENU_GROUP_LABEL, MENU_GROUP_LABEL_OTH, MENU_NAME, MENU_NAME_OTH, MENU_SEQ, MENU_PATH, MENU_ICON, MENU_PARENT, MENU_STATUS, MENU_DT_CREATE, MENU_UID_CREATE, MENU_DT_LUPD, MENU_UID_LUPD) | N10: =CONCATENATE(" VALUES('",A10,"','",B10,"','",D10,"','",E10,"','",F10,"','",G10,"',",IF(H10="NULL","NULL",CONCATENATE("'",H10,"'")),",",IF(I10="NULL","NULL",CONCATENATE("'",I10,"'")),",",IF(J10="NULL","NULL",CONCATENATE("'",J10,"'")),",",IF(K10="NULL","NULL",CONCATENATE("'",K10,"'")),",'A',NOW(),'SYS',NOW(),'SYS');") -> VALUES('CKT_MA_030600','CKT','','','Live Monitoring','Live Monitoring','30600','/administrations/live-monitoring',NULL,'CKT_MA_030000','A',NOW(),'SYS',NOW(),'SYS'); | O10: =CONCATENATE(M10,N10) -> INSERT INTO T_CORE_MENU_EX (MENU_ID, MENU_APPS_CODE, MENU_GROUP_LABEL, MENU_GROUP_LABEL_OTH, MENU_NAME, MENU_NAME_OTH, MENU_SEQ, MENU_PATH, MENU_ICON, MENU_PARENT, MENU_STATUS, MENU_DT_CREATE, MENU_UID_CREATE, MENU_DT_LUPD, MENU_UID_LUPD) VALUES('CKT_MA_030600','CKT','','','Live Monitoring','Live Monitoring','30600','/administrations/live-monitoring',NULL,'CKT_MA_030000','A',NOW(),'SYS',NOW(),'SYS');
A11: CKT_MA_030700 | B11: CKT | F11: Historical Monitoring | G11: Historical Monitoring | H11: 30700 | I11: /administrations/historical-monitoring | J11: NULL | K11: CKT_MA_030000 | L11: A | M11: =CONCATENATE("INSERT INTO T_CORE_MENU_EX (MENU_ID, MENU_APPS_CODE, MENU_GROUP_LABEL, MENU_GROUP_LABEL_OTH, MENU_NAME, MENU_NAME_OTH, MENU_SEQ, MENU_PATH, MENU_ICON, MENU_PARENT, MENU_STATUS, MENU_DT_CREATE, MENU_UID_CREATE, MENU_DT_LUPD, MENU_UID_LUPD) ") -> INSERT INTO T_CORE_MENU_EX (MENU_ID, MENU_APPS_CODE, MENU_GROUP_LABEL, MENU_GROUP_LABEL_OTH, MENU_NAME, MENU_NAME_OTH, MENU_SEQ, MENU_PATH, MENU_ICON, MENU_PARENT, MENU_STATUS, MENU_DT_CREATE, MENU_UID_CREATE, MENU_DT_LUPD, MENU_UID_LUPD) | N11: =CONCATENATE(" VALUES('",A11,"','",B11,"','",D11,"','",E11,"','",F11,"','",G11,"',",IF(H11="NULL","NULL",CONCATENATE("'",H11,"'")),",",IF(I11="NULL","NULL",CONCATENATE("'",I11,"'")),",",IF(J11="NULL","NULL",CONCATENATE("'",J11,"'")),",",IF(K11="NULL","NULL",CONCATENATE("'",K11,"'")),",'A',NOW(),'SYS',NOW(),'SYS');") -> VALUES('CKT_MA_030700','CKT','','','Historical Monitoring','Historical Monitoring','30700','/administrations/historical-monitoring',NULL,'CKT_MA_030000','A',NOW(),'SYS',NOW(),'SYS'); | O11: =CONCATENATE(M11,N11) -> INSERT INTO T_CORE_MENU_EX (MENU_ID, MENU_APPS_CODE, MENU_GROUP_LABEL, MENU_GROUP_LABEL_OTH, MENU_NAME, MENU_NAME_OTH, MENU_SEQ, MENU_PATH, MENU_ICON, MENU_PARENT, MENU_STATUS, MENU_DT_CREATE, MENU_UID_CREATE, MENU_DT_LUPD, MENU_UID_LUPD) VALUES('CKT_MA_030700','CKT','','','Historical Monitoring','Historical Monitoring','30700','/administrations/historical-monitoring',NULL,'CKT_MA_030000','A',NOW(),'SYS',NOW(),'SYS');
A12: CKT_MA_030800 | B12: CKT | F12: Truck Performance | G12: Truck Performance | H12: 30800 | I12: /administrations/trackTrackEnterExit/list | J12: NULL | K12: CKT_MA_030000 | L12: A | M12: =CONCATENATE("INSERT INTO T_CORE_MENU_EX (MENU_ID, MENU_APPS_CODE, MENU_GROUP_LABEL, MENU_GROUP_LABEL_OTH, MENU_NAME, MENU_NAME_OTH, MENU_SEQ, MENU_PATH, MENU_ICON, MENU_PARENT, MENU_STATUS, MENU_DT_CREATE, MENU_UID_CREATE, MENU_DT_LUPD, MENU_UID_LUPD) ") -> INSERT INTO T_CORE_MENU_EX (MENU_ID, MENU_APPS_CODE, MENU_GROUP_LABEL, MENU_GROUP_LABEL_OTH, MENU_NAME, MENU_NAME_OTH, MENU_SEQ, MENU_PATH, MENU_ICON, MENU_PARENT, MENU_STATUS, MENU_DT_CREATE, MENU_UID_CREATE, MENU_DT_LUPD, MENU_UID_LUPD) | N12: =CONCATENATE(" VALUES('",A12,"','",B12,"','",D12,"','",E12,"','",F12,"','",G12,"',",IF(H12="NULL","NULL",CONCATENATE("'",H12,"'")),",",IF(I12="NULL","NULL",CONCATENATE("'",I12,"'")),",",IF(J12="NULL","NULL",CONCATENATE("'",J12,"'")),",",IF(K12="NULL","NULL",CONCATENATE("'",K12,"'")),",'A',NOW(),'SYS',NOW(),'SYS');") -> VALUES('CKT_MA_030800','CKT','','','Truck Performance','Truck Performance','30800','/administrations/trackTrackEnterExit/list',NULL,'CKT_MA_030000','A',NOW(),'SYS',NOW(),'SYS'); | O12: =CONCATENATE(M12,N12) -> INSERT INTO T_CORE_MENU_EX (MENU_ID, MENU_APPS_CODE, MENU_GROUP_LABEL, MENU_GROUP_LABEL_OTH, MENU_NAME, MENU_NAME_OTH, MENU_SEQ, MENU_PATH, MENU_ICON, MENU_PARENT, MENU_STATUS, MENU_DT_CREATE, MENU_UID_CREATE, MENU_DT_LUPD, MENU_UID_LUPD) VALUES('CKT_MA_030800','CKT','','','Truck Performance','Truck Performance','30800','/administrations/trackTrackEnterExit/list',NULL,'CKT_MA_030000','A',NOW(),'SYS',NOW(),'SYS');
A13: CKT_MA_030900 | B13: CKT | F13: Manage Chassis | G13: Manage Chassis | H13: 30900 | I13: /administrations/chassis-management/list | J13: NULL | K13: CKT_MA_030000 | L13: A | M13: =CONCATENATE("INSERT INTO T_CORE_MENU_EX (MENU_ID, MENU_APPS_CODE, MENU_GROUP_LABEL, MENU_GROUP_LABEL_OTH, MENU_NAME, MENU_NAME_OTH, MENU_SEQ, MENU_PATH, MENU_ICON, MENU_PARENT, MENU_STATUS, MENU_DT_CREATE, MENU_UID_CREATE, MENU_DT_LUPD, MENU_UID_LUPD) ") -> INSERT INTO T_CORE_MENU_EX (MENU_ID, MENU_APPS_CODE, MENU_GROUP_LABEL, MENU_GROUP_LABEL_OTH, MENU_NAME, MENU_NAME_OTH, MENU_SEQ, MENU_PATH, MENU_ICON, MENU_PARENT, MENU_STATUS, MENU_DT_CREATE, MENU_UID_CREATE, MENU_DT_LUPD, MENU_UID_LUPD) | N13: =CONCATENATE(" VALUES('",A13,"','",B13,"','",D13,"','",E13,"','",F13,"','",G13,"',",IF(H13="NULL","NULL",CONCATENATE("'",H13,"'")),",",IF(I13="NULL","NULL",CONCATENATE("'",I13,"'")),",",IF(J13="NULL","NULL",CONCATENATE("'",J13,"'")),",",IF(K13="NULL","NULL",CONCATENATE("'",K13,"'")),",'A',NOW(),'SYS',NOW(),'SYS');") -> VALUES('CKT_MA_030900','CKT','','','Manage Chassis','Manage Chassis','30900','/administrations/chassis-management/list',NULL,'CKT_MA_030000','A',NOW(),'SYS',NOW(),'SYS'); | O13: =CONCATENATE(M13,N13) -> INSERT INTO T_CORE_MENU_EX (MENU_ID, MENU_APPS_CODE, MENU_GROUP_LABEL, MENU_GROUP_LABEL_OTH, MENU_NAME, MENU_NAME_OTH, MENU_SEQ, MENU_PATH, MENU_ICON, MENU_PARENT, MENU_STATUS, MENU_DT_CREATE, MENU_UID_CREATE, MENU_DT_LUPD, MENU_UID_LUPD) VALUES('CKT_MA_030900','CKT','','','Manage Chassis','Manage Chassis','30900','/administrations/chassis-management/list',NULL,'CKT_MA_030000','A',NOW(),'SYS',NOW(),'SYS');
A14: CKT_AA_050000 | B14: CKT | D14: Account Administration | E14: Account Administration | F14: Account Administration | G14: Account Administration | H14: 50000 | I14: NULL | J14: manage_accounts | K14: NULL | L14: A | M14: =CONCATENATE("INSERT INTO T_CORE_MENU_EX (MENU_ID, MENU_APPS_CODE, MENU_GROUP_LABEL, MENU_GROUP_LABEL_OTH, MENU_NAME, MENU_NAME_OTH, MENU_SEQ, MENU_PATH, MENU_ICON, MENU_PARENT, MENU_STATUS, MENU_DT_CREATE, MENU_UID_CREATE, MENU_DT_LUPD, MENU_UID_LUPD) ") -> INSERT INTO T_CORE_MENU_EX (MENU_ID, MENU_APPS_CODE, MENU_GROUP_LABEL, MENU_GROUP_LABEL_OTH, MENU_NAME, MENU_NAME_OTH, MENU_SEQ, MENU_PATH, MENU_ICON, MENU_PARENT, MENU_STATUS, MENU_DT_CREATE, MENU_UID_CREATE, MENU_DT_LUPD, MENU_UID_LUPD) | N14: =CONCATENATE(" VALUES('",A14,"','",B14,"','",D14,"','",E14,"','",F14,"','",G14,"',",IF(H14="NULL","NULL",CONCATENATE("'",H14,"'")),",",IF(I14="NULL","NULL",CONCATENATE("'",I14,"'")),",",IF(J14="NULL","NULL",CONCATENATE("'",J14,"'")),",",IF(K14="NULL","NULL",CONCATENATE("'",K14,"'")),",'A',NOW(),'SYS',NOW(),'SYS');") -> VALUES('CKT_AA_050000','CKT','Account Administration','Account Administration','Account Administration','Account Administration','50000',NULL,'manage_accounts',NULL,'A',NOW(),'SYS',NOW(),'SYS'); | O14: =CONCATENATE(M14,N14) -> INSERT INTO T_CORE_MENU_EX (MENU_ID, MENU_APPS_CODE, MENU_GROUP_LABEL, MENU_GROUP_LABEL_OTH, MENU_NAME, MENU_NAME_OTH, MENU_SEQ, MENU_PATH, MENU_ICON, MENU_PARENT, MENU_STATUS, MENU_DT_CREATE, MENU_UID_CREATE, MENU_DT_LUPD, MENU_UID_LUPD) VALUES('CKT_AA_050000','CKT','Account Administration','Account Administration','Account Administration','Account Administration','50000',NULL,'manage_accounts',NULL,'A',NOW(),'SYS',NOW(),'SYS');
A15: CKT_AA_050100 | B15: CKT | F15: Account Profile | G15: Account Profile | H15: 50100 | I15: /account/profile | J15: NULL | K15: CKT_AA_050000 | L15: A | M15: =CONCATENATE("INSERT INTO T_CORE_MENU_EX (MENU_ID, MENU_APPS_CODE, MENU_GROUP_LABEL, MENU_GROUP_LABEL_OTH, MENU_NAME, MENU_NAME_OTH, MENU_SEQ, MENU_PATH, MENU_ICON, MENU_PARENT, MENU_STATUS, MENU_DT_CREATE, MENU_UID_CREATE, MENU_DT_LUPD, MENU_UID_LUPD) ") -> INSERT INTO T_CORE_MENU_EX (MENU_ID, MENU_APPS_CODE, MENU_GROUP_LABEL, MENU_GROUP_LABEL_OTH, MENU_NAME, MENU_NAME_OTH, MENU_SEQ, MENU_PATH, MENU_ICON, MENU_PARENT, MENU_STATUS, MENU_DT_CREATE, MENU_UID_CREATE, MENU_DT_LUPD, MENU_UID_LUPD) | N15: =CONCATENATE(" VALUES('",A15,"','",B15,"','",D15,"','",E15,"','",F15,"','",G15,"',",IF(H15="NULL","NULL",CONCATENATE("'",H15,"'")),",",IF(I15="NULL","NULL",CONCATENATE("'",I15,"'")),",",IF(J15="NULL","NULL",CONCATENATE("'",J15,"'")),",",IF(K15="NULL","NULL",CONCATENATE("'",K15,"'")),",'A',NOW(),'SYS',NOW(),'SYS');") -> VALUES('CKT_AA_050100','CKT','','','Account Profile','Account Profile','50100','/account/profile',NULL,'CKT_AA_050000','A',NOW(),'SYS',NOW(),'SYS'); | O15: =CONCATENATE(M15,N15) -> INSERT INTO T_CORE_MENU_EX (MENU_ID, MENU_APPS_CODE, MENU_GROUP_LABEL, MENU_GROUP_LABEL_OTH, MENU_NAME, MENU_NAME_OTH, MENU_SEQ, MENU_PATH, MENU_ICON, MENU_PARENT, MENU_STATUS, MENU_DT_CREATE, MENU_UID_CREATE, MENU_DT_LUPD, MENU_UID_LUPD) VALUES('CKT_AA_050100','CKT','','','Account Profile','Account Profile','50100','/account/profile',NULL,'CKT_AA_050000','A',NOW(),'SYS',NOW(),'SYS');
A16: CKT_AA_050200 | B16: CKT | F16: Manage Users | G16: Manage Users | H16: 50200 | I16: /account/users | J16: NULL | K16: CKT_AA_050000 | L16: A | M16: =CONCATENATE("INSERT INTO T_CORE_MENU_EX (MENU_ID, MENU_APPS_CODE, MENU_GROUP_LABEL, MENU_GROUP_LABEL_OTH, MENU_NAME, MENU_NAME_OTH, MENU_SEQ, MENU_PATH, MENU_ICON, MENU_PARENT, MENU_STATUS, MENU_DT_CREATE, MENU_UID_CREATE, MENU_DT_LUPD, MENU_UID_LUPD) ") -> INSERT INTO T_CORE_MENU_EX (MENU_ID, MENU_APPS_CODE, MENU_GROUP_LABEL, MENU_GROUP_LABEL_OTH, MENU_NAME, MENU_NAME_OTH, MENU_SEQ, MENU_PATH, MENU_ICON, MENU_PARENT, MENU_STATUS, MENU_DT_CREATE, MENU_UID_CREATE, MENU_DT_LUPD, MENU_UID_LUPD) | N16: =CONCATENATE(" VALUES('",A16,"','",B16,"','",D16,"','",E16,"','",F16,"','",G16,"',",IF(H16="NULL","NULL",CONCATENATE("'",H16,"'")),",",IF(I16="NULL","NULL",CONCATENATE("'",I16,"'")),",",IF(J16="NULL","NULL",CONCATENATE("'",J16,"'")),",",IF(K16="NULL","NULL",CONCATENATE("'",K16,"'")),",'A',NOW(),'SYS',NOW(),'SYS');") -> VALUES('CKT_AA_050200','CKT','','','Manage Users','Manage Users','50200','/account/users',NULL,'CKT_AA_050000','A',NOW(),'SYS',NOW(),'SYS'); | O16: =CONCATENATE(M16,N16) -> INSERT INTO T_CORE_MENU_EX (MENU_ID, MENU_APPS_CODE, MENU_GROUP_LABEL, MENU_GROUP_LABEL_OTH, MENU_NAME, MENU_NAME_OTH, MENU_SEQ, MENU_PATH, MENU_ICON, MENU_PARENT, MENU_STATUS, MENU_DT_CREATE, MENU_UID_CREATE, MENU_DT_LUPD, MENU_UID_LUPD) VALUES('CKT_AA_050200','CKT','','','Manage Users','Manage Users','50200','/account/users',NULL,'CKT_AA_050000','A',NOW(),'SYS',NOW(),'SYS');
A17: CKT_AA_050300 | B17: CKT | F17: Manage Cargo Owners | G17: Manage Cargo Owners | H17: 50300 | I17: /manageAccountsFfCo/all/list | J17: NULL | K17: CKT_AA_050000 | L17: A | M17: =CONCATENATE("INSERT INTO T_CORE_MENU_EX (MENU_ID, MENU_APPS_CODE, MENU_GROUP_LABEL, MENU_GROUP_LABEL_OTH, MENU_NAME, MENU_NAME_OTH, MENU_SEQ, MENU_PATH, MENU_ICON, MENU_PARENT, MENU_STATUS, MENU_DT_CREATE, MENU_UID_CREATE, MENU_DT_LUPD, MENU_UID_LUPD) ") -> INSERT INTO T_CORE_MENU_EX (MENU_ID, MENU_APPS_CODE, MENU_GROUP_LABEL, MENU_GROUP_LABEL_OTH, MENU_NAME, MENU_NAME_OTH, MENU_SEQ, MENU_PATH, MENU_ICON, MENU_PARENT, MENU_STATUS, MENU_DT_CREATE, MENU_UID_CREATE, MENU_DT_LUPD, MENU_UID_LUPD) | N17: =CONCATENATE(" VALUES('",A17,"','",B17,"','",D17,"','",E17,"','",F17,"','",G17,"',",IF(H17="NULL","NULL", CONCATENATE("'",H17,"'")),",",IF(I17="NULL","NULL", CONCATENATE("'",I17,"'")),",",IF(J17="NULL","NULL", CONCATENATE("'",J17,"'")),",",IF(K17="NULL","NULL", CONCATENATE("'",K17,"'")),",'A',NOW(),'SYS',NOW(),'SYS');") -> VALUES('CKT_AA_050300','CKT','','','Manage Cargo Owners','Manage Cargo Owners','50300','/manageAccountsFfCo/all/list',NULL,'CKT_AA_050000','A',NOW(),'SYS',NOW(),'SYS'); | O17: =CONCATENATE(M17,N17) -> INSERT INTO T_CORE_MENU_EX (MENU_ID, MENU_APPS_CODE, MENU_GROUP_LABEL, MENU_GROUP_LABEL_OTH, MENU_NAME, MENU_NAME_OTH, MENU_SEQ, MENU_PATH, MENU_ICON, MENU_PARENT, MENU_STATUS, MENU_DT_CREATE, MENU_UID_CREATE, MENU_DT_LUPD, MENU_UID_LUPD) VALUES('CKT_AA_050300','CKT','','','Manage Cargo Owners','Manage Cargo Owners','50300','/manageAccountsFfCo/all/list',NULL,'CKT_AA_050000','A',NOW(),'SYS',NOW(),'SYS');
A18: CKT_MH_090000 | B18: CKT | D18: Help | E18: Help | F18: Help | G18: Help | H18: 90000 | I18: /help | J18: help | K18: NULL | L18: A | M18: =CONCATENATE("INSERT INTO T_CORE_MENU_EX (MENU_ID, MENU_APPS_CODE, MENU_GROUP_LABEL, MENU_GROUP_LABEL_OTH, MENU_NAME, MENU_NAME_OTH, MENU_SEQ, MENU_PATH, MENU_ICON, MENU_PARENT, MENU_STATUS, MENU_DT_CREATE, MENU_UID_CREATE, MENU_DT_LUPD, MENU_UID_LUPD) ") -> INSERT INTO T_CORE_MENU_EX (MENU_ID, MENU_APPS_CODE, MENU_GROUP_LABEL, MENU_GROUP_LABEL_OTH, MENU_NAME, MENU_NAME_OTH, MENU_SEQ, MENU_PATH, MENU_ICON, MENU_PARENT, MENU_STATUS, MENU_DT_CREATE, MENU_UID_CREATE, MENU_DT_LUPD, MENU_UID_LUPD) | N18: =CONCATENATE(" VALUES('",A18,"','",B18,"','",D18,"','",E18,"','",F18,"','",G18,"',",IF(H18="NULL","NULL",CONCATENATE("'",H18,"'")),",",IF(I18="NULL","NULL",CONCATENATE("'",I18,"'")),",",IF(J18="NULL","NULL",CONCATENATE("'",J18,"'")),",",IF(K18="NULL","NULL",CONCATENATE("'",K18,"'")),",'A',NOW(),'SYS',NOW(),'SYS');") -> VALUES('CKT_MH_090000','CKT','Help','Help','Help','Help','90000','/help','help',NULL,'A',NOW(),'SYS',NOW(),'SYS'); | O18: =CONCATENATE(M18,N18) -> INSERT INTO T_CORE_MENU_EX (MENU_ID, MENU_APPS_CODE, MENU_GROUP_LABEL, MENU_GROUP_LABEL_OTH, MENU_NAME, MENU_NAME_OTH, MENU_SEQ, MENU_PATH, MENU_ICON, MENU_PARENT, MENU_STATUS, MENU_DT_CREATE, MENU_UID_CREATE, MENU_DT_LUPD, MENU_UID_LUPD) VALUES('CKT_MH_090000','CKT','Help','Help','Help','Help','90000','/help','help',NULL,'A',NOW(),'SYS',NOW(),'SYS');
A19: CKT_FA_060000 | B19: CKT | C19: SP Finance Admin | D19: Finance Administration | E19: Finance Administration | F19: Finance Administration | G19: Finance Administration | H19: 60000 | I19: NULL | J19: account_balance | K19: NULL | L19: A | M19: =CONCATENATE("INSERT INTO T_CORE_MENU_EX (MENU_ID, MENU_APPS_CODE, MENU_GROUP_LABEL, MENU_GROUP_LABEL_OTH, MENU_NAME, MENU_NAME_OTH, MENU_SEQ, MENU_PATH, MENU_ICON, MENU_PARENT, MENU_STATUS, MENU_DT_CREATE, MENU_UID_CREATE, MENU_DT_LUPD, MENU_UID_LUPD) ") -> INSERT INTO T_CORE_MENU_EX (MENU_ID, MENU_APPS_CODE, MENU_GROUP_LABEL, MENU_GROUP_LABEL_OTH, MENU_NAME, MENU_NAME_OTH, MENU_SEQ, MENU_PATH, MENU_ICON, MENU_PARENT, MENU_STATUS, MENU_DT_CREATE, MENU_UID_CREATE, MENU_DT_LUPD, MENU_UID_LUPD) | N19: =CONCATENATE(" VALUES('",A19,"','",B19,"','",D19,"','",E19,"','",F19,"','",G19,"',",IF(H19="NULL","NULL",CONCATENATE("'",H19,"'")),",",IF(I19="NULL","NULL",CONCATENATE("'",I19,"'")),",",IF(J19="NULL","NULL",CONCATENATE("'",J19,"'")),",",IF(K19="NULL","NULL",CONCATENATE("'",K19,"'")),",'A',NOW(),'SYS',NOW(),'SYS');") -> VALUES('CKT_FA_060000','CKT','Finance Administration','Finance Administration','Finance Administration','Finance Administration','60000',NULL,'account_balance',NULL,'A',NOW(),'SYS',NOW(),'SYS'); | O19: =CONCATENATE(M19,N19) -> INSERT INTO T_CORE_MENU_EX (MENU_ID, MENU_APPS_CODE, MENU_GROUP_LABEL, MENU_GROUP_LABEL_OTH, MENU_NAME, MENU_NAME_OTH, MENU_SEQ, MENU_PATH, MENU_ICON, MENU_PARENT, MENU_STATUS, MENU_DT_CREATE, MENU_UID_CREATE, MENU_DT_LUPD, MENU_UID_LUPD) VALUES('CKT_FA_060000','CKT','Finance Administration','Finance Administration','Finance Administration','Finance Administration','60000',NULL,'account_balance',NULL,'A',NOW(),'SYS',NOW(),'SYS');
A20: CKT_FA_060100 | B20: CKT | F20: Sage Excel Report | G20: Sage Excel Report | H20: 60100 | I20: /manage/sage/excel | J20: NULL | K20: CKT_FA_060000 | L20: A | M20: =CONCATENATE("INSERT INTO T_CORE_MENU_EX (MENU_ID, MENU_APPS_CODE, MENU_GROUP_LABEL, MENU_GROUP_LABEL_OTH, MENU_NAME, MENU_NAME_OTH, MENU_SEQ, MENU_PATH, MENU_ICON, MENU_PARENT, MENU_STATUS, MENU_DT_CREATE, MENU_UID_CREATE, MENU_DT_LUPD, MENU_UID_LUPD) ") -> INSERT INTO T_CORE_MENU_EX (MENU_ID, MENU_APPS_CODE, MENU_GROUP_LABEL, MENU_GROUP_LABEL_OTH, MENU_NAME, MENU_NAME_OTH, MENU_SEQ, MENU_PATH, MENU_ICON, MENU_PARENT, MENU_STATUS, MENU_DT_CREATE, MENU_UID_CREATE, MENU_DT_LUPD, MENU_UID_LUPD) | N20: =CONCATENATE(" VALUES('",A20,"','",B20,"','",D20,"','",E20,"','",F20,"','",G20,"',",IF(H20="NULL","NULL",CONCATENATE("'",H20,"'")),",",IF(I20="NULL","NULL",CONCATENATE("'",I20,"'")),",",IF(J20="NULL","NULL",CONCATENATE("'",J20,"'")),",",IF(K20="NULL","NULL",CONCATENATE("'",K20,"'")),",'A',NOW(),'SYS',NOW(),'SYS');") -> VALUES('CKT_FA_060100','CKT','','','Sage Excel Report','Sage Excel Report','60100','/manage/sage/excel',NULL,'CKT_FA_060000','A',NOW(),'SYS',NOW(),'SYS'); | O20: =CONCATENATE(M20,N20) -> INSERT INTO T_CORE_MENU_EX (MENU_ID, MENU_APPS_CODE, MENU_GROUP_LABEL, MENU_GROUP_LABEL_OTH, MENU_NAME, MENU_NAME_OTH, MENU_SEQ, MENU_PATH, MENU_ICON, MENU_PARENT, MENU_STATUS, MENU_DT_CREATE, MENU_UID_CREATE, MENU_DT_LUPD, MENU_UID_LUPD) VALUES('CKT_FA_060100','CKT','','','Sage Excel Report','Sage Excel Report','60100','/manage/sage/excel',NULL,'CKT_FA_060000','A',NOW(),'SYS',NOW(),'SYS');
A21: CKT_FA_060200 | B21: CKT | F21: Manage Sage Tax No. | G21: Manage Sage Tax No. | H21: 60200 | I21: /manage/sage/tax | J21: NULL | K21: CKT_FA_060000 | L21: A | M21: =CONCATENATE("INSERT INTO T_CORE_MENU_EX (MENU_ID, MENU_APPS_CODE, MENU_GROUP_LABEL, MENU_GROUP_LABEL_OTH, MENU_NAME, MENU_NAME_OTH, MENU_SEQ, MENU_PATH, MENU_ICON, MENU_PARENT, MENU_STATUS, MENU_DT_CREATE, MENU_UID_CREATE, MENU_DT_LUPD, MENU_UID_LUPD) ") -> INSERT INTO T_CORE_MENU_EX (MENU_ID, MENU_APPS_CODE, MENU_GROUP_LABEL, MENU_GROUP_LABEL_OTH, MENU_NAME, MENU_NAME_OTH, MENU_SEQ, MENU_PATH, MENU_ICON, MENU_PARENT, MENU_STATUS, MENU_DT_CREATE, MENU_UID_CREATE, MENU_DT_LUPD, MENU_UID_LUPD) | N21: =CONCATENATE(" VALUES('",A21,"','",B21,"','",D21,"','",E21,"','",F21,"','",G21,"',",IF(H21="NULL","NULL",CONCATENATE("'",H21,"'")),",",IF(I21="NULL","NULL",CONCATENATE("'",I21,"'")),",",IF(J21="NULL","NULL",CONCATENATE("'",J21,"'")),",",IF(K21="NULL","NULL",CONCATENATE("'",K21,"'")),",'A',NOW(),'SYS',NOW(),'SYS');") -> VALUES('CKT_FA_060200','CKT','','','Manage Sage Tax No.','Manage Sage Tax No.','60200','/manage/sage/tax',NULL,'CKT_FA_060000','A',NOW(),'SYS',NOW(),'SYS'); | O21: =CONCATENATE(M21,N21) -> INSERT INTO T_CORE_MENU_EX (MENU_ID, MENU_APPS_CODE, MENU_GROUP_LABEL, MENU_GROUP_LABEL_OTH, MENU_NAME, MENU_NAME_OTH, MENU_SEQ, MENU_PATH, MENU_ICON, MENU_PARENT, MENU_STATUS, MENU_DT_CREATE, MENU_UID_CREATE, MENU_DT_LUPD, MENU_UID_LUPD) VALUES('CKT_FA_060200','CKT','','','Manage Sage Tax No.','Manage Sage Tax No.','60200','/manage/sage/tax',NULL,'CKT_FA_060000','A',NOW(),'SYS',NOW(),'SYS');
A22: CKT_FN_070000 | B22: CKT | C22: SP Finance | D22: Finance | E22: Finance | F22: Finance | G22: Finance | H22: 70000 | I22: NULL | J22: account_balance | K22: NULL | L22: A | M22: =CONCATENATE("INSERT INTO T_CORE_MENU_EX (MENU_ID, MENU_APPS_CODE, MENU_GROUP_LABEL, MENU_GROUP_LABEL_OTH, MENU_NAME, MENU_NAME_OTH, MENU_SEQ, MENU_PATH, MENU_ICON, MENU_PARENT, MENU_STATUS, MENU_DT_CREATE, MENU_UID_CREATE, MENU_DT_LUPD, MENU_UID_LUPD) ") -> INSERT INTO T_CORE_MENU_EX (MENU_ID, MENU_APPS_CODE, MENU_GROUP_LABEL, MENU_GROUP_LABEL_OTH, MENU_NAME, MENU_NAME_OTH, MENU_SEQ, MENU_PATH, MENU_ICON, MENU_PARENT, MENU_STATUS, MENU_DT_CREATE, MENU_UID_CREATE, MENU_DT_LUPD, MENU_UID_LUPD) | N22: =CONCATENATE(" VALUES('",A22,"','",B22,"','",D22,"','",E22,"','",F22,"','",G22,"',",IF(H22="NULL","NULL",CONCATENATE("'",H22,"'")),",",IF(I22="NULL","NULL",CONCATENATE("'",I22,"'")),",",IF(J22="NULL","NULL",CONCATENATE("'",J22,"'")),",",IF(K22="NULL","NULL",CONCATENATE("'",K22,"'")),",'A',NOW(),'SYS',NOW(),'SYS');") -> VALUES('CKT_FN_070000','CKT','Finance','Finance','Finance','Finance','70000',NULL,'account_balance',NULL,'A',NOW(),'SYS',NOW(),'SYS'); | O22: =CONCATENATE(M22,N22) -> INSERT INTO T_CORE_MENU_EX (MENU_ID, MENU_APPS_CODE, MENU_GROUP_LABEL, MENU_GROUP_LABEL_OTH, MENU_NAME, MENU_NAME_OTH, MENU_SEQ, MENU_PATH, MENU_ICON, MENU_PARENT, MENU_STATUS, MENU_DT_CREATE, MENU_UID_CREATE, MENU_DT_LUPD, MENU_UID_LUPD) VALUES('CKT_FN_070000','CKT','Finance','Finance','Finance','Finance','70000',NULL,'account_balance',NULL,'A',NOW(),'SYS',NOW(),'SYS');
A23: CKT_FN_070100 | B23: CKT | F23: Rate Table Management | G23: Rate Table Management | H23: 70100 | I23: /manage/ratetable | J23: NULL | K23: CKT_FN_070000 | L23: A | M23: =CONCATENATE("INSERT INTO T_CORE_MENU_EX (MENU_ID, MENU_APPS_CODE, MENU_GROUP_LABEL, MENU_GROUP_LABEL_OTH, MENU_NAME, MENU_NAME_OTH, MENU_SEQ, MENU_PATH, MENU_ICON, MENU_PARENT, MENU_STATUS, MENU_DT_CREATE, MENU_UID_CREATE, MENU_DT_LUPD, MENU_UID_LUPD) ") -> INSERT INTO T_CORE_MENU_EX (MENU_ID, MENU_APPS_CODE, MENU_GROUP_LABEL, MENU_GROUP_LABEL_OTH, MENU_NAME, MENU_NAME_OTH, MENU_SEQ, MENU_PATH, MENU_ICON, MENU_PARENT, MENU_STATUS, MENU_DT_CREATE, MENU_UID_CREATE, MENU_DT_LUPD, MENU_UID_LUPD) | N23: =CONCATENATE(" VALUES('",A23,"','",B23,"','",D23,"','",E23,"','",F23,"','",G23,"',",IF(H23="NULL","NULL",CONCATENATE("'",H23,"'")),",",IF(I23="NULL","NULL",CONCATENATE("'",I23,"'")),",",IF(J23="NULL","NULL",CONCATENATE("'",J23,"'")),",",IF(K23="NULL","NULL",CONCATENATE("'",K23,"'")),",'A',NOW(),'SYS',NOW(),'SYS');") -> VALUES('CKT_FN_070100','CKT','','','Rate Table Management','Rate Table Management','70100','/manage/ratetable',NULL,'CKT_FN_070000','A',NOW(),'SYS',NOW(),'SYS'); | O23: =CONCATENATE(M23,N23) -> INSERT INTO T_CORE_MENU_EX (MENU_ID, MENU_APPS_CODE, MENU_GROUP_LABEL, MENU_GROUP_LABEL_OTH, MENU_NAME, MENU_NAME_OTH, MENU_SEQ, MENU_PATH, MENU_ICON, MENU_PARENT, MENU_STATUS, MENU_DT_CREATE, MENU_UID_CREATE, MENU_DT_LUPD, MENU_UID_LUPD) VALUES('CKT_FN_070100','CKT','','','Rate Table Management','Rate Table Management','70100','/manage/ratetable',NULL,'CKT_FN_070000','A',NOW(),'SYS',NOW(),'SYS');
A24: CKT_FN_070200 | B24: CKT | F24: Contract Requests | G24: Contract Requests | H24: 70200 | I24: /opadmin/contractrequest/list | J24: NULL | K24: CKT_FN_070000 | L24: A | M24: =CONCATENATE("INSERT INTO T_CORE_MENU_EX (MENU_ID, MENU_APPS_CODE, MENU_GROUP_LABEL, MENU_GROUP_LABEL_OTH, MENU_NAME, MENU_NAME_OTH, MENU_SEQ, MENU_PATH, MENU_ICON, MENU_PARENT, MENU_STATUS, MENU_DT_CREATE, MENU_UID_CREATE, MENU_DT_LUPD, MENU_UID_LUPD) ") -> INSERT INTO T_CORE_MENU_EX (MENU_ID, MENU_APPS_CODE, MENU_GROUP_LABEL, MENU_GROUP_LABEL_OTH, MENU_NAME, MENU_NAME_OTH, MENU_SEQ, MENU_PATH, MENU_ICON, MENU_PARENT, MENU_STATUS, MENU_DT_CREATE, MENU_UID_CREATE, MENU_DT_LUPD, MENU_UID_LUPD) | N24: =CONCATENATE(" VALUES('",A24,"','",B24,"','",D24,"','",E24,"','",F24,"','",G24,"',",IF(H24="NULL","NULL",CONCATENATE("'",H24,"'")),",",IF(I24="NULL","NULL",CONCATENATE("'",I24,"'")),",",IF(J24="NULL","NULL",CONCATENATE("'",J24,"'")),",",IF(K24="NULL","NULL",CONCATENATE("'",K24,"'")),",'A',NOW(),'SYS',NOW(),'SYS');") -> VALUES('CKT_FN_070200','CKT','','','Contract Requests','Contract Requests','70200','/opadmin/contractrequest/list',NULL,'CKT_FN_070000','A',NOW(),'SYS',NOW(),'SYS'); | O24: =CONCATENATE(M24,N24) -> INSERT INTO T_CORE_MENU_EX (MENU_ID, MENU_APPS_CODE, MENU_GROUP_LABEL, MENU_GROUP_LABEL_OTH, MENU_NAME, MENU_NAME_OTH, MENU_SEQ, MENU_PATH, MENU_ICON, MENU_PARENT, MENU_STATUS, MENU_DT_CREATE, MENU_UID_CREATE, MENU_DT_LUPD, MENU_UID_LUPD) VALUES('CKT_FN_070200','CKT','','','Contract Requests','Contract Requests','70200','/opadmin/contractrequest/list',NULL,'CKT_FN_070000','A',NOW(),'SYS',NOW(),'SYS');
A25: CKT_FN_070300 | B25: CKT | F25: Accounts Management | G25: Accounts Management | H25: 70200 | I25: /manageAccounts/all/list | J25: NULL | K25: CKT_FN_070000 | L25: A | M25: =CONCATENATE("INSERT INTO T_CORE_MENU_EX (MENU_ID, MENU_APPS_CODE, MENU_GROUP_LABEL, MENU_GROUP_LABEL_OTH, MENU_NAME, MENU_NAME_OTH, MENU_SEQ, MENU_PATH, MENU_ICON, MENU_PARENT, MENU_STATUS, MENU_DT_CREATE, MENU_UID_CREATE, MENU_DT_LUPD, MENU_UID_LUPD) ") -> INSERT INTO T_CORE_MENU_EX (MENU_ID, MENU_APPS_CODE, MENU_GROUP_LABEL, MENU_GROUP_LABEL_OTH, MENU_NAME, MENU_NAME_OTH, MENU_SEQ, MENU_PATH, MENU_ICON, MENU_PARENT, MENU_STATUS, MENU_DT_CREATE, MENU_UID_CREATE, MENU_DT_LUPD, MENU_UID_LUPD) | N25: =CONCATENATE(" VALUES('",A25,"','",B25,"','",D25,"','",E25,"','",F25,"','",G25,"',",IF(H25="NULL","NULL",CONCATENATE("'",H25,"'")),",",IF(I25="NULL","NULL",CONCATENATE("'",I25,"'")),",",IF(J25="NULL","NULL",CONCATENATE("'",J25,"'")),",",IF(K25="NULL","NULL",CONCATENATE("'",K25,"'")),",'A',NOW(),'SYS',NOW(),'SYS');") -> VALUES('CKT_FN_070300','CKT','','','Accounts Management','Accounts Management','70200','/manageAccounts/all/list',NULL,'CKT_FN_070000','A',NOW(),'SYS',NOW(),'SYS'); | O25: =CONCATENATE(M25,N25) -> INSERT INTO T_CORE_MENU_EX (MENU_ID, MENU_APPS_CODE, MENU_GROUP_LABEL, MENU_GROUP_LABEL_OTH, MENU_NAME, MENU_NAME_OTH, MENU_SEQ, MENU_PATH, MENU_ICON, MENU_PARENT, MENU_STATUS, MENU_DT_CREATE, MENU_UID_CREATE, MENU_DT_LUPD, MENU_UID_LUPD) VALUES('CKT_FN_070300','CKT','','','Accounts Management','Accounts Management','70200','/manageAccounts/all/list',NULL,'CKT_FN_070000','A',NOW(),'SYS',NOW(),'SYS');
A26: CKT_CS_070000 | B26: CKT | C26: SP Customer Service | D26: Customer Service | E26: Customer Service | F26: Customer Service | G26: Customer Service | H26: 70000 | J26: support_agent | K26: NULL | L26: A | M26: =CONCATENATE("INSERT INTO T_CORE_MENU_EX (MENU_ID, MENU_APPS_CODE, MENU_GROUP_LABEL, MENU_GROUP_LABEL_OTH, MENU_NAME, MENU_NAME_OTH, MENU_SEQ, MENU_PATH, MENU_ICON, MENU_PARENT, MENU_STATUS, MENU_DT_CREATE, MENU_UID_CREATE, MENU_DT_LUPD, MENU_UID_LUPD) ") -> INSERT INTO T_CORE_MENU_EX (MENU_ID, MENU_APPS_CODE, MENU_GROUP_LABEL, MENU_GROUP_LABEL_OTH, MENU_NAME, MENU_NAME_OTH, MENU_SEQ, MENU_PATH, MENU_ICON, MENU_PARENT, MENU_STATUS, MENU_DT_CREATE, MENU_UID_CREATE, MENU_DT_LUPD, MENU_UID_LUPD) | N26: =CONCATENATE(" VALUES('",A26,"','",B26,"','",D26,"','",E26,"','",F26,"','",G26,"',",IF(H26="NULL","NULL",CONCATENATE("'",H26,"'")),",",IF(I26="NULL","NULL",CONCATENATE("'",I26,"'")),",",IF(J26="NULL","NULL",CONCATENATE("'",J26,"'")),",",IF(K26="NULL","NULL",CONCATENATE("'",K26,"'")),",'A',NOW(),'SYS',NOW(),'SYS');") -> VALUES('CKT_CS_070000','CKT','Customer Service','Customer Service','Customer Service','Customer Service','70000','','support_agent',NULL,'A',NOW(),'SYS',NOW(),'SYS'); | O26: =CONCATENATE(M26,N26) -> INSERT INTO T_CORE_MENU_EX (MENU_ID, MENU_APPS_CODE, MENU_GROUP_LABEL, MENU_GROUP_LABEL_OTH, MENU_NAME, MENU_NAME_OTH, MENU_SEQ, MENU_PATH, MENU_ICON, MENU_PARENT, MENU_STATUS, MENU_DT_CREATE, MENU_UID_CREATE, MENU_DT_LUPD, MENU_UID_LUPD) VALUES('CKT_CS_070000','CKT','Customer Service','Customer Service','Customer Service','Customer Service','70000','','support_agent',NULL,'A',NOW(),'SYS',NOW(),'SYS');
A27: CKT_CS_070100 | B27: CKT | F27: Rate Table Management | G27: Rate Table Management | H27: 70100 | I27: /manage/ratetable | J27: NULL | K27: CKT_CS_070000 | L27: A | M27: =CONCATENATE("INSERT INTO T_CORE_MENU_EX (MENU_ID, MENU_APPS_CODE, MENU_GROUP_LABEL, MENU_GROUP_LABEL_OTH, MENU_NAME, MENU_NAME_OTH, MENU_SEQ, MENU_PATH, MENU_ICON, MENU_PARENT, MENU_STATUS, MENU_DT_CREATE, MENU_UID_CREATE, MENU_DT_LUPD, MENU_UID_LUPD) ") -> INSERT INTO T_CORE_MENU_EX (MENU_ID, MENU_APPS_CODE, MENU_GROUP_LABEL, MENU_GROUP_LABEL_OTH, MENU_NAME, MENU_NAME_OTH, MENU_SEQ, MENU_PATH, MENU_ICON, MENU_PARENT, MENU_STATUS, MENU_DT_CREATE, MENU_UID_CREATE, MENU_DT_LUPD, MENU_UID_LUPD) | N27: =CONCATENATE(" VALUES('",A27,"','",B27,"','",D27,"','",E27,"','",F27,"','",G27,"',",IF(H27="NULL","NULL",CONCATENATE("'",H27,"'")),",",IF(I27="NULL","NULL",CONCATENATE("'",I27,"'")),",",IF(J27="NULL","NULL",CONCATENATE("'",J27,"'")),",",IF(K27="NULL","NULL",CONCATENATE("'",K27,"'")),",'A',NOW(),'SYS',NOW(),'SYS');") -> VALUES('CKT_CS_070100','CKT','','','Rate Table Management','Rate Table Management','70100','/manage/ratetable',NULL,'CKT_CS_070000','A',NOW(),'SYS',NOW(),'SYS'); | O27: =CONCATENATE(M27,N27) -> INSERT INTO T_CORE_MENU_EX (MENU_ID, MENU_APPS_CODE, MENU_GROUP_LABEL, MENU_GROUP_LABEL_OTH, MENU_NAME, MENU_NAME_OTH, MENU_SEQ, MENU_PATH, MENU_ICON, MENU_PARENT, MENU_STATUS, MENU_DT_CREATE, MENU_UID_CREATE, MENU_DT_LUPD, MENU_UID_LUPD) VALUES('CKT_CS_070100','CKT','','','Rate Table Management','Rate Table Management','70100','/manage/ratetable',NULL,'CKT_CS_070000','A',NOW(),'SYS',NOW(),'SYS');
A28: CKT_CS_070200 | B28: CKT | F28: Documents Verification | G28: Documents Verification | H28: 70200 | I28: /opadmin/docverification | J28: NULL | K28: CKT_CS_070000 | L28: A | M28: =CONCATENATE("INSERT INTO T_CORE_MENU_EX (MENU_ID, MENU_APPS_CODE, MENU_GROUP_LABEL, MENU_GROUP_LABEL_OTH, MENU_NAME, MENU_NAME_OTH, MENU_SEQ, MENU_PATH, MENU_ICON, MENU_PARENT, MENU_STATUS, MENU_DT_CREATE, MENU_UID_CREATE, MENU_DT_LUPD, MENU_UID_LUPD) ") -> INSERT INTO T_CORE_MENU_EX (MENU_ID, MENU_APPS_CODE, MENU_GROUP_LABEL, MENU_GROUP_LABEL_OTH, MENU_NAME, MENU_NAME_OTH, MENU_SEQ, MENU_PATH, MENU_ICON, MENU_PARENT, MENU_STATUS, MENU_DT_CREATE, MENU_UID_CREATE, MENU_DT_LUPD, MENU_UID_LUPD) | N28: =CONCATENATE(" VALUES('",A28,"','",B28,"','",D28,"','",E28,"','",F28,"','",G28,"',",IF(H28="NULL","NULL",CONCATENATE("'",H28,"'")),",",IF(I28="NULL","NULL",CONCATENATE("'",I28,"'")),",",IF(J28="NULL","NULL",CONCATENATE("'",J28,"'")),",",IF(K28="NULL","NULL",CONCATENATE("'",K28,"'")),",'A',NOW(),'SYS',NOW(),'SYS');") -> VALUES('CKT_CS_070200','CKT','','','Documents Verification','Documents Verification','70200','/opadmin/docverification',NULL,'CKT_CS_070000','A',NOW(),'SYS',NOW(),'SYS'); | O28: =CONCATENATE(M28,N28) -> INSERT INTO T_CORE_MENU_EX (MENU_ID, MENU_APPS_CODE, MENU_GROUP_LABEL, MENU_GROUP_LABEL_OTH, MENU_NAME, MENU_NAME_OTH, MENU_SEQ, MENU_PATH, MENU_ICON, MENU_PARENT, MENU_STATUS, MENU_DT_CREATE, MENU_UID_CREATE, MENU_DT_LUPD, MENU_UID_LUPD) VALUES('CKT_CS_070200','CKT','','','Documents Verification','Documents Verification','70200','/opadmin/docverification',NULL,'CKT_CS_070000','A',NOW(),'SYS',NOW(),'SYS');
A29: CKT_CS_070300 | B29: CKT | F29: Contract Requests | G29: Contract Requests | H29: 70300 | I29: /opadmin/contractrequest/list | J29: NULL | K29: CKT_CS_070000 | L29: A | M29: =CONCATENATE("INSERT INTO T_CORE_MENU_EX (MENU_ID, MENU_APPS_CODE, MENU_GROUP_LABEL, MENU_GROUP_LABEL_OTH, MENU_NAME, MENU_NAME_OTH, MENU_SEQ, MENU_PATH, MENU_ICON, MENU_PARENT, MENU_STATUS, MENU_DT_CREATE, MENU_UID_CREATE, MENU_DT_LUPD, MENU_UID_LUPD) ") -> INSERT INTO T_CORE_MENU_EX (MENU_ID, MENU_APPS_CODE, MENU_GROUP_LABEL, MENU_GROUP_LABEL_OTH, MENU_NAME, MENU_NAME_OTH, MENU_SEQ, MENU_PATH, MENU_ICON, MENU_PARENT, MENU_STATUS, MENU_DT_CREATE, MENU_UID_CREATE, MENU_DT_LUPD, MENU_UID_LUPD) | N29: =CONCATENATE(" VALUES('",A29,"','",B29,"','",D29,"','",E29,"','",F29,"','",G29,"',",IF(H29="NULL","NULL",CONCATENATE("'",H29,"'")),",",IF(I29="NULL","NULL",CONCATENATE("'",I29,"'")),",",IF(J29="NULL","NULL",CONCATENATE("'",J29,"'")),",",IF(K29="NULL","NULL",CONCATENATE("'",K29,"'")),",'A',NOW(),'SYS',NOW(),'SYS');") -> VALUES('CKT_CS_070300','CKT','','','Contract Requests','Contract Requests','70300','/opadmin/contractrequest/list',NULL,'CKT_CS_070000','A',NOW(),'SYS',NOW(),'SYS'); | O29: =CONCATENATE(M29,N29) -> INSERT INTO T_CORE_MENU_EX (MENU_ID, MENU_APPS_CODE, MENU_GROUP_LABEL, MENU_GROUP_LABEL_OTH, MENU_NAME, MENU_NAME_OTH, MENU_SEQ, MENU_PATH, MENU_ICON, MENU_PARENT, MENU_STATUS, MENU_DT_CREATE, MENU_UID_CREATE, MENU_DT_LUPD, MENU_UID_LUPD) VALUES('CKT_CS_070300','CKT','','','Contract Requests','Contract Requests','70300','/opadmin/contractrequest/list',NULL,'CKT_CS_070000','A',NOW(),'SYS',NOW(),'SYS');
A30: CKT_OA_080000 | B30: CKT | C30: SP Operations Admin | D30: Operations Administration | E30: Operations Administration | F30: Operations Administration | G30: Operations Administration | H30: 80000 | J30: admin_panel_settings | K30: NULL | L30: A | M30: =CONCATENATE("INSERT INTO T_CORE_MENU_EX (MENU_ID, MENU_APPS_CODE, MENU_GROUP_LABEL, MENU_GROUP_LABEL_OTH, MENU_NAME, MENU_NAME_OTH, MENU_SEQ, MENU_PATH, MENU_ICON, MENU_PARENT, MENU_STATUS, MENU_DT_CREATE, MENU_UID_CREATE, MENU_DT_LUPD, MENU_UID_LUPD) ") -> INSERT INTO T_CORE_MENU_EX (MENU_ID, MENU_APPS_CODE, MENU_GROUP_LABEL, MENU_GROUP_LABEL_OTH, MENU_NAME, MENU_NAME_OTH, MENU_SEQ, MENU_PATH, MENU_ICON, MENU_PARENT, MENU_STATUS, MENU_DT_CREATE, MENU_UID_CREATE, MENU_DT_LUPD, MENU_UID_LUPD) | N30: =CONCATENATE(" VALUES('",A30,"','",B30,"','",D30,"','",E30,"','",F30,"','",G30,"',",IF(H30="NULL","NULL",CONCATENATE("'",H30,"'")),",",IF(I30="NULL","NULL",CONCATENATE("'",I30,"'")),",",IF(J30="NULL","NULL",CONCATENATE("'",J30,"'")),",",IF(K30="NULL","NULL",CONCATENATE("'",K30,"'")),",'A',NOW(),'SYS',NOW(),'SYS');") -> VALUES('CKT_OA_080000','CKT','Operations Administration','Operations Administration','Operations Administration','Operations Administration','80000','','admin_panel_settings',NULL,'A',NOW(),'SYS',NOW(),'SYS'); | O30: =CONCATENATE(M30,N30) -> INSERT INTO T_CORE_MENU_EX (MENU_ID, MENU_APPS_CODE, MENU_GROUP_LABEL, MENU_GROUP_LABEL_OTH, MENU_NAME, MENU_NAME_OTH, MENU_SEQ, MENU_PATH, MENU_ICON, MENU_PARENT, MENU_STATUS, MENU_DT_CREATE, MENU_UID_CREATE, MENU_DT_LUPD, MENU_UID_LUPD) VALUES('CKT_OA_080000','CKT','Operations Administration','Operations Administration','Operations Administration','Operations Administration','80000','','admin_panel_settings',NULL,'A',NOW(),'SYS',NOW(),'SYS');
A31: CKT_OA_080100 | B31: CKT | F31: Account Suspension/Resumption | G31: Account Suspension/Resumption | H31: 80100 | I31: /opadmin/accounts/co/list | J31: NULL | K31: CKT_OA_080000 | L31: A | M31: =CONCATENATE("INSERT INTO T_CORE_MENU_EX (MENU_ID, MENU_APPS_CODE, MENU_GROUP_LABEL, MENU_GROUP_LABEL_OTH, MENU_NAME, MENU_NAME_OTH, MENU_SEQ, MENU_PATH, MENU_ICON, MENU_PARENT, MENU_STATUS, MENU_DT_CREATE, MENU_UID_CREATE, MENU_DT_LUPD, MENU_UID_LUPD) ") -> INSERT INTO T_CORE_MENU_EX (MENU_ID, MENU_APPS_CODE, MENU_GROUP_LABEL, MENU_GROUP_LABEL_OTH, MENU_NAME, MENU_NAME_OTH, MENU_SEQ, MENU_PATH, MENU_ICON, MENU_PARENT, MENU_STATUS, MENU_DT_CREATE, MENU_UID_CREATE, MENU_DT_LUPD, MENU_UID_LUPD) | N31: =CONCATENATE(" VALUES('",A31,"','",B31,"','",D31,"','",E31,"','",F31,"','",G31,"',",IF(H31="NULL","NULL",CONCATENATE("'",H31,"'")),",",IF(I31="NULL","NULL",CONCATENATE("'",I31,"'")),",",IF(J31="NULL","NULL",CONCATENATE("'",J31,"'")),",",IF(K31="NULL","NULL",CONCATENATE("'",K31,"'")),",'A',NOW(),'SYS',NOW(),'SYS');") -> VALUES('CKT_OA_080100','CKT','','','Account Suspension/Resumption','Account Suspension/Resumption','80100','/opadmin/accounts/co/list',NULL,'CKT_OA_080000','A',NOW(),'SYS',NOW(),'SYS'); | O31: =CONCATENATE(M31,N31) -> INSERT INTO T_CORE_MENU_EX (MENU_ID, MENU_APPS_CODE, MENU_GROUP_LABEL, MENU_GROUP_LABEL_OTH, MENU_NAME, MENU_NAME_OTH, MENU_SEQ, MENU_PATH, MENU_ICON, MENU_PARENT, MENU_STATUS, MENU_DT_CREATE, MENU_UID_CREATE, MENU_DT_LUPD, MENU_UID_LUPD) VALUES('CKT_OA_080100','CKT','','','Account Suspension/Resumption','Account Suspension/Resumption','80100','/opadmin/accounts/co/list',NULL,'CKT_OA_080000','A',NOW(),'SYS',NOW(),'SYS');
A32: CKT_OA_080200 | B32: CKT | F32: Bank Account | G32: Bank Account | H32: 80200 | I32: /opadmin/bankaccounts | J32: NULL | K32: CKT_OA_080000 | L32: A | M32: =CONCATENATE("INSERT INTO T_CORE_MENU_EX (MENU_ID, MENU_APPS_CODE, MENU_GROUP_LABEL, MENU_GROUP_LABEL_OTH, MENU_NAME, MENU_NAME_OTH, MENU_SEQ, MENU_PATH, MENU_ICON, MENU_PARENT, MENU_STATUS, MENU_DT_CREATE, MENU_UID_CREATE, MENU_DT_LUPD, MENU_UID_LUPD) ") -> INSERT INTO T_CORE_MENU_EX (MENU_ID, MENU_APPS_CODE, MENU_GROUP_LABEL, MENU_GROUP_LABEL_OTH, MENU_NAME, MENU_NAME_OTH, MENU_SEQ, MENU_PATH, MENU_ICON, MENU_PARENT, MENU_STATUS, MENU_DT_CREATE, MENU_UID_CREATE, MENU_DT_LUPD, MENU_UID_LUPD) | N32: =CONCATENATE(" VALUES('",A32,"','",B32,"','",D32,"','",E32,"','",F32,"','",G32,"',",IF(H32="NULL","NULL",CONCATENATE("'",H32,"'")),",",IF(I32="NULL","NULL",CONCATENATE("'",I32,"'")),",",IF(J32="NULL","NULL",CONCATENATE("'",J32,"'")),",",IF(K32="NULL","NULL",CONCATENATE("'",K32,"'")),",'A',NOW(),'SYS',NOW(),'SYS');") -> VALUES('CKT_OA_080200','CKT','','','Bank Account','Bank Account','80200','/opadmin/bankaccounts',NULL,'CKT_OA_080000','A',NOW(),'SYS',NOW(),'SYS'); | O32: =CONCATENATE(M32,N32) -> INSERT INTO T_CORE_MENU_EX (MENU_ID, MENU_APPS_CODE, MENU_GROUP_LABEL, MENU_GROUP_LABEL_OTH, MENU_NAME, MENU_NAME_OTH, MENU_SEQ, MENU_PATH, MENU_ICON, MENU_PARENT, MENU_STATUS, MENU_DT_CREATE, MENU_UID_CREATE, MENU_DT_LUPD, MENU_UID_LUPD) VALUES('CKT_OA_080200','CKT','','','Bank Account','Bank Account','80200','/opadmin/bankaccounts',NULL,'CKT_OA_080000','A',NOW(),'SYS',NOW(),'SYS');
A33: CKT_OA_080300 | B33: CKT | F33: Static Virtual Account | G33: Static Virtual Account | H33: 80300 | I33: /opadmin/staticva | J33: NULL | K33: CKT_OA_080000 | L33: A | M33: =CONCATENATE("INSERT INTO T_CORE_MENU_EX (MENU_ID, MENU_APPS_CODE, MENU_GROUP_LABEL, MENU_GROUP_LABEL_OTH, MENU_NAME, MENU_NAME_OTH, MENU_SEQ, MENU_PATH, MENU_ICON, MENU_PARENT, MENU_STATUS, MENU_DT_CREATE, MENU_UID_CREATE, MENU_DT_LUPD, MENU_UID_LUPD) ") -> INSERT INTO T_CORE_MENU_EX (MENU_ID, MENU_APPS_CODE, MENU_GROUP_LABEL, MENU_GROUP_LABEL_OTH, MENU_NAME, MENU_NAME_OTH, MENU_SEQ, MENU_PATH, MENU_ICON, MENU_PARENT, MENU_STATUS, MENU_DT_CREATE, MENU_UID_CREATE, MENU_DT_LUPD, MENU_UID_LUPD) | N33: =CONCATENATE(" VALUES('",A33,"','",B33,"','",D33,"','",E33,"','",F33,"','",G33,"',",IF(H33="NULL","NULL",CONCATENATE("'",H33,"'")),",",IF(I33="NULL","NULL",CONCATENATE("'",I33,"'")),",",IF(J33="NULL","NULL",CONCATENATE("'",J33,"'")),",",IF(K33="NULL","NULL",CONCATENATE("'",K33,"'")),",'A',NOW(),'SYS',NOW(),'SYS');") -> VALUES('CKT_OA_080300','CKT','','','Static Virtual Account','Static Virtual Account','80300','/opadmin/staticva',NULL,'CKT_OA_080000','A',NOW(),'SYS',NOW(),'SYS'); | O33: =CONCATENATE(M33,N33) -> INSERT INTO T_CORE_MENU_EX (MENU_ID, MENU_APPS_CODE, MENU_GROUP_LABEL, MENU_GROUP_LABEL_OTH, MENU_NAME, MENU_NAME_OTH, MENU_SEQ, MENU_PATH, MENU_ICON, MENU_PARENT, MENU_STATUS, MENU_DT_CREATE, MENU_UID_CREATE, MENU_DT_LUPD, MENU_UID_LUPD) VALUES('CKT_OA_080300','CKT','','','Static Virtual Account','Static Virtual Account','80300','/opadmin/staticva',NULL,'CKT_OA_080000','A',NOW(),'SYS',NOW(),'SYS');
A34: CKT_OA_080400 | B34: CKT | F34: Tracking Device | G34: Tracking Device | H34: 80400 | I34: /opadmin/trackingdevices | J34: NULL | K34: CKT_OA_080000 | L34: A | M34: =CONCATENATE("INSERT INTO T_CORE_MENU_EX (MENU_ID, MENU_APPS_CODE, MENU_GROUP_LABEL, MENU_GROUP_LABEL_OTH, MENU_NAME, MENU_NAME_OTH, MENU_SEQ, MENU_PATH, MENU_ICON, MENU_PARENT, MENU_STATUS, MENU_DT_CREATE, MENU_UID_CREATE, MENU_DT_LUPD, MENU_UID_LUPD) ") -> INSERT INTO T_CORE_MENU_EX (MENU_ID, MENU_APPS_CODE, MENU_GROUP_LABEL, MENU_GROUP_LABEL_OTH, MENU_NAME, MENU_NAME_OTH, MENU_SEQ, MENU_PATH, MENU_ICON, MENU_PARENT, MENU_STATUS, MENU_DT_CREATE, MENU_UID_CREATE, MENU_DT_LUPD, MENU_UID_LUPD) | N34: =CONCATENATE(" VALUES('",A34,"','",B34,"','",D34,"','",E34,"','",F34,"','",G34,"',",IF(H34="NULL","NULL",CONCATENATE("'",H34,"'")),",",IF(I34="NULL","NULL",CONCATENATE("'",I34,"'")),",",IF(J34="NULL","NULL",CONCATENATE("'",J34,"'")),",",IF(K34="NULL","NULL",CONCATENATE("'",K34,"'")),",'A',NOW(),'SYS',NOW(),'SYS');") -> VALUES('CKT_OA_080400','CKT','','','Tracking Device','Tracking Device','80400','/opadmin/trackingdevices',NULL,'CKT_OA_080000','A',NOW(),'SYS',NOW(),'SYS'); | O34: =CONCATENATE(M34,N34) -> INSERT INTO T_CORE_MENU_EX (MENU_ID, MENU_APPS_CODE, MENU_GROUP_LABEL, MENU_GROUP_LABEL_OTH, MENU_NAME, MENU_NAME_OTH, MENU_SEQ, MENU_PATH, MENU_ICON, MENU_PARENT, MENU_STATUS, MENU_DT_CREATE, MENU_UID_CREATE, MENU_DT_LUPD, MENU_UID_LUPD) VALUES('CKT_OA_080400','CKT','','','Tracking Device','Tracking Device','80400','/opadmin/trackingdevices',NULL,'CKT_OA_080000','A',NOW(),'SYS',NOW(),'SYS');
A35: CKT_OA_080500 | B35: CKT | F35: SAGE Integration | G35: SAGE Integration | H35: 80500 | I35: /opadmin/sageintegrations | J35: NULL | K35: CKT_OA_080000 | L35: A | M35: =CONCATENATE("INSERT INTO T_CORE_MENU_EX (MENU_ID, MENU_APPS_CODE, MENU_GROUP_LABEL, MENU_GROUP_LABEL_OTH, MENU_NAME, MENU_NAME_OTH, MENU_SEQ, MENU_PATH, MENU_ICON, MENU_PARENT, MENU_STATUS, MENU_DT_CREATE, MENU_UID_CREATE, MENU_DT_LUPD, MENU_UID_LUPD) ") -> INSERT INTO T_CORE_MENU_EX (MENU_ID, MENU_APPS_CODE, MENU_GROUP_LABEL, MENU_GROUP_LABEL_OTH, MENU_NAME, MENU_NAME_OTH, MENU_SEQ, MENU_PATH, MENU_ICON, MENU_PARENT, MENU_STATUS, MENU_DT_CREATE, MENU_UID_CREATE, MENU_DT_LUPD, MENU_UID_LUPD) | N35: =CONCATENATE(" VALUES('",A35,"','",B35,"','",D35,"','",E35,"','",F35,"','",G35,"',",IF(H35="NULL","NULL",CONCATENATE("'",H35,"'")),",",IF(I35="NULL","NULL",CONCATENATE("'",I35,"'")),",",IF(J35="NULL","NULL",CONCATENATE("'",J35,"'")),",",IF(K35="NULL","NULL",CONCATENATE("'",K35,"'")),",'A',NOW(),'SYS',NOW(),'SYS');") -> VALUES('CKT_OA_080500','CKT','','','SAGE Integration','SAGE Integration','80500','/opadmin/sageintegrations',NULL,'CKT_OA_080000','A',NOW(),'SYS',NOW(),'SYS'); | O35: =CONCATENATE(M35,N35) -> INSERT INTO T_CORE_MENU_EX (MENU_ID, MENU_APPS_CODE, MENU_GROUP_LABEL, MENU_GROUP_LABEL_OTH, MENU_NAME, MENU_NAME_OTH, MENU_SEQ, MENU_PATH, MENU_ICON, MENU_PARENT, MENU_STATUS, MENU_DT_CREATE, MENU_UID_CREATE, MENU_DT_LUPD, MENU_UID_LUPD) VALUES('CKT_OA_080500','CKT','','','SAGE Integration','SAGE Integration','80500','/opadmin/sageintegrations',NULL,'CKT_OA_080000','A',NOW(),'SYS',NOW(),'SYS');
A36: CKT_OA_080600 | B36: CKT | F36: User Management | G36: User Management | H36: 80600 | I36: /opadmin/users | J36: NULL | K36: CKT_OA_080000 | L36: A | M36: =CONCATENATE("INSERT INTO T_CORE_MENU_EX (MENU_ID, MENU_APPS_CODE, MENU_GROUP_LABEL, MENU_GROUP_LABEL_OTH, MENU_NAME, MENU_NAME_OTH, MENU_SEQ, MENU_PATH, MENU_ICON, MENU_PARENT, MENU_STATUS, MENU_DT_CREATE, MENU_UID_CREATE, MENU_DT_LUPD, MENU_UID_LUPD) ") -> INSERT INTO T_CORE_MENU_EX (MENU_ID, MENU_APPS_CODE, MENU_GROUP_LABEL, MENU_GROUP_LABEL_OTH, MENU_NAME, MENU_NAME_OTH, MENU_SEQ, MENU_PATH, MENU_ICON, MENU_PARENT, MENU_STATUS, MENU_DT_CREATE, MENU_UID_CREATE, MENU_DT_LUPD, MENU_UID_LUPD) | N36: =CONCATENATE(" VALUES('",A36,"','",B36,"','",D36,"','",E36,"','",F36,"','",G36,"',",IF(H36="NULL","NULL",CONCATENATE("'",H36,"'")),",",IF(I36="NULL","NULL",CONCATENATE("'",I36,"'")),",",IF(J36="NULL","NULL",CONCATENATE("'",J36,"'")),",",IF(K36="NULL","NULL",CONCATENATE("'",K36,"'")),",'A',NOW(),'SYS',NOW(),'SYS');") -> VALUES('CKT_OA_080600','CKT','','','User Management','User Management','80600','/opadmin/users',NULL,'CKT_OA_080000','A',NOW(),'SYS',NOW(),'SYS'); | O36: =CONCATENATE(M36,N36) -> INSERT INTO T_CORE_MENU_EX (MENU_ID, MENU_APPS_CODE, MENU_GROUP_LABEL, MENU_GROUP_LABEL_OTH, MENU_NAME, MENU_NAME_OTH, MENU_SEQ, MENU_PATH, MENU_ICON, MENU_PARENT, MENU_STATUS, MENU_DT_CREATE, MENU_UID_CREATE, MENU_DT_LUPD, MENU_UID_LUPD) VALUES('CKT_OA_080600','CKT','','','User Management','User Management','80600','/opadmin/users',NULL,'CKT_OA_080000','A',NOW(),'SYS',NOW(),'SYS');
A37: CKT_OA_080700 | B37: CKT | F37: Outbound Payments | G37: Outbound Payments | H37: 80700 | I37: /opadmin/outboundpayments | J37: NULL | K37: CKT_OA_080000 | L37: A | M37: =CONCATENATE("INSERT INTO T_CORE_MENU_EX (MENU_ID, MENU_APPS_CODE, MENU_GROUP_LABEL, MENU_GROUP_LABEL_OTH, MENU_NAME, MENU_NAME_OTH, MENU_SEQ, MENU_PATH, MENU_ICON, MENU_PARENT, MENU_STATUS, MENU_DT_CREATE, MENU_UID_CREATE, MENU_DT_LUPD, MENU_UID_LUPD) ") -> INSERT INTO T_CORE_MENU_EX (MENU_ID, MENU_APPS_CODE, MENU_GROUP_LABEL, MENU_GROUP_LABEL_OTH, MENU_NAME, MENU_NAME_OTH, MENU_SEQ, MENU_PATH, MENU_ICON, MENU_PARENT, MENU_STATUS, MENU_DT_CREATE, MENU_UID_CREATE, MENU_DT_LUPD, MENU_UID_LUPD) | N37: =CONCATENATE(" VALUES('",A37,"','",B37,"','",D37,"','",E37,"','",F37,"','",G37,"',",IF(H37="NULL","NULL",CONCATENATE("'",H37,"'")),",",IF(I37="NULL","NULL",CONCATENATE("'",I37,"'")),",",IF(J37="NULL","NULL",CONCATENATE("'",J37,"'")),",",IF(K37="NULL","NULL",CONCATENATE("'",K37,"'")),",'A',NOW(),'SYS',NOW(),'SYS');") -> VALUES('CKT_OA_080700','CKT','','','Outbound Payments','Outbound Payments','80700','/opadmin/outboundpayments',NULL,'CKT_OA_080000','A',NOW(),'SYS',NOW(),'SYS'); | O37: =CONCATENATE(M37,N37) -> INSERT INTO T_CORE_MENU_EX (MENU_ID, MENU_APPS_CODE, MENU_GROUP_LABEL, MENU_GROUP_LABEL_OTH, MENU_NAME, MENU_NAME_OTH, MENU_SEQ, MENU_PATH, MENU_ICON, MENU_PARENT, MENU_STATUS, MENU_DT_CREATE, MENU_UID_CREATE, MENU_DT_LUPD, MENU_UID_LUPD) VALUES('CKT_OA_080700','CKT','','','Outbound Payments','Outbound Payments','80700','/opadmin/outboundpayments',NULL,'CKT_OA_080000','A',NOW(),'SYS',NOW(),'SYS');
A38: CKT_OA_080800 | B38: CKT | F38: Inbound Payments | G38: Inbound Payments | H38: 80800 | I38: /opadmin/inboundpayments | J38: NULL | K38: CKT_OA_080000 | L38: A | M38: =CONCATENATE("INSERT INTO T_CORE_MENU_EX (MENU_ID, MENU_APPS_CODE, MENU_GROUP_LABEL, MENU_GROUP_LABEL_OTH, MENU_NAME, MENU_NAME_OTH, MENU_SEQ, MENU_PATH, MENU_ICON, MENU_PARENT, MENU_STATUS, MENU_DT_CREATE, MENU_UID_CREATE, MENU_DT_LUPD, MENU_UID_LUPD) ") -> INSERT INTO T_CORE_MENU_EX (MENU_ID, MENU_APPS_CODE, MENU_GROUP_LABEL, MENU_GROUP_LABEL_OTH, MENU_NAME, MENU_NAME_OTH, MENU_SEQ, MENU_PATH, MENU_ICON, MENU_PARENT, MENU_STATUS, MENU_DT_CREATE, MENU_UID_CREATE, MENU_DT_LUPD, MENU_UID_LUPD) | N38: =CONCATENATE(" VALUES('",A38,"','",B38,"','",D38,"','",E38,"','",F38,"','",G38,"',",IF(H38="NULL","NULL",CONCATENATE("'",H38,"'")),",",IF(I38="NULL","NULL",CONCATENATE("'",I38,"'")),",",IF(J38="NULL","NULL",CONCATENATE("'",J38,"'")),",",IF(K38="NULL","NULL",CONCATENATE("'",K38,"'")),",'A',NOW(),'SYS',NOW(),'SYS');") -> VALUES('CKT_OA_080800','CKT','','','Inbound Payments','Inbound Payments','80800','/opadmin/inboundpayments',NULL,'CKT_OA_080000','A',NOW(),'SYS',NOW(),'SYS'); | O38: =CONCATENATE(M38,N38) -> INSERT INTO T_CORE_MENU_EX (MENU_ID, MENU_APPS_CODE, MENU_GROUP_LABEL, MENU_GROUP_LABEL_OTH, MENU_NAME, MENU_NAME_OTH, MENU_SEQ, MENU_PATH, MENU_ICON, MENU_PARENT, MENU_STATUS, MENU_DT_CREATE, MENU_UID_CREATE, MENU_DT_LUPD, MENU_UID_LUPD) VALUES('CKT_OA_080800','CKT','','','Inbound Payments','Inbound Payments','80800','/opadmin/inboundpayments',NULL,'CKT_OA_080000','A',NOW(),'SYS',NOW(),'SYS');
A39: CKT_OA_080900 | B39: CKT | F39: Contract Management | G39: Contract Management | H39: 80900 | I39: /opadmin/contracts | J39: NULL | K39: CKT_OA_080000 | L39: A | M39: =CONCATENATE("INSERT INTO T_CORE_MENU_EX (MENU_ID, MENU_APPS_CODE, MENU_GROUP_LABEL, MENU_GROUP_LABEL_OTH, MENU_NAME, MENU_NAME_OTH, MENU_SEQ, MENU_PATH, MENU_ICON, MENU_PARENT, MENU_STATUS, MENU_DT_CREATE, MENU_UID_CREATE, MENU_DT_LUPD, MENU_UID_LUPD) ") -> INSERT INTO T_CORE_MENU_EX (MENU_ID, MENU_APPS_CODE, MENU_GROUP_LABEL, MENU_GROUP_LABEL_OTH, MENU_NAME, MENU_NAME_OTH, MENU_SEQ, MENU_PATH, MENU_ICON, MENU_PARENT, MENU_STATUS, MENU_DT_CREATE, MENU_UID_CREATE, MENU_DT_LUPD, MENU_UID_LUPD) | N39: =CONCATENATE(" VALUES('",A39,"','",B39,"','",D39,"','",E39,"','",F39,"','",G39,"',",IF(H39="NULL","NULL",CONCATENATE("'",H39,"'")),",",IF(I39="NULL","NULL",CONCATENATE("'",I39,"'")),",",IF(J39="NULL","NULL",CONCATENATE("'",J39,"'")),",",IF(K39="NULL","NULL",CONCATENATE("'",K39,"'")),",'A',NOW(),'SYS',NOW(),'SYS');") -> VALUES('CKT_OA_080900','CKT','','','Contract Management','Contract Management','80900','/opadmin/contracts',NULL,'CKT_OA_080000','A',NOW(),'SYS',NOW(),'SYS'); | O39: =CONCATENATE(M39,N39) -> INSERT INTO T_CORE_MENU_EX (MENU_ID, MENU_APPS_CODE, MENU_GROUP_LABEL, MENU_GROUP_LABEL_OTH, MENU_NAME, MENU_NAME_OTH, MENU_SEQ, MENU_PATH, MENU_ICON, MENU_PARENT, MENU_STATUS, MENU_DT_CREATE, MENU_UID_CREATE, MENU_DT_LUPD, MENU_UID_LUPD) VALUES('CKT_OA_080900','CKT','','','Contract Management','Contract Management','80900','/opadmin/contracts',NULL,'CKT_OA_080000','A',NOW(),'SYS',NOW(),'SYS');
A40: CKT_OA_081000 | B40: CKT | F40: Accounts Management | G40: Accounts Management | H40: 81000 | I40: /manageAccounts/all/list | J40: NULL | K40: CKT_OA_080000 | L40: A | M40: =CONCATENATE("INSERT INTO T_CORE_MENU_EX (MENU_ID, MENU_APPS_CODE, MENU_GROUP_LABEL, MENU_GROUP_LABEL_OTH, MENU_NAME, MENU_NAME_OTH, MENU_SEQ, MENU_PATH, MENU_ICON, MENU_PARENT, MENU_STATUS, MENU_DT_CREATE, MENU_UID_CREATE, MENU_DT_LUPD, MENU_UID_LUPD) ") -> INSERT INTO T_CORE_MENU_EX (MENU_ID, MENU_APPS_CODE, MENU_GROUP_LABEL, MENU_GROUP_LABEL_OTH, MENU_NAME, MENU_NAME_OTH, MENU_SEQ, MENU_PATH, MENU_ICON, MENU_PARENT, MENU_STATUS, MENU_DT_CREATE, MENU_UID_CREATE, MENU_DT_LUPD, MENU_UID_LUPD) | N40: =CONCATENATE(" VALUES('",A40,"','",B40,"','",D40,"','",E40,"','",F40,"','",G40,"',",IF(H40="NULL","NULL",CONCATENATE("'",H40,"'")),",",IF(I40="NULL","NULL",CONCATENATE("'",I40,"'")),",",IF(J40="NULL","NULL",CONCATENATE("'",J40,"'")),",",IF(K40="NULL","NULL",CONCATENATE("'",K40,"'")),",'A',NOW(),'SYS',NOW(),'SYS');") -> VALUES('CKT_OA_081000','CKT','','','Accounts Management','Accounts Management','81000','/manageAccounts/all/list',NULL,'CKT_OA_080000','A',NOW(),'SYS',NOW(),'SYS'); | O40: =CONCATENATE(M40,N40) -> INSERT INTO T_CORE_MENU_EX (MENU_ID, MENU_APPS_CODE, MENU_GROUP_LABEL, MENU_GROUP_LABEL_OTH, MENU_NAME, MENU_NAME_OTH, MENU_SEQ, MENU_PATH, MENU_ICON, MENU_PARENT, MENU_STATUS, MENU_DT_CREATE, MENU_UID_CREATE, MENU_DT_LUPD, MENU_UID_LUPD) VALUES('CKT_OA_081000','CKT','','','Accounts Management','Accounts Management','81000','/manageAccounts/all/list',NULL,'CKT_OA_080000','A',NOW(),'SYS',NOW(),'SYS');
A41: CKT_OA_081100 | B41: CKT | F41: Credit Limit | G41: Credit Limit | H41: 81100 | I41: /opadmin/creditlimit | J41: NULL | K41: CKT_OA_080000 | L41: A | M41: =CONCATENATE("INSERT INTO T_CORE_MENU_EX (MENU_ID, MENU_APPS_CODE, MENU_GROUP_LABEL, MENU_GROUP_LABEL_OTH, MENU_NAME, MENU_NAME_OTH, MENU_SEQ, MENU_PATH, MENU_ICON, MENU_PARENT, MENU_STATUS, MENU_DT_CREATE, MENU_UID_CREATE, MENU_DT_LUPD, MENU_UID_LUPD) ") -> INSERT INTO T_CORE_MENU_EX (MENU_ID, MENU_APPS_CODE, MENU_GROUP_LABEL, MENU_GROUP_LABEL_OTH, MENU_NAME, MENU_NAME_OTH, MENU_SEQ, MENU_PATH, MENU_ICON, MENU_PARENT, MENU_STATUS, MENU_DT_CREATE, MENU_UID_CREATE, MENU_DT_LUPD, MENU_UID_LUPD) | N41: =CONCATENATE(" VALUES('",A41,"','",B41,"','",D41,"','",E41,"','",F41,"','",G41,"',",IF(H41="NULL","NULL",CONCATENATE("'",H41,"'")),",",IF(I41="NULL","NULL",CONCATENATE("'",I41,"'")),",",IF(J41="NULL","NULL",CONCATENATE("'",J41,"'")),",",IF(K41="NULL","NULL",CONCATENATE("'",K41,"'")),",'A',NOW(),'SYS',NOW(),'SYS');") -> VALUES('CKT_OA_081100','CKT','','','Credit Limit','Credit Limit','81100','/opadmin/creditlimit',NULL,'CKT_OA_080000','A',NOW(),'SYS',NOW(),'SYS'); | O41: =CONCATENATE(M41,N41) -> INSERT INTO T_CORE_MENU_EX (MENU_ID, MENU_APPS_CODE, MENU_GROUP_LABEL, MENU_GROUP_LABEL_OTH, MENU_NAME, MENU_NAME_OTH, MENU_SEQ, MENU_PATH, MENU_ICON, MENU_PARENT, MENU_STATUS, MENU_DT_CREATE, MENU_UID_CREATE, MENU_DT_LUPD, MENU_UID_LUPD) VALUES('CKT_OA_081100','CKT','','','Credit Limit','Credit Limit','81100','/opadmin/creditlimit',NULL,'CKT_OA_080000','A',NOW(),'SYS',NOW(),'SYS');
A42: CKT_OA_081200 | B42: CKT | F42: Job Termination | G42: Job Termination | H42: 81200 | I42: /opadmin/order-termination/list | J42: NULL | K42: CKT_OA_080000 | L42: A | M42: =CONCATENATE("INSERT INTO T_CORE_MENU_EX (MENU_ID, MENU_APPS_CODE, MENU_GROUP_LABEL, MENU_GROUP_LABEL_OTH, MENU_NAME, MENU_NAME_OTH, MENU_SEQ, MENU_PATH, MENU_ICON, MENU_PARENT, MENU_STATUS, MENU_DT_CREATE, MENU_UID_CREATE, MENU_DT_LUPD, MENU_UID_LUPD) ") -> INSERT INTO T_CORE_MENU_EX (MENU_ID, MENU_APPS_CODE, MENU_GROUP_LABEL, MENU_GROUP_LABEL_OTH, MENU_NAME, MENU_NAME_OTH, MENU_SEQ, MENU_PATH, MENU_ICON, MENU_PARENT, MENU_STATUS, MENU_DT_CREATE, MENU_UID_CREATE, MENU_DT_LUPD, MENU_UID_LUPD) | N42: =CONCATENATE(" VALUES('",A42,"','",B42,"','",D42,"','",E42,"','",F42,"','",G42,"',",IF(H42="NULL","NULL",CONCATENATE("'",H42,"'")),",",IF(I42="NULL","NULL",CONCATENATE("'",I42,"'")),",",IF(J42="NULL","NULL",CONCATENATE("'",J42,"'")),",",IF(K42="NULL","NULL",CONCATENATE("'",K42,"'")),",'A',NOW(),'SYS',NOW(),'SYS');") -> VALUES('CKT_OA_081200','CKT','','','Job Termination','Job Termination','81200','/opadmin/order-termination/list',NULL,'CKT_OA_080000','A',NOW(),'SYS',NOW(),'SYS'); | O42: =CONCATENATE(M42,N42) -> INSERT INTO T_CORE_MENU_EX (MENU_ID, MENU_APPS_CODE, MENU_GROUP_LABEL, MENU_GROUP_LABEL_OTH, MENU_NAME, MENU_NAME_OTH, MENU_SEQ, MENU_PATH, MENU_ICON, MENU_PARENT, MENU_STATUS, MENU_DT_CREATE, MENU_UID_CREATE, MENU_DT_LUPD, MENU_UID_LUPD) VALUES('CKT_OA_081200','CKT','','','Job Termination','Job Termination','81200','/opadmin/order-termination/list',NULL,'CKT_OA_080000','A',NOW(),'SYS',NOW(),'SYS');
A43: CKT_RP_080000 | B43: CKT | D43: Reports | E43: Reports | F43: Reports | G43: Reports | H43: 80000 | I43: /reports/list | J43: summarize | K43: NULL | L43: A | M43: =CONCATENATE("INSERT INTO T_CORE_MENU_EX (MENU_ID, MENU_APPS_CODE, MENU_GROUP_LABEL, MENU_GROUP_LABEL_OTH, MENU_NAME, MENU_NAME_OTH, MENU_SEQ, MENU_PATH, MENU_ICON, MENU_PARENT, MENU_STATUS, MENU_DT_CREATE, MENU_UID_CREATE, MENU_DT_LUPD, MENU_UID_LUPD) ") -> INSERT INTO T_CORE_MENU_EX (MENU_ID, MENU_APPS_CODE, MENU_GROUP_LABEL, MENU_GROUP_LABEL_OTH, MENU_NAME, MENU_NAME_OTH, MENU_SEQ, MENU_PATH, MENU_ICON, MENU_PARENT, MENU_STATUS, MENU_DT_CREATE, MENU_UID_CREATE, MENU_DT_LUPD, MENU_UID_LUPD) | N43: =CONCATENATE(" VALUES('",A43,"','",B43,"','",D43,"','",E43,"','",F43,"','",G43,"',",IF(H43="NULL","NULL",CONCATENATE("'",H43,"'")),",",IF(I43="NULL","NULL",CONCATENATE("'",I43,"'")),",",IF(J43="NULL","NULL",CONCATENATE("'",J43,"'")),",",IF(K43="NULL","NULL",CONCATENATE("'",K43,"'")),",'A',NOW(),'SYS',NOW(),'SYS');") -> VALUES('CKT_RP_080000','CKT','Reports','Reports','Reports','Reports','80000','/reports/list','summarize',NULL,'A',NOW(),'SYS',NOW(),'SYS'); | O43: =CONCATENATE(M43,N43) -> INSERT INTO T_CORE_MENU_EX (MENU_ID, MENU_APPS_CODE, MENU_GROUP_LABEL, MENU_GROUP_LABEL_OTH, MENU_NAME, MENU_NAME_OTH, MENU_SEQ, MENU_PATH, MENU_ICON, MENU_PARENT, MENU_STATUS, MENU_DT_CREATE, MENU_UID_CREATE, MENU_DT_LUPD, MENU_UID_LUPD) VALUES('CKT_RP_080000','CKT','Reports','Reports','Reports','Reports','80000','/reports/list','summarize',NULL,'A',NOW(),'SYS',NOW(),'SYS');
A44: CKDO_MA_030000 | B44: CKDO | D44: Administrations | E44: Administrations | F44: Administrations | G44: Administrations | H44: 30000 | I44: NULL | J44: group | K44: NULL | L44: A | M44: =CONCATENATE("INSERT INTO T_CORE_MENU_EX (MENU_ID, MENU_APPS_CODE, MENU_GROUP_LABEL, MENU_GROUP_LABEL_OTH, MENU_NAME, MENU_NAME_OTH, MENU_SEQ, MENU_PATH, MENU_ICON, MENU_PARENT, MENU_STATUS, MENU_DT_CREATE, MENU_UID_CREATE, MENU_DT_LUPD, MENU_UID_LUPD) ") -> INSERT INTO T_CORE_MENU_EX (MENU_ID, MENU_APPS_CODE, MENU_GROUP_LABEL, MENU_GROUP_LABEL_OTH, MENU_NAME, MENU_NAME_OTH, MENU_SEQ, MENU_PATH, MENU_ICON, MENU_PARENT, MENU_STATUS, MENU_DT_CREATE, MENU_UID_CREATE, MENU_DT_LUPD, MENU_UID_LUPD) | N44: =CONCATENATE(" VALUES('",A44,"','",B44,"','",D44,"','",E44,"','",F44,"','",G44,"',",IF(H44="NULL","NULL",CONCATENATE("'",H44,"'")),",",IF(I44="NULL","NULL",CONCATENATE("'",I44,"'")),",",IF(J44="NULL","NULL",CONCATENATE("'",J44,"'")),",",IF(K44="NULL","NULL",CONCATENATE("'",K44,"'")),",'A',NOW(),'SYS',NOW(),'SYS');") -> VALUES('CKDO_MA_030000','CKDO','Administrations','Administrations','Administrations','Administrations','30000',NULL,'group',NULL,'A',NOW(),'SYS',NOW(),'SYS'); | O44: =CONCATENATE(M44,N44) -> INSERT INTO T_CORE_MENU_EX (MENU_ID, MENU_APPS_CODE, MENU_GROUP_LABEL, MENU_GROUP_LABEL_OTH, MENU_NAME, MENU_NAME_OTH, MENU_SEQ, MENU_PATH, MENU_ICON, MENU_PARENT, MENU_STATUS, MENU_DT_CREATE, MENU_UID_CREATE, MENU_DT_LUPD, MENU_UID_LUPD) VALUES('CKDO_MA_030000','CKDO','Administrations','Administrations','Administrations','Administrations','30000',NULL,'group',NULL,'A',NOW(),'SYS',NOW(),'SYS');
A45: CKDO_MA_030100 | B45: CKDO | F45: Account Profile | G45: Account Profile | H45: 30100 | I45: /accountProfile | J45: NULL | K45: CKDO_MA_030000 | L45: A | M45: =CONCATENATE("INSERT INTO T_CORE_MENU_EX (MENU_ID, MENU_APPS_CODE, MENU_GROUP_LABEL, MENU_GROUP_LABEL_OTH, MENU_NAME, MENU_NAME_OTH, MENU_SEQ, MENU_PATH, MENU_ICON, MENU_PARENT, MENU_STATUS, MENU_DT_CREATE, MENU_UID_CREATE, MENU_DT_LUPD, MENU_UID_LUPD) ") -> INSERT INTO T_CORE_MENU_EX (MENU_ID, MENU_APPS_CODE, MENU_GROUP_LABEL, MENU_GROUP_LABEL_OTH, MENU_NAME, MENU_NAME_OTH, MENU_SEQ, MENU_PATH, MENU_ICON, MENU_PARENT, MENU_STATUS, MENU_DT_CREATE, MENU_UID_CREATE, MENU_DT_LUPD, MENU_UID_LUPD) | N45: =CONCATENATE(" VALUES('",A45,"','",B45,"','",D45,"','",E45,"','",F45,"','",G45,"',",IF(H45="NULL","NULL",CONCATENATE("'",H45,"'")),",",IF(I45="NULL","NULL",CONCATENATE("'",I45,"'")),",",IF(J45="NULL","NULL",CONCATENATE("'",J45,"'")),",",IF(K45="NULL","NULL",CONCATENATE("'",K45,"'")),",'A',NOW(),'SYS',NOW(),'SYS');") -> VALUES('CKDO_MA_030100','CKDO','','','Account Profile','Account Profile','30100','/accountProfile',NULL,'CKDO_MA_030000','A',NOW(),'SYS',NOW(),'SYS'); | O45: =CONCATENATE(M45,N45) -> INSERT INTO T_CORE_MENU_EX (MENU_ID, MENU_APPS_CODE, MENU_GROUP_LABEL, MENU_GROUP_LABEL_OTH, MENU_NAME, MENU_NAME_OTH, MENU_SEQ, MENU_PATH, MENU_ICON, MENU_PARENT, MENU_STATUS, MENU_DT_CREATE, MENU_UID_CREATE, MENU_DT_LUPD, MENU_UID_LUPD) VALUES('CKDO_MA_030100','CKDO','','','Account Profile','Account Profile','30100','/accountProfile',NULL,'CKDO_MA_030000','A',NOW(),'SYS',NOW(),'SYS');
A46: CKDO_MA_030200 | B46: CKDO | F46: Users | G46: Users | H46: 30200 | I46: /accountUsers | J46: NULL | K46: CKDO_MA_030000 | L46: A | M46: =CONCATENATE("INSERT INTO T_CORE_MENU_EX (MENU_ID, MENU_APPS_CODE, MENU_GROUP_LABEL, MENU_GROUP_LABEL_OTH, MENU_NAME, MENU_NAME_OTH, MENU_SEQ, MENU_PATH, MENU_ICON, MENU_PARENT, MENU_STATUS, MENU_DT_CREATE, MENU_UID_CREATE, MENU_DT_LUPD, MENU_UID_LUPD) ") -> INSERT INTO T_CORE_MENU_EX (MENU_ID, MENU_APPS_CODE, MENU_GROUP_LABEL, MENU_GROUP_LABEL_OTH, MENU_NAME, MENU_NAME_OTH, MENU_SEQ, MENU_PATH, MENU_ICON, MENU_PARENT, MENU_STATUS, MENU_DT_CREATE, MENU_UID_CREATE, MENU_DT_LUPD, MENU_UID_LUPD) | N46: =CONCATENATE(" VALUES('",A46,"','",B46,"','",D46,"','",E46,"','",F46,"','",G46,"',",IF(H46="NULL","NULL",CONCATENATE("'",H46,"'")),",",IF(I46="NULL","NULL",CONCATENATE("'",I46,"'")),",",IF(J46="NULL","NULL",CONCATENATE("'",J46,"'")),",",IF(K46="NULL","NULL",CONCATENATE("'",K46,"'")),",'A',NOW(),'SYS',NOW(),'SYS');") -> VALUES('CKDO_MA_030200','CKDO','','','Users','Users','30200','/accountUsers',NULL,'CKDO_MA_030000','A',NOW(),'SYS',NOW(),'SYS'); | O46: =CONCATENATE(M46,N46) -> INSERT INTO T_CORE_MENU_EX (MENU_ID, MENU_APPS_CODE, MENU_GROUP_LABEL, MENU_GROUP_LABEL_OTH, MENU_NAME, MENU_NAME_OTH, MENU_SEQ, MENU_PATH, MENU_ICON, MENU_PARENT, MENU_STATUS, MENU_DT_CREATE, MENU_UID_CREATE, MENU_DT_LUPD, MENU_UID_LUPD) VALUES('CKDO_MA_030200','CKDO','','','Users','Users','30200','/accountUsers',NULL,'CKDO_MA_030000','A',NOW(),'SYS',NOW(),'SYS');
A47: CKDO_MA_030300 | B47: CKDO | F47: Authorisations | G47: Authorisations | H47: 30400 | I47: /accountAuthorisations | J47: NULL | K47: CKDO_MA_030000 | L47: A | M47: =CONCATENATE("INSERT INTO T_CORE_MENU_EX (MENU_ID, MENU_APPS_CODE, MENU_GROUP_LABEL, MENU_GROUP_LABEL_OTH, MENU_NAME, MENU_NAME_OTH, MENU_SEQ, MENU_PATH, MENU_ICON, MENU_PARENT, MENU_STATUS, MENU_DT_CREATE, MENU_UID_CREATE, MENU_DT_LUPD, MENU_UID_LUPD) ") -> INSERT INTO T_CORE_MENU_EX (MENU_ID, MENU_APPS_CODE, MENU_GROUP_LABEL, MENU_GROUP_LABEL_OTH, MENU_NAME, MENU_NAME_OTH, MENU_SEQ, MENU_PATH, MENU_ICON, MENU_PARENT, MENU_STATUS, MENU_DT_CREATE, MENU_UID_CREATE, MENU_DT_LUPD, MENU_UID_LUPD) | N47: =CONCATENATE(" VALUES('",A47,"','",B47,"','",D47,"','",E47,"','",F47,"','",G47,"',",IF(H47="NULL","NULL",CONCATENATE("'",H47,"'")),",",IF(I47="NULL","NULL",CONCATENATE("'",I47,"'")),",",IF(J47="NULL","NULL",CONCATENATE("'",J47,"'")),",",IF(K47="NULL","NULL",CONCATENATE("'",K47,"'")),",'A',NOW(),'SYS',NOW(),'SYS');") -> VALUES('CKDO_MA_030300','CKDO','','','Authorisations','Authorisations','30400','/accountAuthorisations',NULL,'CKDO_MA_030000','A',NOW(),'SYS',NOW(),'SYS'); | O47: =CONCATENATE(M47,N47) -> INSERT INTO T_CORE_MENU_EX (MENU_ID, MENU_APPS_CODE, MENU_GROUP_LABEL, MENU_GROUP_LABEL_OTH, MENU_NAME, MENU_NAME_OTH, MENU_SEQ, MENU_PATH, MENU_ICON, MENU_PARENT, MENU_STATUS, MENU_DT_CREATE, MENU_UID_CREATE, MENU_DT_LUPD, MENU_UID_LUPD) VALUES('CKDO_MA_030300','CKDO','','','Authorisations','Authorisations','30400','/accountAuthorisations',NULL,'CKDO_MA_030000','A',NOW(),'SYS',NOW(),'SYS');
A48: CKDO_MP_020000 | B48: CKDO | D48: DO Payments | E48: DO Payments | F48: DO Payments | G48: DO Payments | H48: 20000 | I48: NULL | J48: payment | K48: NULL | L48: A | M48: =CONCATENATE("INSERT INTO T_CORE_MENU_EX (MENU_ID, MENU_APPS_CODE, MENU_GROUP_LABEL, MENU_GROUP_LABEL_OTH, MENU_NAME, MENU_NAME_OTH, MENU_SEQ, MENU_PATH, MENU_ICON, MENU_PARENT, MENU_STATUS, MENU_DT_CREATE, MENU_UID_CREATE, MENU_DT_LUPD, MENU_UID_LUPD) ") -> INSERT INTO T_CORE_MENU_EX (MENU_ID, MENU_APPS_CODE, MENU_GROUP_LABEL, MENU_GROUP_LABEL_OTH, MENU_NAME, MENU_NAME_OTH, MENU_SEQ, MENU_PATH, MENU_ICON, MENU_PARENT, MENU_STATUS, MENU_DT_CREATE, MENU_UID_CREATE, MENU_DT_LUPD, MENU_UID_LUPD) | N48: =CONCATENATE(" VALUES('",A48,"','",B48,"','",D48,"','",E48,"','",F48,"','",G48,"',",IF(H48="NULL","NULL",CONCATENATE("'",H48,"'")),",",IF(I48="NULL","NULL",CONCATENATE("'",I48,"'")),",",IF(J48="NULL","NULL",CONCATENATE("'",J48,"'")),",",IF(K48="NULL","NULL",CONCATENATE("'",K48,"'")),",'A',NOW(),'SYS',NOW(),'SYS');") -> VALUES('CKDO_MP_020000','CKDO','DO Payments','DO Payments','DO Payments','DO Payments','20000',NULL,'payment',NULL,'A',NOW(),'SYS',NOW(),'SYS'); | O48: =CONCATENATE(M48,N48) -> INSERT INTO T_CORE_MENU_EX (MENU_ID, MENU_APPS_CODE, MENU_GROUP_LABEL, MENU_GROUP_LABEL_OTH, MENU_NAME, MENU_NAME_OTH, MENU_SEQ, MENU_PATH, MENU_ICON, MENU_PARENT, MENU_STATUS, MENU_DT_CREATE, MENU_UID_CREATE, MENU_DT_LUPD, MENU_UID_LUPD) VALUES('CKDO_MP_020000','CKDO','DO Payments','DO Payments','DO Payments','DO Payments','20000',NULL,'payment',NULL,'A',NOW(),'SYS',NOW(),'SYS');
A49: CKDO_MP_020100 | B49: CKDO | D49: Payments | E49: Payments | F49: Payments | G49: Payments | H49: 20100 | I49: /payments/active/list | J49: NULL | K49: CKDO_MP_020000 | L49: A | M49: =CONCATENATE("INSERT INTO T_CORE_MENU_EX (MENU_ID, MENU_APPS_CODE, MENU_GROUP_LABEL, MENU_GROUP_LABEL_OTH, MENU_NAME, MENU_NAME_OTH, MENU_SEQ, MENU_PATH, MENU_ICON, MENU_PARENT, MENU_STATUS, MENU_DT_CREATE, MENU_UID_CREATE, MENU_DT_LUPD, MENU_UID_LUPD) ") -> INSERT INTO T_CORE_MENU_EX (MENU_ID, MENU_APPS_CODE, MENU_GROUP_LABEL, MENU_GROUP_LABEL_OTH, MENU_NAME, MENU_NAME_OTH, MENU_SEQ, MENU_PATH, MENU_ICON, MENU_PARENT, MENU_STATUS, MENU_DT_CREATE, MENU_UID_CREATE, MENU_DT_LUPD, MENU_UID_LUPD) | N49: =CONCATENATE(" VALUES('",A49,"','",B49,"','",D49,"','",E49,"','",F49,"','",G49,"',",IF(H49="NULL","NULL",CONCATENATE("'",H49,"'")),",",IF(I49="NULL","NULL",CONCATENATE("'",I49,"'")),",",IF(J49="NULL","NULL",CONCATENATE("'",J49,"'")),",",IF(K49="NULL","NULL",CONCATENATE("'",K49,"'")),",'A',NOW(),'SYS',NOW(),'SYS');") -> VALUES('CKDO_MP_020100','CKDO','Payments','Payments','Payments','Payments','20100','/payments/active/list',NULL,'CKDO_MP_020000','A',NOW(),'SYS',NOW(),'SYS'); | O49: =CONCATENATE(M49,N49) -> INSERT INTO T_CORE_MENU_EX (MENU_ID, MENU_APPS_CODE, MENU_GROUP_LABEL, MENU_GROUP_LABEL_OTH, MENU_NAME, MENU_NAME_OTH, MENU_SEQ, MENU_PATH, MENU_ICON, MENU_PARENT, MENU_STATUS, MENU_DT_CREATE, MENU_UID_CREATE, MENU_DT_LUPD, MENU_UID_LUPD) VALUES('CKDO_MP_020100','CKDO','Payments','Payments','Payments','Payments','20100','/payments/active/list',NULL,'CKDO_MP_020000','A',NOW(),'SYS',NOW(),'SYS');
A50: CKDO_MP_020300 | B50: CKDO | D50: Transactions | E50: Transactions | F50: Transactions | G50: Transactions | H50: 20300 | I50: /payments/transactions/list | J50: NULL | K50: CKDO_MP_020000 | L50: A | M50: =CONCATENATE("INSERT INTO T_CORE_MENU_EX (MENU_ID, MENU_APPS_CODE, MENU_GROUP_LABEL, MENU_GROUP_LABEL_OTH, MENU_NAME, MENU_NAME_OTH, MENU_SEQ, MENU_PATH, MENU_ICON, MENU_PARENT, MENU_STATUS, MENU_DT_CREATE, MENU_UID_CREATE, MENU_DT_LUPD, MENU_UID_LUPD) ") -> INSERT INTO T_CORE_MENU_EX (MENU_ID, MENU_APPS_CODE, MENU_GROUP_LABEL, MENU_GROUP_LABEL_OTH, MENU_NAME, MENU_NAME_OTH, MENU_SEQ, MENU_PATH, MENU_ICON, MENU_PARENT, MENU_STATUS, MENU_DT_CREATE, MENU_UID_CREATE, MENU_DT_LUPD, MENU_UID_LUPD) | N50: =CONCATENATE(" VALUES('",A50,"','",B50,"','",D50,"','",E50,"','",F50,"','",G50,"',",IF(H50="NULL","NULL",CONCATENATE("'",H50,"'")),",",IF(I50="NULL","NULL",CONCATENATE("'",I50,"'")),",",IF(J50="NULL","NULL",CONCATENATE("'",J50,"'")),",",IF(K50="NULL","NULL",CONCATENATE("'",K50,"'")),",'A',NOW(),'SYS',NOW(),'SYS');") -> VALUES('CKDO_MP_020300','CKDO','Transactions','Transactions','Transactions','Transactions','20300','/payments/transactions/list',NULL,'CKDO_MP_020000','A',NOW(),'SYS',NOW(),'SYS'); | O50: =CONCATENATE(M50,N50) -> INSERT INTO T_CORE_MENU_EX (MENU_ID, MENU_APPS_CODE, MENU_GROUP_LABEL, MENU_GROUP_LABEL_OTH, MENU_NAME, MENU_NAME_OTH, MENU_SEQ, MENU_PATH, MENU_ICON, MENU_PARENT, MENU_STATUS, MENU_DT_CREATE, MENU_UID_CREATE, MENU_DT_LUPD, MENU_UID_LUPD) VALUES('CKDO_MP_020300','CKDO','Transactions','Transactions','Transactions','Transactions','20300','/payments/transactions/list',NULL,'CKDO_MP_020000','A',NOW(),'SYS',NOW(),'SYS');
A51: CKDO_MP_040000 | B51: CKDO | D51: Payments | E51: Payments | F51: Payments | G51: Payments | H51: 40000 | I51: /applications/payments/do/sl | J51: payment | K51: NULL | L51: A | M51: =CONCATENATE("INSERT INTO T_CORE_MENU_EX (MENU_ID, MENU_APPS_CODE, MENU_GROUP_LABEL, MENU_GROUP_LABEL_OTH, MENU_NAME, MENU_NAME_OTH, MENU_SEQ, MENU_PATH, MENU_ICON, MENU_PARENT, MENU_STATUS, MENU_DT_CREATE, MENU_UID_CREATE, MENU_DT_LUPD, MENU_UID_LUPD) ") -> INSERT INTO T_CORE_MENU_EX (MENU_ID, MENU_APPS_CODE, MENU_GROUP_LABEL, MENU_GROUP_LABEL_OTH, MENU_NAME, MENU_NAME_OTH, MENU_SEQ, MENU_PATH, MENU_ICON, MENU_PARENT, MENU_STATUS, MENU_DT_CREATE, MENU_UID_CREATE, MENU_DT_LUPD, MENU_UID_LUPD) | N51: =CONCATENATE(" VALUES('",A51,"','",B51,"','",D51,"','",E51,"','",F51,"','",G51,"',",IF(H51="NULL","NULL",CONCATENATE("'",H51,"'")),",",IF(I51="NULL","NULL",CONCATENATE("'",I51,"'")),",",IF(J51="NULL","NULL",CONCATENATE("'",J51,"'")),",",IF(K51="NULL","NULL",CONCATENATE("'",K51,"'")),",'A',NOW(),'SYS',NOW(),'SYS');") -> VALUES('CKDO_MP_040000','CKDO','Payments','Payments','Payments','Payments','40000','/applications/payments/do/sl','payment',NULL,'A',NOW(),'SYS',NOW(),'SYS'); | O51: =CONCATENATE(M51,N51) -> INSERT INTO T_CORE_MENU_EX (MENU_ID, MENU_APPS_CODE, MENU_GROUP_LABEL, MENU_GROUP_LABEL_OTH, MENU_NAME, MENU_NAME_OTH, MENU_SEQ, MENU_PATH, MENU_ICON, MENU_PARENT, MENU_STATUS, MENU_DT_CREATE, MENU_UID_CREATE, MENU_DT_LUPD, MENU_UID_LUPD) VALUES('CKDO_MP_040000','CKDO','Payments','Payments','Payments','Payments','40000','/applications/payments/do/sl','payment',NULL,'A',NOW(),'SYS',NOW(),'SYS');
A52: CKDO_MP_070000 | B52: CKDO | D52: Payments | E52: Payments | F52: Payments | G52: Payments | H52: 70000 | I52: /applications/payments/viewPaymentHistory | J52: receipt | K52: NULL | L52: A | M52: =CONCATENATE("INSERT INTO T_CORE_MENU_EX (MENU_ID, MENU_APPS_CODE, MENU_GROUP_LABEL, MENU_GROUP_LABEL_OTH, MENU_NAME, MENU_NAME_OTH, MENU_SEQ, MENU_PATH, MENU_ICON, MENU_PARENT, MENU_STATUS, MENU_DT_CREATE, MENU_UID_CREATE, MENU_DT_LUPD, MENU_UID_LUPD) ") -> INSERT INTO T_CORE_MENU_EX (MENU_ID, MENU_APPS_CODE, MENU_GROUP_LABEL, MENU_GROUP_LABEL_OTH, MENU_NAME, MENU_NAME_OTH, MENU_SEQ, MENU_PATH, MENU_ICON, MENU_PARENT, MENU_STATUS, MENU_DT_CREATE, MENU_UID_CREATE, MENU_DT_LUPD, MENU_UID_LUPD) | N52: =CONCATENATE(" VALUES('",A52,"','",B52,"','",D52,"','",E52,"','",F52,"','",G52,"',",IF(H52="NULL","NULL",CONCATENATE("'",H52,"'")),",",IF(I52="NULL","NULL",CONCATENATE("'",I52,"'")),",",IF(J52="NULL","NULL",CONCATENATE("'",J52,"'")),",",IF(K52="NULL","NULL",CONCATENATE("'",K52,"'")),",'A',NOW(),'SYS',NOW(),'SYS');") -> VALUES('CKDO_MP_070000','CKDO','Payments','Payments','Payments','Payments','70000','/applications/payments/viewPaymentHistory','receipt',NULL,'A',NOW(),'SYS',NOW(),'SYS'); | O52: =CONCATENATE(M52,N52) -> INSERT INTO T_CORE_MENU_EX (MENU_ID, MENU_APPS_CODE, MENU_GROUP_LABEL, MENU_GROUP_LABEL_OTH, MENU_NAME, MENU_NAME_OTH, MENU_SEQ, MENU_PATH, MENU_ICON, MENU_PARENT, MENU_STATUS, MENU_DT_CREATE, MENU_UID_CREATE, MENU_DT_LUPD, MENU_UID_LUPD) VALUES('CKDO_MP_070000','CKDO','Payments','Payments','Payments','Payments','70000','/applications/payments/viewPaymentHistory','receipt',NULL,'A',NOW(),'SYS',NOW(),'SYS');
A53: CKDO_MSA_060000 | B53: CKDO | D53: System Administrations | E53: System Administrations | F53: System Administrations | G53: System Administrations | H53: 60000 | I53: NULL | J53: settings | K53: NULL | L53: A | M53: =CONCATENATE("INSERT INTO T_CORE_MENU_EX (MENU_ID, MENU_APPS_CODE, MENU_GROUP_LABEL, MENU_GROUP_LABEL_OTH, MENU_NAME, MENU_NAME_OTH, MENU_SEQ, MENU_PATH, MENU_ICON, MENU_PARENT, MENU_STATUS, MENU_DT_CREATE, MENU_UID_CREATE, MENU_DT_LUPD, MENU_UID_LUPD) ") -> INSERT INTO T_CORE_MENU_EX (MENU_ID, MENU_APPS_CODE, MENU_GROUP_LABEL, MENU_GROUP_LABEL_OTH, MENU_NAME, MENU_NAME_OTH, MENU_SEQ, MENU_PATH, MENU_ICON, MENU_PARENT, MENU_STATUS, MENU_DT_CREATE, MENU_UID_CREATE, MENU_DT_LUPD, MENU_UID_LUPD) | N53: =CONCATENATE(" VALUES('",A53,"','",B53,"','",D53,"','",E53,"','",F53,"','",G53,"',",IF(H53="NULL","NULL",CONCATENATE("'",H53,"'")),",",IF(I53="NULL","NULL",CONCATENATE("'",I53,"'")),",",IF(J53="NULL","NULL",CONCATENATE("'",J53,"'")),",",IF(K53="NULL","NULL",CONCATENATE("'",K53,"'")),",'A',NOW(),'SYS',NOW(),'SYS');") -> VALUES('CKDO_MSA_060000','CKDO','System Administrations','System Administrations','System Administrations','System Administrations','60000',NULL,'settings',NULL,'A',NOW(),'SYS',NOW(),'SYS'); | O53: =CONCATENATE(M53,N53) -> INSERT INTO T_CORE_MENU_EX (MENU_ID, MENU_APPS_CODE, MENU_GROUP_LABEL, MENU_GROUP_LABEL_OTH, MENU_NAME, MENU_NAME_OTH, MENU_SEQ, MENU_PATH, MENU_ICON, MENU_PARENT, MENU_STATUS, MENU_DT_CREATE, MENU_UID_CREATE, MENU_DT_LUPD, MENU_UID_LUPD) VALUES('CKDO_MSA_060000','CKDO','System Administrations','System Administrations','System Administrations','System Administrations','60000',NULL,'settings',NULL,'A',NOW(),'SYS',NOW(),'SYS');
A54: CKDO_MSA_060100 | B54: CKDO | F54: Announcement Setup | G54: Announcement Setup | H54: 60100 | I54: /configuration/announcement/list | J54: NULL | K54: CKDO_MSA_060000 | L54: A | M54: =CONCATENATE("INSERT INTO T_CORE_MENU_EX (MENU_ID, MENU_APPS_CODE, MENU_GROUP_LABEL, MENU_GROUP_LABEL_OTH, MENU_NAME, MENU_NAME_OTH, MENU_SEQ, MENU_PATH, MENU_ICON, MENU_PARENT, MENU_STATUS, MENU_DT_CREATE, MENU_UID_CREATE, MENU_DT_LUPD, MENU_UID_LUPD) ") -> INSERT INTO T_CORE_MENU_EX (MENU_ID, MENU_APPS_CODE, MENU_GROUP_LABEL, MENU_GROUP_LABEL_OTH, MENU_NAME, MENU_NAME_OTH, MENU_SEQ, MENU_PATH, MENU_ICON, MENU_PARENT, MENU_STATUS, MENU_DT_CREATE, MENU_UID_CREATE, MENU_DT_LUPD, MENU_UID_LUPD) | N54: =CONCATENATE(" VALUES('",A54,"','",B54,"','",D54,"','",E54,"','",F54,"','",G54,"',",IF(H54="NULL","NULL",CONCATENATE("'",H54,"'")),",",IF(I54="NULL","NULL",CONCATENATE("'",I54,"'")),",",IF(J54="NULL","NULL",CONCATENATE("'",J54,"'")),",",IF(K54="NULL","NULL",CONCATENATE("'",K54,"'")),",'A',NOW(),'SYS',NOW(),'SYS');") -> VALUES('CKDO_MSA_060100','CKDO','','','Announcement Setup','Announcement Setup','60100','/configuration/announcement/list',NULL,'CKDO_MSA_060000','A',NOW(),'SYS',NOW(),'SYS'); | O54: =CONCATENATE(M54,N54) -> INSERT INTO T_CORE_MENU_EX (MENU_ID, MENU_APPS_CODE, MENU_GROUP_LABEL, MENU_GROUP_LABEL_OTH, MENU_NAME, MENU_NAME_OTH, MENU_SEQ, MENU_PATH, MENU_ICON, MENU_PARENT, MENU_STATUS, MENU_DT_CREATE, MENU_UID_CREATE, MENU_DT_LUPD, MENU_UID_LUPD) VALUES('CKDO_MSA_060100','CKDO','','','Announcement Setup','Announcement Setup','60100','/configuration/announcement/list',NULL,'CKDO_MSA_060000','A',NOW(),'SYS',NOW(),'SYS');
A55: CKDO_MSA_060200 | B55: CKDO | F55: Notification Preferences | G55: Notification Preferences | H55: 60200 | I55: /configuration/notification/preferences/list | J55: NULL | K55: CKDO_MSA_060000 | L55: A | M55: =CONCATENATE("INSERT INTO T_CORE_MENU_EX (MENU_ID, MENU_APPS_CODE, MENU_GROUP_LABEL, MENU_GROUP_LABEL_OTH, MENU_NAME, MENU_NAME_OTH, MENU_SEQ, MENU_PATH, MENU_ICON, MENU_PARENT, MENU_STATUS, MENU_DT_CREATE, MENU_UID_CREATE, MENU_DT_LUPD, MENU_UID_LUPD) ") -> INSERT INTO T_CORE_MENU_EX (MENU_ID, MENU_APPS_CODE, MENU_GROUP_LABEL, MENU_GROUP_LABEL_OTH, MENU_NAME, MENU_NAME_OTH, MENU_SEQ, MENU_PATH, MENU_ICON, MENU_PARENT, MENU_STATUS, MENU_DT_CREATE, MENU_UID_CREATE, MENU_DT_LUPD, MENU_UID_LUPD) | N55: =CONCATENATE(" VALUES('",A55,"','",B55,"','",D55,"','",E55,"','",F55,"','",G55,"',",IF(H55="NULL","NULL",CONCATENATE("'",H55,"'")),",",IF(I55="NULL","NULL",CONCATENATE("'",I55,"'")),",",IF(J55="NULL","NULL",CONCATENATE("'",J55,"'")),",",IF(K55="NULL","NULL",CONCATENATE("'",K55,"'")),",'A',NOW(),'SYS',NOW(),'SYS');") -> VALUES('CKDO_MSA_060200','CKDO','','','Notification Preferences','Notification Preferences','60200','/configuration/notification/preferences/list',NULL,'CKDO_MSA_060000','A',NOW(),'SYS',NOW(),'SYS'); | O55: =CONCATENATE(M55,N55) -> INSERT INTO T_CORE_MENU_EX (MENU_ID, MENU_APPS_CODE, MENU_GROUP_LABEL, MENU_GROUP_LABEL_OTH, MENU_NAME, MENU_NAME_OTH, MENU_SEQ, MENU_PATH, MENU_ICON, MENU_PARENT, MENU_STATUS, MENU_DT_CREATE, MENU_UID_CREATE, MENU_DT_LUPD, MENU_UID_LUPD) VALUES('CKDO_MSA_060200','CKDO','','','Notification Preferences','Notification Preferences','60200','/configuration/notification/preferences/list',NULL,'CKDO_MSA_060000','A',NOW(),'SYS',NOW(),'SYS');
A56: CKDO_MSA_060300 | B56: CKDO | F56: System Parameters | G56: System Parameters | H56: 60300 | I56: /administrations/sysparam/list | J56: NULL | K56: CKDO_MSA_060000 | L56: A | M56: =CONCATENATE("INSERT INTO T_CORE_MENU_EX (MENU_ID, MENU_APPS_CODE, MENU_GROUP_LABEL, MENU_GROUP_LABEL_OTH, MENU_NAME, MENU_NAME_OTH, MENU_SEQ, MENU_PATH, MENU_ICON, MENU_PARENT, MENU_STATUS, MENU_DT_CREATE, MENU_UID_CREATE, MENU_DT_LUPD, MENU_UID_LUPD) ") -> INSERT INTO T_CORE_MENU_EX (MENU_ID, MENU_APPS_CODE, MENU_GROUP_LABEL, MENU_GROUP_LABEL_OTH, MENU_NAME, MENU_NAME_OTH, MENU_SEQ, MENU_PATH, MENU_ICON, MENU_PARENT, MENU_STATUS, MENU_DT_CREATE, MENU_UID_CREATE, MENU_DT_LUPD, MENU_UID_LUPD) | N56: =CONCATENATE(" VALUES('",A56,"','",B56,"','",D56,"','",E56,"','",F56,"','",G56,"',",IF(H56="NULL","NULL",CONCATENATE("'",H56,"'")),",",IF(I56="NULL","NULL",CONCATENATE("'",I56,"'")),",",IF(J56="NULL","NULL",CONCATENATE("'",J56,"'")),",",IF(K56="NULL","NULL",CONCATENATE("'",K56,"'")),",'A',NOW(),'SYS',NOW(),'SYS');") -> VALUES('CKDO_MSA_060300','CKDO','','','System Parameters','System Parameters','60300','/administrations/sysparam/list',NULL,'CKDO_MSA_060000','A',NOW(),'SYS',NOW(),'SYS'); | O56: =CONCATENATE(M56,N56) -> INSERT INTO T_CORE_MENU_EX (MENU_ID, MENU_APPS_CODE, MENU_GROUP_LABEL, MENU_GROUP_LABEL_OTH, MENU_NAME, MENU_NAME_OTH, MENU_SEQ, MENU_PATH, MENU_ICON, MENU_PARENT, MENU_STATUS, MENU_DT_CREATE, MENU_UID_CREATE, MENU_DT_LUPD, MENU_UID_LUPD) VALUES('CKDO_MSA_060300','CKDO','','','System Parameters','System Parameters','60300','/administrations/sysparam/list',NULL,'CKDO_MSA_060000','A',NOW(),'SYS',NOW(),'SYS');
A57: CKDO_MSA_060400 | B57: CKDO | F57: Audit Logs | G57: Audit Logs | H57: 60400 | I57: /administrations/audit/list | J57: NULL | K57: CKDO_MSA_060000 | L57: A | M57: =CONCATENATE("INSERT INTO T_CORE_MENU_EX (MENU_ID, MENU_APPS_CODE, MENU_GROUP_LABEL, MENU_GROUP_LABEL_OTH, MENU_NAME, MENU_NAME_OTH, MENU_SEQ, MENU_PATH, MENU_ICON, MENU_PARENT, MENU_STATUS, MENU_DT_CREATE, MENU_UID_CREATE, MENU_DT_LUPD, MENU_UID_LUPD) ") -> INSERT INTO T_CORE_MENU_EX (MENU_ID, MENU_APPS_CODE, MENU_GROUP_LABEL, MENU_GROUP_LABEL_OTH, MENU_NAME, MENU_NAME_OTH, MENU_SEQ, MENU_PATH, MENU_ICON, MENU_PARENT, MENU_STATUS, MENU_DT_CREATE, MENU_UID_CREATE, MENU_DT_LUPD, MENU_UID_LUPD) | N57: =CONCATENATE(" VALUES('",A57,"','",B57,"','",D57,"','",E57,"','",F57,"','",G57,"',",IF(H57="NULL","NULL",CONCATENATE("'",H57,"'")),",",IF(I57="NULL","NULL",CONCATENATE("'",I57,"'")),",",IF(J57="NULL","NULL",CONCATENATE("'",J57,"'")),",",IF(K57="NULL","NULL",CONCATENATE("'",K57,"'")),",'A',NOW(),'SYS',NOW(),'SYS');") -> VALUES('CKDO_MSA_060400','CKDO','','','Audit Logs','Audit Logs','60400','/administrations/audit/list',NULL,'CKDO_MSA_060000','A',NOW(),'SYS',NOW(),'SYS'); | O57: =CONCATENATE(M57,N57) -> INSERT INTO T_CORE_MENU_EX (MENU_ID, MENU_APPS_CODE, MENU_GROUP_LABEL, MENU_GROUP_LABEL_OTH, MENU_NAME, MENU_NAME_OTH, MENU_SEQ, MENU_PATH, MENU_ICON, MENU_PARENT, MENU_STATUS, MENU_DT_CREATE, MENU_UID_CREATE, MENU_DT_LUPD, MENU_UID_LUPD) VALUES('CKDO_MSA_060400','CKDO','','','Audit Logs','Audit Logs','60400','/administrations/audit/list',NULL,'CKDO_MSA_060000','A',NOW(),'SYS',NOW(),'SYS');
A58: CKDO_MSA_060500 | B58: CKDO | F58: Exceptions | G58: Exceptions | H58: 60500 | I58: /administrations/exception/list | J58: NULL | K58: CKDO_MSA_060000 | L58: A | M58: =CONCATENATE("INSERT INTO T_CORE_MENU_EX (MENU_ID, MENU_APPS_CODE, MENU_GROUP_LABEL, MENU_GROUP_LABEL_OTH, MENU_NAME, MENU_NAME_OTH, MENU_SEQ, MENU_PATH, MENU_ICON, MENU_PARENT, MENU_STATUS, MENU_DT_CREATE, MENU_UID_CREATE, MENU_DT_LUPD, MENU_UID_LUPD) ") -> INSERT INTO T_CORE_MENU_EX (MENU_ID, MENU_APPS_CODE, MENU_GROUP_LABEL, MENU_GROUP_LABEL_OTH, MENU_NAME, MENU_NAME_OTH, MENU_SEQ, MENU_PATH, MENU_ICON, MENU_PARENT, MENU_STATUS, MENU_DT_CREATE, MENU_UID_CREATE, MENU_DT_LUPD, MENU_UID_LUPD) | N58: =CONCATENATE(" VALUES('",A58,"','",B58,"','",D58,"','",E58,"','",F58,"','",G58,"',",IF(H58="NULL","NULL",CONCATENATE("'",H58,"'")),",",IF(I58="NULL","NULL",CONCATENATE("'",I58,"'")),",",IF(J58="NULL","NULL",CONCATENATE("'",J58,"'")),",",IF(K58="NULL","NULL",CONCATENATE("'",K58,"'")),",'A',NOW(),'SYS',NOW(),'SYS');") -> VALUES('CKDO_MSA_060500','CKDO','','','Exceptions','Exceptions','60500','/administrations/exception/list',NULL,'CKDO_MSA_060000','A',NOW(),'SYS',NOW(),'SYS'); | O58: =CONCATENATE(M58,N58) -> INSERT INTO T_CORE_MENU_EX (MENU_ID, MENU_APPS_CODE, MENU_GROUP_LABEL, MENU_GROUP_LABEL_OTH, MENU_NAME, MENU_NAME_OTH, MENU_SEQ, MENU_PATH, MENU_ICON, MENU_PARENT, MENU_STATUS, MENU_DT_CREATE, MENU_UID_CREATE, MENU_DT_LUPD, MENU_UID_LUPD) VALUES('CKDO_MSA_060500','CKDO','','','Exceptions','Exceptions','60500','/administrations/exception/list',NULL,'CKDO_MSA_060000','A',NOW(),'SYS',NOW(),'SYS');
A59: CKDO_MSA_060600 | B59: CKDO | F59: Manage All Users | G59: Manage All Users | H59: 60600 | I59: /manageUsers/users/all/list | J59: NULL | K59: CKDO_MSA_060000 | M59: =CONCATENATE("INSERT INTO T_CORE_MENU_EX (MENU_ID, MENU_APPS_CODE, MENU_GROUP_LABEL, MENU_GROUP_LABEL_OTH, MENU_NAME, MENU_NAME_OTH, MENU_SEQ, MENU_PATH, MENU_ICON, MENU_PARENT, MENU_STATUS, MENU_DT_CREATE, MENU_UID_CREATE, MENU_DT_LUPD, MENU_UID_LUPD) ") -> INSERT INTO T_CORE_MENU_EX (MENU_ID, MENU_APPS_CODE, MENU_GROUP_LABEL, MENU_GROUP_LABEL_OTH, MENU_NAME, MENU_NAME_OTH, MENU_SEQ, MENU_PATH, MENU_ICON, MENU_PARENT, MENU_STATUS, MENU_DT_CREATE, MENU_UID_CREATE, MENU_DT_LUPD, MENU_UID_LUPD) | N59: =CONCATENATE(" VALUES('",A59,"','",B59,"','",D59,"','",E59,"','",F59,"','",G59,"',",IF(H59="NULL","NULL",CONCATENATE("'",H59,"'")),",",IF(I59="NULL","NULL",CONCATENATE("'",I59,"'")),",",IF(J59="NULL","NULL",CONCATENATE("'",J59,"'")),",",IF(K59="NULL","NULL",CONCATENATE("'",K59,"'")),",'A',NOW(),'SYS',NOW(),'SYS');") -> VALUES('CKDO_MSA_060600','CKDO','','','Manage All Users','Manage All Users','60600','/manageUsers/users/all/list',NULL,'CKDO_MSA_060000','A',NOW(),'SYS',NOW(),'SYS'); | O59: =CONCATENATE(M59,N59) -> INSERT INTO T_CORE_MENU_EX (MENU_ID, MENU_APPS_CODE, MENU_GROUP_LABEL, MENU_GROUP_LABEL_OTH, MENU_NAME, MENU_NAME_OTH, MENU_SEQ, MENU_PATH, MENU_ICON, MENU_PARENT, MENU_STATUS, MENU_DT_CREATE, MENU_UID_CREATE, MENU_DT_LUPD, MENU_UID_LUPD) VALUES('CKDO_MSA_060600','CKDO','','','Manage All Users','Manage All Users','60600','/manageUsers/users/all/list',NULL,'CKDO_MSA_060000','A',NOW(),'SYS',NOW(),'SYS');
A60: CKDO_MSA_060700 | B60: CKDO | F60: Manage All Accounts | G60: Manage All Accounts | H60: 60700 | I60: /manageAccounts/all/list | J60: NULL | K60: CKDO_MSA_060000 | L60: A | M60: =CONCATENATE("INSERT INTO T_CORE_MENU_EX (MENU_ID, MENU_APPS_CODE, MENU_GROUP_LABEL, MENU_GROUP_LABEL_OTH, MENU_NAME, MENU_NAME_OTH, MENU_SEQ, MENU_PATH, MENU_ICON, MENU_PARENT, MENU_STATUS, MENU_DT_CREATE, MENU_UID_CREATE, MENU_DT_LUPD, MENU_UID_LUPD) ") -> INSERT INTO T_CORE_MENU_EX (MENU_ID, MENU_APPS_CODE, MENU_GROUP_LABEL, MENU_GROUP_LABEL_OTH, MENU_NAME, MENU_NAME_OTH, MENU_SEQ, MENU_PATH, MENU_ICON, MENU_PARENT, MENU_STATUS, MENU_DT_CREATE, MENU_UID_CREATE, MENU_DT_LUPD, MENU_UID_LUPD) | N60: =CONCATENATE(" VALUES('",A60,"','",B60,"','",D60,"','",E60,"','",F60,"','",G60,"',",IF(H60="NULL","NULL",CONCATENATE("'",H60,"'")),",",IF(I60="NULL","NULL",CONCATENATE("'",I60,"'")),",",IF(J60="NULL","NULL",CONCATENATE("'",J60,"'")),",",IF(K60="NULL","NULL",CONCATENATE("'",K60,"'")),",'A',NOW(),'SYS',NOW(),'SYS');") -> VALUES('CKDO_MSA_060700','CKDO','','','Manage All Accounts','Manage All Accounts','60700','/manageAccounts/all/list',NULL,'CKDO_MSA_060000','A',NOW(),'SYS',NOW(),'SYS'); | O60: =CONCATENATE(M60,N60) -> INSERT INTO T_CORE_MENU_EX (MENU_ID, MENU_APPS_CODE, MENU_GROUP_LABEL, MENU_GROUP_LABEL_OTH, MENU_NAME, MENU_NAME_OTH, MENU_SEQ, MENU_PATH, MENU_ICON, MENU_PARENT, MENU_STATUS, MENU_DT_CREATE, MENU_UID_CREATE, MENU_DT_LUPD, MENU_UID_LUPD) VALUES('CKDO_MSA_060700','CKDO','','','Manage All Accounts','Manage All Accounts','60700','/manageAccounts/all/list',NULL,'CKDO_MSA_060000','A',NOW(),'SYS',NOW(),'SYS');
A61: CKDO_MS_010000 | B61: CKDO | D61: DO Claim | E61: DO Claim | F61: DO Claim | G61: DO Claim | H61: 10000 | I61: / | J61: grid_view | K61: NULL | L61: A | M61: =CONCATENATE("INSERT INTO T_CORE_MENU_EX (MENU_ID, MENU_APPS_CODE, MENU_GROUP_LABEL, MENU_GROUP_LABEL_OTH, MENU_NAME, MENU_NAME_OTH, MENU_SEQ, MENU_PATH, MENU_ICON, MENU_PARENT, MENU_STATUS, MENU_DT_CREATE, MENU_UID_CREATE, MENU_DT_LUPD, MENU_UID_LUPD) ") -> INSERT INTO T_CORE_MENU_EX (MENU_ID, MENU_APPS_CODE, MENU_GROUP_LABEL, MENU_GROUP_LABEL_OTH, MENU_NAME, MENU_NAME_OTH, MENU_SEQ, MENU_PATH, MENU_ICON, MENU_PARENT, MENU_STATUS, MENU_DT_CREATE, MENU_UID_CREATE, MENU_DT_LUPD, MENU_UID_LUPD) | N61: =CONCATENATE(" VALUES('",A61,"','",B61,"','",D61,"','",E61,"','",F61,"','",G61,"',",IF(H61="NULL","NULL",CONCATENATE("'",H61,"'")),",",IF(I61="NULL","NULL",CONCATENATE("'",I61,"'")),",",IF(J61="NULL","NULL",CONCATENATE("'",J61,"'")),",",IF(K61="NULL","NULL",CONCATENATE("'",K61,"'")),",'A',NOW(),'SYS',NOW(),'SYS');") -> VALUES('CKDO_MS_010000','CKDO','DO Claim','DO Claim','DO Claim','DO Claim','10000','/','grid_view',NULL,'A',NOW(),'SYS',NOW(),'SYS'); | O61: =CONCATENATE(M61,N61) -> INSERT INTO T_CORE_MENU_EX (MENU_ID, MENU_APPS_CODE, MENU_GROUP_LABEL, MENU_GROUP_LABEL_OTH, MENU_NAME, MENU_NAME_OTH, MENU_SEQ, MENU_PATH, MENU_ICON, MENU_PARENT, MENU_STATUS, MENU_DT_CREATE, MENU_UID_CREATE, MENU_DT_LUPD, MENU_UID_LUPD) VALUES('CKDO_MS_010000','CKDO','DO Claim','DO Claim','DO Claim','DO Claim','10000','/','grid_view',NULL,'A',NOW(),'SYS',NOW(),'SYS');
A62: CKDO_MS_020000 | B62: CKDO | D62: Documents | E62: Documents | F62: Documents | G62: Documents | H62: 20000 | I62: / | J62: content_copy | K62: NULL | L62: A | M62: =CONCATENATE("INSERT INTO T_CORE_MENU_EX (MENU_ID, MENU_APPS_CODE, MENU_GROUP_LABEL, MENU_GROUP_LABEL_OTH, MENU_NAME, MENU_NAME_OTH, MENU_SEQ, MENU_PATH, MENU_ICON, MENU_PARENT, MENU_STATUS, MENU_DT_CREATE, MENU_UID_CREATE, MENU_DT_LUPD, MENU_UID_LUPD) ") -> INSERT INTO T_CORE_MENU_EX (MENU_ID, MENU_APPS_CODE, MENU_GROUP_LABEL, MENU_GROUP_LABEL_OTH, MENU_NAME, MENU_NAME_OTH, MENU_SEQ, MENU_PATH, MENU_ICON, MENU_PARENT, MENU_STATUS, MENU_DT_CREATE, MENU_UID_CREATE, MENU_DT_LUPD, MENU_UID_LUPD) | N62: =CONCATENATE(" VALUES('",A62,"','",B62,"','",D62,"','",E62,"','",F62,"','",G62,"',",IF(H62="NULL","NULL",CONCATENATE("'",H62,"'")),",",IF(I62="NULL","NULL",CONCATENATE("'",I62,"'")),",",IF(J62="NULL","NULL",CONCATENATE("'",J62,"'")),",",IF(K62="NULL","NULL",CONCATENATE("'",K62,"'")),",'A',NOW(),'SYS',NOW(),'SYS');") -> VALUES('CKDO_MS_020000','CKDO','Documents','Documents','Documents','Documents','20000','/','content_copy',NULL,'A',NOW(),'SYS',NOW(),'SYS'); | O62: =CONCATENATE(M62,N62) -> INSERT INTO T_CORE_MENU_EX (MENU_ID, MENU_APPS_CODE, MENU_GROUP_LABEL, MENU_GROUP_LABEL_OTH, MENU_NAME, MENU_NAME_OTH, MENU_SEQ, MENU_PATH, MENU_ICON, MENU_PARENT, MENU_STATUS, MENU_DT_CREATE, MENU_UID_CREATE, MENU_DT_LUPD, MENU_UID_LUPD) VALUES('CKDO_MS_020000','CKDO','Documents','Documents','Documents','Documents','20000','/','content_copy',NULL,'A',NOW(),'SYS',NOW(),'SYS');
A63: CKDO_MT_050000 | B63: CKDO | D63: Master Table | E63: Master Table | F63: Master Table | G63: Master Table | H63: 50000 | I63: NULL | J63: table_view | K63: NULL | L63: A | M63: =CONCATENATE("INSERT INTO T_CORE_MENU_EX (MENU_ID, MENU_APPS_CODE, MENU_GROUP_LABEL, MENU_GROUP_LABEL_OTH, MENU_NAME, MENU_NAME_OTH, MENU_SEQ, MENU_PATH, MENU_ICON, MENU_PARENT, MENU_STATUS, MENU_DT_CREATE, MENU_UID_CREATE, MENU_DT_LUPD, MENU_UID_LUPD) ") -> INSERT INTO T_CORE_MENU_EX (MENU_ID, MENU_APPS_CODE, MENU_GROUP_LABEL, MENU_GROUP_LABEL_OTH, MENU_NAME, MENU_NAME_OTH, MENU_SEQ, MENU_PATH, MENU_ICON, MENU_PARENT, MENU_STATUS, MENU_DT_CREATE, MENU_UID_CREATE, MENU_DT_LUPD, MENU_UID_LUPD) | N63: =CONCATENATE(" VALUES('",A63,"','",B63,"','",D63,"','",E63,"','",F63,"','",G63,"',",IF(H63="NULL","NULL",CONCATENATE("'",H63,"'")),",",IF(I63="NULL","NULL",CONCATENATE("'",I63,"'")),",",IF(J63="NULL","NULL",CONCATENATE("'",J63,"'")),",",IF(K63="NULL","NULL",CONCATENATE("'",K63,"'")),",'A',NOW(),'SYS',NOW(),'SYS');") -> VALUES('CKDO_MT_050000','CKDO','Master Table','Master Table','Master Table','Master Table','50000',NULL,'table_view',NULL,'A',NOW(),'SYS',NOW(),'SYS'); | O63: =CONCATENATE(M63,N63) -> INSERT INTO T_CORE_MENU_EX (MENU_ID, MENU_APPS_CODE, MENU_GROUP_LABEL, MENU_GROUP_LABEL_OTH, MENU_NAME, MENU_NAME_OTH, MENU_SEQ, MENU_PATH, MENU_ICON, MENU_PARENT, MENU_STATUS, MENU_DT_CREATE, MENU_UID_CREATE, MENU_DT_LUPD, MENU_UID_LUPD) VALUES('CKDO_MT_050000','CKDO','Master Table','Master Table','Master Table','Master Table','50000',NULL,'table_view',NULL,'A',NOW(),'SYS',NOW(),'SYS');
A64: CKDO_MT_050100 | B64: CKDO | F64: Announcement Type | G64: Announcement Type | H64: 50100 | I64: /configuration/announcementType/list | J64: NULL | K64: CKDO_MT_050000 | L64: A | M64: =CONCATENATE("INSERT INTO T_CORE_MENU_EX (MENU_ID, MENU_APPS_CODE, MENU_GROUP_LABEL, MENU_GROUP_LABEL_OTH, MENU_NAME, MENU_NAME_OTH, MENU_SEQ, MENU_PATH, MENU_ICON, MENU_PARENT, MENU_STATUS, MENU_DT_CREATE, MENU_UID_CREATE, MENU_DT_LUPD, MENU_UID_LUPD) ") -> INSERT INTO T_CORE_MENU_EX (MENU_ID, MENU_APPS_CODE, MENU_GROUP_LABEL, MENU_GROUP_LABEL_OTH, MENU_NAME, MENU_NAME_OTH, MENU_SEQ, MENU_PATH, MENU_ICON, MENU_PARENT, MENU_STATUS, MENU_DT_CREATE, MENU_UID_CREATE, MENU_DT_LUPD, MENU_UID_LUPD) | N64: =CONCATENATE(" VALUES('",A64,"','",B64,"','",D64,"','",E64,"','",F64,"','",G64,"',",IF(H64="NULL","NULL",CONCATENATE("'",H64,"'")),",",IF(I64="NULL","NULL",CONCATENATE("'",I64,"'")),",",IF(J64="NULL","NULL",CONCATENATE("'",J64,"'")),",",IF(K64="NULL","NULL",CONCATENATE("'",K64,"'")),",'A',NOW(),'SYS',NOW(),'SYS');") -> VALUES('CKDO_MT_050100','CKDO','','','Announcement Type','Announcement Type','50100','/configuration/announcementType/list',NULL,'CKDO_MT_050000','A',NOW(),'SYS',NOW(),'SYS'); | O64: =CONCATENATE(M64,N64) -> INSERT INTO T_CORE_MENU_EX (MENU_ID, MENU_APPS_CODE, MENU_GROUP_LABEL, MENU_GROUP_LABEL_OTH, MENU_NAME, MENU_NAME_OTH, MENU_SEQ, MENU_PATH, MENU_ICON, MENU_PARENT, MENU_STATUS, MENU_DT_CREATE, MENU_UID_CREATE, MENU_DT_LUPD, MENU_UID_LUPD) VALUES('CKDO_MT_050100','CKDO','','','Announcement Type','Announcement Type','50100','/configuration/announcementType/list',NULL,'CKDO_MT_050000','A',NOW(),'SYS',NOW(),'SYS');
A65: CKDO_MT_050200 | B65: CKDO | F65: Country Codes | G65: Country Codes | H65: 50200 | I65: /master/country/list | J65: NULL | K65: CKDO_MT_050000 | L65: A | M65: =CONCATENATE("INSERT INTO T_CORE_MENU_EX (MENU_ID, MENU_APPS_CODE, MENU_GROUP_LABEL, MENU_GROUP_LABEL_OTH, MENU_NAME, MENU_NAME_OTH, MENU_SEQ, MENU_PATH, MENU_ICON, MENU_PARENT, MENU_STATUS, MENU_DT_CREATE, MENU_UID_CREATE, MENU_DT_LUPD, MENU_UID_LUPD) ") -> INSERT INTO T_CORE_MENU_EX (MENU_ID, MENU_APPS_CODE, MENU_GROUP_LABEL, MENU_GROUP_LABEL_OTH, MENU_NAME, MENU_NAME_OTH, MENU_SEQ, MENU_PATH, MENU_ICON, MENU_PARENT, MENU_STATUS, MENU_DT_CREATE, MENU_UID_CREATE, MENU_DT_LUPD, MENU_UID_LUPD) | N65: =CONCATENATE(" VALUES('",A65,"','",B65,"','",D65,"','",E65,"','",F65,"','",G65,"',",IF(H65="NULL","NULL",CONCATENATE("'",H65,"'")),",",IF(I65="NULL","NULL",CONCATENATE("'",I65,"'")),",",IF(J65="NULL","NULL",CONCATENATE("'",J65,"'")),",",IF(K65="NULL","NULL",CONCATENATE("'",K65,"'")),",'A',NOW(),'SYS',NOW(),'SYS');") -> VALUES('CKDO_MT_050200','CKDO','','','Country Codes','Country Codes','50200','/master/country/list',NULL,'CKDO_MT_050000','A',NOW(),'SYS',NOW(),'SYS'); | O65: =CONCATENATE(M65,N65) -> INSERT INTO T_CORE_MENU_EX (MENU_ID, MENU_APPS_CODE, MENU_GROUP_LABEL, MENU_GROUP_LABEL_OTH, MENU_NAME, MENU_NAME_OTH, MENU_SEQ, MENU_PATH, MENU_ICON, MENU_PARENT, MENU_STATUS, MENU_DT_CREATE, MENU_UID_CREATE, MENU_DT_LUPD, MENU_UID_LUPD) VALUES('CKDO_MT_050200','CKDO','','','Country Codes','Country Codes','50200','/master/country/list',NULL,'CKDO_MT_050000','A',NOW(),'SYS',NOW(),'SYS');
A66: CKDO_MT_050300 | B66: CKDO | F66: Currency Code | G66: Currency Code | H66: 50300 | I66: /master/currency/list | J66: NULL | K66: CKDO_MT_050000 | L66: A | M66: =CONCATENATE("INSERT INTO T_CORE_MENU_EX (MENU_ID, MENU_APPS_CODE, MENU_GROUP_LABEL, MENU_GROUP_LABEL_OTH, MENU_NAME, MENU_NAME_OTH, MENU_SEQ, MENU_PATH, MENU_ICON, MENU_PARENT, MENU_STATUS, MENU_DT_CREATE, MENU_UID_CREATE, MENU_DT_LUPD, MENU_UID_LUPD) ") -> INSERT INTO T_CORE_MENU_EX (MENU_ID, MENU_APPS_CODE, MENU_GROUP_LABEL, MENU_GROUP_LABEL_OTH, MENU_NAME, MENU_NAME_OTH, MENU_SEQ, MENU_PATH, MENU_ICON, MENU_PARENT, MENU_STATUS, MENU_DT_CREATE, MENU_UID_CREATE, MENU_DT_LUPD, MENU_UID_LUPD) | N66: =CONCATENATE(" VALUES('",A66,"','",B66,"','",D66,"','",E66,"','",F66,"','",G66,"',",IF(H66="NULL","NULL",CONCATENATE("'",H66,"'")),",",IF(I66="NULL","NULL",CONCATENATE("'",I66,"'")),",",IF(J66="NULL","NULL",CONCATENATE("'",J66,"'")),",",IF(K66="NULL","NULL",CONCATENATE("'",K66,"'")),",'A',NOW(),'SYS',NOW(),'SYS');") -> VALUES('CKDO_MT_050300','CKDO','','','Currency Code','Currency Code','50300','/master/currency/list',NULL,'CKDO_MT_050000','A',NOW(),'SYS',NOW(),'SYS'); | O66: =CONCATENATE(M66,N66) -> INSERT INTO T_CORE_MENU_EX (MENU_ID, MENU_APPS_CODE, MENU_GROUP_LABEL, MENU_GROUP_LABEL_OTH, MENU_NAME, MENU_NAME_OTH, MENU_SEQ, MENU_PATH, MENU_ICON, MENU_PARENT, MENU_STATUS, MENU_DT_CREATE, MENU_UID_CREATE, MENU_DT_LUPD, MENU_UID_LUPD) VALUES('CKDO_MT_050300','CKDO','','','Currency Code','Currency Code','50300','/master/currency/list',NULL,'CKDO_MT_050000','A',NOW(),'SYS',NOW(),'SYS');
A67: CKDO_MT_050400 | B67: CKDO | F67: Harmonized System Codes | G67: Harmonized System Codes | H67: 50400 | I67: /master/hsCode/list | J67: NULL | K67: CKDO_MT_050000 | L67: A | M67: =CONCATENATE("INSERT INTO T_CORE_MENU_EX (MENU_ID, MENU_APPS_CODE, MENU_GROUP_LABEL, MENU_GROUP_LABEL_OTH, MENU_NAME, MENU_NAME_OTH, MENU_SEQ, MENU_PATH, MENU_ICON, MENU_PARENT, MENU_STATUS, MENU_DT_CREATE, MENU_UID_CREATE, MENU_DT_LUPD, MENU_UID_LUPD) ") -> INSERT INTO T_CORE_MENU_EX (MENU_ID, MENU_APPS_CODE, MENU_GROUP_LABEL, MENU_GROUP_LABEL_OTH, MENU_NAME, MENU_NAME_OTH, MENU_SEQ, MENU_PATH, MENU_ICON, MENU_PARENT, MENU_STATUS, MENU_DT_CREATE, MENU_UID_CREATE, MENU_DT_LUPD, MENU_UID_LUPD) | N67: =CONCATENATE(" VALUES('",A67,"','",B67,"','",D67,"','",E67,"','",F67,"','",G67,"',",IF(H67="NULL","NULL",CONCATENATE("'",H67,"'")),",",IF(I67="NULL","NULL",CONCATENATE("'",I67,"'")),",",IF(J67="NULL","NULL",CONCATENATE("'",J67,"'")),",",IF(K67="NULL","NULL",CONCATENATE("'",K67,"'")),",'A',NOW(),'SYS',NOW(),'SYS');") -> VALUES('CKDO_MT_050400','CKDO','','','Harmonized System Codes','Harmonized System Codes','50400','/master/hsCode/list',NULL,'CKDO_MT_050000','A',NOW(),'SYS',NOW(),'SYS'); | O67: =CONCATENATE(M67,N67) -> INSERT INTO T_CORE_MENU_EX (MENU_ID, MENU_APPS_CODE, MENU_GROUP_LABEL, MENU_GROUP_LABEL_OTH, MENU_NAME, MENU_NAME_OTH, MENU_SEQ, MENU_PATH, MENU_ICON, MENU_PARENT, MENU_STATUS, MENU_DT_CREATE, MENU_UID_CREATE, MENU_DT_LUPD, MENU_UID_LUPD) VALUES('CKDO_MT_050400','CKDO','','','Harmonized System Codes','Harmonized System Codes','50400','/master/hsCode/list',NULL,'CKDO_MT_050000','A',NOW(),'SYS',NOW(),'SYS');
A68: CKDO_MT_050500 | B68: CKDO | F68: Notification Templates | G68: Notification Templates | H68: 50500 | I68: /notification/templates/list | J68: NULL | K68: CKDO_MT_050000 | L68: A | M68: =CONCATENATE("INSERT INTO T_CORE_MENU_EX (MENU_ID, MENU_APPS_CODE, MENU_GROUP_LABEL, MENU_GROUP_LABEL_OTH, MENU_NAME, MENU_NAME_OTH, MENU_SEQ, MENU_PATH, MENU_ICON, MENU_PARENT, MENU_STATUS, MENU_DT_CREATE, MENU_UID_CREATE, MENU_DT_LUPD, MENU_UID_LUPD) ") -> INSERT INTO T_CORE_MENU_EX (MENU_ID, MENU_APPS_CODE, MENU_GROUP_LABEL, MENU_GROUP_LABEL_OTH, MENU_NAME, MENU_NAME_OTH, MENU_SEQ, MENU_PATH, MENU_ICON, MENU_PARENT, MENU_STATUS, MENU_DT_CREATE, MENU_UID_CREATE, MENU_DT_LUPD, MENU_UID_LUPD) | N68: =CONCATENATE(" VALUES('",A68,"','",B68,"','",D68,"','",E68,"','",F68,"','",G68,"',",IF(H68="NULL","NULL",CONCATENATE("'",H68,"'")),",",IF(I68="NULL","NULL",CONCATENATE("'",I68,"'")),",",IF(J68="NULL","NULL",CONCATENATE("'",J68,"'")),",",IF(K68="NULL","NULL",CONCATENATE("'",K68,"'")),",'A',NOW(),'SYS',NOW(),'SYS');") -> VALUES('CKDO_MT_050500','CKDO','','','Notification Templates','Notification Templates','50500','/notification/templates/list',NULL,'CKDO_MT_050000','A',NOW(),'SYS',NOW(),'SYS'); | O68: =CONCATENATE(M68,N68) -> INSERT INTO T_CORE_MENU_EX (MENU_ID, MENU_APPS_CODE, MENU_GROUP_LABEL, MENU_GROUP_LABEL_OTH, MENU_NAME, MENU_NAME_OTH, MENU_SEQ, MENU_PATH, MENU_ICON, MENU_PARENT, MENU_STATUS, MENU_DT_CREATE, MENU_UID_CREATE, MENU_DT_LUPD, MENU_UID_LUPD) VALUES('CKDO_MT_050500','CKDO','','','Notification Templates','Notification Templates','50500','/notification/templates/list',NULL,'CKDO_MT_050000','A',NOW(),'SYS',NOW(),'SYS');
A69: CKDO_MT_050600 | B69: CKDO | F69: Port Codes | G69: Port Codes | H69: 50600 | I69: /master/port/list | J69: NULL | K69: CKDO_MT_050000 | M69: =CONCATENATE("INSERT INTO T_CORE_MENU_EX (MENU_ID, MENU_APPS_CODE, MENU_GROUP_LABEL, MENU_GROUP_LABEL_OTH, MENU_NAME, MENU_NAME_OTH, MENU_SEQ, MENU_PATH, MENU_ICON, MENU_PARENT, MENU_STATUS, MENU_DT_CREATE, MENU_UID_CREATE, MENU_DT_LUPD, MENU_UID_LUPD) ") -> INSERT INTO T_CORE_MENU_EX (MENU_ID, MENU_APPS_CODE, MENU_GROUP_LABEL, MENU_GROUP_LABEL_OTH, MENU_NAME, MENU_NAME_OTH, MENU_SEQ, MENU_PATH, MENU_ICON, MENU_PARENT, MENU_STATUS, MENU_DT_CREATE, MENU_UID_CREATE, MENU_DT_LUPD, MENU_UID_LUPD) | N69: =CONCATENATE(" VALUES('",A69,"','",B69,"','",D69,"','",E69,"','",F69,"','",G69,"',",IF(H69="NULL","NULL",CONCATENATE("'",H69,"'")),",",IF(I69="NULL","NULL",CONCATENATE("'",I69,"'")),",",IF(J69="NULL","NULL",CONCATENATE("'",J69,"'")),",",IF(K69="NULL","NULL",CONCATENATE("'",K69,"'")),",'A',NOW(),'SYS',NOW(),'SYS');") -> VALUES('CKDO_MT_050600','CKDO','','','Port Codes','Port Codes','50600','/master/port/list',NULL,'CKDO_MT_050000','A',NOW(),'SYS',NOW(),'SYS'); | O69: =CONCATENATE(M69,N69) -> INSERT INTO T_CORE_MENU_EX (MENU_ID, MENU_APPS_CODE, MENU_GROUP_LABEL, MENU_GROUP_LABEL_OTH, MENU_NAME, MENU_NAME_OTH, MENU_SEQ, MENU_PATH, MENU_ICON, MENU_PARENT, MENU_STATUS, MENU_DT_CREATE, MENU_UID_CREATE, MENU_DT_LUPD, MENU_UID_LUPD) VALUES('CKDO_MT_050600','CKDO','','','Port Codes','Port Codes','50600','/master/port/list',NULL,'CKDO_MT_050000','A',NOW(),'SYS',NOW(),'SYS');
A70: CKDO_MT_050700 | B70: CKDO | F70: Port Terminal | G70: Port Terminal | H70: 50700 | I70: /master/portTerminal/list | J70: NULL | K70: CKDO_MT_050000 | M70: =CONCATENATE("INSERT INTO T_CORE_MENU_EX (MENU_ID, MENU_APPS_CODE, MENU_GROUP_LABEL, MENU_GROUP_LABEL_OTH, MENU_NAME, MENU_NAME_OTH, MENU_SEQ, MENU_PATH, MENU_ICON, MENU_PARENT, MENU_STATUS, MENU_DT_CREATE, MENU_UID_CREATE, MENU_DT_LUPD, MENU_UID_LUPD) ") -> INSERT INTO T_CORE_MENU_EX (MENU_ID, MENU_APPS_CODE, MENU_GROUP_LABEL, MENU_GROUP_LABEL_OTH, MENU_NAME, MENU_NAME_OTH, MENU_SEQ, MENU_PATH, MENU_ICON, MENU_PARENT, MENU_STATUS, MENU_DT_CREATE, MENU_UID_CREATE, MENU_DT_LUPD, MENU_UID_LUPD) | N70: =CONCATENATE(" VALUES('",A70,"','",B70,"','",D70,"','",E70,"','",F70,"','",G70,"',",IF(H70="NULL","NULL",CONCATENATE("'",H70,"'")),",",IF(I70="NULL","NULL",CONCATENATE("'",I70,"'")),",",IF(J70="NULL","NULL",CONCATENATE("'",J70,"'")),",",IF(K70="NULL","NULL",CONCATENATE("'",K70,"'")),",'A',NOW(),'SYS',NOW(),'SYS');") -> VALUES('CKDO_MT_050700','CKDO','','','Port Terminal','Port Terminal','50700','/master/portTerminal/list',NULL,'CKDO_MT_050000','A',NOW(),'SYS',NOW(),'SYS'); | O70: =CONCATENATE(M70,N70) -> INSERT INTO T_CORE_MENU_EX (MENU_ID, MENU_APPS_CODE, MENU_GROUP_LABEL, MENU_GROUP_LABEL_OTH, MENU_NAME, MENU_NAME_OTH, MENU_SEQ, MENU_PATH, MENU_ICON, MENU_PARENT, MENU_STATUS, MENU_DT_CREATE, MENU_UID_CREATE, MENU_DT_LUPD, MENU_UID_LUPD) VALUES('CKDO_MT_050700','CKDO','','','Port Terminal','Port Terminal','50700','/master/portTerminal/list',NULL,'CKDO_MT_050000','A',NOW(),'SYS',NOW(),'SYS');
A71: CKDO_MT_050800 | B71: CKDO | F71: UOM Codes | G71: UOM Codes | H71: 50800 | I71: /master/uom/list | J71: NULL | K71: CKDO_MT_050000 | M71: =CONCATENATE("INSERT INTO T_CORE_MENU_EX (MENU_ID, MENU_APPS_CODE, MENU_GROUP_LABEL, MENU_GROUP_LABEL_OTH, MENU_NAME, MENU_NAME_OTH, MENU_SEQ, MENU_PATH, MENU_ICON, MENU_PARENT, MENU_STATUS, MENU_DT_CREATE, MENU_UID_CREATE, MENU_DT_LUPD, MENU_UID_LUPD) ") -> INSERT INTO T_CORE_MENU_EX (MENU_ID, MENU_APPS_CODE, MENU_GROUP_LABEL, MENU_GROUP_LABEL_OTH, MENU_NAME, MENU_NAME_OTH, MENU_SEQ, MENU_PATH, MENU_ICON, MENU_PARENT, MENU_STATUS, MENU_DT_CREATE, MENU_UID_CREATE, MENU_DT_LUPD, MENU_UID_LUPD) | N71: =CONCATENATE(" VALUES('",A71,"','",B71,"','",D71,"','",E71,"','",F71,"','",G71,"',",IF(H71="NULL","NULL",CONCATENATE("'",H71,"'")),",",IF(I71="NULL","NULL",CONCATENATE("'",I71,"'")),",",IF(J71="NULL","NULL",CONCATENATE("'",J71,"'")),",",IF(K71="NULL","NULL",CONCATENATE("'",K71,"'")),",'A',NOW(),'SYS',NOW(),'SYS');") -> VALUES('CKDO_MT_050800','CKDO','','','UOM Codes','UOM Codes','50800','/master/uom/list',NULL,'CKDO_MT_050000','A',NOW(),'SYS',NOW(),'SYS'); | O71: =CONCATENATE(M71,N71) -> INSERT INTO T_CORE_MENU_EX (MENU_ID, MENU_APPS_CODE, MENU_GROUP_LABEL, MENU_GROUP_LABEL_OTH, MENU_NAME, MENU_NAME_OTH, MENU_SEQ, MENU_PATH, MENU_ICON, MENU_PARENT, MENU_STATUS, MENU_DT_CREATE, MENU_UID_CREATE, MENU_DT_LUPD, MENU_UID_LUPD) VALUES('CKDO_MT_050800','CKDO','','','UOM Codes','UOM Codes','50800','/master/uom/list',NULL,'CKDO_MT_050000','A',NOW(),'SYS',NOW(),'SYS');
A72: CKDO_MH_080000 | B72: CKDO | D72: Help | E72: Help | F72: Help | G72: Help | H72: 80000 | I72: /help | J72: help | K72: NULL | L72: A | M72: =CONCATENATE("INSERT INTO T_CORE_MENU_EX (MENU_ID, MENU_APPS_CODE, MENU_GROUP_LABEL, MENU_GROUP_LABEL_OTH, MENU_NAME, MENU_NAME_OTH, MENU_SEQ, MENU_PATH, MENU_ICON, MENU_PARENT, MENU_STATUS, MENU_DT_CREATE, MENU_UID_CREATE, MENU_DT_LUPD, MENU_UID_LUPD) ") -> INSERT INTO T_CORE_MENU_EX (MENU_ID, MENU_APPS_CODE, MENU_GROUP_LABEL, MENU_GROUP_LABEL_OTH, MENU_NAME, MENU_NAME_OTH, MENU_SEQ, MENU_PATH, MENU_ICON, MENU_PARENT, MENU_STATUS, MENU_DT_CREATE, MENU_UID_CREATE, MENU_DT_LUPD, MENU_UID_LUPD) | N72: =CONCATENATE(" VALUES('",A72,"','",B72,"','",D72,"','",E72,"','",F72,"','",G72,"',",IF(H72="NULL","NULL",CONCATENATE("'",H72,"'")),",",IF(I72="NULL","NULL",CONCATENATE("'",I72,"'")),",",IF(J72="NULL","NULL",CONCATENATE("'",J72,"'")),",",IF(K72="NULL","NULL",CONCATENATE("'",K72,"'")),",'A',NOW(),'SYS',NOW(),'SYS');") -> VALUES('CKDO_MH_080000','CKDO','Help','Help','Help','Help','80000','/help','help',NULL,'A',NOW(),'SYS',NOW(),'SYS'); | O72: =CONCATENATE(M72,N72) -> INSERT INTO T_CORE_MENU_EX (MENU_ID, MENU_APPS_CODE, MENU_GROUP_LABEL, MENU_GROUP_LABEL_OTH, MENU_NAME, MENU_NAME_OTH, MENU_SEQ, MENU_PATH, MENU_ICON, MENU_PARENT, MENU_STATUS, MENU_DT_CREATE, MENU_UID_CREATE, MENU_DT_LUPD, MENU_UID_LUPD) VALUES('CKDO_MH_080000','CKDO','Help','Help','Help','Help','80000','/help','help',NULL,'A',NOW(),'SYS',NOW(),'SYS');
A73: CKDO_MS_030000 | B73: CKDO | D73: DO Extension Payment | E73: DO Extension Payment | F73: DO Extension Payment | G73: DO Extension Payment | H73: 30000 | I73: /applications/invoices/ext | J73: receipt | K73: NULL | L73: A | M73: =CONCATENATE("INSERT INTO T_CORE_MENU_EX (MENU_ID, MENU_APPS_CODE, MENU_GROUP_LABEL, MENU_GROUP_LABEL_OTH, MENU_NAME, MENU_NAME_OTH, MENU_SEQ, MENU_PATH, MENU_ICON, MENU_PARENT, MENU_STATUS, MENU_DT_CREATE, MENU_UID_CREATE, MENU_DT_LUPD, MENU_UID_LUPD) ") -> INSERT INTO T_CORE_MENU_EX (MENU_ID, MENU_APPS_CODE, MENU_GROUP_LABEL, MENU_GROUP_LABEL_OTH, MENU_NAME, MENU_NAME_OTH, MENU_SEQ, MENU_PATH, MENU_ICON, MENU_PARENT, MENU_STATUS, MENU_DT_CREATE, MENU_UID_CREATE, MENU_DT_LUPD, MENU_UID_LUPD) | N73: =CONCATENATE(" VALUES('",A73,"','",B73,"','",D73,"','",E73,"','",F73,"','",G73,"',",IF(H73="NULL","NULL",CONCATENATE("'",H73,"'")),",",IF(I73="NULL","NULL",CONCATENATE("'",I73,"'")),",",IF(J73="NULL","NULL",CONCATENATE("'",J73,"'")),",",IF(K73="NULL","NULL",CONCATENATE("'",K73,"'")),",'A',NOW(),'SYS',NOW(),'SYS');") -> VALUES('CKDO_MS_030000','CKDO','DO Extension Payment','DO Extension Payment','DO Extension Payment','DO Extension Payment','30000','/applications/invoices/ext','receipt',NULL,'A',NOW(),'SYS',NOW(),'SYS'); | O73: =CONCATENATE(M73,N73) -> INSERT INTO T_CORE_MENU_EX (MENU_ID, MENU_APPS_CODE, MENU_GROUP_LABEL, MENU_GROUP_LABEL_OTH, MENU_NAME, MENU_NAME_OTH, MENU_SEQ, MENU_PATH, MENU_ICON, MENU_PARENT, MENU_STATUS, MENU_DT_CREATE, MENU_UID_CREATE, MENU_DT_LUPD, MENU_UID_LUPD) VALUES('CKDO_MS_030000','CKDO','DO Extension Payment','DO Extension Payment','DO Extension Payment','DO Extension Payment','30000','/applications/invoices/ext','receipt',NULL,'A',NOW(),'SYS',NOW(),'SYS');
A74: CKDO_MS_040000 | B74: CKDO | D74: Platform Fee | E74: Platform Fee | F74: Platform Fee | G74: Platform Fee | H74: 40000 | I74: /applications/platformfee/list | J74: payment | K74: NULL | L74: A | M74: =CONCATENATE("INSERT INTO T_CORE_MENU_EX (MENU_ID, MENU_APPS_CODE, MENU_GROUP_LABEL, MENU_GROUP_LABEL_OTH, MENU_NAME, MENU_NAME_OTH, MENU_SEQ, MENU_PATH, MENU_ICON, MENU_PARENT, MENU_STATUS, MENU_DT_CREATE, MENU_UID_CREATE, MENU_DT_LUPD, MENU_UID_LUPD) ") -> INSERT INTO T_CORE_MENU_EX (MENU_ID, MENU_APPS_CODE, MENU_GROUP_LABEL, MENU_GROUP_LABEL_OTH, MENU_NAME, MENU_NAME_OTH, MENU_SEQ, MENU_PATH, MENU_ICON, MENU_PARENT, MENU_STATUS, MENU_DT_CREATE, MENU_UID_CREATE, MENU_DT_LUPD, MENU_UID_LUPD) | N74: =CONCATENATE(" VALUES('",A74,"','",B74,"','",D74,"','",E74,"','",F74,"','",G74,"',",IF(H74="NULL","NULL",CONCATENATE("'",H74,"'")),",",IF(I74="NULL","NULL",CONCATENATE("'",I74,"'")),",",IF(J74="NULL","NULL",CONCATENATE("'",J74,"'")),",",IF(K74="NULL","NULL",CONCATENATE("'",K74,"'")),",'A',NOW(),'SYS',NOW(),'SYS');") -> VALUES('CKDO_MS_040000','CKDO','Platform Fee','Platform Fee','Platform Fee','Platform Fee','40000','/applications/platformfee/list','payment',NULL,'A',NOW(),'SYS',NOW(),'SYS'); | O74: =CONCATENATE(M74,N74) -> INSERT INTO T_CORE_MENU_EX (MENU_ID, MENU_APPS_CODE, MENU_GROUP_LABEL, MENU_GROUP_LABEL_OTH, MENU_NAME, MENU_NAME_OTH, MENU_SEQ, MENU_PATH, MENU_ICON, MENU_PARENT, MENU_STATUS, MENU_DT_CREATE, MENU_UID_CREATE, MENU_DT_LUPD, MENU_UID_LUPD) VALUES('CKDO_MS_040000','CKDO','Platform Fee','Platform Fee','Platform Fee','Platform Fee','40000','/applications/platformfee/list','payment',NULL,'A',NOW(),'SYS',NOW(),'SYS');
A75: CKDO_MS_050000 | B75: CKDO | D75: Exchange Rate | E75: Exchange Rate | F75: Exchange Rate | G75: Exchange Rate | H75: 50000 | I75: /applications/exchangerate/list | J75: settings | K75: NULL | L75: A | M75: =CONCATENATE("INSERT INTO T_CORE_MENU_EX (MENU_ID, MENU_APPS_CODE, MENU_GROUP_LABEL, MENU_GROUP_LABEL_OTH, MENU_NAME, MENU_NAME_OTH, MENU_SEQ, MENU_PATH, MENU_ICON, MENU_PARENT, MENU_STATUS, MENU_DT_CREATE, MENU_UID_CREATE, MENU_DT_LUPD, MENU_UID_LUPD) ") -> INSERT INTO T_CORE_MENU_EX (MENU_ID, MENU_APPS_CODE, MENU_GROUP_LABEL, MENU_GROUP_LABEL_OTH, MENU_NAME, MENU_NAME_OTH, MENU_SEQ, MENU_PATH, MENU_ICON, MENU_PARENT, MENU_STATUS, MENU_DT_CREATE, MENU_UID_CREATE, MENU_DT_LUPD, MENU_UID_LUPD) | N75: =CONCATENATE(" VALUES('",A75,"','",B75,"','",D75,"','",E75,"','",F75,"','",G75,"',",IF(H75="NULL","NULL",CONCATENATE("'",H75,"'")),",",IF(I75="NULL","NULL",CONCATENATE("'",I75,"'")),",",IF(J75="NULL","NULL",CONCATENATE("'",J75,"'")),",",IF(K75="NULL","NULL",CONCATENATE("'",K75,"'")),",'A',NOW(),'SYS',NOW(),'SYS');") -> VALUES('CKDO_MS_050000','CKDO','Exchange Rate','Exchange Rate','Exchange Rate','Exchange Rate','50000','/applications/exchangerate/list','settings',NULL,'A',NOW(),'SYS',NOW(),'SYS'); | O75: =CONCATENATE(M75,N75) -> INSERT INTO T_CORE_MENU_EX (MENU_ID, MENU_APPS_CODE, MENU_GROUP_LABEL, MENU_GROUP_LABEL_OTH, MENU_NAME, MENU_NAME_OTH, MENU_SEQ, MENU_PATH, MENU_ICON, MENU_PARENT, MENU_STATUS, MENU_DT_CREATE, MENU_UID_CREATE, MENU_DT_LUPD, MENU_UID_LUPD) VALUES('CKDO_MS_050000','CKDO','Exchange Rate','Exchange Rate','Exchange Rate','Exchange Rate','50000','/applications/exchangerate/list','settings',NULL,'A',NOW(),'SYS',NOW(),'SYS');
A76: CKDO_MS_060000 | B76: CKDO | D76: Report | E76: Report | F76: Report | G76: Report | H76: 60000 | I76: content_copy | K76: NULL | L76: A | M76: =CONCATENATE("INSERT INTO T_CORE_MENU_EX (MENU_ID, MENU_APPS_CODE, MENU_GROUP_LABEL, MENU_GROUP_LABEL_OTH, MENU_NAME, MENU_NAME_OTH, MENU_SEQ, MENU_PATH, MENU_ICON, MENU_PARENT, MENU_STATUS, MENU_DT_CREATE, MENU_UID_CREATE, MENU_DT_LUPD, MENU_UID_LUPD) ") -> INSERT INTO T_CORE_MENU_EX (MENU_ID, MENU_APPS_CODE, MENU_GROUP_LABEL, MENU_GROUP_LABEL_OTH, MENU_NAME, MENU_NAME_OTH, MENU_SEQ, MENU_PATH, MENU_ICON, MENU_PARENT, MENU_STATUS, MENU_DT_CREATE, MENU_UID_CREATE, MENU_DT_LUPD, MENU_UID_LUPD) | N76: =CONCATENATE(" VALUES('",A76,"','",B76,"','",D76,"','",E76,"','",F76,"','",G76,"',",IF(H76="NULL","NULL",CONCATENATE("'",H76,"'")),",",IF(I76="NULL","NULL",CONCATENATE("'",I76,"'")),",",IF(J76="NULL","NULL",CONCATENATE("'",J76,"'")),",",IF(K76="NULL","NULL",CONCATENATE("'",K76,"'")),",'A',NOW(),'SYS',NOW(),'SYS');") -> VALUES('CKDO_MS_060000','CKDO','Report','Report','Report','Report','60000','content_copy','',NULL,'A',NOW(),'SYS',NOW(),'SYS'); | O76: =CONCATENATE(M76,N76) -> INSERT INTO T_CORE_MENU_EX (MENU_ID, MENU_APPS_CODE, MENU_GROUP_LABEL, MENU_GROUP_LABEL_OTH, MENU_NAME, MENU_NAME_OTH, MENU_SEQ, MENU_PATH, MENU_ICON, MENU_PARENT, MENU_STATUS, MENU_DT_CREATE, MENU_UID_CREATE, MENU_DT_LUPD, MENU_UID_LUPD) VALUES('CKDO_MS_060000','CKDO','Report','Report','Report','Report','60000','content_copy','',NULL,'A',NOW(),'SYS',NOW(),'SYS');
A77: CKDO_MS_060100 | B77: CKDO | D77: DO Claim | E77: DO Claim | F77: DO Claim | G77: DO Claim | H77: 60100 | I77: /applications/report/do | K77: CKDO_MS_060000 | L77: A | M77: =CONCATENATE("INSERT INTO T_CORE_MENU_EX (MENU_ID, MENU_APPS_CODE, MENU_GROUP_LABEL, MENU_GROUP_LABEL_OTH, MENU_NAME, MENU_NAME_OTH, MENU_SEQ, MENU_PATH, MENU_ICON, MENU_PARENT, MENU_STATUS, MENU_DT_CREATE, MENU_UID_CREATE, MENU_DT_LUPD, MENU_UID_LUPD) ") -> INSERT INTO T_CORE_MENU_EX (MENU_ID, MENU_APPS_CODE, MENU_GROUP_LABEL, MENU_GROUP_LABEL_OTH, MENU_NAME, MENU_NAME_OTH, MENU_SEQ, MENU_PATH, MENU_ICON, MENU_PARENT, MENU_STATUS, MENU_DT_CREATE, MENU_UID_CREATE, MENU_DT_LUPD, MENU_UID_LUPD) | N77: =CONCATENATE(" VALUES('",A77,"','",B77,"','",D77,"','",E77,"','",F77,"','",G77,"',",IF(H77="NULL","NULL",CONCATENATE("'",H77,"'")),",",IF(I77="NULL","NULL",CONCATENATE("'",I77,"'")),",",IF(J77="NULL","NULL",CONCATENATE("'",J77,"'")),",",IF(K77="NULL","NULL",CONCATENATE("'",K77,"'")),",'A',NOW(),'SYS',NOW(),'SYS');") -> VALUES('CKDO_MS_060100','CKDO','DO Claim','DO Claim','DO Claim','DO Claim','60100','/applications/report/do','','CKDO_MS_060000','A',NOW(),'SYS',NOW(),'SYS'); | O77: =CONCATENATE(M77,N77) -> INSERT INTO T_CORE_MENU_EX (MENU_ID, MENU_APPS_CODE, MENU_GROUP_LABEL, MENU_GROUP_LABEL_OTH, MENU_NAME, MENU_NAME_OTH, MENU_SEQ, MENU_PATH, MENU_ICON, MENU_PARENT, MENU_STATUS, MENU_DT_CREATE, MENU_UID_CREATE, MENU_DT_LUPD, MENU_UID_LUPD) VALUES('CKDO_MS_060100','CKDO','DO Claim','DO Claim','DO Claim','DO Claim','60100','/applications/report/do','','CKDO_MS_060000','A',NOW(),'SYS',NOW(),'SYS');
A78: CKDO_MS_060200 | B78: CKDO | D78: DO Extension | E78: DO Extension | F78: DO Extension | G78: DO Extension | H78: 60200 | I78: /applications/report/ext | K78: CKDO_MS_060000 | L78: A | M78: =CONCATENATE("INSERT INTO T_CORE_MENU_EX (MENU_ID, MENU_APPS_CODE, MENU_GROUP_LABEL, MENU_GROUP_LABEL_OTH, MENU_NAME, MENU_NAME_OTH, MENU_SEQ, MENU_PATH, MENU_ICON, MENU_PARENT, MENU_STATUS, MENU_DT_CREATE, MENU_UID_CREATE, MENU_DT_LUPD, MENU_UID_LUPD) ") -> INSERT INTO T_CORE_MENU_EX (MENU_ID, MENU_APPS_CODE, MENU_GROUP_LABEL, MENU_GROUP_LABEL_OTH, MENU_NAME, MENU_NAME_OTH, MENU_SEQ, MENU_PATH, MENU_ICON, MENU_PARENT, MENU_STATUS, MENU_DT_CREATE, MENU_UID_CREATE, MENU_DT_LUPD, MENU_UID_LUPD) | N78: =CONCATENATE(" VALUES('",A78,"','",B78,"','",D78,"','",E78,"','",F78,"','",G78,"',",IF(H78="NULL","NULL",CONCATENATE("'",H78,"'")),",",IF(I78="NULL","NULL",CONCATENATE("'",I78,"'")),",",IF(J78="NULL","NULL",CONCATENATE("'",J78,"'")),",",IF(K78="NULL","NULL",CONCATENATE("'",K78,"'")),",'A',NOW(),'SYS',NOW(),'SYS');") -> VALUES('CKDO_MS_060200','CKDO','DO Extension','DO Extension','DO Extension','DO Extension','60200','/applications/report/ext','','CKDO_MS_060000','A',NOW(),'SYS',NOW(),'SYS'); | O78: =CONCATENATE(M78,N78) -> INSERT INTO T_CORE_MENU_EX (MENU_ID, MENU_APPS_CODE, MENU_GROUP_LABEL, MENU_GROUP_LABEL_OTH, MENU_NAME, MENU_NAME_OTH, MENU_SEQ, MENU_PATH, MENU_ICON, MENU_PARENT, MENU_STATUS, MENU_DT_CREATE, MENU_UID_CREATE, MENU_DT_LUPD, MENU_UID_LUPD) VALUES('CKDO_MS_060200','CKDO','DO Extension','DO Extension','DO Extension','DO Extension','60200','/applications/report/ext','','CKDO_MS_060000','A',NOW(),'SYS',NOW(),'SYS');
A79: CKDO_MS_060300 | B79: CKDO | D79: DO Claim SAP | E79: DO Claim SAP | F79: DO Claim SAP | G79: DO Claim SAP | H79: 60300 | I79: /applications/sap/do | K79: CKDO_MS_060000 | L79: A | M79: =CONCATENATE("INSERT INTO T_CORE_MENU_EX (MENU_ID, MENU_APPS_CODE, MENU_GROUP_LABEL, MENU_GROUP_LABEL_OTH, MENU_NAME, MENU_NAME_OTH, MENU_SEQ, MENU_PATH, MENU_ICON, MENU_PARENT, MENU_STATUS, MENU_DT_CREATE, MENU_UID_CREATE, MENU_DT_LUPD, MENU_UID_LUPD) ") -> INSERT INTO T_CORE_MENU_EX (MENU_ID, MENU_APPS_CODE, MENU_GROUP_LABEL, MENU_GROUP_LABEL_OTH, MENU_NAME, MENU_NAME_OTH, MENU_SEQ, MENU_PATH, MENU_ICON, MENU_PARENT, MENU_STATUS, MENU_DT_CREATE, MENU_UID_CREATE, MENU_DT_LUPD, MENU_UID_LUPD) | N79: =CONCATENATE(" VALUES('",A79,"','",B79,"','",D79,"','",E79,"','",F79,"','",G79,"',",IF(H79="NULL","NULL",CONCATENATE("'",H79,"'")),",",IF(I79="NULL","NULL",CONCATENATE("'",I79,"'")),",",IF(J79="NULL","NULL",CONCATENATE("'",J79,"'")),",",IF(K79="NULL","NULL",CONCATENATE("'",K79,"'")),",'A',NOW(),'SYS',NOW(),'SYS');") -> VALUES('CKDO_MS_060300','CKDO','DO Claim SAP','DO Claim SAP','DO Claim SAP','DO Claim SAP','60300','/applications/sap/do','','CKDO_MS_060000','A',NOW(),'SYS',NOW(),'SYS'); | O79: =CONCATENATE(M79,N79) -> INSERT INTO T_CORE_MENU_EX (MENU_ID, MENU_APPS_CODE, MENU_GROUP_LABEL, MENU_GROUP_LABEL_OTH, MENU_NAME, MENU_NAME_OTH, MENU_SEQ, MENU_PATH, MENU_ICON, MENU_PARENT, MENU_STATUS, MENU_DT_CREATE, MENU_UID_CREATE, MENU_DT_LUPD, MENU_UID_LUPD) VALUES('CKDO_MS_060300','CKDO','DO Claim SAP','DO Claim SAP','DO Claim SAP','DO Claim SAP','60300','/applications/sap/do','','CKDO_MS_060000','A',NOW(),'SYS',NOW(),'SYS');
A80: CKDO_MS_060400 | B80: CKDO | D80: DO Extension SAP | E80: DO Extension SAP | F80: DO Extension SAP | G80: DO Extension SAP | H80: 60400 | I80: /applications/sap/ext | K80: CKDO_MS_060000 | L80: A | M80: =CONCATENATE("INSERT INTO T_CORE_MENU_EX (MENU_ID, MENU_APPS_CODE, MENU_GROUP_LABEL, MENU_GROUP_LABEL_OTH, MENU_NAME, MENU_NAME_OTH, MENU_SEQ, MENU_PATH, MENU_ICON, MENU_PARENT, MENU_STATUS, MENU_DT_CREATE, MENU_UID_CREATE, MENU_DT_LUPD, MENU_UID_LUPD) ") -> INSERT INTO T_CORE_MENU_EX (MENU_ID, MENU_APPS_CODE, MENU_GROUP_LABEL, MENU_GROUP_LABEL_OTH, MENU_NAME, MENU_NAME_OTH, MENU_SEQ, MENU_PATH, MENU_ICON, MENU_PARENT, MENU_STATUS, MENU_DT_CREATE, MENU_UID_CREATE, MENU_DT_LUPD, MENU_UID_LUPD) | N80: =CONCATENATE(" VALUES('",A80,"','",B80,"','",D80,"','",E80,"','",F80,"','",G80,"',",IF(H80="NULL","NULL",CONCATENATE("'",H80,"'")),",",IF(I80="NULL","NULL",CONCATENATE("'",I80,"'")),",",IF(J80="NULL","NULL",CONCATENATE("'",J80,"'")),",",IF(K80="NULL","NULL",CONCATENATE("'",K80,"'")),",'A',NOW(),'SYS',NOW(),'SYS');") -> VALUES('CKDO_MS_060400','CKDO','DO Extension SAP','DO Extension SAP','DO Extension SAP','DO Extension SAP','60400','/applications/sap/ext','','CKDO_MS_060000','A',NOW(),'SYS',NOW(),'SYS'); | O80: =CONCATENATE(M80,N80) -> INSERT INTO T_CORE_MENU_EX (MENU_ID, MENU_APPS_CODE, MENU_GROUP_LABEL, MENU_GROUP_LABEL_OTH, MENU_NAME, MENU_NAME_OTH, MENU_SEQ, MENU_PATH, MENU_ICON, MENU_PARENT, MENU_STATUS, MENU_DT_CREATE, MENU_UID_CREATE, MENU_DT_LUPD, MENU_UID_LUPD) VALUES('CKDO_MS_060400','CKDO','DO Extension SAP','DO Extension SAP','DO Extension SAP','DO Extension SAP','60400','/applications/sap/ext','','CKDO_MS_060000','A',NOW(),'SYS',NOW(),'SYS');
A81: CKDO_MS_070000 | B81: CKDO | D81: COREOR | E81: COREOR | F81: COREOR | G81: COREOR | H81: 70000 | I81: /applications/coreor/list | J81: table_view | K81: NULL | L81: A | M81: =CONCATENATE("INSERT INTO T_CORE_MENU_EX (MENU_ID, MENU_APPS_CODE, MENU_GROUP_LABEL, MENU_GROUP_LABEL_OTH, MENU_NAME, MENU_NAME_OTH, MENU_SEQ, MENU_PATH, MENU_ICON, MENU_PARENT, MENU_STATUS, MENU_DT_CREATE, MENU_UID_CREATE, MENU_DT_LUPD, MENU_UID_LUPD) ") -> INSERT INTO T_CORE_MENU_EX (MENU_ID, MENU_APPS_CODE, MENU_GROUP_LABEL, MENU_GROUP_LABEL_OTH, MENU_NAME, MENU_NAME_OTH, MENU_SEQ, MENU_PATH, MENU_ICON, MENU_PARENT, MENU_STATUS, MENU_DT_CREATE, MENU_UID_CREATE, MENU_DT_LUPD, MENU_UID_LUPD) | N81: =CONCATENATE(" VALUES('",A81,"','",B81,"','",D81,"','",E81,"','",F81,"','",G81,"',",IF(H81="NULL","NULL",CONCATENATE("'",H81,"'")),",",IF(I81="NULL","NULL",CONCATENATE("'",I81,"'")),",",IF(J81="NULL","NULL",CONCATENATE("'",J81,"'")),",",IF(K81="NULL","NULL",CONCATENATE("'",K81,"'")),",'A',NOW(),'SYS',NOW(),'SYS');") -> VALUES('CKDO_MS_070000','CKDO','COREOR','COREOR','COREOR','COREOR','70000','/applications/coreor/list','table_view',NULL,'A',NOW(),'SYS',NOW(),'SYS'); | O81: =CONCATENATE(M81,N81) -> INSERT INTO T_CORE_MENU_EX (MENU_ID, MENU_APPS_CODE, MENU_GROUP_LABEL, MENU_GROUP_LABEL_OTH, MENU_NAME, MENU_NAME_OTH, MENU_SEQ, MENU_PATH, MENU_ICON, MENU_PARENT, MENU_STATUS, MENU_DT_CREATE, MENU_UID_CREATE, MENU_DT_LUPD, MENU_UID_LUPD) VALUES('CKDO_MS_070000','CKDO','COREOR','COREOR','COREOR','COREOR','70000','/applications/coreor/list','table_view',NULL,'A',NOW(),'SYS',NOW(),'SYS');
A82: CKT_SA_090000 | B82: CKT | D82: System Administrations | E82: System Administrations | F82: System Administrations | G82: System Administrations | H82: 90000 | I82: /reports/list | J82: settings | K82: NULL | L82: A | M82: =CONCATENATE("INSERT INTO T_CORE_MENU_EX (MENU_ID, MENU_APPS_CODE, MENU_GROUP_LABEL, MENU_GROUP_LABEL_OTH, MENU_NAME, MENU_NAME_OTH, MENU_SEQ, MENU_PATH, MENU_ICON, MENU_PARENT, MENU_STATUS, MENU_DT_CREATE, MENU_UID_CREATE, MENU_DT_LUPD, MENU_UID_LUPD) ") -> INSERT INTO T_CORE_MENU_EX (MENU_ID, MENU_APPS_CODE, MENU_GROUP_LABEL, MENU_GROUP_LABEL_OTH, MENU_NAME, MENU_NAME_OTH, MENU_SEQ, MENU_PATH, MENU_ICON, MENU_PARENT, MENU_STATUS, MENU_DT_CREATE, MENU_UID_CREATE, MENU_DT_LUPD, MENU_UID_LUPD) | N82: =CONCATENATE(" VALUES('",A82,"','",B82,"','",D82,"','",E82,"','",F82,"','",G82,"',",IF(H82="NULL","NULL", CONCATENATE("'",H82,"'")),",",IF(I82="NULL","NULL", CONCATENATE("'",I82,"'")),",",IF(J82="NULL","NULL", CONCATENATE("'",J82,"'")),",",IF(K82="NULL","NULL", CONCATENATE("'",K82,"'")),",'A',NOW(),'SYS',NOW(),'SYS');") -> VALUES('CKT_SA_090000','CKT','System Administrations','System Administrations','System Administrations','System Administrations','90000','/reports/list','settings',NULL,'A',NOW(),'SYS',NOW(),'SYS'); | O82: =CONCATENATE(M82,N82) -> INSERT INTO T_CORE_MENU_EX (MENU_ID, MENU_APPS_CODE, MENU_GROUP_LABEL, MENU_GROUP_LABEL_OTH, MENU_NAME, MENU_NAME_OTH, MENU_SEQ, MENU_PATH, MENU_ICON, MENU_PARENT, MENU_STATUS, MENU_DT_CREATE, MENU_UID_CREATE, MENU_DT_LUPD, MENU_UID_LUPD) VALUES('CKT_SA_090000','CKT','System Administrations','System Administrations','System Administrations','System Administrations','90000','/reports/list','settings',NULL,'A',NOW(),'SYS',NOW(),'SYS');
A83: CKT_SA_090100 | B83: CKT | F83: System Parameters | G83: System Parameters | H83: 90100 | I83: /administrations/sysparam/list | J83: NULL | K83: CKT_SA_090000 | L83: A | M83: =CONCATENATE("INSERT INTO T_CORE_MENU_EX (MENU_ID, MENU_APPS_CODE, MENU_GROUP_LABEL, MENU_GROUP_LABEL_OTH, MENU_NAME, MENU_NAME_OTH, MENU_SEQ, MENU_PATH, MENU_ICON, MENU_PARENT, MENU_STATUS, MENU_DT_CREATE, MENU_UID_CREATE, MENU_DT_LUPD, MENU_UID_LUPD) ") -> INSERT INTO T_CORE_MENU_EX (MENU_ID, MENU_APPS_CODE, MENU_GROUP_LABEL, MENU_GROUP_LABEL_OTH, MENU_NAME, MENU_NAME_OTH, MENU_SEQ, MENU_PATH, MENU_ICON, MENU_PARENT, MENU_STATUS, MENU_DT_CREATE, MENU_UID_CREATE, MENU_DT_LUPD, MENU_UID_LUPD) | N83: =CONCATENATE(" VALUES('",A83,"','",B83,"','",D83,"','",E83,"','",F83,"','",G83,"',",IF(H83="NULL","NULL", CONCATENATE("'",H83,"'")),",",IF(I83="NULL","NULL", CONCATENATE("'",I83,"'")),",",IF(J83="NULL","NULL", CONCATENATE("'",J83,"'")),",",IF(K83="NULL","NULL", CONCATENATE("'",K83,"'")),",'A',NOW(),'SYS',NOW(),'SYS');") -> VALUES('CKT_SA_090100','CKT','','','System Parameters','System Parameters','90100','/administrations/sysparam/list',NULL,'CKT_SA_090000','A',NOW(),'SYS',NOW(),'SYS'); | O83: =CONCATENATE(M83,N83) -> INSERT INTO T_CORE_MENU_EX (MENU_ID, MENU_APPS_CODE, MENU_GROUP_LABEL, MENU_GROUP_LABEL_OTH, MENU_NAME, MENU_NAME_OTH, MENU_SEQ, MENU_PATH, MENU_ICON, MENU_PARENT, MENU_STATUS, MENU_DT_CREATE, MENU_UID_CREATE, MENU_DT_LUPD, MENU_UID_LUPD) VALUES('CKT_SA_090100','CKT','','','System Parameters','System Parameters','90100','/administrations/sysparam/list',NULL,'CKT_SA_090000','A',NOW(),'SYS',NOW(),'SYS');
A84: CKT_OA_081300 | B84: CKT | F84: Account Inquiry Request | G84: Account Inquiry Request | H84: 81300 | I84: /opadmin/inquiry/accn/list | J84: NULL | K84: CKT_OA_080000 | L84: A | M84: =CONCATENATE("INSERT INTO T_CORE_MENU_EX (MENU_ID, MENU_APPS_CODE, MENU_GROUP_LABEL, MENU_GROUP_LABEL_OTH, MENU_NAME, MENU_NAME_OTH, MENU_SEQ, MENU_PATH, MENU_ICON, MENU_PARENT, MENU_STATUS, MENU_DT_CREATE, MENU_UID_CREATE, MENU_DT_LUPD, MENU_UID_LUPD) ") -> INSERT INTO T_CORE_MENU_EX (MENU_ID, MENU_APPS_CODE, MENU_GROUP_LABEL, MENU_GROUP_LABEL_OTH, MENU_NAME, MENU_NAME_OTH, MENU_SEQ, MENU_PATH, MENU_ICON, MENU_PARENT, MENU_STATUS, MENU_DT_CREATE, MENU_UID_CREATE, MENU_DT_LUPD, MENU_UID_LUPD) | N84: =CONCATENATE(" VALUES('",A84,"','",B84,"','",D84,"','",E84,"','",F84,"','",G84,"',",IF(H84="NULL","NULL",CONCATENATE("'",H84,"'")),",",IF(I84="NULL","NULL",CONCATENATE("'",I84,"'")),",",IF(J84="NULL","NULL",CONCATENATE("'",J84,"'")),",",IF(K84="NULL","NULL",CONCATENATE("'",K84,"'")),",'A',NOW(),'SYS',NOW(),'SYS');") -> VALUES('CKT_OA_081300','CKT','','','Account Inquiry Request','Account Inquiry Request','81300','/opadmin/inquiry/accn/list',NULL,'CKT_OA_080000','A',NOW(),'SYS',NOW(),'SYS'); | O84: =CONCATENATE(M84,N84) -> INSERT INTO T_CORE_MENU_EX (MENU_ID, MENU_APPS_CODE, MENU_GROUP_LABEL, MENU_GROUP_LABEL_OTH, MENU_NAME, MENU_NAME_OTH, MENU_SEQ, MENU_PATH, MENU_ICON, MENU_PARENT, MENU_STATUS, MENU_DT_CREATE, MENU_UID_CREATE, MENU_DT_LUPD, MENU_UID_LUPD) VALUES('CKT_OA_081300','CKT','','','Account Inquiry Request','Account Inquiry Request','81300','/opadmin/inquiry/accn/list',NULL,'CKT_OA_080000','A',NOW(),'SYS',NOW(),'SYS');
A85: CKDO_OA_020000 | B85: CKDO | D85: Operations Administration | E85: Operations Administration | F85: Operations Administration | G85: Operations Administration | H85: 20000 | J85: admin_panel_settings | L85: A | M85: =CONCATENATE("INSERT INTO T_CORE_MENU_EX (MENU_ID, MENU_APPS_CODE, MENU_GROUP_LABEL, MENU_GROUP_LABEL_OTH, MENU_NAME, MENU_NAME_OTH, MENU_SEQ, MENU_PATH, MENU_ICON, MENU_PARENT, MENU_STATUS, MENU_DT_CREATE, MENU_UID_CREATE, MENU_DT_LUPD, MENU_UID_LUPD) ") -> INSERT INTO T_CORE_MENU_EX (MENU_ID, MENU_APPS_CODE, MENU_GROUP_LABEL, MENU_GROUP_LABEL_OTH, MENU_NAME, MENU_NAME_OTH, MENU_SEQ, MENU_PATH, MENU_ICON, MENU_PARENT, MENU_STATUS, MENU_DT_CREATE, MENU_UID_CREATE, MENU_DT_LUPD, MENU_UID_LUPD) | N85: =CONCATENATE(" VALUES('",A85,"','",B85,"','",D85,"','",E85,"','",F85,"','",G85,"',",IF(H85="NULL","NULL",CONCATENATE("'",H85,"'")),",",IF(I85="NULL","NULL",CONCATENATE("'",I85,"'")),",",IF(J85="NULL","NULL",CONCATENATE("'",J85,"'")),",",IF(K85="NULL","NULL",CONCATENATE("'",K85,"'")),",'A',NOW(),'SYS',NOW(),'SYS');") -> VALUES('CKDO_OA_020000','CKDO','Operations Administration','Operations Administration','Operations Administration','Operations Administration','20000','','admin_panel_settings','','A',NOW(),'SYS',NOW(),'SYS'); | O85: =CONCATENATE(M85,N85) -> INSERT INTO T_CORE_MENU_EX (MENU_ID, MENU_APPS_CODE, MENU_GROUP_LABEL, MENU_GROUP_LABEL_OTH, MENU_NAME, MENU_NAME_OTH, MENU_SEQ, MENU_PATH, MENU_ICON, MENU_PARENT, MENU_STATUS, MENU_DT_CREATE, MENU_UID_CREATE, MENU_DT_LUPD, MENU_UID_LUPD) VALUES('CKDO_OA_020000','CKDO','Operations Administration','Operations Administration','Operations Administration','Operations Administration','20000','','admin_panel_settings','','A',NOW(),'SYS',NOW(),'SYS');
A86: CKDO_OA_020100 | B86: CKDO | F86: Static Virtual Account | G86: Static Virtual Account | H86: 20100 | I86: /opadmin/staticva | J86: NULL | K86: CKDO_OA_020000 | L86: A | M86: =CONCATENATE("INSERT INTO T_CORE_MENU_EX (MENU_ID, MENU_APPS_CODE, MENU_GROUP_LABEL, MENU_GROUP_LABEL_OTH, MENU_NAME, MENU_NAME_OTH, MENU_SEQ, MENU_PATH, MENU_ICON, MENU_PARENT, MENU_STATUS, MENU_DT_CREATE, MENU_UID_CREATE, MENU_DT_LUPD, MENU_UID_LUPD) ") -> INSERT INTO T_CORE_MENU_EX (MENU_ID, MENU_APPS_CODE, MENU_GROUP_LABEL, MENU_GROUP_LABEL_OTH, MENU_NAME, MENU_NAME_OTH, MENU_SEQ, MENU_PATH, MENU_ICON, MENU_PARENT, MENU_STATUS, MENU_DT_CREATE, MENU_UID_CREATE, MENU_DT_LUPD, MENU_UID_LUPD) | N86: =CONCATENATE(" VALUES('",A86,"','",B86,"','",D86,"','",E86,"','",F86,"','",G86,"',",IF(H86="NULL","NULL",CONCATENATE("'",H86,"'")),",",IF(I86="NULL","NULL",CONCATENATE("'",I86,"'")),",",IF(J86="NULL","NULL",CONCATENATE("'",J86,"'")),",",IF(K86="NULL","NULL",CONCATENATE("'",K86,"'")),",'A',NOW(),'SYS',NOW(),'SYS');") -> VALUES('CKDO_OA_020100','CKDO','','','Static Virtual Account','Static Virtual Account','20100','/opadmin/staticva',NULL,'CKDO_OA_020000','A',NOW(),'SYS',NOW(),'SYS'); | O86: =CONCATENATE(M86,N86) -> INSERT INTO T_CORE_MENU_EX (MENU_ID, MENU_APPS_CODE, MENU_GROUP_LABEL, MENU_GROUP_LABEL_OTH, MENU_NAME, MENU_NAME_OTH, MENU_SEQ, MENU_PATH, MENU_ICON, MENU_PARENT, MENU_STATUS, MENU_DT_CREATE, MENU_UID_CREATE, MENU_DT_LUPD, MENU_UID_LUPD) VALUES('CKDO_OA_020100','CKDO','','','Static Virtual Account','Static Virtual Account','20100','/opadmin/staticva',NULL,'CKDO_OA_020000','A',NOW(),'SYS',NOW(),'SYS');
A87: CKDO_MA_030400 | B87: CKDO | D87: Tax | E87: Tax | F87: Tax | G87: Tax | H87: 30400 | I87: /manage/tax | J87: NULL | K87: CKDO_MA_030000 | L87: A | M87: =CONCATENATE("INSERT INTO T_CORE_MENU_EX (MENU_ID, MENU_APPS_CODE, MENU_GROUP_LABEL, MENU_GROUP_LABEL_OTH, MENU_NAME, MENU_NAME_OTH, MENU_SEQ, MENU_PATH, MENU_ICON, MENU_PARENT, MENU_STATUS, MENU_DT_CREATE, MENU_UID_CREATE, MENU_DT_LUPD, MENU_UID_LUPD) ") -> INSERT INTO T_CORE_MENU_EX (MENU_ID, MENU_APPS_CODE, MENU_GROUP_LABEL, MENU_GROUP_LABEL_OTH, MENU_NAME, MENU_NAME_OTH, MENU_SEQ, MENU_PATH, MENU_ICON, MENU_PARENT, MENU_STATUS, MENU_DT_CREATE, MENU_UID_CREATE, MENU_DT_LUPD, MENU_UID_LUPD) | N87: =CONCATENATE(" VALUES('",A87,"','",B87,"','",D87,"','",E87,"','",F87,"','",G87,"',",IF(H87="NULL","NULL",CONCATENATE("'",H87,"'")),",",IF(I87="NULL","NULL",CONCATENATE("'",I87,"'")),",",IF(J87="NULL","NULL",CONCATENATE("'",J87,"'")),",",IF(K87="NULL","NULL",CONCATENATE("'",K87,"'")),",'A',NOW(),'SYS',NOW(),'SYS');") -> VALUES('CKDO_MA_030400','CKDO','Tax','Tax','Tax','Tax','30400','/manage/tax',NULL,'CKDO_MA_030000','A',NOW(),'SYS',NOW(),'SYS'); | O87: =CONCATENATE(M87,N87) -> INSERT INTO T_CORE_MENU_EX (MENU_ID, MENU_APPS_CODE, MENU_GROUP_LABEL, MENU_GROUP_LABEL_OTH, MENU_NAME, MENU_NAME_OTH, MENU_SEQ, MENU_PATH, MENU_ICON, MENU_PARENT, MENU_STATUS, MENU_DT_CREATE, MENU_UID_CREATE, MENU_DT_LUPD, MENU_UID_LUPD) VALUES('CKDO_MA_030400','CKDO','Tax','Tax','Tax','Tax','30400','/manage/tax',NULL,'CKDO_MA_030000','A',NOW(),'SYS',NOW(),'SYS');
A88: CKDO_MA_030500 | B88: CKDO | D88: SAGE Integration | E88: SAGE Integration | F88: SAGE Integration | G88: SAGE Integration | H88: 30500 | I88: /opadmin/sageintegrations | J88: NULL | K88: CKDO_MA_030000 | L88: A | M88: =CONCATENATE("INSERT INTO T_CORE_MENU_EX (MENU_ID, MENU_APPS_CODE, MENU_GROUP_LABEL, MENU_GROUP_LABEL_OTH, MENU_NAME, MENU_NAME_OTH, MENU_SEQ, MENU_PATH, MENU_ICON, MENU_PARENT, MENU_STATUS, MENU_DT_CREATE, MENU_UID_CREATE, MENU_DT_LUPD, MENU_UID_LUPD) ") -> INSERT INTO T_CORE_MENU_EX (MENU_ID, MENU_APPS_CODE, MENU_GROUP_LABEL, MENU_GROUP_LABEL_OTH, MENU_NAME, MENU_NAME_OTH, MENU_SEQ, MENU_PATH, MENU_ICON, MENU_PARENT, MENU_STATUS, MENU_DT_CREATE, MENU_UID_CREATE, MENU_DT_LUPD, MENU_UID_LUPD) | N88: =CONCATENATE(" VALUES('",A88,"','",B88,"','",D88,"','",E88,"','",F88,"','",G88,"',",IF(H88="NULL","NULL",CONCATENATE("'",H88,"'")),",",IF(I88="NULL","NULL",CONCATENATE("'",I88,"'")),",",IF(J88="NULL","NULL",CONCATENATE("'",J88,"'")),",",IF(K88="NULL","NULL",CONCATENATE("'",K88,"'")),",'A',NOW(),'SYS',NOW(),'SYS');") -> VALUES('CKDO_MA_030500','CKDO','SAGE Integration','SAGE Integration','SAGE Integration','SAGE Integration','30500','/opadmin/sageintegrations',NULL,'CKDO_MA_030000','A',NOW(),'SYS',NOW(),'SYS'); | O88: =CONCATENATE(M88,N88) -> INSERT INTO T_CORE_MENU_EX (MENU_ID, MENU_APPS_CODE, MENU_GROUP_LABEL, MENU_GROUP_LABEL_OTH, MENU_NAME, MENU_NAME_OTH, MENU_SEQ, MENU_PATH, MENU_ICON, MENU_PARENT, MENU_STATUS, MENU_DT_CREATE, MENU_UID_CREATE, MENU_DT_LUPD, MENU_UID_LUPD) VALUES('CKDO_MA_030500','CKDO','SAGE Integration','SAGE Integration','SAGE Integration','SAGE Integration','30500','/opadmin/sageintegrations',NULL,'CKDO_MA_030000','A',NOW(),'SYS',NOW(),'SYS');
A89: CKDO_OA_020200 | B89: CKDO | F89: Accounts Management | G89: Accounts Management | H89: 20200 | I89: /manageAccounts/all/list | J89: NULL | K89: CKDO_OA_020000 | L89: A | M89: =CONCATENATE("INSERT INTO T_CORE_MENU_EX (MENU_ID, MENU_APPS_CODE, MENU_GROUP_LABEL, MENU_GROUP_LABEL_OTH, MENU_NAME, MENU_NAME_OTH, MENU_SEQ, MENU_PATH, MENU_ICON, MENU_PARENT, MENU_STATUS, MENU_DT_CREATE, MENU_UID_CREATE, MENU_DT_LUPD, MENU_UID_LUPD) ") -> INSERT INTO T_CORE_MENU_EX (MENU_ID, MENU_APPS_CODE, MENU_GROUP_LABEL, MENU_GROUP_LABEL_OTH, MENU_NAME, MENU_NAME_OTH, MENU_SEQ, MENU_PATH, MENU_ICON, MENU_PARENT, MENU_STATUS, MENU_DT_CREATE, MENU_UID_CREATE, MENU_DT_LUPD, MENU_UID_LUPD) | N89: =CONCATENATE(" VALUES('",A89,"','",B89,"','",D89,"','",E89,"','",F89,"','",G89,"',",IF(H89="NULL","NULL",CONCATENATE("'",H89,"'")),",",IF(I89="NULL","NULL",CONCATENATE("'",I89,"'")),",",IF(J89="NULL","NULL",CONCATENATE("'",J89,"'")),",",IF(K89="NULL","NULL",CONCATENATE("'",K89,"'")),",'A',NOW(),'SYS',NOW(),'SYS');") -> VALUES('CKDO_OA_020200','CKDO','','','Accounts Management','Accounts Management','20200','/manageAccounts/all/list',NULL,'CKDO_OA_020000','A',NOW(),'SYS',NOW(),'SYS'); | O89: =CONCATENATE(M89,N89) -> INSERT INTO T_CORE_MENU_EX (MENU_ID, MENU_APPS_CODE, MENU_GROUP_LABEL, MENU_GROUP_LABEL_OTH, MENU_NAME, MENU_NAME_OTH, MENU_SEQ, MENU_PATH, MENU_ICON, MENU_PARENT, MENU_STATUS, MENU_DT_CREATE, MENU_UID_CREATE, MENU_DT_LUPD, MENU_UID_LUPD) VALUES('CKDO_OA_020200','CKDO','','','Accounts Management','Accounts Management','20200','/manageAccounts/all/list',NULL,'CKDO_OA_020000','A',NOW(),'SYS',NOW(),'SYS');
A90: CKDO_OA_020300 | B90: CKDO | F90: Users Management | G90: Users Management | H90: 20300 | I90: /manageUsers/users/all/list | J90: NULL | K90: CKDO_OA_020000 | L90: A | M90: =CONCATENATE("INSERT INTO T_CORE_MENU_EX (MENU_ID, MENU_APPS_CODE, MENU_GROUP_LABEL, MENU_GROUP_LABEL_OTH, MENU_NAME, MENU_NAME_OTH, MENU_SEQ, MENU_PATH, MENU_ICON, MENU_PARENT, MENU_STATUS, MENU_DT_CREATE, MENU_UID_CREATE, MENU_DT_LUPD, MENU_UID_LUPD) ") -> INSERT INTO T_CORE_MENU_EX (MENU_ID, MENU_APPS_CODE, MENU_GROUP_LABEL, MENU_GROUP_LABEL_OTH, MENU_NAME, MENU_NAME_OTH, MENU_SEQ, MENU_PATH, MENU_ICON, MENU_PARENT, MENU_STATUS, MENU_DT_CREATE, MENU_UID_CREATE, MENU_DT_LUPD, MENU_UID_LUPD) | N90: =CONCATENATE(" VALUES('",A90,"','",B90,"','",D90,"','",E90,"','",F90,"','",G90,"',",IF(H90="NULL","NULL",CONCATENATE("'",H90,"'")),",",IF(I90="NULL","NULL",CONCATENATE("'",I90,"'")),",",IF(J90="NULL","NULL",CONCATENATE("'",J90,"'")),",",IF(K90="NULL","NULL",CONCATENATE("'",K90,"'")),",'A',NOW(),'SYS',NOW(),'SYS');") -> VALUES('CKDO_OA_020300','CKDO','','','Users Management','Users Management','20300','/manageUsers/users/all/list',NULL,'CKDO_OA_020000','A',NOW(),'SYS',NOW(),'SYS'); | O90: =CONCATENATE(M90,N90) -> INSERT INTO T_CORE_MENU_EX (MENU_ID, MENU_APPS_CODE, MENU_GROUP_LABEL, MENU_GROUP_LABEL_OTH, MENU_NAME, MENU_NAME_OTH, MENU_SEQ, MENU_PATH, MENU_ICON, MENU_PARENT, MENU_STATUS, MENU_DT_CREATE, MENU_UID_CREATE, MENU_DT_LUPD, MENU_UID_LUPD) VALUES('CKDO_OA_020300','CKDO','','','Users Management','Users Management','20300','/manageUsers/users/all/list',NULL,'CKDO_OA_020000','A',NOW(),'SYS',NOW(),'SYS');

Sheet Menu_EX
A1: MENU_ID | B1: MENU_APPS_CODE | C1: MENU_GROUP_LABEL | D1: MENU_GROUP_LABEL_OTH | E1: MENU_NAME | F1: MENU_NAME_OTH | G1: MENU_SEQ | H1: MENU_PATH | I1: MENU_ICON | J1: MENU_PARENT | K1: MENU_STATUS | L1: SQL
A2: CK_MS_010000 | B2: CK | C2: Services | D2: Services | E2: Services | F2: Services | G2: 10000 | H2: / | I2: NULL | J2: NULL | K2: A | L2: =CONCATENATE("INSERT INTO T_CORE_MENU_EX (MENU_ID, MENU_APPS_CODE, MENU_GROUP_LABEL, MENU_GROUP_LABEL_OTH, MENU_NAME, MENU_NAME_OTH, MENU_SEQ, MENU_PATH, MENU_ICON, MENU_PARENT, MENU_STATUS, MENU_DT_CREATE, MENU_UID_CREATE, MENU_DT_LUPD, MENU_UID_LUPD) ") -> INSERT INTO T_CORE_MENU_EX (MENU_ID, MENU_APPS_CODE, MENU_GROUP_LABEL, MENU_GROUP_LABEL_OTH, MENU_NAME, MENU_NAME_OTH, MENU_SEQ, MENU_PATH, MENU_ICON, MENU_PARENT, MENU_STATUS, MENU_DT_CREATE, MENU_UID_CREATE, MENU_DT_LUPD, MENU_UID_LUPD) | M2: =CONCATENATE(" VALUES('",A2,"','",B2,"','",C2,"','",D2,"','",E2,"','",F2,"',",IF(G2="NULL","NULL",CONCATENATE("'",G2,"'")),",",IF(H2="NULL","NULL",CONCATENATE("'",H2,"'")),",",IF(I2="NULL","NULL",CONCATENATE("'",I2,"'")),",",IF(J2="NULL","NULL",CONCATENATE("'",J2,"'")),",'A',NOW(),'SYS',NOW(),'SYS');") -> VALUES('CK_MS_010000','CK','Services','Services','Services','Services','10000','/',NULL,NULL,'A',NOW(),'SYS',NOW(),'SYS'); | N2: =CONCATENATE(L2,M2) -> INSERT INTO T_CORE_MENU_EX (MENU_ID, MENU_APPS_CODE, MENU_GROUP_LABEL, MENU_GROUP_LABEL_OTH, MENU_NAME, MENU_NAME_OTH, MENU_SEQ, MENU_PATH, MENU_ICON, MENU_PARENT, MENU_STATUS, MENU_DT_CREATE, MENU_UID_CREATE, MENU_DT_LUPD, MENU_UID_LUPD) VALUES('CK_MS_010000','CK','Services','Services','Services','Services','10000','/',NULL,NULL,'A',NOW(),'SYS',NOW(),'SYS');
A3: CK_MP_020000 | B3: CK | C3: Payments | D3: Payments | E3: Payments | F3: Payments | G3: 20000 | H3: /payments | I3: NULL | J3: NULL | K3: A | L3: =CONCATENATE("INSERT INTO T_CORE_MENU_EX (MENU_ID, MENU_APPS_CODE, MENU_GROUP_LABEL, MENU_GROUP_LABEL_OTH, MENU_NAME, MENU_NAME_OTH, MENU_SEQ, MENU_PATH, MENU_ICON, MENU_PARENT, MENU_STATUS, MENU_DT_CREATE, MENU_UID_CREATE, MENU_DT_LUPD, MENU_UID_LUPD) ") -> INSERT INTO T_CORE_MENU_EX (MENU_ID, MENU_APPS_CODE, MENU_GROUP_LABEL, MENU_GROUP_LABEL_OTH, MENU_NAME, MENU_NAME_OTH, MENU_SEQ, MENU_PATH, MENU_ICON, MENU_PARENT, MENU_STATUS, MENU_DT_CREATE, MENU_UID_CREATE, MENU_DT_LUPD, MENU_UID_LUPD) | M3: =CONCATENATE(" VALUES('",A3,"','",B3,"','",C3,"','",D3,"','",E3,"','",F3,"',",IF(G3="NULL","NULL",CONCATENATE("'",G3,"'")),",",IF(H3="NULL","NULL",CONCATENATE("'",H3,"'")),",",IF(I3="NULL","NULL",CONCATENATE("'",I3,"'")),",",IF(J3="NULL","NULL",CONCATENATE("'",J3,"'")),",'A',NOW(),'SYS',NOW(),'SYS');") -> VALUES('CK_MP_020000','CK','Payments','Payments','Payments','Payments','20000','/payments',NULL,NULL,'A',NOW(),'SYS',NOW(),'SYS'); | N3: =CONCATENATE(L3,M3) -> INSERT INTO T_CORE_MENU_EX (MENU_ID, MENU_APPS_CODE, MENU_GROUP_LABEL, MENU_GROUP_LABEL_OTH, MENU_NAME, MENU_NAME_OTH, MENU_SEQ, MENU_PATH, MENU_ICON, MENU_PARENT, MENU_STATUS, MENU_DT_CREATE, MENU_UID_CREATE, MENU_DT_LUPD, MENU_UID_LUPD) VALUES('CK_MP_020000','CK','Payments','Payments','Payments','Payments','20000','/payments',NULL,NULL,'A',NOW(),'SYS',NOW(),'SYS');
A4: CK_MA_030000 | B4: CK | C4: Administrations | D4: Administrations | E4: Administrations | F4: Administrations | G4: 30000 | H4: NULL | I4: group | J4: NULL | K4: A | L4: =CONCATENATE("INSERT INTO T_CORE_MENU_EX (MENU_ID, MENU_APPS_CODE, MENU_GROUP_LABEL, MENU_GROUP_LABEL_OTH, MENU_NAME, MENU_NAME_OTH, MENU_SEQ, MENU_PATH, MENU_ICON, MENU_PARENT, MENU_STATUS, MENU_DT_CREATE, MENU_UID_CREATE, MENU_DT_LUPD, MENU_UID_LUPD) ") -> INSERT INTO T_CORE_MENU_EX (MENU_ID, MENU_APPS_CODE, MENU_GROUP_LABEL, MENU_GROUP_LABEL_OTH, MENU_NAME, MENU_NAME_OTH, MENU_SEQ, MENU_PATH, MENU_ICON, MENU_PARENT, MENU_STATUS, MENU_DT_CREATE, MENU_UID_CREATE, MENU_DT_LUPD, MENU_UID_LUPD) | M4: =CONCATENATE(" VALUES('",A4,"','",B4,"','",C4,"','",D4,"','",E4,"','",F4,"',",IF(G4="NULL","NULL",CONCATENATE("'",G4,"'")),",",IF(H4="NULL","NULL",CONCATENATE("'",H4,"'")),",",IF(I4="NULL","NULL",CONCATENATE("'",I4,"'")),",",IF(J4="NULL","NULL",CONCATENATE("'",J4,"'")),",'A',NOW(),'SYS',NOW(),'SYS');") -> VALUES('CK_MA_030000','CK','Administrations','Administrations','Administrations','Administrations','30000',NULL,'group',NULL,'A',NOW(),'SYS',NOW(),'SYS'); | N4: =CONCATENATE(L4,M4) -> INSERT INTO T_CORE_MENU_EX (MENU_ID, MENU_APPS_CODE, MENU_GROUP_LABEL, MENU_GROUP_LABEL_OTH, MENU_NAME, MENU_NAME_OTH, MENU_SEQ, MENU_PATH, MENU_ICON, MENU_PARENT, MENU_STATUS, MENU_DT_CREATE, MENU_UID_CREATE, MENU_DT_LUPD, MENU_UID_LUPD) VALUES('CK_MA_030000','CK','Administrations','Administrations','Administrations','Administrations','30000',NULL,'group',NULL,'A',NOW(),'SYS',NOW(),'SYS');
A5: CK_MA_030100 | B5: CK | E5: Account Profile | F5: Account Profile | G5: 30100 | H5: /accountProfile | I5: NULL | J5: CK_MA_030000 | K5: A | L5: =CONCATENATE("INSERT INTO T_CORE_MENU_EX (MENU_ID, MENU_APPS_CODE, MENU_GROUP_LABEL, MENU_GROUP_LABEL_OTH, MENU_NAME, MENU_NAME_OTH, MENU_SEQ, MENU_PATH, MENU_ICON, MENU_PARENT, MENU_STATUS, MENU_DT_CREATE, MENU_UID_CREATE, MENU_DT_LUPD, MENU_UID_LUPD) ") -> INSERT INTO T_CORE_MENU_EX (MENU_ID, MENU_APPS_CODE, MENU_GROUP_LABEL, MENU_GROUP_LABEL_OTH, MENU_NAME, MENU_NAME_OTH, MENU_SEQ, MENU_PATH, MENU_ICON, MENU_PARENT, MENU_STATUS, MENU_DT_CREATE, MENU_UID_CREATE, MENU_DT_LUPD, MENU_UID_LUPD) | M5: =CONCATENATE(" VALUES('",A5,"','",B5,"','",C5,"','",D5,"','",E5,"','",F5,"',",IF(G5="NULL","NULL",CONCATENATE("'",G5,"'")),",",IF(H5="NULL","NULL",CONCATENATE("'",H5,"'")),",",IF(I5="NULL","NULL",CONCATENATE("'",I5,"'")),",",IF(J5="NULL","NULL",CONCATENATE("'",J5,"'")),",'A',NOW(),'SYS',NOW(),'SYS');") -> VALUES('CK_MA_030100','CK','','','Account Profile','Account Profile','30100','/accountProfile',NULL,'CK_MA_030000','A',NOW(),'SYS',NOW(),'SYS'); | N5: =CONCATENATE(L5,M5) -> INSERT INTO T_CORE_MENU_EX (MENU_ID, MENU_APPS_CODE, MENU_GROUP_LABEL, MENU_GROUP_LABEL_OTH, MENU_NAME, MENU_NAME_OTH, MENU_SEQ, MENU_PATH, MENU_ICON, MENU_PARENT, MENU_STATUS, MENU_DT_CREATE, MENU_UID_CREATE, MENU_DT_LUPD, MENU_UID_LUPD) VALUES('CK_MA_030100','CK','','','Account Profile','Account Profile','30100','/accountProfile',NULL,'CK_MA_030000','A',NOW(),'SYS',NOW(),'SYS');
A6: CK_MA_030200 | B6: CK | E6: Users | F6: Users | G6: 30200 | H6: /accountUsers | I6: NULL | J6: CK_MA_030000 | K6: A | L6: =CONCATENATE("INSERT INTO T_CORE_MENU_EX (MENU_ID, MENU_APPS_CODE, MENU_GROUP_LABEL, MENU_GROUP_LABEL_OTH, MENU_NAME, MENU_NAME_OTH, MENU_SEQ, MENU_PATH, MENU_ICON, MENU_PARENT, MENU_STATUS, MENU_DT_CREATE, MENU_UID_CREATE, MENU_DT_LUPD, MENU_UID_LUPD) ") -> INSERT INTO T_CORE_MENU_EX (MENU_ID, MENU_APPS_CODE, MENU_GROUP_LABEL, MENU_GROUP_LABEL_OTH, MENU_NAME, MENU_NAME_OTH, MENU_SEQ, MENU_PATH, MENU_ICON, MENU_PARENT, MENU_STATUS, MENU_DT_CREATE, MENU_UID_CREATE, MENU_DT_LUPD, MENU_UID_LUPD) | M6: =CONCATENATE(" VALUES('",A6,"','",B6,"','",C6,"','",D6,"','",E6,"','",F6,"',",IF(G6="NULL","NULL",CONCATENATE("'",G6,"'")),",",IF(H6="NULL","NULL",CONCATENATE("'",H6,"'")),",",IF(I6="NULL","NULL",CONCATENATE("'",I6,"'")),",",IF(J6="NULL","NULL",CONCATENATE("'",J6,"'")),",'A',NOW(),'SYS',NOW(),'SYS');") -> VALUES('CK_MA_030200','CK','','','Users','Users','30200','/accountUsers',NULL,'CK_MA_030000','A',NOW(),'SYS',NOW(),'SYS'); | N6: =CONCATENATE(L6,M6) -> INSERT INTO T_CORE_MENU_EX (MENU_ID, MENU_APPS_CODE, MENU_GROUP_LABEL, MENU_GROUP_LABEL_OTH, MENU_NAME, MENU_NAME_OTH, MENU_SEQ, MENU_PATH, MENU_ICON, MENU_PARENT, MENU_STATUS, MENU_DT_CREATE, MENU_UID_CREATE, MENU_DT_LUPD, MENU_UID_LUPD) VALUES('CK_MA_030200','CK','','','Users','Users','30200','/accountUsers',NULL,'CK_MA_030000','A',NOW(),'SYS',NOW(),'SYS');
A7: CK_MA_030300 | B7: CK | E7: Authorisations | F7: Authorisations | G7: 30400 | H7: /accountAuthorisations | I7: NULL | J7: CK_MA_030000 | K7: A | L7: =CONCATENATE("INSERT INTO T_CORE_MENU_EX (MENU_ID, MENU_APPS_CODE, MENU_GROUP_LABEL, MENU_GROUP_LABEL_OTH, MENU_NAME, MENU_NAME_OTH, MENU_SEQ, MENU_PATH, MENU_ICON, MENU_PARENT, MENU_STATUS, MENU_DT_CREATE, MENU_UID_CREATE, MENU_DT_LUPD, MENU_UID_LUPD) ") -> INSERT INTO T_CORE_MENU_EX (MENU_ID, MENU_APPS_CODE, MENU_GROUP_LABEL, MENU_GROUP_LABEL_OTH, MENU_NAME, MENU_NAME_OTH, MENU_SEQ, MENU_PATH, MENU_ICON, MENU_PARENT, MENU_STATUS, MENU_DT_CREATE, MENU_UID_CREATE, MENU_DT_LUPD, MENU_UID_LUPD) | M7: =CONCATENATE(" VALUES('",A7,"','",B7,"','",C7,"','",D7,"','",E7,"','",F7,"',",IF(G7="NULL","NULL",CONCATENATE("'",G7,"'")),",",IF(H7="NULL","NULL",CONCATENATE("'",H7,"'")),",",IF(I7="NULL","NULL",CONCATENATE("'",I7,"'")),",",IF(J7="NULL","NULL",CONCATENATE("'",J7,"'")),",'A',NOW(),'SYS',NOW(),'SYS');") -> VALUES('CK_MA_030300','CK','','','Authorisations','Authorisations','30400','/accountAuthorisations',NULL,'CK_MA_030000','A',NOW(),'SYS',NOW(),'SYS'); | N7: =CONCATENATE(L7,M7) -> INSERT INTO T_CORE_MENU_EX (MENU_ID, MENU_APPS_CODE, MENU_GROUP_LABEL, MENU_GROUP_LABEL_OTH, MENU_NAME, MENU_NAME_OTH, MENU_SEQ, MENU_PATH, MENU_ICON, MENU_PARENT, MENU_STATUS, MENU_DT_CREATE, MENU_UID_CREATE, MENU_DT_LUPD, MENU_UID_LUPD) VALUES('CK_MA_030300','CK','','','Authorisations','Authorisations','30400','/accountAuthorisations',NULL,'CK_MA_030000','A',NOW(),'SYS',NOW(),'SYS');
A8: CK_MH_040000 | B8: CK | C8: Help | D8: Help | E8: Help | F8: Help | G8: 40000 | H8: /help | I8: NULL | J8: NULL | K8: A | L8: =CONCATENATE("INSERT INTO T_CORE_MENU_EX (MENU_ID, MENU_APPS_CODE, MENU_GROUP_LABEL, MENU_GROUP_LABEL_OTH, MENU_NAME, MENU_NAME_OTH, MENU_SEQ, MENU_PATH, MENU_ICON, MENU_PARENT, MENU_STATUS, MENU_DT_CREATE, MENU_UID_CREATE, MENU_DT_LUPD, MENU_UID_LUPD) ") -> INSERT INTO T_CORE_MENU_EX (MENU_ID, MENU_APPS_CODE, MENU_GROUP_LABEL, MENU_GROUP_LABEL_OTH, MENU_NAME, MENU_NAME_OTH, MENU_SEQ, MENU_PATH, MENU_ICON, MENU_PARENT, MENU_STATUS, MENU_DT_CREATE, MENU_UID_CREATE, MENU_DT_LUPD, MENU_UID_LUPD) | M8: =CONCATENATE(" VALUES('",A8,"','",B8,"','",C8,"','",D8,"','",E8,"','",F8,"',",IF(G8="NULL","NULL",CONCATENATE("'",G8,"'")),",",IF(H8="NULL","NULL",CONCATENATE("'",H8,"'")),",",IF(I8="NULL","NULL",CONCATENATE("'",I8,"'")),",",IF(J8="NULL","NULL",CONCATENATE("'",J8,"'")),",'A',NOW(),'SYS',NOW(),'SYS');") -> VALUES('CK_MH_040000','CK','Help','Help','Help','Help','40000','/help',NULL,NULL,'A',NOW(),'SYS',NOW(),'SYS'); | N8: =CONCATENATE(L8,M8) -> INSERT INTO T_CORE_MENU_EX (MENU_ID, MENU_APPS_CODE, MENU_GROUP_LABEL, MENU_GROUP_LABEL_OTH, MENU_NAME, MENU_NAME_OTH, MENU_SEQ, MENU_PATH, MENU_ICON, MENU_PARENT, MENU_STATUS, MENU_DT_CREATE, MENU_UID_CREATE, MENU_DT_LUPD, MENU_UID_LUPD) VALUES('CK_MH_040000','CK','Help','Help','Help','Help','40000','/help',NULL,NULL,'A',NOW(),'SYS',NOW(),'SYS');
A9: CK_MT_050000 | B9: CK | C9: Master Table | D9: Master Table | E9: Master Table | F9: Master Table | G9: 50000 | H9: NULL | I9: table_view | J9: NULL | K9: A | L9: =CONCATENATE("INSERT INTO T_CORE_MENU_EX (MENU_ID, MENU_APPS_CODE, MENU_GROUP_LABEL, MENU_GROUP_LABEL_OTH, MENU_NAME, MENU_NAME_OTH, MENU_SEQ, MENU_PATH, MENU_ICON, MENU_PARENT, MENU_STATUS, MENU_DT_CREATE, MENU_UID_CREATE, MENU_DT_LUPD, MENU_UID_LUPD) ") -> INSERT INTO T_CORE_MENU_EX (MENU_ID, MENU_APPS_CODE, MENU_GROUP_LABEL, MENU_GROUP_LABEL_OTH, MENU_NAME, MENU_NAME_OTH, MENU_SEQ, MENU_PATH, MENU_ICON, MENU_PARENT, MENU_STATUS, MENU_DT_CREATE, MENU_UID_CREATE, MENU_DT_LUPD, MENU_UID_LUPD) | M9: =CONCATENATE(" VALUES('",A9,"','",B9,"','",C9,"','",D9,"','",E9,"','",F9,"',",IF(G9="NULL","NULL",CONCATENATE("'",G9,"'")),",",IF(H9="NULL","NULL",CONCATENATE("'",H9,"'")),",",IF(I9="NULL","NULL",CONCATENATE("'",I9,"'")),",",IF(J9="NULL","NULL",CONCATENATE("'",J9,"'")),",'A',NOW(),'SYS',NOW(),'SYS');") -> VALUES('CK_MT_050000','CK','Master Table','Master Table','Master Table','Master Table','50000',NULL,'table_view',NULL,'A',NOW(),'SYS',NOW(),'SYS'); | N9: =CONCATENATE(L9,M9) -> INSERT INTO T_CORE_MENU_EX (MENU_ID, MENU_APPS_CODE, MENU_GROUP_LABEL, MENU_GROUP_LABEL_OTH, MENU_NAME, MENU_NAME_OTH, MENU_SEQ, MENU_PATH, MENU_ICON, MENU_PARENT, MENU_STATUS, MENU_DT_CREATE, MENU_UID_CREATE, MENU_DT_LUPD, MENU_UID_LUPD) VALUES('CK_MT_050000','CK','Master Table','Master Table','Master Table','Master Table','50000',NULL,'table_view',NULL,'A',NOW(),'SYS',NOW(),'SYS');
A10: CK_MT_050100 | B10: CK | E10: Announcement Type | F10: Announcement Type | G10: 50100 | H10: /configuration/announcementType/list | I10: NULL | J10: CK_MT_050000 | K10: A | L10: =CONCATENATE("INSERT INTO T_CORE_MENU_EX (MENU_ID, MENU_APPS_CODE, MENU_GROUP_LABEL, MENU_GROUP_LABEL_OTH, MENU_NAME, MENU_NAME_OTH, MENU_SEQ, MENU_PATH, MENU_ICON, MENU_PARENT, MENU_STATUS, MENU_DT_CREATE, MENU_UID_CREATE, MENU_DT_LUPD, MENU_UID_LUPD) ") -> INSERT INTO T_CORE_MENU_EX (MENU_ID, MENU_APPS_CODE, MENU_GROUP_LABEL, MENU_GROUP_LABEL_OTH, MENU_NAME, MENU_NAME_OTH, MENU_SEQ, MENU_PATH, MENU_ICON, MENU_PARENT, MENU_STATUS, MENU_DT_CREATE, MENU_UID_CREATE, MENU_DT_LUPD, MENU_UID_LUPD) | M10: =CONCATENATE(" VALUES('",A10,"','",B10,"','",C10,"','",D10,"','",E10,"','",F10,"',",IF(G10="NULL","NULL",CONCATENATE("'",G10,"'")),",",IF(H10="NULL","NULL",CONCATENATE("'",H10,"'")),",",IF(I10="NULL","NULL",CONCATENATE("'",I10,"'")),",",IF(J10="NULL","NULL",CONCATENATE("'",J10,"'")),",'A',NOW(),'SYS',NOW(),'SYS');") -> VALUES('CK_MT_050100','CK','','','Announcement Type','Announcement Type','50100','/configuration/announcementType/list',NULL,'CK_MT_050000','A',NOW(),'SYS',NOW(),'SYS'); | N10: =CONCATENATE(L10,M10) -> INSERT INTO T_CORE_MENU_EX (MENU_ID, MENU_APPS_CODE, MENU_GROUP_LABEL, MENU_GROUP_LABEL_OTH, MENU_NAME, MENU_NAME_OTH, MENU_SEQ, MENU_PATH, MENU_ICON, MENU_PARENT, MENU_STATUS, MENU_DT_CREATE, MENU_UID_CREATE, MENU_DT_LUPD, MENU_UID_LUPD) VALUES('CK_MT_050100','CK','','','Announcement Type','Announcement Type','50100','/configuration/announcementType/list',NULL,'CK_MT_050000','A',NOW(),'SYS',NOW(),'SYS');
A11: CK_MT_050200 | B11: CK | E11: Country Codes | F11: Country Codes | G11: 50200 | H11: /master/country/list | I11: NULL | J11: CK_MT_050000 | K11: A | L11: =CONCATENATE("INSERT INTO T_CORE_MENU_EX (MENU_ID, MENU_APPS_CODE, MENU_GROUP_LABEL, MENU_GROUP_LABEL_OTH, MENU_NAME, MENU_NAME_OTH, MENU_SEQ, MENU_PATH, MENU_ICON, MENU_PARENT, MENU_STATUS, MENU_DT_CREATE, MENU_UID_CREATE, MENU_DT_LUPD, MENU_UID_LUPD) ") -> INSERT INTO T_CORE_MENU_EX (MENU_ID, MENU_APPS_CODE, MENU_GROUP_LABEL, MENU_GROUP_LABEL_OTH, MENU_NAME, MENU_NAME_OTH, MENU_SEQ, MENU_PATH, MENU_ICON, MENU_PARENT, MENU_STATUS, MENU_DT_CREATE, MENU_UID_CREATE, MENU_DT_LUPD, MENU_UID_LUPD) | M11: =CONCATENATE(" VALUES('",A11,"','",B11,"','",C11,"','",D11,"','",E11,"','",F11,"',",IF(G11="NULL","NULL",CONCATENATE("'",G11,"'")),",",IF(H11="NULL","NULL",CONCATENATE("'",H11,"'")),",",IF(I11="NULL","NULL",CONCATENATE("'",I11,"'")),",",IF(J11="NULL","NULL",CONCATENATE("'",J11,"'")),",'A',NOW(),'SYS',NOW(),'SYS');") -> VALUES('CK_MT_050200','CK','','','Country Codes','Country Codes','50200','/master/country/list',NULL,'CK_MT_050000','A',NOW(),'SYS',NOW(),'SYS'); | N11: =CONCATENATE(L11,M11) -> INSERT INTO T_CORE_MENU_EX (MENU_ID, MENU_APPS_CODE, MENU_GROUP_LABEL, MENU_GROUP_LABEL_OTH, MENU_NAME, MENU_NAME_OTH, MENU_SEQ, MENU_PATH, MENU_ICON, MENU_PARENT, MENU_STATUS, MENU_DT_CREATE, MENU_UID_CREATE, MENU_DT_LUPD, MENU_UID_LUPD) VALUES('CK_MT_050200','CK','','','Country Codes','Country Codes','50200','/master/country/list',NULL,'CK_MT_050000','A',NOW(),'SYS',NOW(),'SYS');
A12: CK_MT_050300 | B12: CK | E12: Currency Code | F12: Currency Code | G12: 50300 | H12: /master/currency/list | I12: NULL | J12: CK_MT_050000 | K12: A | L12: =CONCATENATE("INSERT INTO T_CORE_MENU_EX (MENU_ID, MENU_APPS_CODE, MENU_GROUP_LABEL, MENU_GROUP_LABEL_OTH, MENU_NAME, MENU_NAME_OTH, MENU_SEQ, MENU_PATH, MENU_ICON, MENU_PARENT, MENU_STATUS, MENU_DT_CREATE, MENU_UID_CREATE, MENU_DT_LUPD, MENU_UID_LUPD) ") -> INSERT INTO T_CORE_MENU_EX (MENU_ID, MENU_APPS_CODE, MENU_GROUP_LABEL, MENU_GROUP_LABEL_OTH, MENU_NAME, MENU_NAME_OTH, MENU_SEQ, MENU_PATH, MENU_ICON, MENU_PARENT, MENU_STATUS, MENU_DT_CREATE, MENU_UID_CREATE, MENU_DT_LUPD, MENU_UID_LUPD) | M12: =CONCATENATE(" VALUES('",A12,"','",B12,"','",C12,"','",D12,"','",E12,"','",F12,"',",IF(G12="NULL","NULL",CONCATENATE("'",G12,"'")),",",IF(H12="NULL","NULL",CONCATENATE("'",H12,"'")),",",IF(I12="NULL","NULL",CONCATENATE("'",I12,"'")),",",IF(J12="NULL","NULL",CONCATENATE("'",J12,"'")),",'A',NOW(),'SYS',NOW(),'SYS');") -> VALUES('CK_MT_050300','CK','','','Currency Code','Currency Code','50300','/master/currency/list',NULL,'CK_MT_050000','A',NOW(),'SYS',NOW(),'SYS'); | N12: =CONCATENATE(L12,M12) -> INSERT INTO T_CORE_MENU_EX (MENU_ID, MENU_APPS_CODE, MENU_GROUP_LABEL, MENU_GROUP_LABEL_OTH, MENU_NAME, MENU_NAME_OTH, MENU_SEQ, MENU_PATH, MENU_ICON, MENU_PARENT, MENU_STATUS, MENU_DT_CREATE, MENU_UID_CREATE, MENU_DT_LUPD, MENU_UID_LUPD) VALUES('CK_MT_050300','CK','','','Currency Code','Currency Code','50300','/master/currency/list',NULL,'CK_MT_050000','A',NOW(),'SYS',NOW(),'SYS');
A13: CK_MT_050400 | B13: CK | E13: Harmonized System Codes | F13: Harmonized System Codes | G13: 50400 | H13: /master/hsCode/list | I13: NULL | J13: CK_MT_050000 | K13: A | L13: =CONCATENATE("INSERT INTO T_CORE_MENU_EX (MENU_ID, MENU_APPS_CODE, MENU_GROUP_LABEL, MENU_GROUP_LABEL_OTH, MENU_NAME, MENU_NAME_OTH, MENU_SEQ, MENU_PATH, MENU_ICON, MENU_PARENT, MENU_STATUS, MENU_DT_CREATE, MENU_UID_CREATE, MENU_DT_LUPD, MENU_UID_LUPD) ") -> INSERT INTO T_CORE_MENU_EX (MENU_ID, MENU_APPS_CODE, MENU_GROUP_LABEL, MENU_GROUP_LABEL_OTH, MENU_NAME, MENU_NAME_OTH, MENU_SEQ, MENU_PATH, MENU_ICON, MENU_PARENT, MENU_STATUS, MENU_DT_CREATE, MENU_UID_CREATE, MENU_DT_LUPD, MENU_UID_LUPD) | M13: =CONCATENATE(" VALUES('",A13,"','",B13,"','",C13,"','",D13,"','",E13,"','",F13,"',",IF(G13="NULL","NULL",CONCATENATE("'",G13,"'")),",",IF(H13="NULL","NULL",CONCATENATE("'",H13,"'")),",",IF(I13="NULL","NULL",CONCATENATE("'",I13,"'")),",",IF(J13="NULL","NULL",CONCATENATE("'",J13,"'")),",'A',NOW(),'SYS',NOW(),'SYS');") -> VALUES('CK_MT_050400','CK','','','Harmonized System Codes','Harmonized System Codes','50400','/master/hsCode/list',NULL,'CK_MT_050000','A',NOW(),'SYS',NOW(),'SYS'); | N13: =CONCATENATE(L13,M13) -> INSERT INTO T_CORE_MENU_EX (MENU_ID, MENU_APPS_CODE, MENU_GROUP_LABEL, MENU_GROUP_LABEL_OTH, MENU_NAME, MENU_NAME_OTH, MENU_SEQ, MENU_PATH, MENU_ICON, MENU_PARENT, MENU_STATUS, MENU_DT_CREATE, MENU_UID_CREATE, MENU_DT_LUPD, MENU_UID_LUPD) VALUES('CK_MT_050400','CK','','','Harmonized System Codes','Harmonized System Codes','50400','/master/hsCode/list',NULL,'CK_MT_050000','A',NOW(),'SYS',NOW(),'SYS');
A14: CK_MT_050500 | B14: CK | E14: Notification Templates | F14: Notification Templates | G14: 50500 | H14: /notification/templates/list | I14: NULL | J14: CK_MT_050000 | K14: A | L14: =CONCATENATE("INSERT INTO T_CORE_MENU_EX (MENU_ID, MENU_APPS_CODE, MENU_GROUP_LABEL, MENU_GROUP_LABEL_OTH, MENU_NAME, MENU_NAME_OTH, MENU_SEQ, MENU_PATH, MENU_ICON, MENU_PARENT, MENU_STATUS, MENU_DT_CREATE, MENU_UID_CREATE, MENU_DT_LUPD, MENU_UID_LUPD) ") -> INSERT INTO T_CORE_MENU_EX (MENU_ID, MENU_APPS_CODE, MENU_GROUP_LABEL, MENU_GROUP_LABEL_OTH, MENU_NAME, MENU_NAME_OTH, MENU_SEQ, MENU_PATH, MENU_ICON, MENU_PARENT, MENU_STATUS, MENU_DT_CREATE, MENU_UID_CREATE, MENU_DT_LUPD, MENU_UID_LUPD) | M14: =CONCATENATE(" VALUES('",A14,"','",B14,"','",C14,"','",D14,"','",E14,"','",F14,"',",IF(G14="NULL","NULL",CONCATENATE("'",G14,"'")),",",IF(H14="NULL","NULL",CONCATENATE("'",H14,"'")),",",IF(I14="NULL","NULL",CONCATENATE("'",I14,"'")),",",IF(J14="NULL","NULL",CONCATENATE("'",J14,"'")),",'A',NOW(),'SYS',NOW(),'SYS');") -> VALUES('CK_MT_050500','CK','','','Notification Templates','Notification Templates','50500','/notification/templates/list',NULL,'CK_MT_050000','A',NOW(),'SYS',NOW(),'SYS'); | N14: =CONCATENATE(L14,M14) -> INSERT INTO T_CORE_MENU_EX (MENU_ID, MENU_APPS_CODE, MENU_GROUP_LABEL, MENU_GROUP_LABEL_OTH, MENU_NAME, MENU_NAME_OTH, MENU_SEQ, MENU_PATH, MENU_ICON, MENU_PARENT, MENU_STATUS, MENU_DT_CREATE, MENU_UID_CREATE, MENU_DT_LUPD, MENU_UID_LUPD) VALUES('CK_MT_050500','CK','','','Notification Templates','Notification Templates','50500','/notification/templates/list',NULL,'CK_MT_050000','A',NOW(),'SYS',NOW(),'SYS');
A15: CK_MT_050600 | B15: CK | E15: Port Codes | F15: Port Codes | G15: 50600 | H15: /master/port/list | I15: NULL | J15: CK_MT_050000 | K15: A | L15: =CONCATENATE("INSERT INTO T_CORE_MENU_EX (MENU_ID, MENU_APPS_CODE, MENU_GROUP_LABEL, MENU_GROUP_LABEL_OTH, MENU_NAME, MENU_NAME_OTH, MENU_SEQ, MENU_PATH, MENU_ICON, MENU_PARENT, MENU_STATUS, MENU_DT_CREATE, MENU_UID_CREATE, MENU_DT_LUPD, MENU_UID_LUPD) ") -> INSERT INTO T_CORE_MENU_EX (MENU_ID, MENU_APPS_CODE, MENU_GROUP_LABEL, MENU_GROUP_LABEL_OTH, MENU_NAME, MENU_NAME_OTH, MENU_SEQ, MENU_PATH, MENU_ICON, MENU_PARENT, MENU_STATUS, MENU_DT_CREATE, MENU_UID_CREATE, MENU_DT_LUPD, MENU_UID_LUPD) | M15: =CONCATENATE(" VALUES('",A15,"','",B15,"','",C15,"','",D15,"','",E15,"','",F15,"',",IF(G15="NULL","NULL",CONCATENATE("'",G15,"'")),",",IF(H15="NULL","NULL",CONCATENATE("'",H15,"'")),",",IF(I15="NULL","NULL",CONCATENATE("'",I15,"'")),",",IF(J15="NULL","NULL",CONCATENATE("'",J15,"'")),",'A',NOW(),'SYS',NOW(),'SYS');") -> VALUES('CK_MT_050600','CK','','','Port Codes','Port Codes','50600','/master/port/list',NULL,'CK_MT_050000','A',NOW(),'SYS',NOW(),'SYS'); | N15: =CONCATENATE(L15,M15) -> INSERT INTO T_CORE_MENU_EX (MENU_ID, MENU_APPS_CODE, MENU_GROUP_LABEL, MENU_GROUP_LABEL_OTH, MENU_NAME, MENU_NAME_OTH, MENU_SEQ, MENU_PATH, MENU_ICON, MENU_PARENT, MENU_STATUS, MENU_DT_CREATE, MENU_UID_CREATE, MENU_DT_LUPD, MENU_UID_LUPD) VALUES('CK_MT_050600','CK','','','Port Codes','Port Codes','50600','/master/port/list',NULL,'CK_MT_050000','A',NOW(),'SYS',NOW(),'SYS');
A16: CK_MT_050700 | B16: CK | E16: Port Terminal | F16: Port Terminal | G16: 50700 | H16: /master/portTerminal/list | I16: NULL | J16: CK_MT_050000 | K16: A | L16: =CONCATENATE("INSERT INTO T_CORE_MENU_EX (MENU_ID, MENU_APPS_CODE, MENU_GROUP_LABEL, MENU_GROUP_LABEL_OTH, MENU_NAME, MENU_NAME_OTH, MENU_SEQ, MENU_PATH, MENU_ICON, MENU_PARENT, MENU_STATUS, MENU_DT_CREATE, MENU_UID_CREATE, MENU_DT_LUPD, MENU_UID_LUPD) ") -> INSERT INTO T_CORE_MENU_EX (MENU_ID, MENU_APPS_CODE, MENU_GROUP_LABEL, MENU_GROUP_LABEL_OTH, MENU_NAME, MENU_NAME_OTH, MENU_SEQ, MENU_PATH, MENU_ICON, MENU_PARENT, MENU_STATUS, MENU_DT_CREATE, MENU_UID_CREATE, MENU_DT_LUPD, MENU_UID_LUPD) | M16: =CONCATENATE(" VALUES('",A16,"','",B16,"','",C16,"','",D16,"','",E16,"','",F16,"',",IF(G16="NULL","NULL",CONCATENATE("'",G16,"'")),",",IF(H16="NULL","NULL",CONCATENATE("'",H16,"'")),",",IF(I16="NULL","NULL",CONCATENATE("'",I16,"'")),",",IF(J16="NULL","NULL",CONCATENATE("'",J16,"'")),",'A',NOW(),'SYS',NOW(),'SYS');") -> VALUES('CK_MT_050700','CK','','','Port Terminal','Port Terminal','50700','/master/portTerminal/list',NULL,'CK_MT_050000','A',NOW(),'SYS',NOW(),'SYS'); | N16: =CONCATENATE(L16,M16) -> INSERT INTO T_CORE_MENU_EX (MENU_ID, MENU_APPS_CODE, MENU_GROUP_LABEL, MENU_GROUP_LABEL_OTH, MENU_NAME, MENU_NAME_OTH, MENU_SEQ, MENU_PATH, MENU_ICON, MENU_PARENT, MENU_STATUS, MENU_DT_CREATE, MENU_UID_CREATE, MENU_DT_LUPD, MENU_UID_LUPD) VALUES('CK_MT_050700','CK','','','Port Terminal','Port Terminal','50700','/master/portTerminal/list',NULL,'CK_MT_050000','A',NOW(),'SYS',NOW(),'SYS');
A17: CK_MT_050800 | B17: CK | E17: UOM Codes | F17: UOM Codes | G17: 50800 | H17: /master/uom/list | I17: NULL | J17: CK_MT_050000 | K17: A | L17: =CONCATENATE("INSERT INTO T_CORE_MENU_EX (MENU_ID, MENU_APPS_CODE, MENU_GROUP_LABEL, MENU_GROUP_LABEL_OTH, MENU_NAME, MENU_NAME_OTH, MENU_SEQ, MENU_PATH, MENU_ICON, MENU_PARENT, MENU_STATUS, MENU_DT_CREATE, MENU_UID_CREATE, MENU_DT_LUPD, MENU_UID_LUPD) ") -> INSERT INTO T_CORE_MENU_EX (MENU_ID, MENU_APPS_CODE, MENU_GROUP_LABEL, MENU_GROUP_LABEL_OTH, MENU_NAME, MENU_NAME_OTH, MENU_SEQ, MENU_PATH, MENU_ICON, MENU_PARENT, MENU_STATUS, MENU_DT_CREATE, MENU_UID_CREATE, MENU_DT_LUPD, MENU_UID_LUPD) | M17: =CONCATENATE(" VALUES('",A17,"','",B17,"','",C17,"','",D17,"','",E17,"','",F17,"',",IF(G17="NULL","NULL",CONCATENATE("'",G17,"'")),",",IF(H17="NULL","NULL",CONCATENATE("'",H17,"'")),",",IF(I17="NULL","NULL",CONCATENATE("'",I17,"'")),",",IF(J17="NULL","NULL",CONCATENATE("'",J17,"'")),",'A',NOW(),'SYS',NOW(),'SYS');") -> VALUES('CK_MT_050800','CK','','','UOM Codes','UOM Codes','50800','/master/uom/list',NULL,'CK_MT_050000','A',NOW(),'SYS',NOW(),'SYS'); | N17: =CONCATENATE(L17,M17) -> INSERT INTO T_CORE_MENU_EX (MENU_ID, MENU_APPS_CODE, MENU_GROUP_LABEL, MENU_GROUP_LABEL_OTH, MENU_NAME, MENU_NAME_OTH, MENU_SEQ, MENU_PATH, MENU_ICON, MENU_PARENT, MENU_STATUS, MENU_DT_CREATE, MENU_UID_CREATE, MENU_DT_LUPD, MENU_UID_LUPD) VALUES('CK_MT_050800','CK','','','UOM Codes','UOM Codes','50800','/master/uom/list',NULL,'CK_MT_050000','A',NOW(),'SYS',NOW(),'SYS');
A18: CK_MSA_060000 | B18: CK | C18: System Administrations | D18: System Administrations | E18: System Administrations | F18: System Administrations | G18: 60000 | H18: NULL | I18: settings | J18: NULL | K18: A | L18: =CONCATENATE("INSERT INTO T_CORE_MENU_EX (MENU_ID, MENU_APPS_CODE, MENU_GROUP_LABEL, MENU_GROUP_LABEL_OTH, MENU_NAME, MENU_NAME_OTH, MENU_SEQ, MENU_PATH, MENU_ICON, MENU_PARENT, MENU_STATUS, MENU_DT_CREATE, MENU_UID_CREATE, MENU_DT_LUPD, MENU_UID_LUPD) ") -> INSERT INTO T_CORE_MENU_EX (MENU_ID, MENU_APPS_CODE, MENU_GROUP_LABEL, MENU_GROUP_LABEL_OTH, MENU_NAME, MENU_NAME_OTH, MENU_SEQ, MENU_PATH, MENU_ICON, MENU_PARENT, MENU_STATUS, MENU_DT_CREATE, MENU_UID_CREATE, MENU_DT_LUPD, MENU_UID_LUPD) | M18: =CONCATENATE(" VALUES('",A18,"','",B18,"','",C18,"','",D18,"','",E18,"','",F18,"',",IF(G18="NULL","NULL",CONCATENATE("'",G18,"'")),",",IF(H18="NULL","NULL",CONCATENATE("'",H18,"'")),",",IF(I18="NULL","NULL",CONCATENATE("'",I18,"'")),",",IF(J18="NULL","NULL",CONCATENATE("'",J18,"'")),",'A',NOW(),'SYS',NOW(),'SYS');") -> VALUES('CK_MSA_060000','CK','System Administrations','System Administrations','System Administrations','System Administrations','60000',NULL,'settings',NULL,'A',NOW(),'SYS',NOW(),'SYS'); | N18: =CONCATENATE(L18,M18) -> INSERT INTO T_CORE_MENU_EX (MENU_ID, MENU_APPS_CODE, MENU_GROUP_LABEL, MENU_GROUP_LABEL_OTH, MENU_NAME, MENU_NAME_OTH, MENU_SEQ, MENU_PATH, MENU_ICON, MENU_PARENT, MENU_STATUS, MENU_DT_CREATE, MENU_UID_CREATE, MENU_DT_LUPD, MENU_UID_LUPD) VALUES('CK_MSA_060000','CK','System Administrations','System Administrations','System Administrations','System Administrations','60000',NULL,'settings',NULL,'A',NOW(),'SYS',NOW(),'SYS');
A19: CK_MSA_060100 | B19: CK | E19: Announcement Setup | F19: Announcement Setup | G19: 60100 | H19: /configuration/announcement/list | I19: NULL | J19: CK_MSA_060100 | K19: A | L19: =CONCATENATE("INSERT INTO T_CORE_MENU_EX (MENU_ID, MENU_APPS_CODE, MENU_GROUP_LABEL, MENU_GROUP_LABEL_OTH, MENU_NAME, MENU_NAME_OTH, MENU_SEQ, MENU_PATH, MENU_ICON, MENU_PARENT, MENU_STATUS, MENU_DT_CREATE, MENU_UID_CREATE, MENU_DT_LUPD, MENU_UID_LUPD) ") -> INSERT INTO T_CORE_MENU_EX (MENU_ID, MENU_APPS_CODE, MENU_GROUP_LABEL, MENU_GROUP_LABEL_OTH, MENU_NAME, MENU_NAME_OTH, MENU_SEQ, MENU_PATH, MENU_ICON, MENU_PARENT, MENU_STATUS, MENU_DT_CREATE, MENU_UID_CREATE, MENU_DT_LUPD, MENU_UID_LUPD) | M19: =CONCATENATE(" VALUES('",A19,"','",B19,"','",C19,"','",D19,"','",E19,"','",F19,"',",IF(G19="NULL","NULL",CONCATENATE("'",G19,"'")),",",IF(H19="NULL","NULL",CONCATENATE("'",H19,"'")),",",IF(I19="NULL","NULL",CONCATENATE("'",I19,"'")),",",IF(J19="NULL","NULL",CONCATENATE("'",J19,"'")),",'A',NOW(),'SYS',NOW(),'SYS');") -> VALUES('CK_MSA_060100','CK','','','Announcement Setup','Announcement Setup','60100','/configuration/announcement/list',NULL,'CK_MSA_060100','A',NOW(),'SYS',NOW(),'SYS'); | N19: =CONCATENATE(L19,M19) -> INSERT INTO T_CORE_MENU_EX (MENU_ID, MENU_APPS_CODE, MENU_GROUP_LABEL, MENU_GROUP_LABEL_OTH, MENU_NAME, MENU_NAME_OTH, MENU_SEQ, MENU_PATH, MENU_ICON, MENU_PARENT, MENU_STATUS, MENU_DT_CREATE, MENU_UID_CREATE, MENU_DT_LUPD, MENU_UID_LUPD) VALUES('CK_MSA_060100','CK','','','Announcement Setup','Announcement Setup','60100','/configuration/announcement/list',NULL,'CK_MSA_060100','A',NOW(),'SYS',NOW(),'SYS');
A20: CK_MSA_060200 | B20: CK | E20: Notification Preferences | F20: Notification Preferences | G20: 60200 | H20: /configuration/notification/preferences/list | I20: NULL | J20: CK_MSA_060100 | K20: A | L20: =CONCATENATE("INSERT INTO T_CORE_MENU_EX (MENU_ID, MENU_APPS_CODE, MENU_GROUP_LABEL, MENU_GROUP_LABEL_OTH, MENU_NAME, MENU_NAME_OTH, MENU_SEQ, MENU_PATH, MENU_ICON, MENU_PARENT, MENU_STATUS, MENU_DT_CREATE, MENU_UID_CREATE, MENU_DT_LUPD, MENU_UID_LUPD) ") -> INSERT INTO T_CORE_MENU_EX (MENU_ID, MENU_APPS_CODE, MENU_GROUP_LABEL, MENU_GROUP_LABEL_OTH, MENU_NAME, MENU_NAME_OTH, MENU_SEQ, MENU_PATH, MENU_ICON, MENU_PARENT, MENU_STATUS, MENU_DT_CREATE, MENU_UID_CREATE, MENU_DT_LUPD, MENU_UID_LUPD) | M20: =CONCATENATE(" VALUES('",A20,"','",B20,"','",C20,"','",D20,"','",E20,"','",F20,"',",IF(G20="NULL","NULL",CONCATENATE("'",G20,"'")),",",IF(H20="NULL","NULL",CONCATENATE("'",H20,"'")),",",IF(I20="NULL","NULL",CONCATENATE("'",I20,"'")),",",IF(J20="NULL","NULL",CONCATENATE("'",J20,"'")),",'A',NOW(),'SYS',NOW(),'SYS');") -> VALUES('CK_MSA_060200','CK','','','Notification Preferences','Notification Preferences','60200','/configuration/notification/preferences/list',NULL,'CK_MSA_060100','A',NOW(),'SYS',NOW(),'SYS'); | N20: =CONCATENATE(L20,M20) -> INSERT INTO T_CORE_MENU_EX (MENU_ID, MENU_APPS_CODE, MENU_GROUP_LABEL, MENU_GROUP_LABEL_OTH, MENU_NAME, MENU_NAME_OTH, MENU_SEQ, MENU_PATH, MENU_ICON, MENU_PARENT, MENU_STATUS, MENU_DT_CREATE, MENU_UID_CREATE, MENU_DT_LUPD, MENU_UID_LUPD) VALUES('CK_MSA_060200','CK','','','Notification Preferences','Notification Preferences','60200','/configuration/notification/preferences/list',NULL,'CK_MSA_060100','A',NOW(),'SYS',NOW(),'SYS');
A21: CK_MSA_060300 | B21: CK | E21: System Parameters | F21: System Parameters | G21: 60300 | H21: /administrations/sysparam/list | I21: NULL | J21: CK_MSA_060100 | K21: A | L21: =CONCATENATE("INSERT INTO T_CORE_MENU_EX (MENU_ID, MENU_APPS_CODE, MENU_GROUP_LABEL, MENU_GROUP_LABEL_OTH, MENU_NAME, MENU_NAME_OTH, MENU_SEQ, MENU_PATH, MENU_ICON, MENU_PARENT, MENU_STATUS, MENU_DT_CREATE, MENU_UID_CREATE, MENU_DT_LUPD, MENU_UID_LUPD) ") -> INSERT INTO T_CORE_MENU_EX (MENU_ID, MENU_APPS_CODE, MENU_GROUP_LABEL, MENU_GROUP_LABEL_OTH, MENU_NAME, MENU_NAME_OTH, MENU_SEQ, MENU_PATH, MENU_ICON, MENU_PARENT, MENU_STATUS, MENU_DT_CREATE, MENU_UID_CREATE, MENU_DT_LUPD, MENU_UID_LUPD) | M21: =CONCATENATE(" VALUES('",A21,"','",B21,"','",C21,"','",D21,"','",E21,"','",F21,"',",IF(G21="NULL","NULL",CONCATENATE("'",G21,"'")),",",IF(H21="NULL","NULL",CONCATENATE("'",H21,"'")),",",IF(I21="NULL","NULL",CONCATENATE("'",I21,"'")),",",IF(J21="NULL","NULL",CONCATENATE("'",J21,"'")),",'A',NOW(),'SYS',NOW(),'SYS');") -> VALUES('CK_MSA_060300','CK','','','System Parameters','System Parameters','60300','/administrations/sysparam/list',NULL,'CK_MSA_060100','A',NOW(),'SYS',NOW(),'SYS'); | N21: =CONCATENATE(L21,M21) -> INSERT INTO T_CORE_MENU_EX (MENU_ID, MENU_APPS_CODE, MENU_GROUP_LABEL, MENU_GROUP_LABEL_OTH, MENU_NAME, MENU_NAME_OTH, MENU_SEQ, MENU_PATH, MENU_ICON, MENU_PARENT, MENU_STATUS, MENU_DT_CREATE, MENU_UID_CREATE, MENU_DT_LUPD, MENU_UID_LUPD) VALUES('CK_MSA_060300','CK','','','System Parameters','System Parameters','60300','/administrations/sysparam/list',NULL,'CK_MSA_060100','A',NOW(),'SYS',NOW(),'SYS');
A22: CK_MSA_060400 | B22: CK | E22: Audit Logs | F22: Audit Logs | G22: 60400 | H22: /administrations/audit/list | I22: NULL | J22: CK_MSA_060100 | K22: A | L22: =CONCATENATE("INSERT INTO T_CORE_MENU_EX (MENU_ID, MENU_APPS_CODE, MENU_GROUP_LABEL, MENU_GROUP_LABEL_OTH, MENU_NAME, MENU_NAME_OTH, MENU_SEQ, MENU_PATH, MENU_ICON, MENU_PARENT, MENU_STATUS, MENU_DT_CREATE, MENU_UID_CREATE, MENU_DT_LUPD, MENU_UID_LUPD) ") -> INSERT INTO T_CORE_MENU_EX (MENU_ID, MENU_APPS_CODE, MENU_GROUP_LABEL, MENU_GROUP_LABEL_OTH, MENU_NAME, MENU_NAME_OTH, MENU_SEQ, MENU_PATH, MENU_ICON, MENU_PARENT, MENU_STATUS, MENU_DT_CREATE, MENU_UID_CREATE, MENU_DT_LUPD, MENU_UID_LUPD) | M22: =CONCATENATE(" VALUES('",A22,"','",B22,"','",C22,"','",D22,"','",E22,"','",F22,"',",IF(G22="NULL","NULL",CONCATENATE("'",G22,"'")),",",IF(H22="NULL","NULL",CONCATENATE("'",H22,"'")),",",IF(I22="NULL","NULL",CONCATENATE("'",I22,"'")),",",IF(J22="NULL","NULL",CONCATENATE("'",J22,"'")),",'A',NOW(),'SYS',NOW(),'SYS');") -> VALUES('CK_MSA_060400','CK','','','Audit Logs','Audit Logs','60400','/administrations/audit/list',NULL,'CK_MSA_060100','A',NOW(),'SYS',NOW(),'SYS'); | N22: =CONCATENATE(L22,M22) -> INSERT INTO T_CORE_MENU_EX (MENU_ID, MENU_APPS_CODE, MENU_GROUP_LABEL, MENU_GROUP_LABEL_OTH, MENU_NAME, MENU_NAME_OTH, MENU_SEQ, MENU_PATH, MENU_ICON, MENU_PARENT, MENU_STATUS, MENU_DT_CREATE, MENU_UID_CREATE, MENU_DT_LUPD, MENU_UID_LUPD) VALUES('CK_MSA_060400','CK','','','Audit Logs','Audit Logs','60400','/administrations/audit/list',NULL,'CK_MSA_060100','A',NOW(),'SYS',NOW(),'SYS');
A23: CK_MSA_060500 | B23: CK | E23: Exceptions | F23: Exceptions | G23: 60500 | H23: /administrations/exception/list | I23: NULL | J23: CK_MSA_060100 | K23: A | L23: =CONCATENATE("INSERT INTO T_CORE_MENU_EX (MENU_ID, MENU_APPS_CODE, MENU_GROUP_LABEL, MENU_GROUP_LABEL_OTH, MENU_NAME, MENU_NAME_OTH, MENU_SEQ, MENU_PATH, MENU_ICON, MENU_PARENT, MENU_STATUS, MENU_DT_CREATE, MENU_UID_CREATE, MENU_DT_LUPD, MENU_UID_LUPD) ") -> INSERT INTO T_CORE_MENU_EX (MENU_ID, MENU_APPS_CODE, MENU_GROUP_LABEL, MENU_GROUP_LABEL_OTH, MENU_NAME, MENU_NAME_OTH, MENU_SEQ, MENU_PATH, MENU_ICON, MENU_PARENT, MENU_STATUS, MENU_DT_CREATE, MENU_UID_CREATE, MENU_DT_LUPD, MENU_UID_LUPD) | M23: =CONCATENATE(" VALUES('",A23,"','",B23,"','",C23,"','",D23,"','",E23,"','",F23,"',",IF(G23="NULL","NULL",CONCATENATE("'",G23,"'")),",",IF(H23="NULL","NULL",CONCATENATE("'",H23,"'")),",",IF(I23="NULL","NULL",CONCATENATE("'",I23,"'")),",",IF(J23="NULL","NULL",CONCATENATE("'",J23,"'")),",'A',NOW(),'SYS',NOW(),'SYS');") -> VALUES('CK_MSA_060500','CK','','','Exceptions','Exceptions','60500','/administrations/exception/list',NULL,'CK_MSA_060100','A',NOW(),'SYS',NOW(),'SYS'); | N23: =CONCATENATE(L23,M23) -> INSERT INTO T_CORE_MENU_EX (MENU_ID, MENU_APPS_CODE, MENU_GROUP_LABEL, MENU_GROUP_LABEL_OTH, MENU_NAME, MENU_NAME_OTH, MENU_SEQ, MENU_PATH, MENU_ICON, MENU_PARENT, MENU_STATUS, MENU_DT_CREATE, MENU_UID_CREATE, MENU_DT_LUPD, MENU_UID_LUPD) VALUES('CK_MSA_060500','CK','','','Exceptions','Exceptions','60500','/administrations/exception/list',NULL,'CK_MSA_060100','A',NOW(),'SYS',NOW(),'SYS');
