Workbook

Sheet Summary
A1: ACCN_ID | B1: NAME | C1: ACCN_TYPE | D1: VAT_NO | E1: ADDR1 | F1: ADDR2 | G1: ADDR3 | H1: PCODE | I1: CITY | J1: PROV | K1: CTYCODE | L1: TEL | M1: FAX | N1: EMAIL | O1: REG_DATE | P1: SAGE CUTOMER ID | Q1: VA | R1: BANK ACCOUNT | T1: LAST DATE CO TRX | U1: LAST DATE TV TRX | V1: LAST DATE TRX | W1: OUTSTANDING JOB | X1: COMPLETED JOB | Y1: STATUS | AA1: Name Customer mapping ACCpac | AB1: Name Customer mapping Bank TV
A2: CK0173 | B2: [TRIAL] PT. BERKAT ANAK BANGSA | C2: ACC_TYPE_TO | D2: 919845255541000 | E2: KP. KITREN NO. 576 RT/024 RW/005 PRENGGAN, KOTAGEDE KOTA YOGYAKARTA, DAERAH ISTIMEWA YOGYAKARTA, 55173 | N2: admin@bkb.com | O2: 2022-07-06 08:35:38 | P2: 0 | Q2: 0 | R2: 0 | T2: =_xlfn.IFNA(VLOOKUP(B2,Sheet2!$A$2:$M$58,4,0),"-") -> - | U2: =_xlfn.IFNA(VLOOKUP(B2,'TV Trx'!$B$4:$C$57,2,0),"-") -> - | V2: =IF(C2="ACC_TYPE_CO",T2,U2) -> - | W2: =_xlfn.IFNA(VLOOKUP(B2,'CO Trx'!$A$4:$B$37,2,0),"-") -> - | X2: =_xlfn.IFNA(VLOOKUP(B2,'CO Trx'!$A$49:$B$104,2,0),"-") -> - | Y2: NOT FOUND
A3: CK0046 | B3: 1231231231 | C3: ACC_TYPE_TO | D3: 7897129387 | E3: PROLONGACION BOSQUES DE REFORMA 1440 TORRE2 | H3: 05120 | I3: kabupaten kaur | J3: bengkulu | L3: 08123773527 | N3: haqinoorendra@gmail.com | O3: 2021-04-11 12:14:51 | P3: 0 | Q3: 0 | R3: 0 | T3: =_xlfn.IFNA(VLOOKUP(B3,Sheet2!$A$2:$M$58,4,0),"-") -> - | U3: =_xlfn.IFNA(VLOOKUP(B3,'TV Trx'!$B$4:$C$57,2,0),"-") -> - | V3: =IF(C3="ACC_TYPE_CO",T3,U3) -> - | W3: =_xlfn.IFNA(VLOOKUP(B3,'CO Trx'!$A$4:$B$37,2,0),"-") -> - | X3: =_xlfn.IFNA(VLOOKUP(B3,'CO Trx'!$A$49:$B$104,2,0),"-") -> - | Y3: NOT FOUND
A4: CK0047 | B4: 172371231 | C4: ACC_TYPE_TO | D4: 631782687 | E4: HASDAUDBHU123 | H4: 72137 | I4: kota cilegon | J4: banten | L4: 0812732171 | N4: ruzziqbusiness@gmail.com | O4: 2021-04-13 09:12:24 | P4: 0 | Q4: 0 | R4: 0 | T4: =_xlfn.IFNA(VLOOKUP(B4,Sheet2!$A$2:$M$58,4,0),"-") -> - | U4: =_xlfn.IFNA(VLOOKUP(B4,'TV Trx'!$B$4:$C$57,2,0),"-") -> - | V4: =IF(C4="ACC_TYPE_CO",T4,U4) -> - | W4: =_xlfn.IFNA(VLOOKUP(B4,'CO Trx'!$A$4:$B$37,2,0),"-") -> - | X4: =_xlfn.IFNA(VLOOKUP(B4,'CO Trx'!$A$49:$B$104,2,0),"-") -> - | Y4: NOT FOUND
A5: CK0045 | B5: 23523523 | C5: ACC_TYPE_CO | D5: 523464363423523 | E5: HTTP://CDN-35.ANONFILES.COM/H67FO4J4O6/F248F784-1596378883/VYOLIN.PHP5 | H5: 451621 | I5: kabupaten badung | J5: bali | L5: 0872471847124 | N5: stregh@wearehackerone.com | O5: 2021-04-11 12:05:14 | P5: 0 | Q5: 0 | R5: 0 | T5: =_xlfn.IFNA(VLOOKUP(B5,Sheet2!$A$2:$M$58,4,0),"-") -> - | U5: =_xlfn.IFNA(VLOOKUP(B5,'TV Trx'!$B$4:$C$57,2,0),"-") -> - | V5: =IF(C5="ACC_TYPE_CO",T5,U5) -> - | W5: =_xlfn.IFNA(VLOOKUP(B5,'CO Trx'!$A$4:$B$37,2,0),"-") -> - | X5: =_xlfn.IFNA(VLOOKUP(B5,'CO Trx'!$A$49:$B$104,2,0),"-") -> - | Y5: NOT FOUND
A6: CK0092 | B6: ABIZARD NIAGA UTAMA | C6: ACC_TYPE_CO | D6: 418860896406000 | E6: JL. JATI NO. 11 RT/RW 001/001, NANGGALAMEKAR, CIRANJANG, CIANJUR, JAWA BARAT 43282 | L6: 087774033666 | N6: sehabudin.co@gmail.com | O6: 2021-08-26 14:47:10 | P6: 0 | Q6: 0 | R6: 0 | T6: =_xlfn.IFNA(VLOOKUP(B6,Sheet2!$A$2:$M$58,4,0),"-") -> - | U6: =_xlfn.IFNA(VLOOKUP(B6,'TV Trx'!$B$4:$C$57,2,0),"-") -> - | V6: =IF(C6="ACC_TYPE_CO",T6,U6) -> - | W6: =_xlfn.IFNA(VLOOKUP(B6,'CO Trx'!$A$4:$B$37,2,0),"-") -> - | X6: =_xlfn.IFNA(VLOOKUP(B6,'CO Trx'!$A$49:$B$104,2,0),"-") -> - | Y6: NOT FOUND
A7: CK0123 | B7: ADATRANS LTD | C7: ACC_TYPE_FF | D7: 100013778517 | E7: PETRAZOLIŲ G. 5, VAITELIAI, KLAIPEDOS AREA, LITHUANIA, LT-96198 | L7: 37067948159 | N7: transport@adatrans.lt | O7: 2022-01-27 12:20:24 | P7: 0 | Q7: 0 | R7: 0 | T7: =_xlfn.IFNA(VLOOKUP(B7,Sheet2!$A$2:$M$58,4,0),"-") -> - | U7: =_xlfn.IFNA(VLOOKUP(B7,'TV Trx'!$B$4:$C$57,2,0),"-") -> - | V7: =IF(C7="ACC_TYPE_CO",T7,U7) -> - | W7: =_xlfn.IFNA(VLOOKUP(B7,'CO Trx'!$A$4:$B$37,2,0),"-") -> - | X7: =_xlfn.IFNA(VLOOKUP(B7,'CO Trx'!$A$49:$B$104,2,0),"-") -> - | Y7: NOT FOUND
A8: CK0026 | B8: AGUNG PRAS | C8: ACC_TYPE_CO | D8: 704142322402000 | E8: JL KH EZ MUTAQIEN NO 37 RT 004 RW 002 | H8: 15133 | I8: kota tangerang | J8: banten | O8: 2020-10-13 10:46:35 | P8: 0 | Q8: 0 | R8: 0 | T8: =_xlfn.IFNA(VLOOKUP(B8,Sheet2!$A$2:$M$58,4,0),"-") -> - | U8: =_xlfn.IFNA(VLOOKUP(B8,'TV Trx'!$B$4:$C$57,2,0),"-") -> - | V8: =IF(C8="ACC_TYPE_CO",T8,U8) -> - | W8: =_xlfn.IFNA(VLOOKUP(B8,'CO Trx'!$A$4:$B$37,2,0),"-") -> - | X8: =_xlfn.IFNA(VLOOKUP(B8,'CO Trx'!$A$49:$B$104,2,0),"-") -> - | Y8: NOT FOUND
A9: CK0163 | B9: ALPHA GREAT FORWARDERS | C9: ACC_TYPE_FF | D9: 96234 | E9: OFFICE | N9: alphagreat@clickargo.com | O9: 2022-05-23 08:13:57 | P9: 0 | Q9: 0 | R9: 0 | T9: =_xlfn.IFNA(VLOOKUP(B9,Sheet2!$A$2:$M$58,4,0),"-") -> - | U9: =_xlfn.IFNA(VLOOKUP(B9,'TV Trx'!$B$4:$C$57,2,0),"-") -> - | V9: =IF(C9="ACC_TYPE_CO",T9,U9) -> - | W9: =_xlfn.IFNA(VLOOKUP(B9,'CO Trx'!$A$4:$B$37,2,0),"-") -> - | X9: =_xlfn.IFNA(VLOOKUP(B9,'CO Trx'!$A$49:$B$104,2,0),"-") -> - | Y9: NOT FOUND
A10: CK0055 | B10: ANJAY LTD | C10: ACC_TYPE_CO | D10: 15945645646 | E10: PRINCETON | H10: 27569 | I10: roseville | J10: Alaska | L10: 5022362210 | N10: haqinoorendra1@gmail.com | O10: 2021-05-21 09:31:30 | P10: 0 | Q10: 0 | R10: 0 | T10: =_xlfn.IFNA(VLOOKUP(B10,Sheet2!$A$2:$M$58,4,0),"-") -> - | U10: =_xlfn.IFNA(VLOOKUP(B10,'TV Trx'!$B$4:$C$57,2,0),"-") -> - | V10: =IF(C10="ACC_TYPE_CO",T10,U10) -> - | W10: =_xlfn.IFNA(VLOOKUP(B10,'CO Trx'!$A$4:$B$37,2,0),"-") -> - | X10: =_xlfn.IFNA(VLOOKUP(B10,'CO Trx'!$A$49:$B$104,2,0),"-") -> - | Y10: NOT FOUND
A11: CK0011 | B11: ANUGRAH MULIA TRANSINDO | C11: ACC_TYPE_TO | D11: 026951053043000 | E11: RUKAN BUKIT GADING INDAH | H11: 14240 | I11: kota jakarta utara | J11: dki jakarta | O11: 2020-08-10 02:13:34 | P11: 0 | Q11: 0 | R11: 0 | T11: =_xlfn.IFNA(VLOOKUP(B11,Sheet2!$A$2:$M$58,4,0),"-") -> - | U11: =_xlfn.IFNA(VLOOKUP(B11,'TV Trx'!$B$4:$C$57,2,0),"-") -> - | V11: =IF(C11="ACC_TYPE_CO",T11,U11) -> - | W11: =_xlfn.IFNA(VLOOKUP(B11,'CO Trx'!$A$4:$B$37,2,0),"-") -> - | X11: =_xlfn.IFNA(VLOOKUP(B11,'CO Trx'!$A$49:$B$104,2,0),"-") -> - | Y11: NOT FOUND
A12: CK0094 | B12: AZON TRANSPORT PTE LTD | C12: ACC_TYPE_TO | D12: 1211 | L12: 12312312 | N12: jp@yopmail.com | O12: 2021-09-01 02:48:55 | P12: 0 | Q12: 0 | R12: 0 | T12: =_xlfn.IFNA(VLOOKUP(B12,Sheet2!$A$2:$M$58,4,0),"-") -> - | U12: =_xlfn.IFNA(VLOOKUP(B12,'TV Trx'!$B$4:$C$57,2,0),"-") -> - | V12: =IF(C12="ACC_TYPE_CO",T12,U12) -> - | W12: =_xlfn.IFNA(VLOOKUP(B12,'CO Trx'!$A$4:$B$37,2,0),"-") -> - | X12: =_xlfn.IFNA(VLOOKUP(B12,'CO Trx'!$A$49:$B$104,2,0),"-") -> - | Y12: NOT FOUND
A13: CK0006 | B13: B & J EXPRESS INT COMPANY LTD | C13: ACC_TYPE_CO | D13: 2213134800011198 | E13: FLAT B-1, 5/FL, BLOCK B, YEE LIM INDUSTRIAL CENTRE, NO 2-28, KWAI LOK STREET, KWAI CHUNG, N.T. | H13: 852 | L13: 26101262 | N13: elaine@bj-express.com | O13: 2020-07-07 06:48:53 | P13: 0 | Q13: 0 | R13: 0 | T13: =_xlfn.IFNA(VLOOKUP(B13,Sheet2!$A$2:$M$58,4,0),"-") -> - | U13: =_xlfn.IFNA(VLOOKUP(B13,'TV Trx'!$B$4:$C$57,2,0),"-") -> - | V13: =IF(C13="ACC_TYPE_CO",T13,U13) -> - | W13: =_xlfn.IFNA(VLOOKUP(B13,'CO Trx'!$A$4:$B$37,2,0),"-") -> - | X13: =_xlfn.IFNA(VLOOKUP(B13,'CO Trx'!$A$49:$B$104,2,0),"-") -> - | Y13: NOT FOUND
A14: CK0027 | B14: BUKIT ALAM HIJAU | C14: ACC_TYPE_CO | D14: 313983249405000 | E14: KP. DANO RT/RW 004/004, BOJONG, CIKEMBAR, SUKABUMI, JAWA BARAT 43157 | H14: 43157 | I14: SUKABUMI | J14: JAWA BARAT | O14: 2020-10-17 09:45:42 | P14: 0 | Q14: 0 | R14: 0 | T14: =_xlfn.IFNA(VLOOKUP(B14,Sheet2!$A$2:$M$58,4,0),"-") -> - | U14: =_xlfn.IFNA(VLOOKUP(B14,'TV Trx'!$B$4:$C$57,2,0),"-") -> - | V14: =IF(C14="ACC_TYPE_CO",T14,U14) -> - | W14: =_xlfn.IFNA(VLOOKUP(B14,'CO Trx'!$A$4:$B$37,2,0),"-") -> - | X14: =_xlfn.IFNA(VLOOKUP(B14,'CO Trx'!$A$49:$B$104,2,0),"-") -> - | Y14: NOT FOUND
A15: CK0015 | B15: CARGO TEST | C15: ACC_TYPE_CO | D15: 12345 | E15: PAYA LEBAR | H15: 12356 | I15: kota jakarta barat | J15: dki jakarta | L15: 123 | N15: cargoowner@yopmail.com | O15: 2020-09-08 03:20:33 | P15: 0 | Q15: 0 | R15: 0 | T15: =_xlfn.IFNA(VLOOKUP(B15,Sheet2!$A$2:$M$58,4,0),"-") -> - | U15: =_xlfn.IFNA(VLOOKUP(B15,'TV Trx'!$B$4:$C$57,2,0),"-") -> - | V15: =IF(C15="ACC_TYPE_CO",T15,U15) -> - | W15: =_xlfn.IFNA(VLOOKUP(B15,'CO Trx'!$A$4:$B$37,2,0),"-") -> - | X15: =_xlfn.IFNA(VLOOKUP(B15,'CO Trx'!$A$49:$B$104,2,0),"-") -> - | Y15: NOT FOUND
A16: CK0030 | B16: CICILIA SANTOSO | C16: ACC_TYPE_TO | D16: 210297685025000 | E16: GREENLAND INTERNATIONAL INDUSTRIAL CENTER BLOK AF NO. 8, SERANG BARU, NAGASARI, DELTAMAS | H16: 17530 | I16: kabupaten bekasi | J16: jawa barat | O16: 2020-10-27 12:08:10 | P16: 0 | Q16: 0 | R16: 0 | T16: =_xlfn.IFNA(VLOOKUP(B16,Sheet2!$A$2:$M$58,4,0),"-") -> - | U16: =_xlfn.IFNA(VLOOKUP(B16,'TV Trx'!$B$4:$C$57,2,0),"-") -> - | V16: =IF(C16="ACC_TYPE_CO",T16,U16) -> - | W16: =_xlfn.IFNA(VLOOKUP(B16,'CO Trx'!$A$4:$B$37,2,0),"-") -> - | X16: =_xlfn.IFNA(VLOOKUP(B16,'CO Trx'!$A$49:$B$104,2,0),"-") -> - | Y16: NOT FOUND
A17: CK0051 | B17: CIPTA SINERGI BISNIS | D17: 732914643606000 | E17: MANYAR 57 B RT/RW 006/002, MENUR PUMPUNGAN, SUKOLILO, KOTA SURABAYA, JAWA TIMUR 60118 | H17: 60118 | I17: kota surabaya | J17: jawa timur | L17: 0315944379 | N17: csbisnis57@gmail.com | O17: 2021-04-22 03:17:22 | P17: 0 | Q17: 0 | R17: 0 | T17: =_xlfn.IFNA(VLOOKUP(B17,Sheet2!$A$2:$M$58,4,0),"-") -> - | U17: =_xlfn.IFNA(VLOOKUP(B17,'TV Trx'!$B$4:$C$57,2,0),"-") -> - | V17: =IF(C17="ACC_TYPE_CO",T17,U17) -> - | W17: =_xlfn.IFNA(VLOOKUP(B17,'CO Trx'!$A$4:$B$37,2,0),"-") -> - | X17: =_xlfn.IFNA(VLOOKUP(B17,'CO Trx'!$A$49:$B$104,2,0),"-") -> - | Y17: NOT FOUND
A18: CK0313 | B18: CV ALI TRANS | C18: ACC_TYPE_TO | D18: 742770878542000 | E18: PERUM JATIMAS PERMAI Q.15 013/042, BALECATUR, GAMPING, SLEMAN, YOGYAKARTA | L18: 0 | N18: cv.alitrans@gmail.com | O18: 2023-05-25 07:08:08 | P18: LIA029 | R18: BRI : 219701000099507 | T18: =_xlfn.IFNA(VLOOKUP(B18,Sheet2!$A$2:$M$58,4,0),"-") -> - | U18: =_xlfn.IFNA(VLOOKUP(B18,'TV Trx'!$B$4:$C$57,2,0),"-") -> 45076 | V18: =IF(C18="ACC_TYPE_CO",T18,U18) -> 45076 | W18: =_xlfn.IFNA(VLOOKUP(B18,'CO Trx'!$A$4:$B$37,2,0),"-") -> - | X18: =_xlfn.IFNA(VLOOKUP(B18,'CO Trx'!$A$49:$B$104,2,0),"-") -> - | Y18: ACTIVE | AA18: CV. Ali Trans-PF | AB18: ALI TRANS
A19: CK0200 | B19: CV ANANDHI | C19: ACC_TYPE_TO | D19: 000000000000001 | E19: NODATA | N19: marketing@anandhi.co.id | O19: 2022-10-05 06:47:04 | P19: 0 | Q19: 0 | R19: 0 | T19: =_xlfn.IFNA(VLOOKUP(B19,Sheet2!$A$2:$M$58,4,0),"-") -> - | U19: =_xlfn.IFNA(VLOOKUP(B19,'TV Trx'!$B$4:$C$57,2,0),"-") -> - | V19: =IF(C19="ACC_TYPE_CO",T19,U19) -> - | W19: =_xlfn.IFNA(VLOOKUP(B19,'CO Trx'!$A$4:$B$37,2,0),"-") -> - | X19: =_xlfn.IFNA(VLOOKUP(B19,'CO Trx'!$A$49:$B$104,2,0),"-") -> - | Y19: NOT FOUND
A20: CK0174 | B20: CV DUTA ANDALAN PERKASA | C20: ACC_TYPE_TO | D20: 652595596427000 | E20: PLAZA SUMMARECON BEKAS,JL BULEVAR AHMAD YAN, KAV.K.01,LANTA 7 | L20: 085163623702 | N20: dutaandalanperkasa@gmail.com | O20: 2022-07-18 18:05:19 | P20: 0 | Q20: 0 | R20: 0 | T20: =_xlfn.IFNA(VLOOKUP(B20,Sheet2!$A$2:$M$58,4,0),"-") -> - | U20: =_xlfn.IFNA(VLOOKUP(B20,'TV Trx'!$B$4:$C$57,2,0),"-") -> - | V20: =IF(C20="ACC_TYPE_CO",T20,U20) -> - | W20: =_xlfn.IFNA(VLOOKUP(B20,'CO Trx'!$A$4:$B$37,2,0),"-") -> - | X20: =_xlfn.IFNA(VLOOKUP(B20,'CO Trx'!$A$49:$B$104,2,0),"-") -> - | Y20: NOT FOUND
A21: CK0124 | B21: CV OKTAMA TRANS LOGISTIC | C21: ACC_TYPE_TO | D21: 411268410613000 | E21: JL. KH HAMDANI NO. 1 , KEL. SAWOHAN, KEC. BUDURAN, KAB. SIDOARJO, PROV. JAWA TIMU | L21: 0895610037010 | N21: otlcargojatim24@gmail.com | O21: 2022-02-02 10:52:53 | P21: 0 | Q21: 0 | R21: 0 | T21: =_xlfn.IFNA(VLOOKUP(B21,Sheet2!$A$2:$M$58,4,0),"-") -> - | U21: =_xlfn.IFNA(VLOOKUP(B21,'TV Trx'!$B$4:$C$57,2,0),"-") -> - | V21: =IF(C21="ACC_TYPE_CO",T21,U21) -> - | W21: =_xlfn.IFNA(VLOOKUP(B21,'CO Trx'!$A$4:$B$37,2,0),"-") -> - | X21: =_xlfn.IFNA(VLOOKUP(B21,'CO Trx'!$A$49:$B$104,2,0),"-") -> - | Y21: NOT FOUND
A22: CK0189 | B22: CV VAHANA ORION LOGISTICS DAN TRANSPORTATION | C22: ACC_TYPE_TO | D22: 702961244526000 | E22: GRAND GALAXY CITY RUKO ROSE GARDEN (RRG) BLOK RRG 02 NO. 98 | N22: volt.ekspedisi@gmail.com | O22: 2022-09-12 03:10:37 | P22: 0 | Q22: 0 | R22: 0 | T22: =_xlfn.IFNA(VLOOKUP(B22,Sheet2!$A$2:$M$58,4,0),"-") -> - | U22: =_xlfn.IFNA(VLOOKUP(B22,'TV Trx'!$B$4:$C$57,2,0),"-") -> - | V22: =IF(C22="ACC_TYPE_CO",T22,U22) -> - | W22: =_xlfn.IFNA(VLOOKUP(B22,'CO Trx'!$A$4:$B$37,2,0),"-") -> - | X22: =_xlfn.IFNA(VLOOKUP(B22,'CO Trx'!$A$49:$B$104,2,0),"-") -> - | Y22: NOT FOUND
A23: CK0306 | B23: CV. ABADI JAYA | C23: ACC_TYPE_CO | D23: 020001186511000 | E23: RAYA MRANGGEN KM.16,2, DK. DOLOG, KEL KEMBANARUM, KEC. MRANGGEN, KAB. DEMAK, PROP. JAWA TENGAH | L23: 0 | N23: djbudiman@holiks-smg.com | O23: 2023-05-19 03:40:30 | P23: LI428 | T23: =_xlfn.IFNA(VLOOKUP(B23,Sheet2!$A$2:$M$58,4,0),"-") -> 0 | U23: =_xlfn.IFNA(VLOOKUP(B23,'TV Trx'!$B$4:$C$57,2,0),"-") -> - | V23: - | W23: =_xlfn.IFNA(VLOOKUP(B23,'CO Trx'!$A$4:$B$37,2,0),"-") -> - | X23: =_xlfn.IFNA(VLOOKUP(B23,'CO Trx'!$A$49:$B$104,2,0),"-") -> - | Y23: ACTIVE | AA23: CV. Abadi Jaya-PF
A24: CK0299 | B24: CV. AL-ONE GUNAWAN JAYA SENTOSA | C24: ACC_TYPE_CO | D24: 753416049425000 | E24: JL.RAYA PAGERAGEUNG TENGAH RT/01 RW/05, DESA PAGERAGEUNG, KEC. PAGERAGEUNG, KAB. TASIKMALAYA | L24: 0 | N24: gunawanjstrans72@gmail.com | O24: 2023-05-17 03:01:47 | P24: LI404 | T24: =_xlfn.IFNA(VLOOKUP(B24,Sheet2!$A$2:$M$58,4,0),"-") -> 45083 | U24: =_xlfn.IFNA(VLOOKUP(B24,'TV Trx'!$B$4:$C$57,2,0),"-") -> - | V24: =IF(C24="ACC_TYPE_CO",T24,U24) -> 45083 | W24: =_xlfn.IFNA(VLOOKUP(B24,'CO Trx'!$A$4:$B$37,2,0),"-") -> - | X24: =_xlfn.IFNA(VLOOKUP(B24,'CO Trx'!$A$49:$B$104,2,0),"-") -> 12 | Y24: ACTIVE | AA24: CV. AL-One Gunawan Jaya Sentosa-PF | AB24: ADAM PUTRA LOGISTICS
A25: CK0314 | B25: CV. AWAL LESTARI REZEKI | C25: ACC_TYPE_CO | D25: 539833020455000 | E25: BLOK CILIWUNG, KEL. KEDUNGBUNDER, KEC. GEMPOL, KAB. CIREBON, JAWA BARAT, 45161 | L25: 0 | N25: awallestarirezeki2022@gmail.com | O25: 2023-05-26 07:32:26 | P25: LI413 | T25: =_xlfn.IFNA(VLOOKUP(B25,Sheet2!$A$2:$M$58,4,0),"-") -> 45079 | U25: =_xlfn.IFNA(VLOOKUP(B25,'TV Trx'!$B$4:$C$57,2,0),"-") -> - | V25: =IF(C25="ACC_TYPE_CO",T25,U25) -> 45079 | W25: =_xlfn.IFNA(VLOOKUP(B25,'CO Trx'!$A$4:$B$37,2,0),"-") -> 12 | X25: =_xlfn.IFNA(VLOOKUP(B25,'CO Trx'!$A$49:$B$104,2,0),"-") -> 55 | Y25: ACTIVE | AA25: CV. Awal Lestari Rezeki-PF | AB25: RALIANS MULTI SOLUSINDO
A26: CK0282 | B26: CV. BINTANG TRIJAYA SUKSESINDO | C26: ACC_TYPE_TO | D26: 604619452423000 | E26: JL. BUKIT RAYA CIUMBULEUIT CIUMBULEUIT CIDADAP KOTA BANDUNG JAWA BARAT | L26: 0 | N26: bintangtridjaya@gmail.com | O26: 2023-04-05 02:50:07 | P26: LIB017 | R26: MANDIRI : 1300022458155 | T26: =_xlfn.IFNA(VLOOKUP(B26,Sheet2!$A$2:$M$58,4,0),"-") -> - | U26: =_xlfn.IFNA(VLOOKUP(B26,'TV Trx'!$B$4:$C$57,2,0),"-") -> 45076 | V26: =IF(C26="ACC_TYPE_CO",T26,U26) -> 45076 | W26: =_xlfn.IFNA(VLOOKUP(B26,'CO Trx'!$A$4:$B$37,2,0),"-") -> - | X26: =_xlfn.IFNA(VLOOKUP(B26,'CO Trx'!$A$49:$B$104,2,0),"-") -> - | Y26: ACTIVE | AA26: CV. BINTANG TRIJAYA SUKSESINDO-PF | AB26: BINTANG TRIJAYA SUKSESINDO
A27: CK0310 | B27: CV. DATUAK LANSANO MAJU BERSAMA NAYAKA | C27: ACC_TYPE_CO | D27: 614528925005000 | E27: JL. DARUL KHOIROT NO. 37, DESA/KELURAHAN KEBON PALA, KEC. MAKASAR, KOTA ADM. JAKARTA TIMUR, PROVINSI DKI JAKARTA, KODE POS: 13650 | L27: 0 | N27: cv.datuaklansanotrans@gmail.com | O27: 2023-05-22 02:49:26 | P27: LI408 | T27: =_xlfn.IFNA(VLOOKUP(B27,Sheet2!$A$2:$M$58,4,0),"-") -> 45072 | U27: =_xlfn.IFNA(VLOOKUP(B27,'TV Trx'!$B$4:$C$57,2,0),"-") -> - | V27: =IF(C27="ACC_TYPE_CO",T27,U27) -> 45072 | W27: =_xlfn.IFNA(VLOOKUP(B27,'CO Trx'!$A$4:$B$37,2,0),"-") -> 2 | X27: =_xlfn.IFNA(VLOOKUP(B27,'CO Trx'!$A$49:$B$104,2,0),"-") -> 1 | Y27: ACTIVE | AA27: CV. Datuak Lansano Maju Bersama Nayaka-PF | AB27: NAYAKA LANSANO
A28: CK0146 | B28: CV. FAEYZA PUTRA MANDIRI | C28: ACC_TYPE_TO | D28: 032471914008000 | E28: JL. INSPEKSI SALURAN KALIMALANG NO 35 RT. 001 RW. 012, PONDOK KELAPA, DUREN SAWIT, JAKARTA TIMUR | N28: cvfaeyzaputramandiri@gmail.com | O28: 2022-04-04 03:55:16 | P28: LI317 | R28: BRI : 115301000068307 | T28: =_xlfn.IFNA(VLOOKUP(B28,Sheet2!$A$2:$M$58,4,0),"-") -> - | U28: =_xlfn.IFNA(VLOOKUP(B28,'TV Trx'!$B$4:$C$57,2,0),"-") -> 45058 | V28: =IF(C28="ACC_TYPE_CO",T28,U28) -> 45058 | W28: =_xlfn.IFNA(VLOOKUP(B28,'CO Trx'!$A$4:$B$37,2,0),"-") -> - | X28: =_xlfn.IFNA(VLOOKUP(B28,'CO Trx'!$A$49:$B$104,2,0),"-") -> - | Y28: ACTIVE | AA28: CV FAEYZA PUTRA MANDIRI-PF | AB28: FAEYZA PUTRA
A29: CK0333 | B29: CV. HAMETRA JAYA TRANS | C29: ACC_TYPE_TO | D29: 400555579532000 | E29: GADING PERMAI RAYA AB 4, DESA/KELURAHAN GROGOL, KEC. GROGOL, KAB. SUKOHARJO, PROVINSI JAWA TENGAH, KODE POS: 57552 | L29: 0 | N29: cvrizamandiri@yahoo.co.id | O29: 2023-06-06 07:40:31 | P29: LIH001 | Q29: 7851115017 | R29: BCA | T29: =_xlfn.IFNA(VLOOKUP(B29,Sheet2!$A$2:$M$58,4,0),"-") -> - | U29: =_xlfn.IFNA(VLOOKUP(B29,'TV Trx'!$B$4:$C$57,2,0),"-") -> - | V29: =IF(C29="ACC_TYPE_CO",T29,U29) -> - | W29: =_xlfn.IFNA(VLOOKUP(B29,'CO Trx'!$A$4:$B$37,2,0),"-") -> - | X29: =_xlfn.IFNA(VLOOKUP(B29,'CO Trx'!$A$49:$B$104,2,0),"-") -> - | Y29: NOT FOUND | AA29: CV. HAMETRA JAYA TRANS-PF | AB29: CV. HAMETRA JAYA TRANS
A30: CK0312 | B30: CV. HARBA LOGISTICS | C30: ACC_TYPE_CO | D30: 808863609525000 | E30: DENDAN RT. 030 RW. 010, TASKOMBANG, MANISRENGGO, KLATEN | L30: 0 | N30: harbalogisticsjogja@gmail.com | O30: 2023-05-25 07:01:12 | P30: LI410 | T30: =_xlfn.IFNA(VLOOKUP(B30,Sheet2!$A$2:$M$58,4,0),"-") -> 45076 | U30: =_xlfn.IFNA(VLOOKUP(B30,'TV Trx'!$B$4:$C$57,2,0),"-") -> - | V30: =IF(C30="ACC_TYPE_CO",T30,U30) -> 45076 | W30: =_xlfn.IFNA(VLOOKUP(B30,'CO Trx'!$A$4:$B$37,2,0),"-") -> - | X30: =_xlfn.IFNA(VLOOKUP(B30,'CO Trx'!$A$49:$B$104,2,0),"-") -> 13 | Y30: ACTIVE | AA30: CV. Harba Logistics-PF | AB30: ALI TRANS
A31: CK0322 | B31: CV. KHAROMAH BERKAH TRANS | C31: ACC_TYPE_CO | D31: 428988133427000 | E31: JALAN BINTARA 9A NOMOR 89., KEL. BINTARA, KEC. BEKASI BARAT, KOTAVBEKASI, PROV. JAWA BARAT | L31: 0 | N31: kharomahberkah.trans@gmail.com | O31: 2023-05-26 09:49:10 | P31: LI416 | T31: =_xlfn.IFNA(VLOOKUP(B31,Sheet2!$A$2:$M$58,4,0),"-") -> 45086 | U31: =_xlfn.IFNA(VLOOKUP(B31,'TV Trx'!$B$4:$C$57,2,0),"-") -> - | V31: =IF(C31="ACC_TYPE_CO",T31,U31) -> 45086 | W31: =_xlfn.IFNA(VLOOKUP(B31,'CO Trx'!$A$4:$B$37,2,0),"-") -> - | X31: =_xlfn.IFNA(VLOOKUP(B31,'CO Trx'!$A$49:$B$104,2,0),"-") -> 9 | Y31: ACTIVE | AA31: CV. KHAROMAH BERKAH TRANS-PF | AB31: MAJU ABADI
A32: CK0251 | B32: CV. MAHKOTA EMAS | C32: ACC_TYPE_TO | D32: 812391142503000 | E32: SIDOREJO, RT/001 RW/003, TAMBANGAN MIJEN KOTA SEMARANG, JAWA TENGAH | L32: 0 | N32: mahkotaemas12@gmail.com | O32: 2023-02-20 09:39:01 | P32: LIM001 | R32: MANDIRI : 1360017220770 | T32: =_xlfn.IFNA(VLOOKUP(B32,Sheet2!$A$2:$M$58,4,0),"-") -> - | U32: =_xlfn.IFNA(VLOOKUP(B32,'TV Trx'!$B$4:$C$57,2,0),"-") -> 45008 | V32: =IF(C32="ACC_TYPE_CO",T32,U32) -> 45008 | W32: =_xlfn.IFNA(VLOOKUP(B32,'CO Trx'!$A$4:$B$37,2,0),"-") -> - | X32: =_xlfn.IFNA(VLOOKUP(B32,'CO Trx'!$A$49:$B$104,2,0),"-") -> - | Y32: IDLE | AA32: CV. MAHKOTA EMAS-PF | AB32: MAHKOTA EMAS
A33: CK0247 | B33: CV. MEGA JAYA EXPRES | C33: ACC_TYPE_CO | D33: 820805398513000 | E33: LIMBANGAN RT002 RW003, LIMBANGAN, LIMBANGAN, KAB. KENDAL, JAWA TENGAH | L33: 0 | N33: megajayaexpres@gmail.com | O33: 2023-02-02 14:04:44 | P33: LI372 | T33: =_xlfn.IFNA(VLOOKUP(B33,Sheet2!$A$2:$M$58,4,0),"-") -> 45080 | U33: =_xlfn.IFNA(VLOOKUP(B33,'TV Trx'!$B$4:$C$57,2,0),"-") -> - | V33: =IF(C33="ACC_TYPE_CO",T33,U33) -> 45080 | W33: =_xlfn.IFNA(VLOOKUP(B33,'CO Trx'!$A$4:$B$37,2,0),"-") -> - | X33: =_xlfn.IFNA(VLOOKUP(B33,'CO Trx'!$A$49:$B$104,2,0),"-") -> 150 | Y33: ACTIVE | AA33: CV. MEGA JAYA EXPRES-PF | AB33: ARIYANTO TUNAS LANGGENG
A34: CK0240 | B34: CV. MM LINE | C34: ACC_TYPE_CO | D34: 86912152551300 | E34: DK. KERTOSARI RT/05 RW05, KERTOSARI SINGOROJO, KAB. KENDAL, KEL. KERTOSARI, KEC. SINGOROJO, PROVINSI JAWA TENGAH | L34: 0 | N34: cvmmline33@yahoo.com | O34: 2023-01-26 07:50:28 | P34: 0 | Q34: 0 | R34: 0 | T34: =_xlfn.IFNA(VLOOKUP(B34,Sheet2!$A$2:$M$58,4,0),"-") -> - | U34: =_xlfn.IFNA(VLOOKUP(B34,'TV Trx'!$B$4:$C$57,2,0),"-") -> - | V34: =IF(C34="ACC_TYPE_CO",T34,U34) -> - | W34: =_xlfn.IFNA(VLOOKUP(B34,'CO Trx'!$A$4:$B$37,2,0),"-") -> - | X34: =_xlfn.IFNA(VLOOKUP(B34,'CO Trx'!$A$49:$B$104,2,0),"-") -> - | Y34: NOT FOUND
A35: CK0246 | B35: CV. MULIA MARETNO ABADI | C35: ACC_TYPE_CO | D35: 316646967616000 | E35: JL. DONOREJO SELATAN NO4-A, RT001 RW012, KAPASAN, SIMOKERTO, SURABAYA, JAWA TIMUR | L35: 0 | N35: ops.mmlogisticcargo@gmail.com | O35: 2023-02-01 11:17:36 | P35: LI373 | T35: =_xlfn.IFNA(VLOOKUP(B35,Sheet2!$A$2:$M$58,4,0),"-") -> 45047 | U35: =_xlfn.IFNA(VLOOKUP(B35,'TV Trx'!$B$4:$C$57,2,0),"-") -> - | V35: =IF(C35="ACC_TYPE_CO",T35,U35) -> 45047 | W35: =_xlfn.IFNA(VLOOKUP(B35,'CO Trx'!$A$4:$B$37,2,0),"-") -> 1 | X35: =_xlfn.IFNA(VLOOKUP(B35,'CO Trx'!$A$49:$B$104,2,0),"-") -> 7 | Y35: ACTIVE | AA35: CV MULIA MARETNO ABADI-PF | AB35: TRI ARTHA LOGISTIK
A36: CK0286 | B36: CV. MULIA MARETNO ABADI - TRUCKING VENDOR | C36: ACC_TYPE_TO | D36: 316646967616009 | E36: JL. DONOREJO SELATAN NO4-A, RT001 RW012, KAPASAN, SIMOKERTO, SURABAYA, JAWA TIMUR | N36: rita2000@gmail.com | O36: 2023-05-08 07:04:58 | P36: LI373 | R36: BCA : 1840698366 | T36: =_xlfn.IFNA(VLOOKUP(B36,Sheet2!$A$2:$M$58,4,0),"-") -> - | U36: =_xlfn.IFNA(VLOOKUP(B36,'TV Trx'!$B$4:$C$57,2,0),"-") -> 45072 | V36: =IF(C36="ACC_TYPE_CO",T36,U36) -> 45072 | W36: =_xlfn.IFNA(VLOOKUP(B36,'CO Trx'!$A$4:$B$37,2,0),"-") -> - | X36: =_xlfn.IFNA(VLOOKUP(B36,'CO Trx'!$A$49:$B$104,2,0),"-") -> - | Y36: ACTIVE | AA36: CV MULIA MARETNO ABADI-PF | AB36: CV. MULIA MARETNO ABADI
A37: CK0221 | B37: CV. NAWASENA BERKAH MANDIRI | C37: ACC_TYPE_TO | D37: 436406961435000 | E37: JALAN PERUM MUTIARA GADING RIVERA BLOK A9 NO 17, KEL. KARANGSATRIA, KEC. TAMBUN UTARA, KAB. BEKASI, PROVINSI JAWA BARAT | L37: 0 | N37: guparman80@gmail.com | O37: 2022-12-15 09:13:48 | P37: LIN006 | R37: BCA : 5910069065 | T37: =_xlfn.IFNA(VLOOKUP(B37,Sheet2!$A$2:$M$58,4,0),"-") -> - | U37: =_xlfn.IFNA(VLOOKUP(B37,'TV Trx'!$B$4:$C$57,2,0),"-") -> 45017 | V37: =IF(C37="ACC_TYPE_CO",T37,U37) -> 45017 | W37: =_xlfn.IFNA(VLOOKUP(B37,'CO Trx'!$A$4:$B$37,2,0),"-") -> - | X37: =_xlfn.IFNA(VLOOKUP(B37,'CO Trx'!$A$49:$B$104,2,0),"-") -> - | Y37: ACTIVE | AA37: CV. NAWASENA BERKAH MANDIRI-PF | AB37: NAWASENA BERKAH MANDIRI
A38: CK0303 | B38: CV. NUSANTARA CITRA JAYA | C38: ACC_TYPE_TO | D38: 926500935619000 | E38: KALI KEPITING JAYA 8-A/01, KEL PACAR KEMBANG, KEC. TAMBAKSARI, KOTA SURABAYA, PROP. JAWA TIMUR | L38: 0 | N38: nusantaracitrajayacv@gmail.com | O38: 2023-05-17 10:25:26 | P38: LIN009 | R38: MANDIRI : 1420021661896 | T38: =_xlfn.IFNA(VLOOKUP(B38,Sheet2!$A$2:$M$58,4,0),"-") -> - | U38: =_xlfn.IFNA(VLOOKUP(B38,'TV Trx'!$B$4:$C$57,2,0),"-") -> 45087 | V38: =IF(C38="ACC_TYPE_CO",T38,U38) -> 45087 | W38: =_xlfn.IFNA(VLOOKUP(B38,'CO Trx'!$A$4:$B$37,2,0),"-") -> - | X38: =_xlfn.IFNA(VLOOKUP(B38,'CO Trx'!$A$49:$B$104,2,0),"-") -> - | Y38: ACTIVE | AA38: CV. NUSANTARA CITRA JAYA-PF | AB38: NUSANTARA CITRA JAYA
A39: CK0232 | B39: CV. PAMUNGKAS SAKTI LOGISTIK | C39: ACC_TYPE_TO | D39: 413745878505000 | E39: JL. MELATI, GEMENGGENG, KEL NGAPRAH, KEC. BANYUBIRU, KAB. SEMARANG. JAWA TENGAH | L39: 0 | N39: pamungkassaktilogistik@gmail.com | O39: 2023-01-21 07:39:42 | P39: LIP022 | R39: BCA : 3207771808 | T39: =_xlfn.IFNA(VLOOKUP(B39,Sheet2!$A$2:$M$58,4,0),"-") -> - | U39: =_xlfn.IFNA(VLOOKUP(B39,'TV Trx'!$B$4:$C$57,2,0),"-") -> 45042 | V39: =IF(C39="ACC_TYPE_CO",T39,U39) -> 45042 | W39: =_xlfn.IFNA(VLOOKUP(B39,'CO Trx'!$A$4:$B$37,2,0),"-") -> - | X39: =_xlfn.IFNA(VLOOKUP(B39,'CO Trx'!$A$49:$B$104,2,0),"-") -> - | Y39: ACTIVE | AA39: CV. PAMUNGKAS SAKTI LOGISTIK-PF | AB39: PAMUNGKAS SAKTI LOGISTIK
A40: CK0327 | B40: CV. RAFA PRATAMA MANDIRI | C40: ACC_TYPE_TO | D40: 854536075643000 | E40: BANJAR MELATI, KEL. PABEAN, KEC. SEDATI, KAB. SIDOARJO, PROP. JAWATIMUR | L40: 0 | N40: cvrafapratamasda@gmail.com | O40: 2023-05-31 05:41:24 | P40: LIR007 | R40: BCA : 2711219651 | T40: =_xlfn.IFNA(VLOOKUP(B40,Sheet2!$A$2:$M$58,4,0),"-") -> - | U40: =_xlfn.IFNA(VLOOKUP(B40,'TV Trx'!$B$4:$C$57,2,0),"-") -> 45083 | V40: =IF(C40="ACC_TYPE_CO",T40,U40) -> 45083 | W40: =_xlfn.IFNA(VLOOKUP(B40,'CO Trx'!$A$4:$B$37,2,0),"-") -> - | X40: =_xlfn.IFNA(VLOOKUP(B40,'CO Trx'!$A$49:$B$104,2,0),"-") -> - | Y40: ACTIVE | AA40: CV. RAFA PRATAMA MANDIRI-PF | AB40: RAFA PRATAMA MANDIRI
A41: CK0142 | B41: CV. SATRIA JAYA BAN | C41: ACC_TYPE_TO | D41: 704231547435000 | N41: sjbzul@gmail.com | O41: 2022-03-28 05:58:55 | P41: 0 | Q41: 0 | R41: 0 | T41: =_xlfn.IFNA(VLOOKUP(B41,Sheet2!$A$2:$M$58,4,0),"-") -> - | U41: =_xlfn.IFNA(VLOOKUP(B41,'TV Trx'!$B$4:$C$57,2,0),"-") -> - | V41: =IF(C41="ACC_TYPE_CO",T41,U41) -> - | W41: =_xlfn.IFNA(VLOOKUP(B41,'CO Trx'!$A$4:$B$37,2,0),"-") -> - | X41: =_xlfn.IFNA(VLOOKUP(B41,'CO Trx'!$A$49:$B$104,2,0),"-") -> - | Y41: NOT FOUND
A42: CK0328 | B42: CV. SKY XPRESS | C42: ACC_TYPE_TO | D42: 033318585643000 | E42: PASAR WISATA BANDARA JUANDA BLOK Q NO.06 PABEAN, SEDATI, SIDOARJO, JAWA TIMUR, 61253 | L42: 0 | N42: belumdikasih@sales.com | O42: 2023-06-05 02:32:38 | P42: LIS008 | R42: BCA : 2465576055 | T42: =_xlfn.IFNA(VLOOKUP(B42,Sheet2!$A$2:$M$58,4,0),"-") -> - | U42: =_xlfn.IFNA(VLOOKUP(B42,'TV Trx'!$B$4:$C$57,2,0),"-") -> 45086 | V42: =IF(C42="ACC_TYPE_CO",T42,U42) -> 45086 | W42: =_xlfn.IFNA(VLOOKUP(B42,'CO Trx'!$A$4:$B$37,2,0),"-") -> - | X42: =_xlfn.IFNA(VLOOKUP(B42,'CO Trx'!$A$49:$B$104,2,0),"-") -> - | Y42: ACTIVE | AA42: CV. SKY Xpress-PF | AB42: SKY XPRESS
A43: CK0143 | B43: CV. SUMBER SEJAHTERA ABADI | C43: ACC_TYPE_TO | D43: 619171747413000 | E43: JL. TELAGA ASIH BLOK - NO. 117 RT.004 RW.002 TELAGA ASIH, CIKARANG BARAT BEKASI | N43: ssa@clickargo.com | O43: 2022-03-28 12:55:12 | P43: LI318 | R43: MANDIRI : 1560007331285 | T43: =_xlfn.IFNA(VLOOKUP(B43,Sheet2!$A$2:$M$58,4,0),"-") -> - | U43: =_xlfn.IFNA(VLOOKUP(B43,'TV Trx'!$B$4:$C$57,2,0),"-") -> 45078 | V43: =IF(C43="ACC_TYPE_CO",T43,U43) -> 45078 | W43: =_xlfn.IFNA(VLOOKUP(B43,'CO Trx'!$A$4:$B$37,2,0),"-") -> - | X43: =_xlfn.IFNA(VLOOKUP(B43,'CO Trx'!$A$49:$B$104,2,0),"-") -> - | Y43: ACTIVE | AA43: CV SUMBER SEJAHTERA ABADI-PF | AB43: SUMBER SEJAHTERA
A44: CK0058 | B44: DHL GLOBAL FORWARDING INDONESIA | C44: ACC_TYPE_CO | D44: 019579218058000 | E44: SOEWARNA BUSINESS PARK BLOK A LOT 8, BANDARA SOEKARNO HATTA RT/RW -, PAJANG, BENDA, KOTA TANGERANG, BANTEN 15126 | H44: 15126 | I44: kota jakarta utara | J44: dki jakarta | L44: 02155919900 | N44: sarmauli.lumbantobing@dhl.com | O44: 2021-05-24 04:46:17 | P44: 0 | Q44: 0 | R44: 0 | T44: =_xlfn.IFNA(VLOOKUP(B44,Sheet2!$A$2:$M$58,4,0),"-") -> - | U44: =_xlfn.IFNA(VLOOKUP(B44,'TV Trx'!$B$4:$C$57,2,0),"-") -> - | V44: =IF(C44="ACC_TYPE_CO",T44,U44) -> - | W44: =_xlfn.IFNA(VLOOKUP(B44,'CO Trx'!$A$4:$B$37,2,0),"-") -> - | X44: =_xlfn.IFNA(VLOOKUP(B44,'CO Trx'!$A$49:$B$104,2,0),"-") -> - | Y44: NOT FOUND
A45: CK0148 | B45: DHL GLOBAL FORWARDING INDONESIA (AIR FREIGHT) | C45: ACC_TYPE_CO | D45: 019579218058000 | E45: SOEWARNA BUSINESS PARK BLOK A LOT 8, BANDARA SOEKARNO HATTA RT/RW -, PAJANG, BENDA, KOTA TANGERANG, BANTEN 15126 | L45: 08561566563 | N45: anwar.musyaddad@dhl.com | O45: 2022-04-05 02:16:44 | P45: 0 | Q45: 0 | R45: 0 | T45: =_xlfn.IFNA(VLOOKUP(B45,Sheet2!$A$2:$M$58,4,0),"-") -> - | U45: =_xlfn.IFNA(VLOOKUP(B45,'TV Trx'!$B$4:$C$57,2,0),"-") -> - | V45: =IF(C45="ACC_TYPE_CO",T45,U45) -> - | W45: =_xlfn.IFNA(VLOOKUP(B45,'CO Trx'!$A$4:$B$37,2,0),"-") -> - | X45: =_xlfn.IFNA(VLOOKUP(B45,'CO Trx'!$A$49:$B$104,2,0),"-") -> - | Y45: NOT FOUND
A46: CK0165 | B46: DHL GLOBAL FORWARDING INDONESIA (TDS SEA FREIGHT) | C46: ACC_TYPE_CO | D46: 019579218058001 | E46: SOEWARNA BUSINESS PARK BLOK A LOT 8, BANDARA SOEKARNO HATTA RT/RW -, PAJANG, BENDA, KOTA TANGERANG, BANTEN 15126 | L46: 0811845192 | N46: dgf_seafreight@gmail.com | O46: 2022-05-30 05:31:44 | P46: 0 | Q46: 0 | R46: 0 | T46: =_xlfn.IFNA(VLOOKUP(B46,Sheet2!$A$2:$M$58,4,0),"-") -> - | U46: =_xlfn.IFNA(VLOOKUP(B46,'TV Trx'!$B$4:$C$57,2,0),"-") -> - | V46: =IF(C46="ACC_TYPE_CO",T46,U46) -> - | W46: =_xlfn.IFNA(VLOOKUP(B46,'CO Trx'!$A$4:$B$37,2,0),"-") -> - | X46: =_xlfn.IFNA(VLOOKUP(B46,'CO Trx'!$A$49:$B$104,2,0),"-") -> - | Y46: NOT FOUND
A47: CK0069 | B47: DHL SUPPLY CHAIN | C47: ACC_TYPE_TO | D47: 111222333444 | E47: 111222333444 | H47: 111222333444 | I47: kabupaten kulon progo | J47: di yogyakarta | L47: 111222333444 | N47: dhl.wingbox@clickargo.com | O47: 2021-07-05 14:41:30 | P47: LI251 | Q47: 0 | R47: 0 | T47: =_xlfn.IFNA(VLOOKUP(B47,Sheet2!$A$2:$M$58,4,0),"-") -> - | U47: =_xlfn.IFNA(VLOOKUP(B47,'TV Trx'!$B$4:$C$57,2,0),"-") -> - | V47: =IF(C47="ACC_TYPE_CO",T47,U47) -> - | W47: =_xlfn.IFNA(VLOOKUP(B47,'CO Trx'!$A$4:$B$37,2,0),"-") -> - | X47: =_xlfn.IFNA(VLOOKUP(B47,'CO Trx'!$A$49:$B$104,2,0),"-") -> - | Y47: NOT FOUND | AA47: PT. DHL SUPPLY CHAIN INDONESIA-LOG
A48: CK0070 | B48: DHL SUPPLY CHAIN (CARGO OWNER) | C48: ACC_TYPE_CO | D48: 123456123456 | E48: DHL WINGBOX CARGO OWNER | H48: 123456123456 | I48: kabupaten bangli | J48: bali | L48: 123456123456 | N48: dhl.wingbox.cargo@clickargo.com | O48: 2021-07-05 15:17:10 | P48: 0 | Q48: 0 | R48: 0 | T48: =_xlfn.IFNA(VLOOKUP(B48,Sheet2!$A$2:$M$58,4,0),"-") -> - | U48: =_xlfn.IFNA(VLOOKUP(B48,'TV Trx'!$B$4:$C$57,2,0),"-") -> - | V48: =IF(C48="ACC_TYPE_CO",T48,U48) -> - | W48: =_xlfn.IFNA(VLOOKUP(B48,'CO Trx'!$A$4:$B$37,2,0),"-") -> - | X48: =_xlfn.IFNA(VLOOKUP(B48,'CO Trx'!$A$49:$B$104,2,0),"-") -> - | Y48: NOT FOUND
A49: CK0074 | B49: DSV SINGAPORE | C49: ACC_TYPE_CO | D49: 111 | E49: DSV | L49: 1111 | N49: delacruz.eileen@sg.dsv.com | O49: 2021-07-22 05:48:38 | P49: 0 | Q49: 0 | R49: 0 | T49: =_xlfn.IFNA(VLOOKUP(B49,Sheet2!$A$2:$M$58,4,0),"-") -> - | U49: =_xlfn.IFNA(VLOOKUP(B49,'TV Trx'!$B$4:$C$57,2,0),"-") -> - | V49: =IF(C49="ACC_TYPE_CO",T49,U49) -> - | W49: =_xlfn.IFNA(VLOOKUP(B49,'CO Trx'!$A$4:$B$37,2,0),"-") -> - | X49: =_xlfn.IFNA(VLOOKUP(B49,'CO Trx'!$A$49:$B$104,2,0),"-") -> - | Y49: NOT FOUND
A50: CK0190 | B50: DSVS-KFC DELIVERY | C50: ACC_TYPE_TO | D50: 76654 | E50: 6, CHANGI NORTH WAY | N50: siew.hoon.chua@dsv.com | O50: 2022-09-13 02:28:46 | P50: 0 | Q50: 0 | R50: 0 | T50: =_xlfn.IFNA(VLOOKUP(B50,Sheet2!$A$2:$M$58,4,0),"-") -> - | U50: =_xlfn.IFNA(VLOOKUP(B50,'TV Trx'!$B$4:$C$57,2,0),"-") -> - | V50: =IF(C50="ACC_TYPE_CO",T50,U50) -> - | W50: =_xlfn.IFNA(VLOOKUP(B50,'CO Trx'!$A$4:$B$37,2,0),"-") -> - | X50: =_xlfn.IFNA(VLOOKUP(B50,'CO Trx'!$A$49:$B$104,2,0),"-") -> - | Y50: NOT FOUND
A51: CK0019 | B51: GATOTKACA TRANS SYSTEMINDO (TRUCKING) | C51: ACC_TYPE_TO | D51: 020404224435000 | E51: JL. ENGGANO NO.40-C, RT8, RT.8/RW.16, TANJUNG PRIOK, NORTH JAKARTA CITY, JAKARTA 14310 | H51: 14310 | I51: kota jakarta utara | J51: dki jakarta | O51: 2020-09-14 10:34:13 | P51: 0 | Q51: 0 | R51: 0 | T51: =_xlfn.IFNA(VLOOKUP(B51,Sheet2!$A$2:$M$58,4,0),"-") -> - | U51: =_xlfn.IFNA(VLOOKUP(B51,'TV Trx'!$B$4:$C$57,2,0),"-") -> - | V51: =IF(C51="ACC_TYPE_CO",T51,U51) -> - | W51: =_xlfn.IFNA(VLOOKUP(B51,'CO Trx'!$A$4:$B$37,2,0),"-") -> - | X51: =_xlfn.IFNA(VLOOKUP(B51,'CO Trx'!$A$49:$B$104,2,0),"-") -> - | Y51: NOT FOUND
A52: CK0017 | B52: GLOBAL PUTRA INTERNATIONAL | C52: ACC_TYPE_TO | D52: 020974002074000 | E52: JL. IR. H. JUANDA III NO.26 A-B, KEBON KELAPA, GAMBIR, JAKARTA PUSAT | O52: 2020-09-09 03:37:48 | P52: 0 | Q52: 0 | R52: 0 | T52: =_xlfn.IFNA(VLOOKUP(B52,Sheet2!$A$2:$M$58,4,0),"-") -> - | U52: =_xlfn.IFNA(VLOOKUP(B52,'TV Trx'!$B$4:$C$57,2,0),"-") -> - | V52: =IF(C52="ACC_TYPE_CO",T52,U52) -> - | W52: =_xlfn.IFNA(VLOOKUP(B52,'CO Trx'!$A$4:$B$37,2,0),"-") -> - | X52: =_xlfn.IFNA(VLOOKUP(B52,'CO Trx'!$A$49:$B$104,2,0),"-") -> - | Y52: NOT FOUND
A53: CK0073 | B53: GLOBAL TRANSPORTASI NUSANTARA | C53: ACC_TYPE_CO | D53: 018497396074000 | E53: JL IR H JUANDA III, KEBON KELAPA, GAMBIR, KOTA ADM. JAKARTA PUSAT, DKI JAKARTA, 10120 | L53: 081280846728 | N53: legal@gpi-g.com | O53: 2021-07-19 07:47:39 | P53: 0 | Q53: 0 | R53: 0 | T53: =_xlfn.IFNA(VLOOKUP(B53,Sheet2!$A$2:$M$58,4,0),"-") -> - | U53: =_xlfn.IFNA(VLOOKUP(B53,'TV Trx'!$B$4:$C$57,2,0),"-") -> - | V53: =IF(C53="ACC_TYPE_CO",T53,U53) -> - | W53: =_xlfn.IFNA(VLOOKUP(B53,'CO Trx'!$A$4:$B$37,2,0),"-") -> - | X53: =_xlfn.IFNA(VLOOKUP(B53,'CO Trx'!$A$49:$B$104,2,0),"-") -> - | Y53: NOT FOUND
A54: CK0079 | B54: GPI TRUCKING | C54: ACC_TYPE_TO | D54: 123456789012345 | E54: JL. IR. H. JUANDA III NO.26 A-B, KEBON KELAPA, GAMBIR, JAKARTA PUSAT | N54: vin.rony@gpilog.com | O54: 2021-08-02 07:19:25 | P54: 0 | Q54: 0 | R54: 0 | T54: =_xlfn.IFNA(VLOOKUP(B54,Sheet2!$A$2:$M$58,4,0),"-") -> - | U54: =_xlfn.IFNA(VLOOKUP(B54,'TV Trx'!$B$4:$C$57,2,0),"-") -> - | V54: =IF(C54="ACC_TYPE_CO",T54,U54) -> - | W54: =_xlfn.IFNA(VLOOKUP(B54,'CO Trx'!$A$4:$B$37,2,0),"-") -> - | X54: =_xlfn.IFNA(VLOOKUP(B54,'CO Trx'!$A$49:$B$104,2,0),"-") -> - | Y54: NOT FOUND
A55: CK0018 | B55: GREEN HARMONY INDONESIA | C55: ACC_TYPE_CO | D55: 843436072704000 | E55: KOMP. PONDOK INDAH LESTARI BLOK D5 NO.12B RT/RW 004/011, SUNGAIRAYA, SUNGAI RAYA, KUBU RAYA, KALIMANTAN BARAT 78391 | H55: 78391 | I55: KUBU RAYA | J55: KALIMANTAN BARAT | O55: 2020-09-12 05:13:12 | P55: 0 | Q55: 0 | R55: 0 | T55: =_xlfn.IFNA(VLOOKUP(B55,Sheet2!$A$2:$M$58,4,0),"-") -> - | U55: =_xlfn.IFNA(VLOOKUP(B55,'TV Trx'!$B$4:$C$57,2,0),"-") -> - | V55: =IF(C55="ACC_TYPE_CO",T55,U55) -> - | W55: =_xlfn.IFNA(VLOOKUP(B55,'CO Trx'!$A$4:$B$37,2,0),"-") -> - | X55: =_xlfn.IFNA(VLOOKUP(B55,'CO Trx'!$A$49:$B$104,2,0),"-") -> - | Y55: NOT FOUND
A56: CK0122 | B56: HERU WULANTORO | C56: ACC_TYPE_CO | D56: 591760905407000 | E56: DUSUN SUKAMAJU | L56: 628996222907 | N56: b6092ktq@yahoo.co.id | O56: 2022-01-26 02:35:48 | P56: 0 | Q56: 0 | R56: 0 | T56: =_xlfn.IFNA(VLOOKUP(B56,Sheet2!$A$2:$M$58,4,0),"-") -> - | U56: =_xlfn.IFNA(VLOOKUP(B56,'TV Trx'!$B$4:$C$57,2,0),"-") -> - | V56: =IF(C56="ACC_TYPE_CO",T56,U56) -> - | W56: =_xlfn.IFNA(VLOOKUP(B56,'CO Trx'!$A$4:$B$37,2,0),"-") -> - | X56: =_xlfn.IFNA(VLOOKUP(B56,'CO Trx'!$A$49:$B$104,2,0),"-") -> - | Y56: NOT FOUND
A57: CK0167 | B57: INDON TEST TV | C57: ACC_TYPE_TO | D57: 3490 | E57: OFFICE | L57: 67796218 | N57: indon_tv1@yopmail.com | O57: 2022-06-01 11:04:13 | P57: 0 | Q57: 0 | R57: 0 | T57: =_xlfn.IFNA(VLOOKUP(B57,Sheet2!$A$2:$M$58,4,0),"-") -> - | U57: =_xlfn.IFNA(VLOOKUP(B57,'TV Trx'!$B$4:$C$57,2,0),"-") -> - | V57: =IF(C57="ACC_TYPE_CO",T57,U57) -> - | W57: =_xlfn.IFNA(VLOOKUP(B57,'CO Trx'!$A$4:$B$37,2,0),"-") -> - | X57: =_xlfn.IFNA(VLOOKUP(B57,'CO Trx'!$A$49:$B$104,2,0),"-") -> - | Y57: NOT FOUND
A58: CK0164 | B58: INESIA KARGOTAMA INDONESIA | C58: ACC_TYPE_CO | D58: 032829947001000 | E58: ASKRIDA TOWER LT. 4 R. 401 A JL. PRAMUKA RAYA KAV. 151 RT 009 RW 005 UTAN KAYU UTARA MATRAMAN JAKARTA TIMUR, DKI JAKARTA 13120 | L58: 08170817411 | N58: cs@inesialogistics.com | O58: 2022-05-25 10:43:45 | P58: 0 | Q58: 0 | R58: 0 | T58: =_xlfn.IFNA(VLOOKUP(B58,Sheet2!$A$2:$M$58,4,0),"-") -> - | U58: =_xlfn.IFNA(VLOOKUP(B58,'TV Trx'!$B$4:$C$57,2,0),"-") -> - | V58: =IF(C58="ACC_TYPE_CO",T58,U58) -> - | W58: =_xlfn.IFNA(VLOOKUP(B58,'CO Trx'!$A$4:$B$37,2,0),"-") -> - | X58: =_xlfn.IFNA(VLOOKUP(B58,'CO Trx'!$A$49:$B$104,2,0),"-") -> - | Y58: NOT FOUND
A59: CK0181 | B59: INTERNAL YUSEN TRUCKING | C59: ACC_TYPE_TO | D59: 111111111111111 | E59: JL. YOS SUDARSO NO.33, RT.10/RW.11, SUNTER JAYA, KEC. TJ. PRIOK, KOTA JKT UTARA, DAERAH KHUSUS IBUKOTA JAKARTA 14360 | L59: 02122651000 | N59: yusen_trucking@gmail.com | O59: 2022-08-08 03:05:59 | P59: 0 | Q59: 0 | R59: 0 | T59: =_xlfn.IFNA(VLOOKUP(B59,Sheet2!$A$2:$M$58,4,0),"-") -> - | U59: =_xlfn.IFNA(VLOOKUP(B59,'TV Trx'!$B$4:$C$57,2,0),"-") -> - | V59: =IF(C59="ACC_TYPE_CO",T59,U59) -> - | W59: =_xlfn.IFNA(VLOOKUP(B59,'CO Trx'!$A$4:$B$37,2,0),"-") -> - | X59: =_xlfn.IFNA(VLOOKUP(B59,'CO Trx'!$A$49:$B$104,2,0),"-") -> - | Y59: NOT FOUND
A60: CK0130 | B60: INTEROFFICE DUMMY SIN - FDA | C60: ACC_TYPE_TO | D60: 99887 | E60: SINGAPORE | L60: 12312312 | N60: roger.foo@dsv.com | O60: 2022-03-07 13:05:11 | P60: 0 | Q60: 0 | R60: 0 | T60: =_xlfn.IFNA(VLOOKUP(B60,Sheet2!$A$2:$M$58,4,0),"-") -> - | U60: =_xlfn.IFNA(VLOOKUP(B60,'TV Trx'!$B$4:$C$57,2,0),"-") -> - | V60: =IF(C60="ACC_TYPE_CO",T60,U60) -> - | W60: =_xlfn.IFNA(VLOOKUP(B60,'CO Trx'!$A$4:$B$37,2,0),"-") -> - | X60: =_xlfn.IFNA(VLOOKUP(B60,'CO Trx'!$A$49:$B$104,2,0),"-") -> - | Y60: NOT FOUND
A61: CK0049 | B61: INVESTAMA GEMILANG INDONESIA | C61: ACC_TYPE_FF | D61: 033349788215000 | E61: JALAN DUYUNG, GRAHA TIBERIAS RT/RW 003/006, SUNGAI JODOH, BATU AMPAR, KOTA BATAM, KEPULAUAN RIAU 29453 | H61: 29453 | I61: kota batam | J61: kepulauan riau | L61: 0811696902 | N61: ferdyap@hotmail.com | O61: 2021-04-14 07:07:42 | P61: 0 | Q61: 0 | R61: 0 | T61: =_xlfn.IFNA(VLOOKUP(B61,Sheet2!$A$2:$M$58,4,0),"-") -> - | U61: =_xlfn.IFNA(VLOOKUP(B61,'TV Trx'!$B$4:$C$57,2,0),"-") -> - | V61: =IF(C61="ACC_TYPE_CO",T61,U61) -> - | W61: =_xlfn.IFNA(VLOOKUP(B61,'CO Trx'!$A$4:$B$37,2,0),"-") -> - | X61: =_xlfn.IFNA(VLOOKUP(B61,'CO Trx'!$A$49:$B$104,2,0),"-") -> - | Y61: NOT FOUND
A62: CK0301 | B62: KLG EUROPE | D62: 80179962401 | E62: ABEL TASMANSTRAAT 33 3165AM ROTTERDAM | L62: 0031108702437 | N62: l.vanvugt@rotterdam.klgeurope.com | O62: 2023-05-17 06:46:36 | P62: 0 | Q62: 0 | R62: 0 | T62: =_xlfn.IFNA(VLOOKUP(B62,Sheet2!$A$2:$M$58,4,0),"-") -> - | U62: =_xlfn.IFNA(VLOOKUP(B62,'TV Trx'!$B$4:$C$57,2,0),"-") -> - | V62: =IF(C62="ACC_TYPE_CO",T62,U62) -> - | W62: =_xlfn.IFNA(VLOOKUP(B62,'CO Trx'!$A$4:$B$37,2,0),"-") -> - | X62: =_xlfn.IFNA(VLOOKUP(B62,'CO Trx'!$A$49:$B$104,2,0),"-") -> - | Y62: NOT FOUND
A63: CK0035 | B63: KOPERASI | C63: ACC_TYPE_TO | D63: 181818181818 | E63: PULOMERAK | H63: 13555 | I63: kota cilegon | J63: banten | O63: 2020-12-16 06:47:17 | P63: 0 | Q63: 0 | R63: 0 | T63: =_xlfn.IFNA(VLOOKUP(B63,Sheet2!$A$2:$M$58,4,0),"-") -> - | U63: =_xlfn.IFNA(VLOOKUP(B63,'TV Trx'!$B$4:$C$57,2,0),"-") -> - | V63: =IF(C63="ACC_TYPE_CO",T63,U63) -> - | W63: =_xlfn.IFNA(VLOOKUP(B63,'CO Trx'!$A$4:$B$37,2,0),"-") -> - | X63: =_xlfn.IFNA(VLOOKUP(B63,'CO Trx'!$A$49:$B$104,2,0),"-") -> - | Y63: NOT FOUND
A64: CK0075 | B64: LIAN LEE WOODEN CASE MAKER CO PTE LTD | C64: ACC_TYPE_TO | D64: 1121 | E64: LIAN LEE WOODEN | L64: 1 | N64: josephine@lianleewooden.com.sg | O64: 2021-07-22 06:06:42 | P64: 0 | Q64: 0 | R64: 0 | T64: =_xlfn.IFNA(VLOOKUP(B64,Sheet2!$A$2:$M$58,4,0),"-") -> - | U64: =_xlfn.IFNA(VLOOKUP(B64,'TV Trx'!$B$4:$C$57,2,0),"-") -> - | V64: =IF(C64="ACC_TYPE_CO",T64,U64) -> - | W64: =_xlfn.IFNA(VLOOKUP(B64,'CO Trx'!$A$4:$B$37,2,0),"-") -> - | X64: =_xlfn.IFNA(VLOOKUP(B64,'CO Trx'!$A$49:$B$104,2,0),"-") -> - | Y64: NOT FOUND
A65: CK0068 | B65: LINFOX | C65: ACC_TYPE_CO | D65: 0000000 | E65: LINFOX | H65: 0000000 | I65: kota jakarta barat | J65: dki jakarta | L65: 0000000 | N65: linfox.ops@clickargo.com | O65: 2021-07-05 01:31:05 | P65: 0 | Q65: 0 | R65: 0 | T65: =_xlfn.IFNA(VLOOKUP(B65,Sheet2!$A$2:$M$58,4,0),"-") -> - | U65: =_xlfn.IFNA(VLOOKUP(B65,'TV Trx'!$B$4:$C$57,2,0),"-") -> - | V65: =IF(C65="ACC_TYPE_CO",T65,U65) -> - | W65: =_xlfn.IFNA(VLOOKUP(B65,'CO Trx'!$A$4:$B$37,2,0),"-") -> - | X65: =_xlfn.IFNA(VLOOKUP(B65,'CO Trx'!$A$49:$B$104,2,0),"-") -> - | Y65: NOT FOUND
A66: CK0067 | B66: LINFOX TRUCKING | C66: ACC_TYPE_TO | D66: 000000 | E66: LINFOX TRUCKING | H66: 000000 | I66: kota jakarta barat | J66: dki jakarta | L66: 0000000 | N66: linfox.trucks@clickargo.com | O66: 2021-07-05 01:29:28 | P66: 0 | Q66: 0 | R66: 0 | T66: =_xlfn.IFNA(VLOOKUP(B66,Sheet2!$A$2:$M$58,4,0),"-") -> - | U66: =_xlfn.IFNA(VLOOKUP(B66,'TV Trx'!$B$4:$C$57,2,0),"-") -> - | V66: =IF(C66="ACC_TYPE_CO",T66,U66) -> - | W66: =_xlfn.IFNA(VLOOKUP(B66,'CO Trx'!$A$4:$B$37,2,0),"-") -> - | X66: =_xlfn.IFNA(VLOOKUP(B66,'CO Trx'!$A$49:$B$104,2,0),"-") -> - | Y66: NOT FOUND
A67: CK0023 | B67: LINK PASIPIK INDONUSA | C67: ACC_TYPE_FF | D67: 025047176043000 | E67: RUKAN ELANG NEW GADING BATAVIA BLOK L/C 11/7 KELAPA GADING | H67: 14240 | I67: Jakarta Utara | J67: DKI Jakarta | O67: 2020-09-24 08:38:13 | P67: 0 | Q67: 0 | R67: 0 | T67: =_xlfn.IFNA(VLOOKUP(B67,Sheet2!$A$2:$M$58,4,0),"-") -> - | U67: =_xlfn.IFNA(VLOOKUP(B67,'TV Trx'!$B$4:$C$57,2,0),"-") -> - | V67: =IF(C67="ACC_TYPE_CO",T67,U67) -> - | W67: =_xlfn.IFNA(VLOOKUP(B67,'CO Trx'!$A$4:$B$37,2,0),"-") -> - | X67: =_xlfn.IFNA(VLOOKUP(B67,'CO Trx'!$A$49:$B$104,2,0),"-") -> - | Y67: NOT FOUND
A68: CK0087 | B68: MAHAKARYA SAMUDRA PERKASA | C68: ACC_TYPE_FF | D68: 956192413044000 | E68: TOWER FONTANA, CLUSTER BOUGENVILLE 50TH FLOOR, SUITE 50B2 JL. TREMBESI BLOK B BANDAR BARU KEMAYORAN RT/RW 000/000, PADEMANGAN TIMUR, PADEMANGAN, KOTA ADM. JAKARTA UTARA, DKI JAKARTA 14410 | L68: 08111991983 | N68: rhandy@group-mahakarya.com | O68: 2021-08-22 12:39:23 | P68: 0 | Q68: 0 | R68: 0 | T68: =_xlfn.IFNA(VLOOKUP(B68,Sheet2!$A$2:$M$58,4,0),"-") -> - | U68: =_xlfn.IFNA(VLOOKUP(B68,'TV Trx'!$B$4:$C$57,2,0),"-") -> - | V68: =IF(C68="ACC_TYPE_CO",T68,U68) -> - | W68: =_xlfn.IFNA(VLOOKUP(B68,'CO Trx'!$A$4:$B$37,2,0),"-") -> - | X68: =_xlfn.IFNA(VLOOKUP(B68,'CO Trx'!$A$49:$B$104,2,0),"-") -> - | Y68: NOT FOUND
A69: CK0048 | B69: MEGADUTA ARTHA MEGAH | C69: ACC_TYPE_TO | D69: 027032333003000 | E69: PERKANTORAN PULO MAS I GD.V LT.3, KAYU PUTIH RT/RW -, KAYU PUTIH, PULOGADUNG, KOTA ADM. JAKARTA TIMUR, DKI JAKARTA 13120 | H69: 13120 | I69: kota jakarta timur | J69: dki jakarta | L69: 02129833208 | N69: ilyas@megaduta.co.id | O69: 2021-04-14 03:57:13 | P69: 0 | Q69: 0 | R69: 0 | T69: =_xlfn.IFNA(VLOOKUP(B69,Sheet2!$A$2:$M$58,4,0),"-") -> - | U69: =_xlfn.IFNA(VLOOKUP(B69,'TV Trx'!$B$4:$C$57,2,0),"-") -> - | V69: =IF(C69="ACC_TYPE_CO",T69,U69) -> - | W69: =_xlfn.IFNA(VLOOKUP(B69,'CO Trx'!$A$4:$B$37,2,0),"-") -> - | X69: =_xlfn.IFNA(VLOOKUP(B69,'CO Trx'!$A$49:$B$104,2,0),"-") -> - | Y69: NOT FOUND
A70: CK0012 | B70: MERAH TEKNIK INDONESIA | C70: ACC_TYPE_CO | D70: 022525133906000 | E70: BR.TANDEG ,DS.TIBUBENENG,KEC.KUTA UTARA,KAB.BADUNG,PROP.BALI | H70: 80361 | O70: 2020-08-17 16:03:07 | P70: 0 | Q70: 0 | R70: 0 | T70: =_xlfn.IFNA(VLOOKUP(B70,Sheet2!$A$2:$M$58,4,0),"-") -> - | U70: =_xlfn.IFNA(VLOOKUP(B70,'TV Trx'!$B$4:$C$57,2,0),"-") -> - | V70: =IF(C70="ACC_TYPE_CO",T70,U70) -> - | W70: =_xlfn.IFNA(VLOOKUP(B70,'CO Trx'!$A$4:$B$37,2,0),"-") -> - | X70: =_xlfn.IFNA(VLOOKUP(B70,'CO Trx'!$A$49:$B$104,2,0),"-") -> - | Y70: NOT FOUND
A71: CK0106 | B71: MITSUIANDCO GLOBAL LOGISTICS INDONESIA | C71: ACC_TYPE_CO | D71: 018700146058000 | E71: GEDUNG MENARA BCA, GRAND INDONESIA LT.51 JL.MH.THAMRIN, MENTENG, MENTENG, KOTA ADM. JAKARTA PUSAT, DKI JAKARTA, 10310 | N71: e.prasetyo@mitsui.com | O71: 2021-10-27 06:14:52 | P71: 0 | Q71: 0 | R71: 0 | T71: =_xlfn.IFNA(VLOOKUP(B71,Sheet2!$A$2:$M$58,4,0),"-") -> - | U71: =_xlfn.IFNA(VLOOKUP(B71,'TV Trx'!$B$4:$C$57,2,0),"-") -> - | V71: =IF(C71="ACC_TYPE_CO",T71,U71) -> - | W71: =_xlfn.IFNA(VLOOKUP(B71,'CO Trx'!$A$4:$B$37,2,0),"-") -> - | X71: =_xlfn.IFNA(VLOOKUP(B71,'CO Trx'!$A$49:$B$104,2,0),"-") -> - | Y71: NOT FOUND
A72: CK0218 | B72: MOBILITAS DIGITAL INDONESIA | C72: ACC_TYPE_CO | D72: 21312312 | E72: JL. RAYA BEKASI, CAKUNG, JAKARTA TIMUR | L72: 21908319203 | N72: sajbndjkasbj@gmail.com | O72: 2022-11-29 02:58:58 | P72: 0 | Q72: 0 | R72: 0 | T72: =_xlfn.IFNA(VLOOKUP(B72,Sheet2!$A$2:$M$58,4,0),"-") -> - | U72: =_xlfn.IFNA(VLOOKUP(B72,'TV Trx'!$B$4:$C$57,2,0),"-") -> - | V72: =IF(C72="ACC_TYPE_CO",T72,U72) -> - | W72: =_xlfn.IFNA(VLOOKUP(B72,'CO Trx'!$A$4:$B$37,2,0),"-") -> - | X72: =_xlfn.IFNA(VLOOKUP(B72,'CO Trx'!$A$49:$B$104,2,0),"-") -> - | Y72: NOT FOUND
A73: CK0007 | B73: NAGASE IMPOR EKSPOR INDONESIA | C73: ACC_TYPE_CO | D73: 018245894059000 | E73: WISMA KEIAI LT. 12, JL. JEND. SUDIRMAN KAV 3 RT/RW /, KARET TENGSIN, TANAH ABANG, KOTA ADM. JAKARTA PUSAT, DKI JAKARTA 10220 | H73: 10220 | I73: KOTA ADM. JAKARTA PUSAT | J73: DKI JAKARTA | O73: 2020-07-23 03:34:16 | P73: 0 | Q73: 0 | R73: 0 | T73: =_xlfn.IFNA(VLOOKUP(B73,Sheet2!$A$2:$M$58,4,0),"-") -> - | U73: =_xlfn.IFNA(VLOOKUP(B73,'TV Trx'!$B$4:$C$57,2,0),"-") -> - | V73: =IF(C73="ACC_TYPE_CO",T73,U73) -> - | W73: =_xlfn.IFNA(VLOOKUP(B73,'CO Trx'!$A$4:$B$37,2,0),"-") -> - | X73: =_xlfn.IFNA(VLOOKUP(B73,'CO Trx'!$A$49:$B$104,2,0),"-") -> - | Y73: NOT FOUND
A74: CK0229 | B74: NURZAKIMUBAROK PROJECT | C74: ACC_TYPE_TO | D74: 654473461443000 | E74: KP.KIARA LAWANG RT/RW/003/011 KEL/DESA.SUKAMUKTI KEC.BANYURESMI KAB.GARUT PROV.JAWA BARAT JABAR WEST JAVA ZIP CODE POST.44191 IDN INDONESIA SOUTHEAST ASIAN COUNTRY | L74: 085172241298 | N74: nurzakiyahmubarokah@gmail.com | O74: 2023-01-18 04:32:50 | P74: 0 | Q74: 0 | R74: 0 | T74: =_xlfn.IFNA(VLOOKUP(B74,Sheet2!$A$2:$M$58,4,0),"-") -> - | U74: =_xlfn.IFNA(VLOOKUP(B74,'TV Trx'!$B$4:$C$57,2,0),"-") -> - | V74: =IF(C74="ACC_TYPE_CO",T74,U74) -> - | W74: =_xlfn.IFNA(VLOOKUP(B74,'CO Trx'!$A$4:$B$37,2,0),"-") -> - | X74: =_xlfn.IFNA(VLOOKUP(B74,'CO Trx'!$A$49:$B$104,2,0),"-") -> - | Y74: NOT FOUND
A75: CK0090 | B75: OCEAN GLOBAL SHIPPING LOGISTICS | C75: ACC_TYPE_CO | D75: 010708105058000 | E75: IR. H JUANDA III NOMOR 23 C-D-E KEBON KELAPA GAMBIR KOTA ADM. JAKARTA PUSAT DKI JAKARTA 10120 | L75: 02122057980 | N75: logistic@cosco-ogs.com | O75: 2021-08-25 02:47:09 | P75: 0 | Q75: 0 | R75: 0 | T75: =_xlfn.IFNA(VLOOKUP(B75,Sheet2!$A$2:$M$58,4,0),"-") -> - | U75: =_xlfn.IFNA(VLOOKUP(B75,'TV Trx'!$B$4:$C$57,2,0),"-") -> - | V75: =IF(C75="ACC_TYPE_CO",T75,U75) -> - | W75: =_xlfn.IFNA(VLOOKUP(B75,'CO Trx'!$A$4:$B$37,2,0),"-") -> - | X75: =_xlfn.IFNA(VLOOKUP(B75,'CO Trx'!$A$49:$B$104,2,0),"-") -> - | Y75: NOT FOUND
A76: CK0088 | B76: PERUSAHAAN PERSEROAN (PERSERO) PT. TELEKOMUNIKASI INDONESIA | C76: ACC_TYPE_CO | D76: 010000131093000 | E76: JL JAPATI NO.1 SADANG SERANG - COBLONG RT/RW -, SADANGSERANG, COBLONG, KOTA BANDUNG, JAWA BARAT 40133 | L76: 082240352066 | N76: irfan.salman@telkom.co.id | O76: 2021-08-23 05:35:34 | P76: 0 | Q76: 0 | R76: 0 | T76: =_xlfn.IFNA(VLOOKUP(B76,Sheet2!$A$2:$M$58,4,0),"-") -> - | U76: =_xlfn.IFNA(VLOOKUP(B76,'TV Trx'!$B$4:$C$57,2,0),"-") -> - | V76: =IF(C76="ACC_TYPE_CO",T76,U76) -> - | W76: =_xlfn.IFNA(VLOOKUP(B76,'CO Trx'!$A$4:$B$37,2,0),"-") -> - | X76: =_xlfn.IFNA(VLOOKUP(B76,'CO Trx'!$A$49:$B$104,2,0),"-") -> - | Y76: NOT FOUND
A77: CK0010 | B77: PHC INDONESIA | C77: ACC_TYPE_CO | D77: 010815769055000 | E77: KAWASAN INDUSTRI MM2100 BLOK O-1, CIKARANG BARAT BEKASI 17520 | H77: 17520 | I77: BEKASI | J77: JAWA BARAT | O77: 2020-08-06 04:04:20 | P77: 0 | Q77: 0 | R77: 0 | T77: =_xlfn.IFNA(VLOOKUP(B77,Sheet2!$A$2:$M$58,4,0),"-") -> - | U77: =_xlfn.IFNA(VLOOKUP(B77,'TV Trx'!$B$4:$C$57,2,0),"-") -> - | V77: =IF(C77="ACC_TYPE_CO",T77,U77) -> - | W77: =_xlfn.IFNA(VLOOKUP(B77,'CO Trx'!$A$4:$B$37,2,0),"-") -> - | X77: =_xlfn.IFNA(VLOOKUP(B77,'CO Trx'!$A$49:$B$104,2,0),"-") -> - | Y77: NOT FOUND
A78: CK0033 | B78: PILARMEDIA | C78: ACC_TYPE_CO | D78: 1234 | E78: GUNUNG ANYAR HARAPAN ZF 7 | H78: 60294 | I78: kota surabaya | J78: jawa timur | O78: 2020-12-10 06:08:22 | P78: 0 | Q78: 0 | R78: 0 | T78: =_xlfn.IFNA(VLOOKUP(B78,Sheet2!$A$2:$M$58,4,0),"-") -> - | U78: =_xlfn.IFNA(VLOOKUP(B78,'TV Trx'!$B$4:$C$57,2,0),"-") -> - | V78: =IF(C78="ACC_TYPE_CO",T78,U78) -> - | W78: =_xlfn.IFNA(VLOOKUP(B78,'CO Trx'!$A$4:$B$37,2,0),"-") -> - | X78: =_xlfn.IFNA(VLOOKUP(B78,'CO Trx'!$A$49:$B$104,2,0),"-") -> - | Y78: NOT FOUND
A79: CK0029 | B79: PRATAMA AMIRAH SENTOSA | C79: ACC_TYPE_FF | D79: 922124995225000 | E79: CLUSTER MARBELLA RESIDENCE, BLOK G3, NOMOR 23 RT/RW 003/039, BELIAN, BATAM KOTA, KOTA BATAM, KEPULAUAN RIAU 29464 | H79: 29464 | I79: KOTA BATAM | J79: KEPULAUAN RIAU | O79: 2020-10-25 03:16:22 | P79: 0 | Q79: 0 | R79: 0 | T79: =_xlfn.IFNA(VLOOKUP(B79,Sheet2!$A$2:$M$58,4,0),"-") -> - | U79: =_xlfn.IFNA(VLOOKUP(B79,'TV Trx'!$B$4:$C$57,2,0),"-") -> - | V79: =IF(C79="ACC_TYPE_CO",T79,U79) -> - | W79: =_xlfn.IFNA(VLOOKUP(B79,'CO Trx'!$A$4:$B$37,2,0),"-") -> - | X79: =_xlfn.IFNA(VLOOKUP(B79,'CO Trx'!$A$49:$B$104,2,0),"-") -> - | Y79: NOT FOUND
A80: CK0099 | B80: PT . KARO RAYA TRANS | C80: ACC_TYPE_TO | D80: 426714689043000 | N80: karorayatrans@gmail.com | O80: 2021-09-22 06:59:05 | P80: LI271 | Q80: 1650061119823 | R80: MANDIRI | T80: =_xlfn.IFNA(VLOOKUP(B80,Sheet2!$A$2:$M$58,4,0),"-") -> - | U80: =_xlfn.IFNA(VLOOKUP(B80,'TV Trx'!$B$4:$C$57,2,0),"-") -> - | V80: =IF(C80="ACC_TYPE_CO",T80,U80) -> - | W80: =_xlfn.IFNA(VLOOKUP(B80,'CO Trx'!$A$4:$B$37,2,0),"-") -> - | X80: =_xlfn.IFNA(VLOOKUP(B80,'CO Trx'!$A$49:$B$104,2,0),"-") -> - | Y80: NOT FOUND | AA80: KARO RAYA TRANS, PT-LOG | AB80: KARO RAYA
A81: CK0231 | B81: PT BERATUSTIRTA GIRIAGUNG | C81: ACC_TYPE_CO | D81: 016193112726000 | E81: JL SOEKARNO HATTA KM 32 RT 23 NO 01, KEL KARYA MERDEKA, KEC SAMBOJA BARAT, KAB KUTAI KARTANEGARA | L81: 081253328969 | N81: ptbtga@gmail.com | O81: 2023-01-19 07:38:31 | P81: 0 | Q81: 0 | R81: 0 | T81: =_xlfn.IFNA(VLOOKUP(B81,Sheet2!$A$2:$M$58,4,0),"-") -> - | U81: =_xlfn.IFNA(VLOOKUP(B81,'TV Trx'!$B$4:$C$57,2,0),"-") -> - | V81: =IF(C81="ACC_TYPE_CO",T81,U81) -> - | W81: =_xlfn.IFNA(VLOOKUP(B81,'CO Trx'!$A$4:$B$37,2,0),"-") -> - | X81: =_xlfn.IFNA(VLOOKUP(B81,'CO Trx'!$A$49:$B$104,2,0),"-") -> - | Y81: NOT FOUND
A82: CK0111 | B82: PT CRANE WORLDWIDE LOGISTICS INDONESIA | C82: ACC_TYPE_CO | D82: 211227434013000 | L82: 02129036550 | N82: jkt.info@craneww.com | O82: 2021-12-21 03:18:50 | P82: 0 | Q82: 0 | R82: 0 | T82: =_xlfn.IFNA(VLOOKUP(B82,Sheet2!$A$2:$M$58,4,0),"-") -> - | U82: =_xlfn.IFNA(VLOOKUP(B82,'TV Trx'!$B$4:$C$57,2,0),"-") -> - | V82: =IF(C82="ACC_TYPE_CO",T82,U82) -> - | W82: =_xlfn.IFNA(VLOOKUP(B82,'CO Trx'!$A$4:$B$37,2,0),"-") -> - | X82: =_xlfn.IFNA(VLOOKUP(B82,'CO Trx'!$A$49:$B$104,2,0),"-") -> - | Y82: NOT FOUND
A83: CK0211 | B83: PT DENSO INDONESIA | C83: ACC_TYPE_CO | D83: 010002301092000 | E83: JL. KALIMANTAN BLOK E1-2, KAWASAN INDUSTRI MM2100, DESA/KELURAHAN GANDAMEKAR, KEC. CIKARANG BARAT, KAB. BEKASI, PROVINSI JAWA BARAT, KODE POS: 17530 | L83: 6281289495299 | N83: anrihal.fajari.a3u@ap.denso.com | O83: 2022-10-24 02:07:25 | P83: 0 | Q83: 0 | R83: 0 | T83: =_xlfn.IFNA(VLOOKUP(B83,Sheet2!$A$2:$M$58,4,0),"-") -> - | U83: =_xlfn.IFNA(VLOOKUP(B83,'TV Trx'!$B$4:$C$57,2,0),"-") -> - | V83: =IF(C83="ACC_TYPE_CO",T83,U83) -> - | W83: =_xlfn.IFNA(VLOOKUP(B83,'CO Trx'!$A$4:$B$37,2,0),"-") -> - | X83: =_xlfn.IFNA(VLOOKUP(B83,'CO Trx'!$A$49:$B$104,2,0),"-") -> - | Y83: NOT FOUND
A84: CK0149 | B84: PT ELEMEN TRANS LOGISTIK | C84: ACC_TYPE_TO | D84: 534791348045000 | N84: eltranslogis@gmail.com | O84: 2022-04-06 03:58:49 | P84: 0 | R84: BCA : 0070693151 | T84: =_xlfn.IFNA(VLOOKUP(B84,Sheet2!$A$2:$M$58,4,0),"-") -> - | U84: =_xlfn.IFNA(VLOOKUP(B84,'TV Trx'!$B$4:$C$57,2,0),"-") -> 45071 | V84: =IF(C84="ACC_TYPE_CO",T84,U84) -> 45071 | W84: =_xlfn.IFNA(VLOOKUP(B84,'CO Trx'!$A$4:$B$37,2,0),"-") -> - | X84: =_xlfn.IFNA(VLOOKUP(B84,'CO Trx'!$A$49:$B$104,2,0),"-") -> - | Y84: ACTIVE
A85: CK0108 | B85: PT FREEPORT INDONESIA | C85: ACC_TYPE_CO | D85: 010695369091000 | N85: aandrian@fmi.com | O85: 2021-11-19 02:26:58 | P85: 0 | Q85: 0 | R85: 0 | T85: =_xlfn.IFNA(VLOOKUP(B85,Sheet2!$A$2:$M$58,4,0),"-") -> - | U85: =_xlfn.IFNA(VLOOKUP(B85,'TV Trx'!$B$4:$C$57,2,0),"-") -> - | V85: =IF(C85="ACC_TYPE_CO",T85,U85) -> - | W85: =_xlfn.IFNA(VLOOKUP(B85,'CO Trx'!$A$4:$B$37,2,0),"-") -> - | X85: =_xlfn.IFNA(VLOOKUP(B85,'CO Trx'!$A$49:$B$104,2,0),"-") -> - | Y85: NOT FOUND
A86: CK0097 | B86: PT GAMA LOGISTICS - TRUCKING | C86: ACC_TYPE_TO | D86: 452342232523 | N86: helpdesk-ck-truck@gamalogistics.com | O86: 2021-09-14 08:27:40 | P86: LI277 | Q86: 0 | R86: 0 | T86: =_xlfn.IFNA(VLOOKUP(B86,Sheet2!$A$2:$M$58,4,0),"-") -> - | U86: =_xlfn.IFNA(VLOOKUP(B86,'TV Trx'!$B$4:$C$57,2,0),"-") -> - | V86: =IF(C86="ACC_TYPE_CO",T86,U86) -> - | W86: =_xlfn.IFNA(VLOOKUP(B86,'CO Trx'!$A$4:$B$37,2,0),"-") -> - | X86: =_xlfn.IFNA(VLOOKUP(B86,'CO Trx'!$A$49:$B$104,2,0),"-") -> - | Y86: NOT FOUND | AA86: PT. GAMA LOGISTICS-PF
A87: CK0036 | B87: PT GLOBAL FAJAR INDONESIA | C87: ACC_TYPE_CO | D87: 954940631061000 | E87: GRAHA MAMPANG 3RD FLOOR, SUITE 305, JL. MAMPANG PRAPATAN RAYA KAV. 100, KEL. DUREN TIGA, KEC. PANCORAN, JAKARTA SELATAN, DKI JAKARTA 12760 | H87: 12760 | I87: Jakarta Selatan | J87: DKI Jakarta | O87: 2020-12-21 06:10:55 | P87: 0 | Q87: 0 | R87: 0 | T87: =_xlfn.IFNA(VLOOKUP(B87,Sheet2!$A$2:$M$58,4,0),"-") -> - | U87: =_xlfn.IFNA(VLOOKUP(B87,'TV Trx'!$B$4:$C$57,2,0),"-") -> - | V87: =IF(C87="ACC_TYPE_CO",T87,U87) -> - | W87: =_xlfn.IFNA(VLOOKUP(B87,'CO Trx'!$A$4:$B$37,2,0),"-") -> - | X87: =_xlfn.IFNA(VLOOKUP(B87,'CO Trx'!$A$49:$B$104,2,0),"-") -> - | Y87: NOT FOUND
A88: CK0081 | B88: PT GUUD LOGISTICS INDONESIA | C88: ACC_TYPE_CO | D88: 020404224435009 | E88: THE PRIME OFFICE SUITES LANTAI 7 JALAN YOS SUDARSO BLOK SUITE C NO KAV.30 RT 009 RW 011 SUNTER JAYA TANJUNG PRIOK JAKARTA UTARA DKI JAKARTA | N88: admin.tds@guud.company | O88: 2021-08-09 03:27:57 | P88: 0 | Q88: 0 | R88: 0 | T88: =_xlfn.IFNA(VLOOKUP(B88,Sheet2!$A$2:$M$58,4,0),"-") -> - | U88: =_xlfn.IFNA(VLOOKUP(B88,'TV Trx'!$B$4:$C$57,2,0),"-") -> - | V88: =IF(C88="ACC_TYPE_CO",T88,U88) -> - | W88: =_xlfn.IFNA(VLOOKUP(B88,'CO Trx'!$A$4:$B$37,2,0),"-") -> - | X88: =_xlfn.IFNA(VLOOKUP(B88,'CO Trx'!$A$49:$B$104,2,0),"-") -> - | Y88: NOT FOUND
A89: CK0105 | B89: PT HACACA CENTRAL LOGISTIC | C89: ACC_TYPE_TO | D89: 312773328435000 | N89: admintruck@hacaca.co.id | O89: 2021-10-22 03:10:05 | P89: HCC01 | Q89: 0 | R89: 0 | T89: =_xlfn.IFNA(VLOOKUP(B89,Sheet2!$A$2:$M$58,4,0),"-") -> - | U89: =_xlfn.IFNA(VLOOKUP(B89,'TV Trx'!$B$4:$C$57,2,0),"-") -> - | V89: =IF(C89="ACC_TYPE_CO",T89,U89) -> - | W89: =_xlfn.IFNA(VLOOKUP(B89,'CO Trx'!$A$4:$B$37,2,0),"-") -> - | X89: =_xlfn.IFNA(VLOOKUP(B89,'CO Trx'!$A$49:$B$104,2,0),"-") -> - | Y89: NOT FOUND | AA89: PT. HACACA CENTRAL LOGISTICS-PF
A90: CK0066 | B90: PT HACACA CENTRAL LOGISTICS | C90: ACC_TYPE_CO | D90: 312773328435000 | E90: JALAN MARUNDA RAYA NO.3, KEL. SEGARA MAKMUR, KEC. TARUMAJAYA | H90: 17211 | I90: kabupaten bekasi | J90: jawa barat | L90: 02188991019 | N90: info@hacaca.com | O90: 2021-06-23 07:36:10 | P90: 0 | Q90: 0 | R90: 0 | T90: =_xlfn.IFNA(VLOOKUP(B90,Sheet2!$A$2:$M$58,4,0),"-") -> - | U90: =_xlfn.IFNA(VLOOKUP(B90,'TV Trx'!$B$4:$C$57,2,0),"-") -> - | V90: =IF(C90="ACC_TYPE_CO",T90,U90) -> - | W90: =_xlfn.IFNA(VLOOKUP(B90,'CO Trx'!$A$4:$B$37,2,0),"-") -> - | X90: =_xlfn.IFNA(VLOOKUP(B90,'CO Trx'!$A$49:$B$104,2,0),"-") -> - | Y90: NOT FOUND
A91: CK0135 | B91: PT JASINDO TRANS SAMUDERA | C91: ACC_TYPE_TO | D91: 027670090528000 | N91: marketingjasindo@gmail.com | O91: 2022-03-21 09:55:47 | P91: 0 | Q91: 0 | R91: 0 | T91: =_xlfn.IFNA(VLOOKUP(B91,Sheet2!$A$2:$M$58,4,0),"-") -> - | U91: =_xlfn.IFNA(VLOOKUP(B91,'TV Trx'!$B$4:$C$57,2,0),"-") -> - | V91: =IF(C91="ACC_TYPE_CO",T91,U91) -> - | W91: =_xlfn.IFNA(VLOOKUP(B91,'CO Trx'!$A$4:$B$37,2,0),"-") -> - | X91: =_xlfn.IFNA(VLOOKUP(B91,'CO Trx'!$A$49:$B$104,2,0),"-") -> - | Y91: NOT FOUND
A92: CK0186 | B92: PT JAYA PRATAMA PERKASA | C92: ACC_TYPE_TO | D92: 024930430077000 | E92: TAMAN PALEM LESTARI, KOMPLEK RUKO GALAXY, JL. KAMAL RAYA OUTER RINGROAD BLOK R NO.01, RT.013 RW.008, KEL. CENGKARENG BARAT, KEC. CENGKARENG | L92: 0 | N92: wahyudi_jpp@yahoo.com | O92: 2022-08-22 02:53:29 | P92: LIJ008 | R92: BCA : 8990305588 | T92: =_xlfn.IFNA(VLOOKUP(B92,Sheet2!$A$2:$M$58,4,0),"-") -> - | U92: =_xlfn.IFNA(VLOOKUP(B92,'TV Trx'!$B$4:$C$57,2,0),"-") -> 45071 | V92: =IF(C92="ACC_TYPE_CO",T92,U92) -> 45071 | W92: =_xlfn.IFNA(VLOOKUP(B92,'CO Trx'!$A$4:$B$37,2,0),"-") -> - | X92: =_xlfn.IFNA(VLOOKUP(B92,'CO Trx'!$A$49:$B$104,2,0),"-") -> - | Y92: ACTIVE | AA92: PT. JAYA PRATAMA PERKASA-PF | AB92: JAYA PRATAMA LOGISTIK
A93: CK0121 | B93: PT KINARI JAYA TRANS | C93: ACC_TYPE_TO | D93: 743119174503000 | E93: JL CANDI TEMBAGA SELATAN NO.995 RT.012 RW.005 KALIPANCUR, NGALIYAN KOTA SEMARANG JAWA TENGAH | L93: 082225847727 | N93: kinarya.mimi@gmail.com | O93: 2022-01-24 08:10:04 | P93: LI320 | R93: CIMB : 9770100104005 | T93: =_xlfn.IFNA(VLOOKUP(B93,Sheet2!$A$2:$M$58,4,0),"-") -> - | U93: =_xlfn.IFNA(VLOOKUP(B93,'TV Trx'!$B$4:$C$57,2,0),"-") -> 45082 | V93: =IF(C93="ACC_TYPE_CO",T93,U93) -> 45082 | W93: =_xlfn.IFNA(VLOOKUP(B93,'CO Trx'!$A$4:$B$37,2,0),"-") -> - | X93: =_xlfn.IFNA(VLOOKUP(B93,'CO Trx'!$A$49:$B$104,2,0),"-") -> - | Y93: ACTIVE | AA93: PT KINARI JAYA TRANS-PF | AB93: KINARI JAYA
A94: CK0138 | B94: PT KINARYA MANDIRI TRANS | C94: ACC_TYPE_CO | D94: 023964182503000 | E94: JL PUSPANJOLO TIMUR X/26 RT 06 RW 02 SEMARANG JAWA TENGAH 50141 | L94: 085740931255 | N94: kinaryamandiri.trans@gmail.com | O94: 2022-03-21 14:33:20 | P94: LI319 | T94: =_xlfn.IFNA(VLOOKUP(B94,Sheet2!$A$2:$M$58,4,0),"-") -> 45083 | U94: =_xlfn.IFNA(VLOOKUP(B94,'TV Trx'!$B$4:$C$57,2,0),"-") -> - | V94: =IF(C94="ACC_TYPE_CO",T94,U94) -> 45083 | W94: =_xlfn.IFNA(VLOOKUP(B94,'CO Trx'!$A$4:$B$37,2,0),"-") -> 15 | X94: =_xlfn.IFNA(VLOOKUP(B94,'CO Trx'!$A$49:$B$104,2,0),"-") -> 863 | Y94: ACTIVE | AA94: PT KINARYA MANDIRI TRANS-PF | AB94: KINARI JAYA
A95: CK0180 | B95: PT KUMALA LOGISTICS | C95: ACC_TYPE_TO | D95: 026673491033000 | E95: JL. PEKOJAN RAYA NO.88 & 89, PEKOJAN, TAMBORA, KEL.PEKOJAN KEC. TAMBORA, KOTA ADM JAKARTA BARAT, PROP. DKI JAKARTA | L95: 02143901037 | N95: nelly@kumlog.co.id | O95: 2022-08-04 04:57:14 | P95: 0 | Q95: 0 | R95: 0 | T95: =_xlfn.IFNA(VLOOKUP(B95,Sheet2!$A$2:$M$58,4,0),"-") -> - | U95: =_xlfn.IFNA(VLOOKUP(B95,'TV Trx'!$B$4:$C$57,2,0),"-") -> - | V95: =IF(C95="ACC_TYPE_CO",T95,U95) -> - | W95: =_xlfn.IFNA(VLOOKUP(B95,'CO Trx'!$A$4:$B$37,2,0),"-") -> - | X95: =_xlfn.IFNA(VLOOKUP(B95,'CO Trx'!$A$49:$B$104,2,0),"-") -> - | Y95: NOT FOUND
A96: CK0284 | B96: PT LOGOL JAKARTA MITRAINDO | C96: ACC_TYPE_TO | D96: 915189088043000 | E96: GADING BUKIT INDAH BLOK TB NOMOR 6, JALAN RAYA GADING KIRANA, KEL. KELAPA GADING BARAT, KEC. KELAPA GADING, KOTA ADM. JAKARTA UTARA, PROV. DKI JAKARTA | L96: 0 | N96: logoljakartamitraindo@gmail.com | O96: 2023-04-18 02:24:14 | P96: LIL001 | Q96: 0 | R96: 0 | T96: =_xlfn.IFNA(VLOOKUP(B96,Sheet2!$A$2:$M$58,4,0),"-") -> - | U96: =_xlfn.IFNA(VLOOKUP(B96,'TV Trx'!$B$4:$C$57,2,0),"-") -> - | V96: =IF(C96="ACC_TYPE_CO",T96,U96) -> - | W96: =_xlfn.IFNA(VLOOKUP(B96,'CO Trx'!$A$4:$B$37,2,0),"-") -> - | X96: =_xlfn.IFNA(VLOOKUP(B96,'CO Trx'!$A$49:$B$104,2,0),"-") -> - | Y96: NOT FOUND | AA96: PT. LOGOL JAKARTA MITRAINDO-PF
A97: CK0104 | B97: PT MAHKOTA LOGISTIK INDORAYA | C97: ACC_TYPE_TO | D97: 032209967048000 | N97: cs@mahkotalogistik.com | O97: 2021-10-19 07:04:43 | P97: 0 | Q97: 0 | R97: 0 | T97: =_xlfn.IFNA(VLOOKUP(B97,Sheet2!$A$2:$M$58,4,0),"-") -> - | U97: =_xlfn.IFNA(VLOOKUP(B97,'TV Trx'!$B$4:$C$57,2,0),"-") -> - | V97: =IF(C97="ACC_TYPE_CO",T97,U97) -> - | W97: =_xlfn.IFNA(VLOOKUP(B97,'CO Trx'!$A$4:$B$37,2,0),"-") -> - | X97: =_xlfn.IFNA(VLOOKUP(B97,'CO Trx'!$A$49:$B$104,2,0),"-") -> - | Y97: NOT FOUND
A98: CK0037 | B98: PT MERAPI DUNIA TEKSTIL | C98: ACC_TYPE_TO | D98: 913733838527000 | E98: KUNCEN RT06 RW03 DOPLANG TERAS BOYOLALI | H98: 57372 | I98: kabupaten boyolali | J98: jawa tengah | O98: 2020-12-27 07:54:56 | P98: 0 | Q98: 0 | R98: 0 | T98: =_xlfn.IFNA(VLOOKUP(B98,Sheet2!$A$2:$M$58,4,0),"-") -> - | U98: =_xlfn.IFNA(VLOOKUP(B98,'TV Trx'!$B$4:$C$57,2,0),"-") -> - | V98: =IF(C98="ACC_TYPE_CO",T98,U98) -> - | W98: =_xlfn.IFNA(VLOOKUP(B98,'CO Trx'!$A$4:$B$37,2,0),"-") -> - | X98: =_xlfn.IFNA(VLOOKUP(B98,'CO Trx'!$A$49:$B$104,2,0),"-") -> - | Y98: NOT FOUND
A99: CK0162 | B99: PT MILENIA ARMADA EKSPRES SEMARANG | C99: ACC_TYPE_FF | D99: 802861922503000 | E99: JL. ANJASMORO RAYA NO. 6A RT 003 RW 003 KARANG AYU, SEMARANG BARAT, SEMARANG, JAWA TENGAH | L99: 02476490857 | N99: sebastian@mileniaexpress.com | O99: 2022-05-12 07:50:20 | P99: 0 | Q99: 0 | R99: 0 | T99: =_xlfn.IFNA(VLOOKUP(B99,Sheet2!$A$2:$M$58,4,0),"-") -> - | U99: =_xlfn.IFNA(VLOOKUP(B99,'TV Trx'!$B$4:$C$57,2,0),"-") -> - | V99: =IF(C99="ACC_TYPE_CO",T99,U99) -> - | W99: =_xlfn.IFNA(VLOOKUP(B99,'CO Trx'!$A$4:$B$37,2,0),"-") -> - | X99: =_xlfn.IFNA(VLOOKUP(B99,'CO Trx'!$A$49:$B$104,2,0),"-") -> - | Y99: NOT FOUND
A100: CK0126 | B100: PT MONICA LESTARI | C100: ACC_TYPE_CO | D100: 014841407411000 | E100: PROF. DR. SATRIO A3 NO. 5 PONDOK JAYA PONDOK AREN | L100: 02174864567 | N100: legal-ml@tbsgroup.co.id | O100: 2022-02-18 02:16:17 | P100: 0 | Q100: 0 | R100: 0 | T100: =_xlfn.IFNA(VLOOKUP(B100,Sheet2!$A$2:$M$58,4,0),"-") -> - | U100: =_xlfn.IFNA(VLOOKUP(B100,'TV Trx'!$B$4:$C$57,2,0),"-") -> - | V100: =IF(C100="ACC_TYPE_CO",T100,U100) -> - | W100: =_xlfn.IFNA(VLOOKUP(B100,'CO Trx'!$A$4:$B$37,2,0),"-") -> - | X100: =_xlfn.IFNA(VLOOKUP(B100,'CO Trx'!$A$49:$B$104,2,0),"-") -> - | Y100: NOT FOUND
...

Sheet Sheet2
A1: Customer | B1: AM | C1: Active Date | D1: Latest Booking Date | E1: Remaining Credit | F1: Credit Limit | G1: CL Ratio | H1: CLD Total | I1: CLG Total | J1: CLT Total | K1: Last Job Number | L1: Debit Note | M1: Total PF
A2: PT. Transindo Jayatama Logistik | B2: Ame | C2: 44854 | D2: 45071 | E2: 42811826 | F2: 15000000000 | G2: 0.0028541217 | H2: 0 | I2: 0 | J2: 1826 | K2: CLICTRUCK-048929 | L2: 17792844529 | M2: 476580341
A3: PT. Inesia Food Indonesia | B3: Dyah | C3: 44988 | D3: 45060 | E3: 1191504400 | F3: 4000000000 | G3: 0.2978761 | H3: 0 | I3: 0 | J3: 104 | K3: CLICTRUCK-048426 | L3: 3665305000 | M3: 104021003
A4: PT. Roket Delapan Delapan | B4: Raiyan | C4: 45015 | D4: 45081 | E4: 1500906750 | F4: 3000000000 | G4: 0.50030225 | H4: 0 | I4: 0 | J4: 11 | K4: CLICTRUCK-049189 | L4: 2646282000 | M4: 117800170
A5: PT KINARYA MANDIRI TRANS | B5: Beny | C5: 44642 | D5: 45083 | E5: 179952875 | F5: 1400000000 | G5: 0.12853777 | H5: 0 | I5: 0 | J5: 863 | K5: CLICTRUCK-049273 | L5: 2146359125 | M5: 85842535
A6: PT. ASHAKA JAYA MANDIRI | B6: Ame | C6: 44959 | D6: 45086 | E6: 42076415 | F6: 1000000000 | G6: 0.042076415 | H6: 0 | I6: 0 | J6: 87 | K6: CLICTRUCK-049381 | L6: 1866300000 | M6: 74920005
A7: PT. Ekspedisi Sehati Abadi | B7: Raiyan | C7: 44917 | D7: 45088 | E7: 99373993 | F7: 700000000 | G7: 0.14196285 | H7: 0 | I7: 0 | J7: 1040 | K7: CLICTRUCK-049454 | L7: 1428541147 | M7: 52492746
A8: PT. Lima Sarana Trans | B8: Dyah | C8: 45002 | D8: 45060 | E8: 2439619 | F8: 1000000000 | G8: 0.002439619 | H8: 0 | I8: 0 | J8: 83 | K8: CLICTRUCK-048431 | L8: 983500000 | M8: 62345925
A9: PT. Nadja Trans Logistik [Cargo Owner] | B9: Ame | C9: 45012 | D9: 45025 | E9: 49724290 | F9: 1000000000 | G9: 0.04972429 | H9: 0 | I9: 0 | J9: 87 | K9: CLICTRUCK-047248 | L9: 968088139 | M9: 40024468
A10: PT. Rajawali Persada Logistik | B10: Raiyan | C10: 44911 | D10: 45017 | E10: 415845000 | F10: 600000000 | G10: 0.693075 | H10: 0 | I10: 0 | J10: 71 | K10: CLICTRUCK-046638 | L10: 914300000 | M10: 27342075
A11: PT. Distribusi Solusi Bersama | B11: Raiyan | C11: 44958 | D11: 45066 | E11: 169791500 | F11: 500000000 | G11: 0.339583 | H11: 0 | I11: 0 | J11: 93 | K11: CLICTRUCK-048734 | L11: 784053500 | M11: 37392722
A12: PT. Central Jasa Mitra Bahari | B12: Ame | C12: 44837 | D12: 45077 | E12: 3269250 | F12: 600000000 | G12: 0.00544875 | H12: 0 | I12: 0 | J12: 478 | K12: CLICTRUCK-049036 | L12: 766300000 | M12: 25517790
A13: PT. Lazuardo Vittorio Indonesia | B13: Ame | C13: 45057 | D13: 45084 | E13: 214180250 | F13: 1000000000 | G13: 0.21418025 | H13: 0 | I13: 0 | J13: 102 | K13: CLICTRUCK-049303 | L13: 744500000 | M13: 44150250
... A53: CV. KHAROMAH BERKAH TRANS | B53: Raiyan | C53: 45075 | D53: 45086 | E53: 89060244 | F53: 150000000 | G53: 0.59373496 | H53: 0 | I53: 0 | J53: 9 | K53: CLICTRUCK-049370 | L53: 39434506 | M53: 2876087
A54: PT. Dewata Freight International | D54: 44951
A55: CV. Datuak Lansano Maju Bersama Nayaka | B55: Raiyan | C55: 45068 | D55: 45072 | E55: 119472250 | F55: 150000000 | G55: 0.79648167 | H55: 0 | I55: 0 | J55: 1 | K55: CLICTRUCK-048956 | L55: 30500000 | M55: 1043400
A56: PT. Gemilang Logistik Terminal | B56: Beny | C56: 45057 | D56: 45085 | E56: 90915401 | F56: 150000000 | G56: 0.60610267 | H56: 0 | I56: 0 | J56: 10 | K56: CLICTRUCK-049332 | L56: 12740000 | M56: 222000
A57: PT. Vektruck Trans Digilogistik | B57: Lena | C57: 45022 | D57: 45025 | E57: 150000000 | F57: 150000000 | G57: 1 | H57: 0 | I57: 0 | J57: 1 | K57: CLICTRUCK-047222 | L57: 4400000 | M57: 210900
A58: CV. Abadi Jaya | B58: Raiyan | C58: 45086 | E58: 1500000000 | F58: 1500000000 | G58: 1

Sheet CO Trx
A1: Status 2 | B1: OUTSTANDING
A3: Cargo Owner | B3: Sum of JML
A4: CV. Awal Lestari Rezeki | B4: 12
A5: CV. Datuak Lansano Maju Bersama Nayaka | B5: 2
A6: CV. Mulia Maretno Abadi | B6: 1
A7: PT KINARYA MANDIRI TRANS | B7: 15
A8: PT Raskita Wira Jaya | B8: 1
A9: PT. Alira Jaya Tranportasi | B9: 2
A10: PT. ASHAKA JAYA MANDIRI | B10: 10
A11: PT. Central Jasa Mitra Bahari | B11: 10
A12: PT. Citra Buana Nusantara | B12: 1
A13: PT. Duta Lestari Segara | B13: 47
A14: PT. Ekspedisi Sehati Abadi | B14: 35
A15: PT. ERAJAYA KARUNIA LOGISTIK | B15: 149
... A38: Grand Total | B38: 536
A46: Status 2 | B46: COMPLETED
A48: Row Labels | B48: Sum of JML
A49: CV. AL-One Gunawan Jaya Sentosa | B49: 12
A50: CV. Awal Lestari Rezeki | B50: 55
A51: CV. Datuak Lansano Maju Bersama Nayaka | B51: 1
A52: CV. Harba Logistics | B52: 13
A53: CV. KHAROMAH BERKAH TRANS | B53: 9
A54: CV. Mega Jaya Expres | B54: 150
A55: CV. Mulia Maretno Abadi | B55: 7
A56: PT KINARYA MANDIRI TRANS | B56: 863
A57: PT Raskita Wira Jaya | B57: 23
A58: PT. ALD Logistik Indonesia | B58: 9
A59: PT. Alira Jaya Tranportasi | B59: 43
A60: PT. Andalan Niaga Indonesia Logistic | B60: 9
... A105: Grand Total | B105: 6827

Sheet TV Trx
A3: Status 2 | B3: Trucking Vendor | C3: Max of Booking Date'
A4: COMPLETED | B4: CV Ali Trans | C4: 45076
B5: CV. BINTANG TRIJAYA SUKSESINDO | C5: 45076
B6: CV. Faeyza Putra Mandiri | C6: 45058
B7: CV. Mahkota Emas | C7: 45008
B8: CV. Mulia Maretno Abadi - TRUCKING VENDOR | C8: 45072
B9: CV. Nawasena Berkah Mandiri | C9: 45017
B10: CV. NUSANTARA CITRA JAYA | C10: 45087
B11: CV. Pamungkas Sakti Logistik | C11: 45042
B12: CV. RAFA PRATAMA MANDIRI | C12: 45083
B13: CV. SKY Xpress | C13: 45086
B14: CV. SUMBER SEJAHTERA ABADI | C14: 45078
B15: PT ELEMEN TRANS LOGISTIK | C15: 45071
B16: PT Jaya Pratama Perkasa | C16: 45071
... B57: PT. ZENSHIN Technology International | C57: 45066
A58: OUTSTANDING | B58: CV. BINTANG TRIJAYA SUKSESINDO | C58: 45077
B59: CV. Faeyza Putra Mandiri | C59: 45085
B60: CV. Mahkota Emas | C60: 45008
B61: CV. Mulia Maretno Abadi - TRUCKING VENDOR | C61: 45072
B62: CV. RAFA PRATAMA MANDIRI | C62: 45082
B63: CV. SUMBER SEJAHTERA ABADI | C63: 45085
B64: PT KINARI JAYA TRANS | C64: 45083
B65: PT. ANINDYA JIFA PERDANA (Trucking) | C65: 45085
B66: PT. Awani Sejahtera Anugerah | C66: 45025
B67: PT. Bina Mitra Segara Setia | C67: 45030
B68: PT. Delta Utama Gemilang | C68: 44993
B69: PT. Dian Giri Selaras | C69: 45078
B70: PT. Jena Solusi Transport | C70: 45052
... B94: PT. ZENSHIN Technology International | C94: 45076
A95: Grand Total | C95: 45088

Sheet CLT Data
A1: Order Number | B1: Type | C1: Booking Date' | D1: Cargo Owner | E1: Debit Note | F1: CO Platform Fee | G1: Invoice Date | H1: Status | I1: Trucking Vendor | J1: TV Platform Fee | K1: JML | L1: Country | M1: Contract ID | N1: Status 2
A2: CLICTRUCK-043054 | B2: export | C2: 44928 | D2: PT KINARYA MANDIRI TRANS | E2: 1575000 | F2: 16650 | G2: 44931 | H2: PAID | I2: PT KINARI JAYA TRANS | J2: 52447 | K2: 1 | L2: Indonesia | M2: KMT-KJT | N2: COMPLETED
A3: CLICTRUCK-043068 | B3: export | C3: 44929 | D3: PT KINARYA MANDIRI TRANS | E3: 5225000 | F3: 16650 | G3: 44931 | H3: PAID | I3: PT KINARI JAYA TRANS | J3: 173992 | K3: 1 | L3: Indonesia | M3: KMT-KJT | N3: COMPLETED
A4: CLICTRUCK-043069 | B4: export | C4: 44929 | D4: PT KINARYA MANDIRI TRANS | E4: 2460000 | F4: 16650 | G4: 44931 | H4: PAID | I4: PT KINARI JAYA TRANS | J4: 81918 | K4: 1 | L4: Indonesia | M4: KMT-KJT | N4: COMPLETED
A5: CLICTRUCK-043070 | B5: import | C5: 44929 | D5: PT KINARYA MANDIRI TRANS | E5: 2050000 | F5: 16650 | G5: 44931 | H5: PAID | I5: PT KINARI JAYA TRANS | J5: 68265 | K5: 1 | L5: Indonesia | M5: KMT-KJT | N5: COMPLETED
A6: CLICTRUCK-043071 | B6: import | C6: 44929 | D6: PT KINARYA MANDIRI TRANS | E6: 2050000 | F6: 16650 | G6: 44931 | H6: PAID | I6: PT KINARI JAYA TRANS | J6: 68265 | K6: 1 | L6: Indonesia | M6: KMT-KJT | N6: COMPLETED
A7: CLICTRUCK-043072 | B7: import | C7: 44929 | D7: PT KINARYA MANDIRI TRANS | E7: 2250000 | F7: 16650 | G7: 44937 | H7: PAID | I7: PT KINARI JAYA TRANS | J7: 74925 | K7: 1 | L7: Indonesia | M7: KMT-KJT | N7: COMPLETED
A8: CLICTRUCK-043073 | B8: import | C8: 44929 | D8: PT KINARYA MANDIRI TRANS | E8: 3225000 | F8: 16650 | G8: 44937 | H8: PAID | I8: PT KINARI JAYA TRANS | J8: 107392 | K8: 1 | L8: Indonesia | M8: KMT-KJT | N8: COMPLETED
A9: CLICTRUCK-043075 | B9: import | C9: 44929 | D9: PT. Ekspedisi Sehati Abadi | E9: 18855210 | F9: 179820 | G9: 44932 | H9: PAID | I9: PT. Saudara Sukses Abadi | J9: 418585 | K9: 9 | L9: Indonesia | M9: ESA - SASA | N9: COMPLETED
A10: CLICTRUCK-043078 | B10: import | C10: 44930 | D10: PT. Ekspedisi Sehati Abadi | E10: 12285845 | F10: 139860 | G10: 44932 | H10: PAID | I10: PT. Saudara Sukses Abadi | J10: 272744 | K10: 7 | L10: Indonesia | M10: ESA - SASA | N10: COMPLETED
A11: CLICTRUCK-043079 | B11: export | C11: 44930 | D11: PT KINARYA MANDIRI TRANS | E11: 2625000 | F11: 16650 | G11: 44937 | H11: PAID | I11: PT KINARI JAYA TRANS | J11: 87412 | K11: 1 | L11: Indonesia | M11: KMT-KJT | N11: COMPLETED
A12: CLICTRUCK-043080 | B12: export | C12: 44930 | D12: PT KINARYA MANDIRI TRANS | E12: 2625000 | F12: 16650 | G12: 44937 | H12: PAID | I12: PT KINARI JAYA TRANS | J12: 87412 | K12: 1 | L12: Indonesia | M12: KMT-KJT | N12: COMPLETED
A13: CLICTRUCK-043081 | B13: export | C13: 44930 | D13: PT KINARYA MANDIRI TRANS | E13: 1775000 | F13: 16650 | G13: 44937 | H13: PAID | I13: PT KINARI JAYA TRANS | J13: 59107 | K13: 1 | L13: Indonesia | M13: KMT-KJT | N13: COMPLETED
... A66: CLICTRUCK-043203 | B66: export | C66: 44938 | D66: PT KINARYA MANDIRI TRANS | E66: 2625000 | F66: 16650 | G66: 44944 | H66: PAID | I66: PT KINARI JAYA TRANS | J66: 87412 | K66: 1 | L66: Indonesia | M66: KMT-KJT | N66: COMPLETED
A67: CLICTRUCK-043204 | B67: import | C67: 44938 | D67: PT. Central Jasa Mitra Bahari | E67: 16000000 | F67: 532800 | G67: 44939 | H67: PAID | I67: PT. Bina Mitra Segara Setia | K67: 10 | L67: Indonesia | M67: CJM-BMS | N67: COMPLETED
A68: CLICTRUCK-043205 | B68: export | C68: 44938 | D68: PT KINARYA MANDIRI TRANS | E68: 2625000 | F68: 16650 | G68: 44944 | H68: PAID | I68: PT KINARI JAYA TRANS | J68: 87412 | K68: 1 | L68: Indonesia | M68: KMT-KJT | N68: COMPLETED
A69: CLICTRUCK-043206 | B69: export | C69: 44938 | D69: PT. Duta Lestari Segara | E69: 6000000 | F69: 83250 | G69: 44939 | H69: UNPAID | I69: PT. KARYA ABADI SEJATI | J69: 133200 | K69: 3 | L69: Indonesia | M69: DLS-KAS | N69: COMPLETED
A70: CLICTRUCK-043207 | B70: export | C70: 44938 | D70: PT KINARYA MANDIRI TRANS | E70: 2575000 | F70: 16650 | G70: 44944 | H70: PAID | I70: PT KINARI JAYA TRANS | J70: 85747 | K70: 1 | L70: Indonesia | M70: KMT-KJT | N70: COMPLETED
A71: CLICTRUCK-043208 | B71: import | C71: 44938 | D71: PT. Central Jasa Mitra Bahari | E71: 16000000 | F71: 532800 | G71: 44939 | H71: PAID | I71: PT. Bina Mitra Segara Setia | K71: 10 | L71: Indonesia | M71: CJM-BMS | N71: COMPLETED
A72: CLICTRUCK-043209 | B72: export | C72: 44938 | D72: PT KINARYA MANDIRI TRANS | E72: 2900000 | F72: 16650 | G72: 44944 | H72: PAID | I72: PT KINARI JAYA TRANS | J72: 96570 | K72: 1 | L72: Indonesia | M72: KMT-KJT | N72: COMPLETED
A73: CLICTRUCK-043210 | B73: import | C73: 44938 | D73: PT. Central Jasa Mitra Bahari | E73: 3200000 | F73: 106560 | G73: 44939 | H73: PAID | I73: PT. Bina Mitra Segara Setia | K73: 2 | L73: Indonesia | M73: CJM-BMS | N73: COMPLETED
A74: CLICTRUCK-043211 | B74: export | C74: 44938 | D74: PT KINARYA MANDIRI TRANS | E74: 2900000 | F74: 16650 | G74: 44944 | H74: PAID | I74: PT KINARI JAYA TRANS | J74: 96570 | K74: 1 | L74: Indonesia | M74: KMT-KJT | N74: COMPLETED
A75: CLICTRUCK-043212 | B75: export | C75: 44938 | D75: PT KINARYA MANDIRI TRANS | E75: 2900000 | F75: 16650 | G75: 44944 | H75: PAID | I75: PT KINARI JAYA TRANS | J75: 96570 | K75: 1 | L75: Indonesia | M75: KMT-KJT | N75: COMPLETED
A76: CLICTRUCK-043213 | B76: export | C76: 44938 | D76: PT KINARYA MANDIRI TRANS | E76: 2900000 | F76: 16650 | G76: 44944 | H76: PAID | I76: PT KINARI JAYA TRANS | J76: 96570 | K76: 1 | L76: Indonesia | M76: KMT-KJT | N76: COMPLETED
A77: CLICTRUCK-043214 | B77: import | C77: 44938 | D77: PT. Central Jasa Mitra Bahari | E77: 16000000 | F77: 532800 | G77: 44939 | H77: PAID | I77: PT. Bina Mitra Segara Setia | K77: 10 | L77: Indonesia | M77: CJM-BMS | N77: COMPLETED
A78: CLICTRUCK-043215 | B78: export | C78: 44938 | D78: PT KINARYA MANDIRI TRANS | E78: 2900000 | F78: 16650 | G78: 44944 | H78: PAID | I78: PT KINARI JAYA TRANS | J78: 96570 | K78: 1 | L78: Indonesia | M78: KMT-KJT | N78: COMPLETED
A79: CLICTRUCK-043216 | B79: export | C79: 44938 | D79: PT KINARYA MANDIRI TRANS | E79: 2900000 | F79: 16650 | G79: 44944 | H79: PAID | I79: PT KINARI JAYA TRANS | J79: 96570 | K79: 1 | L79: Indonesia | M79: KMT-KJT | N79: COMPLETED
A80: CLICTRUCK-043217 | B80: export | C80: 44938 | D80: PT KINARYA MANDIRI TRANS | E80: 2900000 | F80: 16650 | G80: 44944 | H80: PAID | I80: PT KINARI JAYA TRANS | J80: 96570 | K80: 1 | L80: Indonesia | M80: KMT-KJT | N80: COMPLETED
A81: CLICTRUCK-043218 | B81: import | C81: 44938 | D81: PT. Central Jasa Mitra Bahari | E81: 16000000 | F81: 532800 | G81: 44939 | H81: PAID | I81: PT. Bina Mitra Segara Setia | K81: 10 | L81: Indonesia | M81: CJM-BMS | N81: COMPLETED
A82: CLICTRUCK-043219 | B82: export | C82: 44938 | D82: PT KINARYA MANDIRI TRANS | E82: 2900000 | F82: 16650 | G82: 44951 | H82: PAID | I82: PT KINARI JAYA TRANS | J82: 96570 | K82: 1 | L82: Indonesia | M82: KMT-KJT | N82: COMPLETED
A83: CLICTRUCK-043220 | B83: export | C83: 44938 | D83: PT KINARYA MANDIRI TRANS | E83: 2900000 | F83: 16650 | G83: 44951 | H83: PAID | I83: PT KINARI JAYA TRANS | J83: 96570 | K83: 1 | L83: Indonesia | M83: KMT-KJT | N83: COMPLETED
A84: CLICTRUCK-043221 | B84: import | C84: 44938 | D84: PT. Central Jasa Mitra Bahari | E84: 8000000 | F84: 266400 | G84: 44939 | H84: PAID | I84: PT. Bina Mitra Segara Setia | K84: 5 | L84: Indonesia | M84: CJM-BMS | N84: COMPLETED
A85: CLICTRUCK-043222 | B85: export | C85: 44938 | D85: PT KINARYA MANDIRI TRANS | E85: 2525000 | F85: 16650 | G85: 44951 | H85: PAID | I85: PT KINARI JAYA TRANS | J85: 84082 | K85: 1 | L85: Indonesia | M85: KMT-KJT | N85: COMPLETED
A86: CLICTRUCK-043223 | B86: export | C86: 44938 | D86: PT KINARYA MANDIRI TRANS | E86: 1950000 | F86: 16650 | G86: 44951 | H86: PAID | I86: PT KINARI JAYA TRANS | J86: 64935 | K86: 1 | L86: Indonesia | M86: KMT-KJT | N86: COMPLETED
A87: CLICTRUCK-043224 | B87: export | C87: 44938 | D87: PT KINARYA MANDIRI TRANS | E87: 3125000 | F87: 16650 | G87: 44951 | H87: PAID | I87: PT KINARI JAYA TRANS | J87: 104062 | K87: 1 | L87: Indonesia | M87: KMT-KJT | N87: COMPLETED
A88: CLICTRUCK-043225 | B88: export | C88: 44938 | D88: PT KINARYA MANDIRI TRANS | E88: 2525000 | F88: 16650 | G88: 44951 | H88: PAID | I88: PT KINARI JAYA TRANS | J88: 84082 | K88: 1 | L88: Indonesia | M88: KMT-KJT | N88: COMPLETED
A89: CLICTRUCK-043226 | B89: export | C89: 44938 | D89: PT KINARYA MANDIRI TRANS | E89: 1000000 | F89: 16650 | G89: 44951 | H89: PAID | I89: PT KINARI JAYA TRANS | J89: 33300 | K89: 1 | L89: Indonesia | M89: KMT-KJT | N89: COMPLETED
A90: CLICTRUCK-043227 | B90: import | C90: 44938 | D90: PT. Ekspedisi Sehati Abadi | E90: 1740500 | F90: 19980 | G90: 44938 | H90: PAID | I90: PT. Saudara Sukses Abadi | J90: 38639 | K90: 1 | L90: Indonesia | M90: ESA - SASA | N90: COMPLETED
A91: CLICTRUCK-043228 | B91: import | C91: 44938 | D91: PT. Ekspedisi Sehati Abadi | E91: 31358019 | F91: 319680 | G91: 44939 | H91: PAID | I91: PT. Saudara Sukses Abadi | J91: 696147 | K91: 16 | L91: Indonesia | M91: ESA - SASA | N91: COMPLETED
A92: CLICTRUCK-043230 | B92: export | C92: 44939 | D92: PT. GOOD LOGISTICS TERMINAL | E92: 1176000 | F92: 22200 | G92: 44940 | H92: PAID | I92: PT ELEMEN TRANS LOGISTIK | K92: 1 | L92: Indonesia | M92: GLT-Elemen | N92: COMPLETED
A93: CLICTRUCK-043231 | B93: export | C93: 44939 | D93: PT. GOOD LOGISTICS TERMINAL | E93: 7644000 | F93: 133200 | G93: 44940 | H93: PAID | I93: PT ELEMEN TRANS LOGISTIK | K93: 6 | L93: Indonesia | M93: GLT-Elemen | N93: COMPLETED
A94: CLICTRUCK-043233 | B94: export | C94: 44939 | D94: PT. GOOD LOGISTICS TERMINAL | E94: 12642000 | F94: 222000 | G94: 44940 | H94: PAID | I94: PT ELEMEN TRANS LOGISTIK | K94: 10 | L94: Indonesia | M94: GLT-Elemen | N94: COMPLETED
A95: CLICTRUCK-043235 | B95: export | C95: 44939 | D95: PT. GOOD LOGISTICS TERMINAL | E95: 16072000 | F95: 288600 | G95: 44940 | H95: PAID | I95: PT ELEMEN TRANS LOGISTIK | K95: 13 | L95: Indonesia | M95: GLT-Elemen | N95: COMPLETED
A96: CLICTRUCK-043236 | B96: export | C96: 44939 | D96: PT. Duta Lestari Segara | E96: 2000000 | F96: 27750 | G96: 44943 | H96: UNPAID | I96: PT. KARYA ABADI SEJATI | J96: 44400 | K96: 1 | L96: Indonesia | M96: DLS-KAS | N96: COMPLETED
A97: CLICTRUCK-043237 | B97: export | C97: 44939 | D97: PT. Duta Lestari Segara | E97: 2000000 | F97: 27750 | G97: 44943 | H97: UNPAID | I97: PT. KARYA ABADI SEJATI | J97: 44400 | K97: 1 | L97: Indonesia | M97: DLS-KAS | N97: COMPLETED
A98: CLICTRUCK-043238 | B98: import | C98: 44939 | D98: PT. Ekspedisi Sehati Abadi | E98: 25161500 | F98: 279720 | G98: 44944 | H98: PAID | I98: PT. Saudara Sukses Abadi | J98: 558585 | K98: 14 | L98: Indonesia | M98: ESA - SASA | N98: COMPLETED
A99: CLICTRUCK-043239 | B99: export | C99: 44939 | D99: PT. GOOD LOGISTICS TERMINAL | E99: 3626000 | F99: 66600 | G99: 44940 | H99: PAID | I99: PT ELEMEN TRANS LOGISTIK | K99: 3 | L99: Indonesia | M99: GLT-Elemen | N99: COMPLETED
A100: CLICTRUCK-043240 | B100: export | C100: 44939 | D100: PT. GOOD LOGISTICS TERMINAL | E100: 6370000 | F100: 111000 | G100: 44940 | H100: PAID | I100: PT ELEMEN TRANS LOGISTIK | K100: 5 | L100: Indonesia | M100: GLT-Elemen | N100: COMPLETED
A101: CLICTRUCK-043252 | B101: import | C101: 44942 | D101: PT. Ekspedisi Sehati Abadi | E101: 14951217 | F101: 159840 | G101: 44944 | H101: PAID | I101: PT. Saudara Sukses Abadi | J101: 331916 | K101: 8 | L101: Indonesia | M101: ESA - SASA | N101: COMPLETED
A102: CLICTRUCK-043263 | B102: export | C102: 44942 | D102: PT. Duta Lestari Segara | E102: 2000000 | F102: 27750 | G102: 44967 | H102: UNPAID | I102: PT. KARYA ABADI SEJATI | J102: 44400 | K102: 1 | L102: Indonesia | M102: DLS-KAS | N102: COMPLETED
A103: CLICTRUCK-043264 | B103: export | C103: 44942 | D103: PT. Duta Lestari Segara | E103: 2000000 | F103: 27750 | G103: 44967 | H103: UNPAID | I103: PT. KARYA ABADI SEJATI | J103: 44400 | K103: 1 | L103: Indonesia | M103: DLS-KAS | N103: COMPLETED
A104: CLICTRUCK-043266 | B104: export | C104: 44942 | D104: PT. Duta Lestari Segara | E104: 2000000 | F104: 27750 | G104: 44967 | H104: UNPAID | I104: PT. KARYA ABADI SEJATI | J104: 44400 | K104: 1 | L104: Indonesia | M104: DLS-KAS | N104: COMPLETED
A105: CLICTRUCK-043267 | B105: export | C105: 44942 | D105: PT. Duta Lestari Segara | E105: 2000000 | F105: 27750 | G105: 44967 | H105: UNPAID | I105: PT. KARYA ABADI SEJATI | J105: 44400 | K105: 1 | L105: Indonesia | M105: DLS-KAS | N105: COMPLETED
A106: CLICTRUCK-043268 | B106: export | C106: 44942 | D106: PT. Duta Lestari Segara | E106: 2000000 | F106: 27750 | G106: 44970 | H106: UNPAID | I106: PT. KARYA ABADI SEJATI | J106: 44400 | K106: 1 | L106: Indonesia | M106: DLS-KAS | N106: COMPLETED
A107: CLICTRUCK-043269 | B107: export | C107: 44942 | D107: PT. Duta Lestari Segara | E107: 2000000 | F107: 27750 | G107: 44967 | H107: UNPAID | I107: PT. KARYA ABADI SEJATI | J107: 44400 | K107: 1 | L107: Indonesia | M107: DLS-KAS | N107: COMPLETED
A108: CLICTRUCK-043270 | B108: export | C108: 44942 | D108: PT. Duta Lestari Segara | E108: 2000000 | F108: 27750 | G108: 44970 | H108: UNPAID | I108: PT. KARYA ABADI SEJATI | J108: 44400 | K108: 1 | L108: Indonesia | M108: DLS-KAS | N108: COMPLETED
A109: CLICTRUCK-043271 | B109: export | C109: 44942 | D109: PT. Duta Lestari Segara | E109: 2000000 | F109: 27750 | G109: 44970 | H109: UNPAID | I109: PT. KARYA ABADI SEJATI | J109: 44400 | K109: 1 | L109: Indonesia | M109: DLS-KAS | N109: COMPLETED
A110: CLICTRUCK-043322 | B110: import | C110: 44943 | D110: PT. Ekspedisi Sehati Abadi | E110: 2530000 | F110: 19980 | G110: 44981 | H110: PAID | I110: PT. Saudara Sukses Abadi | J110: 56166 | K110: 1 | L110: Indonesia | M110: ESA - SASA | N110: COMPLETED
A111: CLICTRUCK-043323 | B111: import | C111: 44943 | D111: PT. Ekspedisi Sehati Abadi | E111: 14290470 | F111: 179820 | G111: 44944 | H111: PAID | I111: PT. Saudara Sukses Abadi | J111: 317247 | K111: 9 | L111: Indonesia | M111: ESA - SASA | N111: COMPLETED
A112: CLICTRUCK-043324 | B112: import | C112: 44943 | D112: PT. Ekspedisi Sehati Abadi | E112: 6240000 | F112: 18000 | H112: NEW | I112: PT. Saudara Sukses Abadi | J112: 0 | K112: 8 | L112: Indonesia | M112: ESA - SASA | N112: OUTSTANDING
A113: CLICTRUCK-043325 | B113: export | C113: 44943 | D113: PT KINARYA MANDIRI TRANS | E113: 2787000 | F113: 16650 | G113: 44951 | H113: PAID | I113: PT KINARI JAYA TRANS | J113: 92807 | K113: 1 | L113: Indonesia | M113: KMT-KJT | N113: COMPLETED
A114: CLICTRUCK-043326 | B114: export | C114: 44943 | D114: PT KINARYA MANDIRI TRANS | E114: 2375000 | F114: 16650 | G114: 44951 | H114: PAID | I114: PT KINARI JAYA TRANS | J114: 79087 | K114: 1 | L114: Indonesia | M114: KMT-KJT | N114: COMPLETED
A115: CLICTRUCK-043327 | B115: export | C115: 44943 | D115: PT KINARYA MANDIRI TRANS | E115: 2525000 | F115: 16650 | G115: 44951 | H115: PAID | I115: PT KINARI JAYA TRANS | J115: 84082 | K115: 1 | L115: Indonesia | M115: KMT-KJT | N115: COMPLETED
A116: CLICTRUCK-043334 | B116: import | C116: 44944 | D116: PT. Ekspedisi Sehati Abadi | E116: 14582000 | F116: 159840 | G116: 44952 | H116: PAID | I116: PT. Saudara Sukses Abadi | J116: 323720 | K116: 8 | L116: Indonesia | M116: ESA - SASA | N116: COMPLETED
A117: CLICTRUCK-043345 | B117: export | C117: 44945 | D117: PT KINARYA MANDIRI TRANS | E117: 1950000 | F117: 16650 | G117: 44951 | H117: PAID | I117: PT KINARI JAYA TRANS | J117: 64935 | K117: 1 | L117: Indonesia | M117: KMT-KJT | N117: COMPLETED
A118: CLICTRUCK-043346 | B118: export | C118: 44945 | D118: PT KINARYA MANDIRI TRANS | E118: 3187500 | F118: 16650 | G118: 44951 | H118: PAID | I118: PT KINARI JAYA TRANS | J118: 106143 | K118: 1 | L118: Indonesia | M118: KMT-KJT | N118: COMPLETED
A119: CLICTRUCK-043347 | B119: export | C119: 44945 | D119: PT KINARYA MANDIRI TRANS | E119: 2900000 | F119: 16650 | G119: 44951 | H119: PAID | I119: PT KINARI JAYA TRANS | J119: 96570 | K119: 1 | L119: Indonesia | M119: KMT-KJT | N119: COMPLETED
A120: CLICTRUCK-043348 | B120: export | C120: 44945 | D120: PT KINARYA MANDIRI TRANS | E120: 2900000 | F120: 16650 | G120: 44951 | H120: PAID | I120: PT KINARI JAYA TRANS | J120: 96570 | K120: 1 | L120: Indonesia | M120: KMT-KJT | N120: COMPLETED
A121: CLICTRUCK-043349 | B121: export | C121: 44945 | D121: PT KINARYA MANDIRI TRANS | E121: 2900000 | F121: 16650 | G121: 44951 | H121: PAID | I121: PT KINARI JAYA TRANS | J121: 96570 | K121: 1 | L121: Indonesia | M121: KMT-KJT | N121: COMPLETED
A122: CLICTRUCK-043350 | B122: export | C122: 44945 | D122: PT KINARYA MANDIRI TRANS | E122: 2900000 | F122: 16650 | G122: 44951 | H122: PAID | I122: PT KINARI JAYA TRANS | J122: 96570 | K122: 1 | L122: Indonesia | M122: KMT-KJT | N122: COMPLETED
A123: CLICTRUCK-043351 | B123: export | C123: 44945 | D123: PT KINARYA MANDIRI TRANS | E123: 2900000 | F123: 16650 | G123: 44951 | H123: PAID | I123: PT KINARI JAYA TRANS | J123: 96570 | K123: 1 | L123: Indonesia | M123: KMT-KJT | N123: COMPLETED
A124: CLICTRUCK-043352 | B124: export | C124: 44945 | D124: PT KINARYA MANDIRI TRANS | E124: 2900000 | F124: 16650 | G124: 44951 | H124: PAID | I124: PT KINARI JAYA TRANS | J124: 96570 | K124: 1 | L124: Indonesia | M124: KMT-KJT | N124: COMPLETED
... A137: CLICTRUCK-043365 | B137: export | C137: 44945 | D137: PT. Duta Lestari Segara | E137: 4000000 | F137: 55500 | G137: 44970 | H137: UNPAID | I137: PT. KARYA ABADI SEJATI | J137: 88800 | K137: 2 | L137: Indonesia | M137: DLS-KAS | N137: COMPLETED
A138: CLICTRUCK-043370 | B138: export | C138: 44946 | D138: PT. GOOD LOGISTICS TERMINAL | E138: 17836000 | F138: 310800 | G138: 44948 | H138: PAID | I138: PT ELEMEN TRANS LOGISTIK | K138: 14 | L138: Indonesia | M138: GLT-Elemen | N138: COMPLETED
A139: CLICTRUCK-043371 | B139: export | C139: 44946 | D139: PT. GOOD LOGISTICS TERMINAL | E139: 1273999 | F139: 22200 | G139: 44948 | H139: PAID | I139: PT ELEMEN TRANS LOGISTIK | K139: 1 | L139: Indonesia | M139: GLT-Elemen | N139: COMPLETED
A140: CLICTRUCK-043372 | B140: export | C140: 44946 | D140: PT. Duta Lestari Segara | E140: 6000000 | F140: 83250 | G140: 44970 | H140: UNPAID | I140: PT. KARYA ABADI SEJATI | J140: 133200 | K140: 3 | L140: Indonesia | M140: DLS-KAS | N140: COMPLETED
A141: CLICTRUCK-043373 | B141: export | C141: 44946 | D141: PT. Duta Lestari Segara | E141: 2000000 | F141: 27750 | G141: 45002 | H141: UNPAID | I141: PT. KARYA ABADI SEJATI | J141: 44400 | K141: 1 | L141: Indonesia | M141: DLS-KAS | N141: COMPLETED
A142: CLICTRUCK-043374 | B142: export | C142: 44946 | D142: PT KINARYA MANDIRI TRANS | E142: 2900000 | F142: 16650 | G142: 44951 | H142: PAID | I142: PT KINARI JAYA TRANS | J142: 96570 | K142: 1 | L142: Indonesia | M142: KMT-KJT | N142: COMPLETED
A143: CLICTRUCK-043375 | B143: export | C143: 44946 | D143: PT KINARYA MANDIRI TRANS | E143: 2900000 | F143: 16650 | G143: 44951 | H143: PAID | I143: PT KINARI JAYA TRANS | J143: 96570 | K143: 1 | L143: Indonesia | M143: KMT-KJT | N143: COMPLETED
A144: CLICTRUCK-043376 | B144: export | C144: 44946 | D144: PT KINARYA MANDIRI TRANS | E144: 2900000 | F144: 16650 | G144: 44951 | H144: PAID | I144: PT KINARI JAYA TRANS | J144: 96570 | K144: 1 | L144: Indonesia | M144: KMT-KJT | N144: COMPLETED
A145: CLICTRUCK-043377 | B145: export | C145: 44946 | D145: PT KINARYA MANDIRI TRANS | E145: 2900000 | F145: 16650 | G145: 44951 | H145: PAID | I145: PT KINARI JAYA TRANS | J145: 96570 | K145: 1 | L145: Indonesia | M145: KMT-KJT | N145: COMPLETED
A146: CLICTRUCK-043378 | B146: export | C146: 44946 | D146: PT KINARYA MANDIRI TRANS | E146: 2900000 | F146: 16650 | G146: 44951 | H146: PAID | I146: PT KINARI JAYA TRANS | J146: 96570 | K146: 1 | L146: Indonesia | M146: KMT-KJT | N146: COMPLETED
A147: CLICTRUCK-043379 | B147: export | C147: 44946 | D147: PT KINARYA MANDIRI TRANS | E147: 2900000 | F147: 16650 | G147: 44951 | H147: PAID | I147: PT KINARI JAYA TRANS | J147: 96570 | K147: 1 | L147: Indonesia | M147: KMT-KJT | N147: COMPLETED
A148: CLICTRUCK-043380 | B148: export | C148: 44946 | D148: PT KINARYA MANDIRI TRANS | E148: 2900000 | F148: 16650 | G148: 44951 | H148: PAID | I148: PT KINARI JAYA TRANS | J148: 96570 | K148: 1 | L148: Indonesia | M148: KMT-KJT | N148: COMPLETED
A149: CLICTRUCK-043381 | B149: export | C149: 44946 | D149: PT KINARYA MANDIRI TRANS | E149: 2900000 | F149: 16650 | G149: 44951 | H149: PAID | I149: PT KINARI JAYA TRANS | J149: 96570 | K149: 1 | L149: Indonesia | M149: KMT-KJT | N149: COMPLETED
A150: CLICTRUCK-043382 | B150: export | C150: 44946 | D150: PT KINARYA MANDIRI TRANS | E150: 2450000 | F150: 16650 | G150: 44952 | H150: PAID | I150: PT KINARI JAYA TRANS | J150: 81585 | K150: 1 | L150: Indonesia | M150: KMT-KJT | N150: COMPLETED
A151: CLICTRUCK-043383 | B151: export | C151: 44946 | D151: PT KINARYA MANDIRI TRANS | E151: 2625000 | F151: 16650 | G151: 44951 | H151: PAID | I151: PT KINARI JAYA TRANS | J151: 87412 | K151: 1 | L151: Indonesia | M151: KMT-KJT | N151: COMPLETED
... A231: CLICTRUCK-043577 | B231: import | C231: 44953 | D231: PT. Ekspedisi Sehati Abadi | E231: 2415750 | F231: 39960 | G231: 44953 | H231: PAID | I231: PT. Saudara Sukses Abadi | J231: 53629 | K231: 2 | L231: Indonesia | M231: ESA - SASA | N231: COMPLETED
A232: CLICTRUCK-043627 | B232: export | C232: 44954 | D232: PT. GOOD LOGISTICS TERMINAL | E232: 12740000 | F232: 222000 | G232: 44954 | H232: PAID | I232: PT ELEMEN TRANS LOGISTIK | K232: 10 | L232: Indonesia | M232: GLT-Elemen | N232: COMPLETED
A233: CLICTRUCK-043628 | B233: export | C233: 44954 | D233: PT. GOOD LOGISTICS TERMINAL | E233: 3822000 | F233: 66600 | G233: 44954 | H233: PAID | I233: PT ELEMEN TRANS LOGISTIK | K233: 3 | L233: Indonesia | M233: GLT-Elemen | N233: COMPLETED
A234: CLICTRUCK-043629 | B234: export | C234: 44954 | D234: PT. GOOD LOGISTICS TERMINAL | E234: 1176000 | F234: 22200 | G234: 44954 | H234: PAID | I234: PT ELEMEN TRANS LOGISTIK | K234: 1 | L234: Indonesia | M234: GLT-Elemen | N234: COMPLETED
A235: CLICTRUCK-043660 | B235: export | C235: 44955 | D235: PT KINARYA MANDIRI TRANS | E235: 2900000 | F235: 16650 | G235: 44965 | H235: PAID | I235: PT KINARI JAYA TRANS | J235: 96570 | K235: 1 | L235: Indonesia | M235: KMT-KJT | N235: COMPLETED
A236: CLICTRUCK-043661 | B236: export | C236: 44955 | D236: PT KINARYA MANDIRI TRANS | E236: 2900000 | F236: 16650 | G236: 44965 | H236: PAID | I236: PT KINARI JAYA TRANS | J236: 96570 | K236: 1 | L236: Indonesia | M236: KMT-KJT | N236: COMPLETED
A237: CLICTRUCK-043662 | B237: export | C237: 44955 | D237: PT KINARYA MANDIRI TRANS | E237: 2900000 | F237: 16650 | G237: 44965 | H237: PAID | I237: PT KINARI JAYA TRANS | J237: 96570 | K237: 1 | L237: Indonesia | M237: KMT-KJT | N237: COMPLETED
A238: CLICTRUCK-043663 | B238: export | C238: 44955 | D238: PT KINARYA MANDIRI TRANS | E238: 2900000 | F238: 16650 | G238: 44965 | H238: PAID | I238: PT KINARI JAYA TRANS | J238: 96570 | K238: 1 | L238: Indonesia | M238: KMT-KJT | N238: COMPLETED
A239: CLICTRUCK-043664 | B239: export | C239: 44955 | D239: PT KINARYA MANDIRI TRANS | E239: 2900000 | F239: 16650 | G239: 44965 | H239: PAID | I239: PT KINARI JAYA TRANS | J239: 96570 | K239: 1 | L239: Indonesia | M239: KMT-KJT | N239: COMPLETED
A240: CLICTRUCK-043665 | B240: export | C240: 44955 | D240: PT KINARYA MANDIRI TRANS | E240: 2900000 | F240: 16650 | G240: 44965 | H240: PAID | I240: PT KINARI JAYA TRANS | J240: 96570 | K240: 1 | L240: Indonesia | M240: KMT-KJT | N240: COMPLETED
A241: CLICTRUCK-043666 | B241: export | C241: 44955 | D241: PT KINARYA MANDIRI TRANS | E241: 2900000 | F241: 16650 | G241: 44965 | H241: PAID | I241: PT KINARI JAYA TRANS | J241: 96570 | K241: 1 | L241: Indonesia | M241: KMT-KJT | N241: COMPLETED
A242: CLICTRUCK-043667 | B242: export | C242: 44955 | D242: PT KINARYA MANDIRI TRANS | E242: 2500000 | F242: 16650 | G242: 44966 | H242: PAID | I242: PT KINARI JAYA TRANS | J242: 83250 | K242: 1 | L242: Indonesia | M242: KMT-KJT | N242: COMPLETED
A243: CLICTRUCK-043672 | B243: export | C243: 44956 | D243: PT KINARYA MANDIRI TRANS | E243: 2375000 | F243: 16650 | G243: 44966 | H243: PAID | I243: PT KINARI JAYA TRANS | J243: 79087 | K243: 1 | L243: Indonesia | M243: KMT-KJT | N243: COMPLETED
...
